Workbook

Sheet 使用说明
F2: 猫猫背带产品调研
F3: 英文关键词 | H3: Cat Harness | K3: 调研时间 | O3: 编号
G5: 使用需知
G12: 1.本表格只接受160条listing的数据，相当于亚马逊前十页的listing数量。
G17: 2.务必提供准确的数据，如果数据中包含不相干的产品数据，该表格将不能自动分辨，因此，在将数据粘贴到本表格前，请先将杂质清除。
G22: 3.本表格的数据最好是来源于Jungle Scout或米库插件软件下载的CSV文件，可将下载的文件直接粘贴于本表格，其他软件下载的数据需要事先整理。
G27: 4.本表格每页都有“注释”板块，用于讲解或提示本页面的数据及注意事项，使用前需提前了解。
G32: 5.本表格只有绿色区域可用于编辑，其他区域因有函数关系的原因，同时以防不小心修改了函数关系导致数据错乱，所以其他区域为不可选中，不可编辑修改。

Sheet 数据调研
A1: # | B1: Product Name | C1: Brand | D1: Price | E1: Category | F1: Rank | G1: Sales | H1: Revenue | I1: Reviews | J1: Rating | K1: Seller | L1: ASIN | M1: Link | N1: 上架天数 | P1: 市场份额
A2: 86 | B2: 骞垮憡-Small Dog Harness Cat Harness Escape Proof Cat and Dog Harness Adjustable Vest Harnesses with Reflective Strap Soft Mesh Back Metal Clip No Pull No Choke Training Walk for Small Pet Puppy Kitten | C2: Eagloo | D2: 13.99 | E2: Pet Supplies | F2: 764 | G2: 2550 | H2: 35674.5 | I2: 79 | J2: 4 | K2: FBA | L2: B07NQ35VDW | M2: https://www.amazon.com/dp/B07NQ35VDW?psc=1 | N2: 387 | O2: =IFERROR(VLOOKUP(L2,#REF!,5,0),"") | P2: =G2/SUM($G$2:$G$161) -> 0.098391017
A3: 29 | B3: Small Dog Harness Cat Harness Escape Proof Cat and Dog Harness Adjustable Vest Harnesses with Reflective Strap Soft Mesh Back Metal Clip No Pull No Choke Training Walk for Small Pet Puppy Kitten | C3: Eagloo | D3: 13.99 | E3: Pet Supplies | F3: 764 | G3: 2550 | H3: 35674.5 | I3: 79 | J3: 4 | K3: FBA | L3: B07NQ35VDW | M3: https://www.amazon.com/dp/B07NQ35VDW?psc=1 | N3: 387 | O3: =IFERROR(VLOOKUP(L3,#REF!,5,0),"") | P3: =G3/SUM($G$2:$G$161) -> 0.098391017 | R3: 注意： 该表格数据最好来自于JS,JS数据可直接粘贴使用，无需调整格式 此处的上架天数来源于表格“天数换算”的数据匹配，无需手动输入。 没有上架天数的必须手动输入，不然会影响分析结果。可用Keepa查询后补齐
A4: 111 | B4: 骞垮憡-Small Dog Harness Cat Harness Escape Proof Cat and Dog Harness Adjustable Vest Harnesses with Reflective Strap Soft Mesh Back Metal Clip No Pull No Choke Training Walk for Small Pet Puppy Kitten | C4: Eagloo | D4: 13.99 | E4: Pet Supplies | F4: 764 | G4: 2550 | H4: 35674.5 | I4: 79 | J4: 4 | K4: FBA | L4: B07NQ35VDW | M4: https://www.amazon.com/dp/B07NQ35VDW?psc=1 | N4: 387 | O4: =IFERROR(VLOOKUP(L4,#REF!,5,0),"") | P4: =G4/SUM($G$2:$G$161) -> 0.098391017
A5: 80 | B5: BWOGUE 2 Packs Dog Cat Safety Seat Belt Strap Car Headrest Restraint Adjustable Nylon Fabric Dog Restraints Vehicle Seatbelts Harness | C5: BWOGUE | D5: 10.49 | E5: Pet Supplies | F5: 921 | G5: 2220 | H5: 23287.8 | I5: 743 | J5: 4.7 | K5: FBA | L5: B078G6MKTN | M5: https://www.amazon.com/dp/B078G6MKTN?psc=1 | N5: 459 | O5: =IFERROR(VLOOKUP(L5,#REF!,5,0),"") | P5: =G5/SUM($G$2:$G$161) -> 0.085658062
A6: 117 | B6: PetSafe Nylon Dog Leash, Strong and Durable Traditional Style Leash with Easy to Use Collar Hook, Available in Multiple Widths and Colors | C6: PetSafe | D6: 4.79 | E6: Pet Supplies | F6: 1174 | G6: 1830 | H6: 8765.7 | I6: 1616 | J6: 4.4 | K6: AMZ | L6: B000OGRDK0 | M6: https://www.amazon.com/dp/B000OGRDK0?psc=1 | N6: 4374 | O6: =IFERROR(VLOOKUP(L6,#REF!,5,0),"") | P6: =G6/SUM($G$2:$G$161) -> 0.070610024
A7: 14 | B7: PUPTECK Cat Harness with Leash Set - Adjustable Soft Strap with Fashion Design | C7: PUPTECK | D7: 13.99 | E7: Pet Supplies | F7: 2511 | G7: 960 | H7: 13430.4 | I7: 13 | J7: 4.8 | K7: FBA | L7: B07MKQFJSP | M7: https://www.amazon.com/dp/B07MKQFJSP?psc=1 | N7: 96 | O7: =IFERROR(VLOOKUP(L7,#REF!,5,0),"") | P7: =G7/SUM($G$2:$G$161) -> 0.037041324
A8: 25 | B8: 骞垮憡-PUPTECK Cat Harness with Leash Set - Adjustable Soft Strap with Fashion Design | C8: PUPTECK | D8: 13.99 | E8: Pet Supplies | F8: 2921 | G8: 840 | H8: 11751.6 | I8: 13 | J8: 4.8 | K8: FBA | L8: B07MKQFJSP | M8: https://www.amazon.com/dp/B07MKQFJSP?psc=1 | N8: 96 | O8: =IFERROR(VLOOKUP(L8,#REF!,5,0),"") | P8: =G8/SUM($G$2:$G$161) -> 0.032411159
A9: 131 | B9: 骞垮憡-GAUTERF Dog and Cat Universal Harness with Leash Set, Escape Proof Cat Harnesses - Adjustable Reflective Soft Mesh Corduroy Dog Harnesses - Best Pet Supplies | C9: GAUTERF | D9: 10.99 | E9: Pet Supplies | F9: 6044 | G9: 420 | H9: 4615.8 | I9: 601 | J9: 4.2 | K9: FBA | L9: B07GFBW7JT | M9: https://www.amazon.com/dp/B07GFBW7JT?psc=1 | N9: 256 | O9: =IFERROR(VLOOKUP(L9,#REF!,5,0),"") | P9: =G9/SUM($G$2:$G$161) -> 0.016205579
A10: 53 | B10: Cat Harness Escape Proof Small Dogs Mesh Vest Harnesses Adjustable Puppy Kitten Walking Harness No Pull Design with Leash Clip & Reflective Strips for Best Comfort & Safety, Black Green Pink Red | C10: Rabbitgoo | D10: 12.98 | E10: Pet Supplies | F10: 6553 | G10: 390 | H10: 5062.2 | I10: 28 | J10: 3.7 | K10: FBA | L10: B07MZR3MDT | M10: https://www.amazon.com/dp/B07MZR3MDT?psc=1 | N10: 48 | O10: =IFERROR(VLOOKUP(L10,#REF!,5,0),"") | P10: =G10/SUM($G$2:$G$161) -> 0.015048038
A11: 3 | B11: 骞垮憡-Cat Harness Escape Proof Small Dogs Mesh Vest Harnesses Adjustable Puppy Kitten Walking Harness No Pull Design with Leash Clip & Reflective Strips for Best Comfort & Safety, Black Green Pink Red | C11: Rabbitgoo | D11: 12.98 | E11: Pet Supplies | F11: 6553 | G11: 390 | H11: 5062.2 | I11: 28 | J11: 3.7 | K11: FBA | L11: B07MZR3MDT | M11: https://www.amazon.com/dp/B07MZR3MDT?psc=1 | N11: 48 | O11: =IFERROR(VLOOKUP(L11,#REF!,5,0),"") | P11: =G11/SUM($G$2:$G$161) -> 0.015048038
A12: 68 | B12: Escape Proof Cat Harness with Leash Adjustable Soft Mesh - Best for Walking | C12: PUPTECK | D12: 12.99 | E12: Pet Supplies | F12: 6727 | G12: 360 | H12: 4676.4 | I12: 944 | J12: 3.6 | K12: FBA | L12: B074MWRZ5Y | M12: https://www.amazon.com/dp/B074MWRZ5Y?psc=1 | N12: 1080 | O12: =IFERROR(VLOOKUP(L12,#REF!,5,0),"") | P12: =G12/SUM($G$2:$G$161) -> 0.013890497
A13: 46 | B13: 骞垮憡-INVENHO Mesh Harness with Padded Vest for Puppy and Cats No Choke Design Ventilation Gift with One Leash & Seat Belt | C13: INVENHO | D13: 10.99 | E13: Pet Supplies | F13: 7043 | G13: 360 | H13: 3956.4 | I13: 124 | J13: 4.3 | K13: FBA | L13: B07MDLYQR7 | M13: https://www.amazon.com/dp/B07MDLYQR7?psc=1 | N13: 556 | O13: =IFERROR(VLOOKUP(L13,#REF!,5,0),"") | P13: =G13/SUM($G$2:$G$161) -> 0.013890497
A14: 45 | B14: 骞垮憡-INVENHO Mesh Harness with Padded Vest for Puppy and Cats No Choke Design Ventilation Gift with One Leash & Seat Belt | C14: INVENHO | D14: 10.99 | E14: Pet Supplies | F14: 7043 | G14: 360 | H14: 3956.4 | I14: 124 | J14: 4.3 | K14: FBA | L14: B07MDLYQR7 | M14: https://www.amazon.com/dp/B07MDLYQR7?psc=1 | N14: 556 | O14: =IFERROR(VLOOKUP(L14,#REF!,5,0),"") | P14: =G14/SUM($G$2:$G$161) -> 0.013890497
A15: 66 | B15: Voyager All Weather No Pull Step-in Mesh Dog Harness Padded Vest | C15: Best Pet Supplies, Inc. | D15: 12.99 | E15: Pet Supplies | F15: 7965 | G15: 300 | H15: 3897 | I15: 4515 | J15: 4.3 | K15: AMZ | L15: B00M0V7UVE | M15: https://www.amazon.com/dp/B00M0V7UVE?psc=1 | N15: 1921 | O15: =IFERROR(VLOOKUP(L15,#REF!,5,0),"") | P15: =G15/SUM($G$2:$G$161) -> 0.011575414
... A20: 147 | B20: SCENEREAL Escape Proof Cat Harness and Leash - Adjustable Soft Mesh Vest for Rabbits Puppy Kittens | C20: SCENEREAL | D20: 13.99 | E20: Pet Supplies | F20: 10702 | G20: 210 | H20: 2937.9 | I20: 67 | J20: 3.9 | K20: FBA | L20: B07F8RY3C6 | M20: https://www.amazon.com/dp/B07F8RY3C6?psc=1 | N20: 272 | O20: =IFERROR(VLOOKUP(L20,#REF!,5,0),"") | P20: =G20/SUM($G$2:$G$161) -> 0.0081027897
A21: 82 | B21: PetSafe Come with Me Kitty Harness and Bungee Leash, Harness for Cats | C21: PetSafe | D21: 14.95 | E21: Amazon Best Sellers Rank: | F21: N.A. | G21: 210 | H21: 3139.5 | I21: 2543 | J21: 3.9 | K21: AMZ | L21: B001OMD5ZA | M21: https://www.amazon.com/dp/B001OMD5ZA?psc=1 | N21: 4229 | O21: =IFERROR(VLOOKUP(L21,#REF!,5,0),"") | P21: =G21/SUM($G$2:$G$161) -> 0.0081027897
A22: 157 | B22: Escape Proof Cat Harness with Leash, Adjustable Cat Walking Jackets, Padded Cat Vest | C22: Yizhi Miaow | D22: 14.49 | E22: Pet Supplies | F22: 12619 | G22: 180 | H22: 2608.2 | I22: 263 | J22: 4 | K22: FBA | L22: B077XY1CBC | M22: https://www.amazon.com/dp/B077XY1CBC?psc=1 | N22: 533 | O22: =IFERROR(VLOOKUP(L22,#REF!,5,0),"") | P22: =G22/SUM($G$2:$G$161) -> 0.0069452483
A23: 47 | B23: OFPUPPY Adjustable Cat Harness and Leash Set Velvet and Nylon Lead for Kitty Kitten Walking | C23: OFPUPPY | D23: 9.99 | E23: Pet Supplies | F23: 98482 | G23: 180 | H23: 1798.2 | I23: 14 | J23: 3.9 | K23: FBA | L23: B07DWPTT9S | M23: https://www.amazon.com/dp/B07DWPTT9S?psc=1 | N23: 309 | O23: =IFERROR(VLOOKUP(L23,#REF!,5,0),"") | P23: =G23/SUM($G$2:$G$161) -> 0.0069452483
A24: 9 | B24: voopet Boho Soft Mesh Dog Harness, Cats Padded Front Vest Harness with Leash, Adjustable Pets No-Pull Walking Harness - Easy Control for Small Dogs & Puppy | C24: voopet | D24: 10.99 | E24: Pet Supplies | F24: 140925 | G24: 180 | H24: 1978.2 | I24: 2 | J24: 5 | K24: FBA | L24: B07MMHDWTC | M24: https://www.amazon.com/dp/B07MMHDWTC?psc=1 | N24: 1235 | O24: =IFERROR(VLOOKUP(L24,#REF!,5,0),"") | P24: =G24/SUM($G$2:$G$161) -> 0.0069452483
A25: 37 | B25: 骞垮憡-Mellow Shirt Dog Anxiety Calming Wrap | C25: Mellow Shirt | D25: 25.99 | E25: Pet Supplies | F25: 12670 | G25: 180 | H25: 4678.2 | I25: 1611 | J25: 3.5 | K25: FBA | L25: B018S3APEG | M25: https://www.amazon.com/dp/B018S3APEG?psc=1 | N25: 1235 | O25: =IFERROR(VLOOKUP(L25,#REF!,5,0),"") | P25: =G25/SUM($G$2:$G$161) -> 0.0069452483
A26: 158 | B26: Coastal Pet Poly Cat Tie Out with Nickel-Plated Swivel Snaps, Black, 1/8 Width by 15-Feet Long | C26: Coastal Pet | D26: 8.14 | E26: Pet Supplies | F26: 13278 | G26: 180 | H26: 1465.2 | I26: 106 | J26: 4.4 | K26: FBA | L26: B003WRG9O4 | M26: https://www.amazon.com/dp/B003WRG9O4?psc=1 | N26: 980 | O26: =IFERROR(VLOOKUP(L26,#REF!,5,0),"") | P26: =G26/SUM($G$2:$G$161) -> 0.0069452483
A27: 148 | B27: Dog and Cat Universal Harness with Traction Rope, Adjustable Vest-Type Reflective Corduroy Comfortable Pet Harness | C27: Rosestola | D27: 8.99 | E27: Pet Supplies | F27: 130055 | G27: 180 | H27: 1618.2 | I27: 5 | J27: 5 | K27: FBA | L27: B07P74ZSXS | M27: https://www.amazon.com/dp/B07P74ZSXS?psc=1 | N27: 980 | O27: =IFERROR(VLOOKUP(L27,#REF!,5,0),"") | P27: =G27/SUM($G$2:$G$161) -> 0.0069452483
A28: 135 | B28: EliteField Soft Sided Pet Carrier (3 Year Warranty, Airline Approved), Multiple Sizes and Colors Available | C28: EliteField | D28: 29.99 | E28: Pet Supplies | F28: 12784 | G28: 180 | H28: 5398.2 | I28: 534 | J28: 4.3 | K28: FBA | L28: B01CY48OIO | M28: https://www.amazon.com/dp/B01CY48OIO?psc=1 | N28: 1045 | O28: =IFERROR(VLOOKUP(L28,#REF!,5,0),"") | P28: =G28/SUM($G$2:$G$161) -> 0.0069452483
A29: 77 | B29: Best Pet Supplies Voyager Soft Harness for Pets - No Pull Vest | C29: Best Pet Supplies, Inc. | D29: 13.99 | E29: Pet Supplies | F29: 16620 | G29: 150 | H29: 2098.5 | I29: 1529 | J29: 4.4 | K29: AMZ | L29: B07J4W6KW2 | M29: https://www.amazon.com/dp/B07J4W6KW2?psc=1 | N29: 2186 | O29: =IFERROR(VLOOKUP(L29,#REF!,5,0),"") | P29: =G29/SUM($G$2:$G$161) -> 0.0057877069
A30: 81 | B30: 骞垮憡-Kamots Beauty Escape Proof Cat Harness and Leash for Walking Adjustable Soft Mesh Pet Vest with Lead for Kitten | C30: Kamots Beauty | D30: 11.48 | E30: Pet Supplies | F30: 17750 | G30: 120 | H30: 1377.6 | I30: 41 | J30: 3.9 | K30: FBA | L30: B07LGS8M36 | M30: https://www.amazon.com/dp/B07LGS8M36?psc=1 | N30: 159 | O30: =IFERROR(VLOOKUP(L30,#REF!,5,0),"") | P30: =G30/SUM($G$2:$G$161) -> 0.0046301655
A31: 102 | B31: BINGPET Escape Proof Cat Harness with Leash - Adjustable Soft Mesh Vest for Walking | C31: BINGPET | D31: 12.99 | E31: Pet Supplies | F31: 19836 | G31: 120 | H31: 1558.8 | I31: 12 | J31: 4.2 | K31: FBA | L31: B07PNFDG8P | M31: https://www.amazon.com/dp/B07PNFDG8P?psc=1 | N31: 150 | O31: =IFERROR(VLOOKUP(L31,#REF!,5,0),"") | P31: =G31/SUM($G$2:$G$161) -> 0.0046301655
A32: 56 | B32: Kamots Beauty Escape Proof Cat Harness and Leash for Walking Adjustable Soft Mesh Pet Vest with Lead for Kitten | C32: Kamots Beauty | D32: 11.48 | E32: Pet Supplies | F32: 17750 | G32: 120 | H32: 1377.6 | I32: 41 | J32: 3.9 | K32: FBA | L32: B07LGS8M36 | M32: https://www.amazon.com/dp/B07LGS8M36?psc=1 | N32: 159 | O32: =IFERROR(VLOOKUP(L32,#REF!,5,0),"") | P32: =G32/SUM($G$2:$G$161) -> 0.0046301655
A33: 121 | B33: Rella Home Cat Harness and Leash Adjustable Nylon Halter Harness Kitten Nylon Strap Belt Safety Rope Leads | C33: Rella Home | D33: 7.99 | E33: Pet Supplies | F33: 18783 | G33: 120 | H33: 958.8 | I33: 88 | J33: 4.1 | K33: FBA | L33: B0753J3RBC | M33: https://www.amazon.com/dp/B0753J3RBC?psc=1 | N33: 473 | O33: =IFERROR(VLOOKUP(L33,#REF!,5,0),"") | P33: =G33/SUM($G$2:$G$161) -> 0.0046301655
... A69: 92 | B69: TOMKAS Small Dog Cat Carrier Sling Hands Free Pet Puppy Outdoor Travel Bag Tote Reversible | C69: TOMKAS | D69: 19.99 | E69: Pet Supplies | F69: 1483 | G69: 74 | H69: 1479.26 | I69: 920 | J69: 4.3 | K69: FBA | L69: B01M5D90I0 | M69: https://www.amazon.com/dp/B01M5D90I0?psc=1 | N69: 241 | O69: =IFERROR(VLOOKUP(L69,#REF!,5,0),"") | P69: =G69/SUM($G$2:$G$161) -> 0.0028552687
A70: 128 | B70: XPangle No Pull Dog Harness Easy Walk, Adjustable Escape Proof Pet Harness Outdoor for Small Medium Large Dogs | C70: XPangle | D70: 12.99 | E70: Pet Supplies | F70: 150395 | G70: 74 | H70: 961.26 | I70: 0 | J70: N.A. | K70: FBA | L70: B07QM55LKZ | M70: https://www.amazon.com/dp/B07QM55LKZ?psc=1 | N70: 49 | O70: =IFERROR(VLOOKUP(L70,#REF!,5,0),"") | P70: =G70/SUM($G$2:$G$161) -> 0.0028552687
A71: 123 | B71: Hamilton 3/8-Inch Adjustable Reflective Figure 8 Pup-Cat Harness | C71: Hamilton | D71: 18.75 | E71: Pet Supplies | F71: 152809 | G71: 74 | H71: 1387.5 | I71: 18 | J71: 3.3 | K71: AMZ | L71: B00E1C2T3E | M71: https://www.amazon.com/dp/B00E1C2T3E?psc=1 | N71: 1811 | O71: =IFERROR(VLOOKUP(L71,#REF!,5,0),"") | P71: =G71/SUM($G$2:$G$161) -> 0.0028552687
A72: 153 | B72: SlowTon Dog Car Harness Plus Connector Strap, Multifunction Adjustable Vest Harness Double Breathable Mesh Fabric with Car Vehicle Safety Seat Belt | C72: SlowTon | D72: 14.99 | E72: Pet Supplies | F72: 45302 | G72: 69 | H72: 1034.31 | I72: 953 | J72: 4.5 | K72: FBA | L72: B07F75Q3ZW | M72: https://www.amazon.com/dp/B07F75Q3ZW?psc=1 | N72: 714 | O72: =IFERROR(VLOOKUP(L72,#REF!,5,0),"") | P72: =G72/SUM($G$2:$G$161) -> 0.0026623452
A73: 87 | B73: OFPUPPY Escape Proof Cat Harness and Leash Set Adjustable - Soft Mesh - for Kitty Kitten Walking Black | C73: OFPUPPY | D73: 10.99 | E73: Pet Supplies | F73: 91540 | G73: 68 | H73: 747.32 | I73: 22 | J73: 3.7 | K73: FBA | L73: B07FCDWH3Z | M73: https://www.amazon.com/dp/B07FCDWH3Z?psc=1 | N73: 241 | O73: =IFERROR(VLOOKUP(L73,#REF!,5,0),"") | P73: =G73/SUM($G$2:$G$161) -> 0.0026237605
A74: 38 | B74: 骞垮憡-Unihubys Cat Harness with Leash Set- Adjustable Embroidered Bee H Style Harness and Leash for Walking | C74: Unihubys | D74: 10.99 | E74: Pet Supplies | F74: 121441 | G74: 68 | H74: 747.32 | I74: 0 | J74: N.A. | K74: FBA | L74: B07RM3T9B6 | M74: https://www.amazon.com/dp/B07RM3T9B6?psc=1 | N74: 1099 | O74: =IFERROR(VLOOKUP(L74,#REF!,5,0),"") | P74: =G74/SUM($G$2:$G$161) -> 0.0026237605
A75: 90 | B75: Coastal Pet Products CCP7348NPK Nylon Right Adjustable Figure 8 Cat Harness, Neon Pink | C75: Coastal Pet | D75: 13.92 | E75: Pet Supplies | F75: 166174 | G75: 68 | H75: 946.56 | I75: 25 | J75: 4.1 | K75: FBA | L75: B004LO7M4S | M75: https://www.amazon.com/dp/B004LO7M4S?psc=1 | N75: 3396 | O75: =IFERROR(VLOOKUP(L75,#REF!,5,0),"") | P75: =G75/SUM($G$2:$G$161) -> 0.0026237605
A76: 130 | B76: Stock Show Pet Cat Harness with Lead Leash Set Cat Reflective Adjustable Mesh Paddded Chest Harness Escape Proof Harness for Outdoor Walking Jogging for Cat, 12-16, Mint Green | C76: Stock Show | D76: 9.99 | E76: Pet Supplies | F76: 48325 | G76: 63 | H76: 629.37 | I76: 5 | J76: 3.1 | K76: FBA | L76: B07GNDW9Y7 | M76: https://www.amazon.com/dp/B07GNDW9Y7?psc=1 | N76: 221 | O76: =IFERROR(VLOOKUP(L76,#REF!,5,0),"") | P76: =G76/SUM($G$2:$G$161) -> 0.0024308369
A77: 6 | B77: Didog Adjustable Pet Mesh Vest Harness and Leash Set with Cute Bell for Puppy Small Medium Dogs and Cats | C77: Didog | D77: 11.59 | E77: Pet Supplies | F77: 116053 | G77: 63 | H77: 730.17 | I77: 96 | J77: 3.9 | K77: FBA | L77: B0721MH5QH | M77: https://www.amazon.com/dp/B0721MH5QH?psc=1 | N77: 670 | O77: =IFERROR(VLOOKUP(L77,#REF!,5,0),"") | P77: =G77/SUM($G$2:$G$161) -> 0.0024308369
A78: 91 | B78: Smdoxi Dog Puppy Harness Leash Collar Cat Vest Strap with Angel Wings (Pink, XS) | C78: Smdoxi | D78: 2.99 | E78: N.A. | F78: N.A. | G78: 63 | H78: 188.37 | I78: 5 | J78: 4.5 | K78: FBA | L78: B079QVHVHT | M78: https://www.amazon.com/dp/B079QVHVHT?psc=1 | N78: 2517 | O78: =IFERROR(VLOOKUP(L78,#REF!,5,0),"") | P78: =G78/SUM($G$2:$G$161) -> 0.0024308369
A79: 33 | B79: Red Dingo Classic Cat Harness and Lead Combo | C79: Red Dingo | D79: 15.9 | E79: Pet Supplies | F79: 144485 | G79: 63 | H79: 1001.7 | I79: 17 | J79: 3.3 | K79: AMZ | L79: B0088VPH3S | M79: https://www.amazon.com/dp/B0088VPH3S?psc=1 | N79: 2193 | O79: =IFERROR(VLOOKUP(L79,#REF!,5,0),"") | P79: =G79/SUM($G$2:$G$161) -> 0.0024308369
A80: 36 | B80: Forestpaw Skull Dog Harness for Small Dogs - Dog Cat Private Harness and Leash Set - Soft Mesh Pet Harness for Yorkies,Chihuahua,Poodles,Terriers,Beagles Puppy | C80: Forestpaw | D80: 16.99 | E80: Pet Supplies | F80: 49647 | G80: 60 | H80: 1019.4 | I80: 0 | J80: N.A. | K80: FBA | L80: B07GJBKWY7 | M80: https://www.amazon.com/dp/B07GJBKWY7?psc=1 | N80: 172 | O80: =IFERROR(VLOOKUP(L80,#REF!,5,0),"") | P80: =G80/SUM($G$2:$G$161) -> 0.0023150828
A81: 144 | B81: Dexil Luxury Cat Harness Padded and Water Resistant | C81: Dexil Limited | D81: 11.99 | E81: Pet Supplies | F81: 111337 | G81: 60 | H81: 719.4 | I81: 175 | J81: 3.5 | K81: FBA | L81: B01EHWTQXS | M81: https://www.amazon.com/dp/B01EHWTQXS?psc=1 | N81: 387 | O81: =IFERROR(VLOOKUP(L81,#REF!,5,0),"") | P81: =G81/SUM($G$2:$G$161) -> 0.0023150828
A82: 95 | B82: Puppia Basic Soft Harness by Gray | C82: PUPPIA International | D82: 13.99 | E82: Pet Supplies | F82: 49605 | G82: 60 | H82: 839.4 | I82: 59 | J82: 4.4 | K82: AMZ | L82: B001A5IYIE | M82: https://www.amazon.com/dp/B001A5IYIE?psc=1 | N82: 1166 | O82: =IFERROR(VLOOKUP(L82,#REF!,5,0),"") | P82: =G82/SUM($G$2:$G$161) -> 0.0023150828
A83: 132 | B83: senye Cat Harness with Leash,Puppy Dog Training Leashes,Adjustable Soft Nylon Reflective Vest for Walking Running | C83: senye | D83: 11.99 | E83: Pet Supplies | F83: 50857 | G83: 58 | H83: 695.42 | I83: 8 | J83: 5 | K83: FBA | L83: B07PHXBM76 | M83: https://www.amazon.com/dp/B07PHXBM76?psc=1 | N83: 43 | O83: =IFERROR(VLOOKUP(L83,#REF!,5,0),"") | P83: =G83/SUM($G$2:$G$161) -> 0.0022379133
A84: 65 | B84: Niteangel 2 Pack of Adjustable Cat Harness & Leash Set | C84: Niteangel | D84: 11.69 | E84: Pet Supplies | F84: 73148 | G84: 58 | H84: 678.02 | I84: 83 | J84: 4.2 | K84: FBA | L84: B079GNM2C7 | M84: https://www.amazon.com/dp/B079GNM2C7?psc=1 | N84: 394 | O84: =IFERROR(VLOOKUP(L84,#REF!,5,0),"") | P84: =G84/SUM($G$2:$G$161) -> 0.0022379133
A85: 113 | B85: Bond & Co. Buffalo-Check Cat Harness and Leash Set | C85: Bond | D85: 19.99 | E85: Pet Supplies | F85: 196270 | G85: 51 | H85: 1019.49 | I85: 0 | J85: N.A. | K85: FBA | L85: B07K28MM9Y | M85: https://www.amazon.com/dp/B07K28MM9Y?psc=1 | N85: 177 | O85: =IFERROR(VLOOKUP(L85,#REF!,5,0),"") | P85: =G85/SUM($G$2:$G$161) -> 0.0019678203
A86: 99 | B86: JOEJOY Dog Cat Harness Escape Proof Freedom No Pull Dog Harnesses Reflective Adjustable Vest for Small Medium Dogs | C86: JOEJOY | D86: 7.99 | E86: Pet Supplies | F86: 58453 | G86: 43 | H86: 343.57 | I86: 25 | J86: 4.2 | K86: FBA | L86: B07J38MDY9 | M86: https://www.amazon.com/dp/B07J38MDY9?psc=1 | N86: 195 | O86: =IFERROR(VLOOKUP(L86,#REF!,5,0),"") | P86: =G86/SUM($G$2:$G$161) -> 0.0016591426
A87: 143 | B87: Red Dingo Designer Cat Harness and Lead Combo | C87: Red Dingo | D87: 20.16 | E87: Pet Supplies | F87: 168350 | G87: 43 | H87: 866.88 | I87: 11 | J87: 3.8 | K87: AMZ | L87: B0088VPFVM | M87: https://www.amazon.com/dp/B0088VPFVM?psc=1 | N87: 2111 | O87: =IFERROR(VLOOKUP(L87,#REF!,5,0),"") | P87: =G87/SUM($G$2:$G$161) -> 0.0016591426
A88: 145 | B88: FLAdorepet 3Pcs Pink Flower Dog Dress Harness with Matching Leash Set Small Dog Pet Cat Clothes Shirt Costume Dog Skirt,Dress,Hair Bow | C88: FLAdorepet | D88: 23.9 | E88: Pet Supplies | F88: 326777 | G88: 43 | H88: 1027.7 | I88: 0 | J88: N.A. | K88: FBA | L88: B07NYN2S98 | M88: https://www.amazon.com/dp/B07NYN2S98?psc=1 | N88: 346 | O88: =IFERROR(VLOOKUP(L88,#REF!,5,0),"") | P88: =G88/SUM($G$2:$G$161) -> 0.0016591426
A89: 134 | B89: MyfatBOSS Dog and Cat Universal Harness, Escape Proof Cat Harnesses with Leashes, Soft Mesh Dog Cat Harness - Perfect for Pet Cat and Puppy | C89: MyfatBOSS | D89: 10.99 | E89: Pet Supplies | F89: 228279 | G89: 43 | H89: 472.57 | I89: 1 | J89: 5 | K89: FBA | L89: B07JFPMLPD | M89: https://www.amazon.com/dp/B07JFPMLPD?psc=1 | N89: 49 | O89: =IFERROR(VLOOKUP(L89,#REF!,5,0),"") | P89: =G89/SUM($G$2:$G$161) -> 0.0016591426
A90: 11 | B90: Gooby - Comfort X Head-In Harness, Choke Free Small Dog Harness with Micro Suede Trimming and Patented X Frame | C90: Gooby | D90: 26.25 | E90: Pet Supplies | F90: 92498 | G90: 43 | H90: 1128.75 | I90: 536 | J90: 4.2 | K90: AMZ | L90: B01BF5N6XG | M90: https://www.amazon.com/dp/B01BF5N6XG?psc=1 | N90: 2517 | O90: =IFERROR(VLOOKUP(L90,#REF!,5,0),"") | P90: =G90/SUM($G$2:$G$161) -> 0.0016591426
A91: 104 | B91: Mynwood Cat Jacket/Harness Blue Adult Cat | C91: Mynwood Cat Jacket | D91: 28 | E91: Pet Supplies | F91: 177173 | G91: 43 | H91: 1204 | I91: 14 | J91: 5 | K91: FBA | L91: B00UTZZA3I | M91: https://www.amazon.com/dp/B00UTZZA3I?psc=1 | N91: 1099 | O91: =IFERROR(VLOOKUP(L91,#REF!,5,0),"") | P91: =G91/SUM($G$2:$G$161) -> 0.0016591426
A92: 52 | B92: Puppia Authentic Neon Soft Harness A, Orange, Small | C92: Puppia | D92: 21.98 | E92: Pet Supplies | F92: 223421 | G92: 43 | H92: 945.14 | I92: 30 | J92: 4.1 | K92: AMZ | L92: B00UM9OY24 | M92: https://www.amazon.com/dp/B00UM9OY24?psc=1 | N92: 1444 | O92: =IFERROR(VLOOKUP(L92,#REF!,5,0),"") | P92: =G92/SUM($G$2:$G$161) -> 0.0016591426
A93: 8 | B93: 骞垮憡-WONDERPUP Adjustable Cat Harness with Leash Set for Walking Escape Proof Soft Air Mesh for Kitty Puppy Rabbits Small Dogs Animal | C93: WONDERPUP | D93: 12.99 | E93: Pet Supplies | F93: 182758 | G93: 43 | H93: 558.57 | I93: 17 | J93: 3.9 | K93: FBA | L93: B07GGQWFM7 | M93: https://www.amazon.com/dp/B07GGQWFM7?psc=1 | N93: 238 | O93: =IFERROR(VLOOKUP(L93,#REF!,5,0),"") | P93: =G93/SUM($G$2:$G$161) -> 0.0016591426
A94: 93 | B94: 骞垮憡-T.A.Bird Bulldog Reversible Harness No Pull Dog Harness Vest Harness for Small Medium Large Dog | C94: T.A.Bird | D94: 23.99 | E94: Pet Supplies | F94: 162055 | G94: 43 | H94: 1031.57 | I94: 3 | J94: 5 | K94: FBA | L94: B07JQVM2WF | M94: https://www.amazon.com/dp/B07JQVM2WF?psc=1 | N94: 66 | O94: =IFERROR(VLOOKUP(L94,#REF!,5,0),"") | P94: =G94/SUM($G$2:$G$161) -> 0.0016591426
A95: 20 | B95: Pet Club No Pull Dog/Cat Harness and Leash Set for Walking, Padded Dog Vest Harnesses for Puppy Small Dogs/Cats, Cat Dog Training Collar Pink,XS,S | C95: Pet Club | D95: 9.99 | E95: Pet Supplies | F95: 143764 | G95: 43 | H95: 429.57 | I95: 53 | J95: 3.8 | K95: FBA | L95: B01N9O3YGS | M95: https://www.amazon.com/dp/B01N9O3YGS?psc=1 | N95: 649 | O95: =IFERROR(VLOOKUP(L95,#REF!,5,0),"") | P95: =G95/SUM($G$2:$G$161) -> 0.0016591426
A96: 5 | B96: Mesh Cat Harness and Leash - Escape Proof Harness for Puppy, Cats, Small Dogs | C96: PAWCHIE | D96: 10.99 | E96: Pet Supplies | F96: 58834 | G96: 42 | H96: 461.58 | I96: 0 | J96: N.A. | K96: FBA | L96: B07PGCSFXH | M96: https://www.amazon.com/dp/B07PGCSFXH?psc=1 | N96: 1045 | O96: =IFERROR(VLOOKUP(L96,#REF!,5,0),"") | P96: =G96/SUM($G$2:$G$161) -> 0.0016205579
A97: 30 | B97: Lanyar Reflective Mesh Soft Dog Harness Safe Harness No Pull Pet Harnesses for Dogs,Size Runs Smaller,Small Fits 2-4lbs,Medium 6-10lbs | C97: Lanyar | D97: 9.98 | E97: Pet Supplies | F97: 129339 | G97: 42 | H97: 419.16 | I97: 355 | J97: 3.9 | K97: FBA | L97: B00LIE5XD6 | M97: https://www.amazon.com/dp/B00LIE5XD6?psc=1 | N97: 1710 | O97: =IFERROR(VLOOKUP(L97,#REF!,5,0),"") | P97: =G97/SUM($G$2:$G$161) -> 0.0016205579
A98: 16 | B98: Meeyou Adjustable Soft Mesh Cat Harness with Leash | C98: Meeyou | D98: 6.99 | E98: Pet Supplies | F98: 62121 | G98: 35 | H98: 244.65 | I98: 222 | J98: 3.6 | K98: FBA | L98: B01FJPBUF4 | M98: https://www.amazon.com/dp/B01FJPBUF4?psc=1 | N98: 1026 | O98: =IFERROR(VLOOKUP(L98,#REF!,5,0),"") | P98: =G98/SUM($G$2:$G$161) -> 0.0013504649
A99: 154 | B99: Cat Harness, Adjustable Harness Nylon Strap Collar with Leash, Cat Leash and Harness Set, for Cat and Small Pet Walking | C99: Love Pet Home | D99: 9.99 | E99: Pet Supplies | F99: 211426 | G99: 34 | H99: 339.66 | I99: 2 | J99: 1 | K99: FBA | L99: B07P9G9YJ5 | M99: https://www.amazon.com/dp/B07P9G9YJ5?psc=1 | N99: 58 | O99: =IFERROR(VLOOKUP(L99,#REF!,5,0),"") | P99: =G99/SUM($G$2:$G$161) -> 0.0013118802
A100: 21 | B100: Best Pet Supplies Voyager Fully Adjustable Step-in Mesh Harness with Reflective 3M Piping | C100: Best Pet Supplies, Inc. | D100: 13.99 | E100: Pet Supplies | F100: 124475 | G100: 34 | H100: 475.66 | I100: 27 | J100: 4.4 | K100: AMZ | L100: B07K4YX534 | M100: https://www.amazon.com/dp/B07K4YX534?psc=1 | N100: 177 | O100: =IFERROR(VLOOKUP(L100,#REF!,5,0),"") | P100: =G100/SUM($G$2:$G$161) -> 0.0013118802
A101: 51 | B101: Mynwood Cat Jacket/Harness Skulls Adult Cat | C101: Mynwood Cat Jacket | D101: 28 | E101: Pet Supplies | F101: 195585 | G101: 34 | H101: 952 | I101: 20 | J101: 4.5 | K101: FBA | L101: B00UU2JAF4 | M101: https://www.amazon.com/dp/B00UU2JAF4?psc=1 | N101: 1110 | O101: =IFERROR(VLOOKUP(L101,#REF!,5,0),"") | P101: =G101/SUM($G$2:$G$161) -> 0.0013118802
A102: 98 | B102: 1 Pc Pet Puppy Dog Harness Velvet & Leather Leash for Small Dog Puppy Cat Harness Leash Dog Accessories S | C102: TO_GeT For Pet Accessories TgT | D102: 16 | E102: N.A. | F102: N.A. | G102: 34 | H102: 544 | I102: 0 | J102: N.A. | K102: FBA | L102: B07H3R1V2Q | M102: https://www.amazon.com/dp/B07H3R1V2Q?psc=1 | N102: 984 | O102: =IFERROR(VLOOKUP(L102,#REF!,5,0),"") | P102: =G102/SUM($G$2:$G$161) -> 0.0013118802
A103: 70 | B103: HOUNDNINE Escape Proof Cat Harness - Holster Style Adjustable Body Soft Mesh - Best for Walking | C103: HOUNDNINE | D103: 7.99 | E103: Pet Supplies | F103: 196576 | G103: 34 | H103: 271.66 | I103: 13 | J103: 3.4 | K103: FBA | L103: B07B4KV7HY | M103: https://www.amazon.com/dp/B07B4KV7HY?psc=1 | N103: 371 | O103: =IFERROR(VLOOKUP(L103,#REF!,5,0),"") | P103: =G103/SUM($G$2:$G$161) -> 0.0013118802
A104: 116 | B104: Sport Ni Christmas Cat Harness and Leash Set, Durable Nylon Chest Strap Halter Walking Rope Leads for Kitty Pet Small Animals Size Adjustable | C104: Sport Ni | D104: 5.99 | E104: Pet Supplies | F104: 68650 | G104: 34 | H104: 203.66 | I104: 0 | J104: N.A. | K104: FBA | L104: B07KQ2SD52 | M104: https://www.amazon.com/dp/B07KQ2SD52?psc=1 | N104: 390 | O104: =IFERROR(VLOOKUP(L104,#REF!,5,0),"") | P104: =G104/SUM($G$2:$G$161) -> 0.0013118802
A105: 138 | B105: SMALLLEE_LUCKY_STORE Small Dog Tuxedo Harness for Boy, Adjustable Soft Mesh Cat Harness Vest Leash Set | C105: smalllee_lucky_store | D105: 9.99 | E105: Pet Supplies | F105: 136291 | G105: 34 | H105: 339.66 | I105: 15 | J105: 3.4 | K105: FBA | L105: B074FY9Q4R | M105: https://www.amazon.com/dp/B074FY9Q4R?psc=1 | N105: 416 | O105: =IFERROR(VLOOKUP(L105,#REF!,5,0),"") | P105: =G105/SUM($G$2:$G$161) -> 0.0013118802
A106: 76 | B106: 骞垮憡-YujueShop Cat Harness and Leash Dog Harness Walking Adjustable Soft Mesh Pet Vest with Lead Re-Adjustable Pet Leash with Reflective Material and Metal Button Suit for Most Sizes of Pet | C106: YujueShop | D106: 11.99 | E106: Pet Supplies | F106: 82759 | G106: 34 | H106: 407.66 | I106: 3 | J106: 4.6 | K106: FBA | L106: B07PHY5FPN | M106: https://www.amazon.com/dp/B07PHY5FPN?psc=1 | N106: 15 | O106: =IFERROR(VLOOKUP(L106,#REF!,5,0),"") | P106: =G106/SUM($G$2:$G$161) -> 0.0013118802
A107: 129 | B107: 骞垮憡-Pet Club No Pull Dog/Cat Harness Leash Set Escape Proof Walking, Super Comfort Fully Adjustable Double Padded Step in Dog Harness, Cat Dog Training Collar | C107: Pet Club | D107: 14.95 | E107: Pet Supplies | F107: 121347 | G107: 34 | H107: 508.3 | I107: 45 | J107: 3.9 | K107: FBA | L107: B07CWL5JYZ | M107: https://www.amazon.com/dp/B07CWL5JYZ?psc=1 | N107: 313 | O107: =IFERROR(VLOOKUP(L107,#REF!,5,0),"") | P107: =G107/SUM($G$2:$G$161) -> 0.0013118802
A108: 35 | B108: QBLEEV Cat Harness Vest Leash Set | C108: QBLEEV | D108: 13.99 | E108: Pet Supplies | F108: 466219 | G108: 34 | H108: 475.66 | I108: 0 | J108: N.A. | K108: FBA | L108: B07MPZZLGF | M108: https://www.amazon.com/dp/B07MPZZLGF?psc=1 | N108: 48 | O108: =IFERROR(VLOOKUP(L108,#REF!,5,0),"") | P108: =G108/SUM($G$2:$G$161) -> 0.0013118802
A109: 126 | B109: Didog Soft Mesh Padded Dog Cat Vest Harness Leash Set,Dog Cat Body Harness for Puppy Small Dogs and Cats | C109: Didog | D109: 8.99 | E109: Pet Supplies | F109: 152140 | G109: 34 | H109: 305.66 | I109: 14 | J109: 3.3 | K109: FBA | L109: B07D49NBBS | M109: https://www.amazon.com/dp/B07D49NBBS?psc=1 | N109: 217 | O109: =IFERROR(VLOOKUP(L109,#REF!,5,0),"") | P109: =G109/SUM($G$2:$G$161) -> 0.0013118802
A110: 31 | B110: FLAdorepet Cat Hooded Vest Harness and Leash Adjustable Soft Mesh Kitten Harness Jacket Vest with Leash for Cats Puppy Safety Walk/Run | C110: FLAdorepet | D110: 13.9 | E110: Pet Supplies | F110: 407053 | G110: 34 | H110: 472.6 | I110: 0 | J110: N.A. | K110: FBA | L110: B07PVHGPCX | M110: https://www.amazon.com/dp/B07PVHGPCX?psc=1 | N110: 246 | O110: =IFERROR(VLOOKUP(L110,#REF!,5,0),"") | P110: =G110/SUM($G$2:$G$161) -> 0.0013118802
A111: 106 | B111: MyfatBOSS Cat Leash, Cat Harness and Leash, Adjustable Pet Mesh Vest Leashes for Small Large Cats Walking Escape Proof | C111: MyfatBOSS | D111: 13.99 | E111: Pet Supplies | F111: 268133 | G111: 34 | H111: 475.66 | I111: 8 | J111: 3.6 | K111: FBA | L111: B07F6DY2YJ | M111: https://www.amazon.com/dp/B07F6DY2YJ?psc=1 | N111: 233 | O111: =IFERROR(VLOOKUP(L111,#REF!,5,0),"") | P111: =G111/SUM($G$2:$G$161) -> 0.0013118802
A112: 151 | B112: 骞垮憡-WONDERPUP Reflective Dog Cat Harness No Pull Soft Mesh Adjustable Safe Harness for Small and Medium | C112: WONDERPUP | D112: 11.69 | E112: Pet Supplies | F112: 209678 | G112: 34 | H112: 397.46 | I112: 4 | J112: 5 | K112: FBA | L112: B07KSSGKZP | M112: https://www.amazon.com/dp/B07KSSGKZP?psc=1 | N112: 98 | O112: =IFERROR(VLOOKUP(L112,#REF!,5,0),"") | P112: =G112/SUM($G$2:$G$161) -> 0.0013118802
A113: 50 | B113: PAWISE Adjustable Cat Harness with 4ft. Leash, Nylon Material, Red/Blue | C113: PAWISE | D113: 11.99 | E113: Pet Supplies | F113: 209032 | G113: 34 | H113: 407.66 | I113: 0 | J113: N.A. | K113: FBA | L113: B07FTD2M1S | M113: https://www.amazon.com/dp/B07FTD2M1S?psc=1 | N113: 1079 | O113: =IFERROR(VLOOKUP(L113,#REF!,5,0),"") | P113: =G113/SUM($G$2:$G$161) -> 0.0013118802
A114: 23 | B114: Wiz BBQT Purple Bright Soft Comfortable Mesh Heart Printed Dog Cat Pet Vest Harness and Matching Leash Set for Dogs Cats | C114: Wiz BBQT | D114: 10.99 | E114: Pet Supplies | F114: 63610 | G114: 32 | H114: 351.68 | I114: 27 | J114: 3.9 | K114: FBA | L114: B01LYGJ92P | M114: https://www.amazon.com/dp/B01LYGJ92P?psc=1 | N114: 858 | O114: =IFERROR(VLOOKUP(L114,#REF!,5,0),"") | P114: =G114/SUM($G$2:$G$161) -> 0.0012347108
A115: 75 | B115: SHUNAI Cat Harness, No Pull Padded Vest for Pet, Adjustable and Reflective Design,Nylon Material Great Fit for Exotic,Ragdoll,British Shorthair,Persian,Maine Coon Cat, Large Size(Not Include Leash) | C115: shunai | D115: 15.99 | E115: Pet Supplies | F115: 192532 | G115: 28 | H115: 447.72 | I115: 19 | J115: 3.5 | K115: FBA | L115: B07D4DQ1BM | M115: https://www.amazon.com/dp/B07D4DQ1BM?psc=1 | N115: 293 | O115: =IFERROR(VLOOKUP(L115,#REF!,5,0),"") | P115: =G115/SUM($G$2:$G$161) -> 0.001080372
A116: 119 | B116: Bright Mesh Heart Printed Dog Cat Pet Vest Harness and Matching Leash Set in Blue for Dogs Cats | C116: Wiz BBQT | D116: 10.99 | E116: Pet Supplies | F116: 163334 | G116: 28 | H116: 307.72 | I116: 28 | J116: 4 | K116: FBA | L116: B01LWTYH6Z | M116: https://www.amazon.com/dp/B01LWTYH6Z?psc=1 | N116: 925 | O116: =IFERROR(VLOOKUP(L116,#REF!,5,0),"") | P116: =G116/SUM($G$2:$G$161) -> 0.001080372
A117: 40 | B117: T.A.Bird Bulldog Reversible Harness No Pull Dog Harness Vest Harness for Small Medium Large Dog | C117: T.A.Bird | D117: 23.99 | E117: Pet Supplies | F117: 681151 | G117: 28 | H117: 671.72 | I117: 3 | J117: 5 | K117: FBA | L117: B07JQFL9RW | M117: https://www.amazon.com/dp/B07JQFL9RW?psc=1 | N117: 66 | O117: =IFERROR(VLOOKUP(L117,#REF!,5,0),"") | P117: =G117/SUM($G$2:$G$161) -> 0.001080372
A118: 122 | B118: Lukovee Dog Safety Vest Harness with Seatbelt, Dog Car Harness Seat Belt Adjustable Pet Harnesses Double Breathable Mesh Fabric with Car Vehicle Connector Strap for Dog | C118: Lukovee | D118: 11.99 | E118: Pet Supplies | F118: 118623 | G118: 28 | H118: 335.72 | I118: 141 | J118: 4.4 | K118: FBA | L118: B07F245Z57 | M118: https://www.amazon.com/dp/B07F245Z57?psc=1 | N118: 649 | O118: =IFERROR(VLOOKUP(L118,#REF!,5,0),"") | P118: =G118/SUM($G$2:$G$161) -> 0.001080372
A119: 110 | B119: Puppia Soft Vest Harness B | C119: PUPPIA International | D119: 18.4 | E119: Pet Supplies | F119: 83413 | G119: 28 | H119: 515.2 | I119: 1791 | J119: 4.3 | K119: AMZ | L119: B007AW4DDG | M119: https://www.amazon.com/dp/B007AW4DDG?psc=1 | N119: 3832 | O119: =IFERROR(VLOOKUP(L119,#REF!,5,0),"") | P119: =G119/SUM($G$2:$G$161) -> 0.001080372
A120: 115 | B120: 骞垮憡-WONDERPUP Plaid Dog Cat Harness with Comfort Soft Mesh No Pull Durable for Small Puppy Walking | C120: WONDERPUP | D120: 9.99 | E120: Pet Supplies | F120: 95932 | G120: 28 | H120: 279.72 | I120: 20 | J120: 4.6 | K120: FBA | L120: B0798G43BW | M120: https://www.amazon.com/dp/B0798G43BW?psc=1 | N120: 339 | O120: =IFERROR(VLOOKUP(L120,#REF!,5,0),"") | P120: =G120/SUM($G$2:$G$161) -> 0.001080372
A121: 22 | B121: Kitty Holster Harness M/L Poppy - Litterboy Exclusive | C121: Kitty Holster | D121: 24.95 | E121: Pet Supplies | F121: 148383 | G121: 28 | H121: 698.6 | I121: 1 | J121: 5 | K121: FBA | L121: B0181D98XW | M121: https://www.amazon.com/dp/B0181D98XW?psc=1 | N121: 638 | O121: =IFERROR(VLOOKUP(L121,#REF!,5,0),"") | P121: =G121/SUM($G$2:$G$161) -> 0.001080372
A122: 1 | B122: Mynwood Cat Jacket/Harness Cheetah Adult Cat | C122: Mynwood Cat Jacket | D122: 28 | E122: Pet Supplies | F122: 258938 | G122: 28 | H122: 784 | I122: 6 | J122: 5 | K122: FBA | L122: B00UU30XD6 | M122: https://www.amazon.com/dp/B00UU30XD6?psc=1 | N122: 1061 | O122: =IFERROR(VLOOKUP(L122,#REF!,5,0),"") | P122: =G122/SUM($G$2:$G$161) -> 0.001080372
A123: 34 | B123: TSA Fast Pass Leash Harness - Medium (see sizing Chart) | C123: TSA Fast Pass | D123: 21.99 | E123: Pet Supplies | F123: 127263 | G123: 28 | H123: 615.72 | I123: 33 | J123: 3.8 | K123: FBA | L123: B008AWCLFM | M123: https://www.amazon.com/dp/B008AWCLFM?psc=1 | N123: 2483 | O123: =IFERROR(VLOOKUP(L123,#REF!,5,0),"") | P123: =G123/SUM($G$2:$G$161) -> 0.001080372
A124: 120 | B124: Voyager Adjustable Harness with 3M Reflective Technology by Best Pet Supplies | C124: Best Pet Supplies, Inc. | D124: 19.99 | E124: Pet Supplies | F124: 110970 | G124: 28 | H124: 559.72 | I124: 73 | J124: 4.1 | K124: FBA | L124: B071V53L89 | M124: https://www.amazon.com/dp/B071V53L89?psc=1 | N124: 717 | O124: =IFERROR(VLOOKUP(L124,#REF!,5,0),"") | P124: =G124/SUM($G$2:$G$161) -> 0.001080372
A125: 67 | B125: Good2Go Aqua and Coral Chevron Cat Harness and Leash Set | C125: Good2Go | D125: 19.99 | E125: Pet Supplies | F125: 335309 | G125: 27 | H125: 539.73 | I125: 0 | J125: N.A. | K125: FBA | L125: B074RJ8YTC | M125: https://www.amazon.com/dp/B074RJ8YTC?psc=1 | N125: 49 | O125: =IFERROR(VLOOKUP(L125,#REF!,5,0),"") | P125: =G125/SUM($G$2:$G$161) -> 0.0010417872
A126: 114 | B126: DOGNESS Cat&Small Dogs Package - Three camo Colors, for Walking Training Small Dogs and Cats - Harness and Leash Together | C126: DOGNESS | D126: 19.99 | E126: Pet Supplies | F126: 376053 | G126: 27 | H126: 539.73 | I126: 2 | J126: 5 | K126: FBA | L126: B07DRNHMYP | M126: https://www.amazon.com/dp/B07DRNHMYP?psc=1 | N126: 42 | O126: =IFERROR(VLOOKUP(L126,#REF!,5,0),"") | P126: =G126/SUM($G$2:$G$161) -> 0.0010417872
A127: 124 | B127: Pink Cute Adorable Pet Cat Dog Harness and Leash Set with Lace Artificial Pearl Angel Wing | C127: Wiz BBQT | D127: 12.99 | E127: Pet Supplies | F127: 217447 | G127: 27 | H127: 350.73 | I127: 63 | J127: 3.9 | K127: FBA | L127: B01CHOOT8U | M127: https://www.amazon.com/dp/B01CHOOT8U?psc=1 | N127: 1099 | O127: =IFERROR(VLOOKUP(L127,#REF!,5,0),"") | P127: =G127/SUM($G$2:$G$161) -> 0.0010417872
A128: 10 | B128: Avolare Cat Harness Adjustable Nylon Strap Collar - 2/Pack | C128: Avolare | D128: 9.95 | E128: Pet Supplies | F128: 83593 | G128: 27 | H128: 268.65 | I128: 39 | J128: 3.4 | K128: FBA | L128: B074SZC94G | M128: https://www.amazon.com/dp/B074SZC94G?psc=1 | N128: 602 | O128: =IFERROR(VLOOKUP(L128,#REF!,5,0),"") | P128: =G128/SUM($G$2:$G$161) -> 0.0010417872
A129: 24 | B129: FLAdorepet 3Pcs Pink Flower Dog Dress Harness with Matching Leash Set Small Dog Pet Cat Clothes Shirt Costume Dog Skirt,Dress,Hair Bow | C129: FLAdorepet | D129: 23.9 | E129: Pet Supplies | F129: 326777 | G129: 27 | H129: 645.3 | I129: 0 | J129: N.A. | K129: FBA | L129: B07NYN2S98 | M129: https://www.amazon.com/dp/B07NYN2S98?psc=1 | N129: 235 | O129: =IFERROR(VLOOKUP(L129,#REF!,5,0),"") | P129: =G129/SUM($G$2:$G$161) -> 0.0010417872
A130: 118 | B130: Bond & Co. Donut-Print Hooded Cat Harness and Leash Set | C130: Bond | D130: 19.99 | E130: Pet Supplies | F130: 296613 | G130: 27 | H130: 539.73 | I130: 0 | J130: N.A. | K130: FBA | L130: B07K292JL9 | M130: https://www.amazon.com/dp/B07K292JL9?psc=1 | N130: 164 | O130: =IFERROR(VLOOKUP(L130,#REF!,5,0),"") | P130: =G130/SUM($G$2:$G$161) -> 0.0010417872
A131: 107 | B131: W&Z Cat Kitty Harness and Leash Set for Walking Escape Proof - Adjustable Blue/Pink Cat Walking Jackets with Cute Bowtie - for Small Mediums Large Cats | C131: W&Z | D131: 14.99 | E131: Pet Supplies | F131: 162383 | G131: 27 | H131: 404.73 | I131: 0 | J131: N.A. | K131: FBA | L131: B07HHNSXYG | M131: https://www.amazon.com/dp/B07HHNSXYG?psc=1 | N131: 98 | O131: =IFERROR(VLOOKUP(L131,#REF!,5,0),"") | P131: =G131/SUM($G$2:$G$161) -> 0.0010417872
A132: 149 | B132: voopet Beach Style Soft Dog Harness, Puppy Breathable Mesh Front Padded Vest Harness with Leash, Island Style Pets Adjustable No-Pull Walking Harness - Easy Control for Small Dogs & Cats | C132: voopet | D132: 10.99 | E132: Pet Supplies | F132: 237937 | G132: 25 | H132: 274.75 | I132: 0 | J132: N.A. | K132: FBA | L132: B07MMJS1XV | M132: https://www.amazon.com/dp/B07MMJS1XV?psc=1 | N132: 58 | O132: =IFERROR(VLOOKUP(L132,#REF!,5,0),"") | P132: =G132/SUM($G$2:$G$161) -> 0.00096461782
A133: 4 | B133: Mynwood Cat Jacket/Harness Black Watch Tartan Adult Cat | C133: Mynwood Cat Jacket | D133: 28 | E133: Pet Supplies | F133: 207411 | G133: 25 | H133: 700 | I133: 5 | J133: 5 | K133: FBA | L133: B00UU37X6Q | M133: https://www.amazon.com/dp/B00UU37X6Q?psc=1 | N133: 1161 | O133: =IFERROR(VLOOKUP(L133,#REF!,5,0),"") | P133: =G133/SUM($G$2:$G$161) -> 0.00096461782
A134: 83 | B134: ThinkPet Reflective Breathable Soft Air Mesh No Pull Puppy Dog Vest Harness | C134: ThinkPet | D134: 9.94 | E134: Pet Supplies | F134: 86931 | G134: 25 | H134: 248.5 | I134: 402 | J134: 3.4 | K134: FBA | L134: B07HNZQLBH | M134: https://www.amazon.com/dp/B07HNZQLBH?psc=1 | N134: 1192 | O134: =IFERROR(VLOOKUP(L134,#REF!,5,0),"") | P134: =G134/SUM($G$2:$G$161) -> 0.00096461782
A135: 2 | B135: Kitty Holster Cat Harness, Medium/Large, Gray | C135: Kitty Holster | D135: 24.95 | E135: Pet Supplies | F135: 129567 | G135: 25 | H135: 623.75 | I135: 1 | J135: 2 | K135: FBA | L135: B01FECV6QU | M135: https://www.amazon.com/dp/B01FECV6QU?psc=1 | N135: 390 | O135: =IFERROR(VLOOKUP(L135,#REF!,5,0),"") | P135: =G135/SUM($G$2:$G$161) -> 0.00096461782
A136: 19 | B136: Stock Show Small Pet Summer Spring Cute Cartoon Harness Vest and Matching Polka Dots Lead Leash Set Breathable Soft Mesh Padded Adjustable Chest Strap Hareness for Puppy Kitten Small Animal | C136: Stock Show | D136: 12.99 | E136: Pet Supplies | F136: 137997 | G136: 25 | H136: 324.75 | I136: 15 | J136: 4.7 | K136: FBA | L136: B07BVCGPS6 | M136: https://www.amazon.com/dp/B07BVCGPS6?psc=1 | N136: 358 | O136: =IFERROR(VLOOKUP(L136,#REF!,5,0),"") | P136: =G136/SUM($G$2:$G$161) -> 0.00096461782
A137: 155 | B137: 骞垮憡-WONDERPUP Escape Proof Cat Dog Harness with Leash Set- Adjustable Soft Mesh with D-Ring for Kitty Puppy Rabbits Dogs Animal | C137: WONDERPUP | D137: 16.99 | E137: Pet Supplies | F137: 80760 | G137: 25 | H137: 424.75 | I137: 2 | J137: 3.5 | K137: FBA | L137: B07MW1CQHB | M137: https://www.amazon.com/dp/B07MW1CQHB?psc=1 | N137: 87 | O137: =IFERROR(VLOOKUP(L137,#REF!,5,0),"") | P137: =G137/SUM($G$2:$G$161) -> 0.00096461782
A138: 49 | B138: Decoroom No Pull Dog Harness Padded Cat Harness for Puppy Soft Mesh Reflective Pet Vest Harness | C138: Decoroom | D138: 8.99 | E138: Pet Supplies | F138: 388362 | G138: 25 | H138: 224.75 | I138: 3 | J138: 5 | K138: FBA | L138: B07B9YMYXF | M138: https://www.amazon.com/dp/B07B9YMYXF?psc=1 | N138: 143 | O138: =IFERROR(VLOOKUP(L138,#REF!,5,0),"") | P138: =G138/SUM($G$2:$G$161) -> 0.00096461782
A139: 142 | B139: KZHAREEN Escape Proof Cat Harness with Leash Set Adjustable Soft Mesh for Kitty Puppy Small Dogs Animals | C139: KZHAREEN | D139: 8.99 | E139: Pet Supplies | F139: 107000 | G139: 25 | H139: 224.75 | I139: 4 | J139: 4 | K139: FBA | L139: B07FZY2GNZ | M139: https://www.amazon.com/dp/B07FZY2GNZ?psc=1 | N139: 235 | O139: =IFERROR(VLOOKUP(L139,#REF!,5,0),"") | P139: =G139/SUM($G$2:$G$161) -> 0.00096461782
...

Sheet 竞品分析
A1: ASIN | B1: Brand | C1: Price | D1: Category | E1: Rank | F1: Sales | G1: Revenue | H1: Reviews | I1: Rating | J1: Seller | K1: Link | L1: 上架时间 | M1: 竞品价格 | N1: 竞品数量 | O1: 最低价 | P1: 最高价 | Q1: 竞品销量 | R1: 销量数量 | S1: 最低量 | T1: 最高量 | U1: 价格 | V1: 销量 | X1: 竞品分析
A2: =数据调研!L2 -> B07NQ35VDW | B2: =数据调研!C2 -> Eagloo | C2: =数据调研!D2 -> 13.99 | D2: =数据调研!E2 -> Pet Supplies | E2: =数据调研!F2 -> 764 | F2: =数据调研!G2 -> 2550 | G2: =数据调研!H2 -> 35674.5 | H2: =数据调研!I2 -> 79 | I2: =数据调研!J2 -> 4 | J2: =数据调研!K2 -> FBA | K2: =数据调研!M2 -> https://www.amazon.com/dp/B07NQ35VDW?psc=1 | L2: =数据调研!N2 -> 387 | M2: =IF(AND(AC4<>0,AC4<>"N.A."),AC4,0) -> 13.99 | N2: =IF(M2<>0,1,0) -> 1 | O2: =IF(N2=1,M2,100000) -> 13.99 | P2: =IF(N2=1,M2,0) -> 13.99 | Q2: =IF(AND(AD4<>"N.A.",AD4<>"< 5"),AD4,0) -> 2550 | R2: =IF(Q2<>0,1,0) -> 1 | S2: =IF(R2=1,Q2,10000000) -> 2550 | T2: =IF(R2=1,S2,0) -> 2550 | U2: =M2 -> 13.99 | V2: =Q2 -> 2550
A3: =数据调研!L3 -> B07NQ35VDW | B3: =数据调研!C3 -> Eagloo | C3: =数据调研!D3 -> 13.99 | D3: =数据调研!E3 -> Pet Supplies | E3: =数据调研!F3 -> 764 | F3: =数据调研!G3 -> 2550 | G3: =数据调研!H3 -> 35674.5 | H3: =数据调研!I3 -> 79 | I3: =数据调研!J3 -> 4 | J3: =数据调研!K3 -> FBA | K3: =数据调研!M3 -> https://www.amazon.com/dp/B07NQ35VDW?psc=1 | L3: =数据调研!N3 -> 387 | M3: =IF(AND(AC5<>0,AC5<>"N.A."),AC5,0) -> 13.99 | N3: =IF(M3<>0,1,0) -> 1 | O3: =IF(N3=1,M3,100000) -> 13.99 | P3: =IF(N3=1,M3,0) -> 13.99 | Q3: =IF(AND(AD5<>"N.A.",AD5<>"< 5"),AD5,0) -> 960 | R3: =IF(Q3<>0,1,0) -> 1 | S3: =IF(R3=1,Q3,10000000) -> 960 | T3: =IF(R3=1,S3,0) -> 960 | U3: =M3 -> 13.99 | V3: =Q3 -> 960 | X3: 图片 | AA3: 站点 | AB3: ASIN | AC3: 价格 | AD3: 月销量 | AE3: 品牌 | AF3: 评论数 | AG3: 大类排名 | AH3: 星级 | AI3: 链接 | AJ3: 上架天数 | AK3: 店铺背景分析 | AM3: 产品特色 | AO3: 注意 1、该表格有自动填充功能，当你输入产品的ASIN码时会自动填充其他内容。但是除了图片。所以使用表格时先输入图片和ASIN码。如果输入ASIN码后不能自动填充，其他信息就需要手动输入。 2、请勿改动除图片、ASIN、优点以外的任何数据，不然被改动的单元格不再具备自动填充功能。
A4: =数据调研!L4 -> B07NQ35VDW | B4: =数据调研!C4 -> Eagloo | C4: =数据调研!D4 -> 13.99 | D4: =数据调研!E4 -> Pet Supplies | E4: =数据调研!F4 -> 764 | F4: =数据调研!G4 -> 2550 | G4: =数据调研!H4 -> 35674.5 | H4: =数据调研!I4 -> 79 | I4: =数据调研!J4 -> 4 | J4: =数据调研!K4 -> FBA | K4: =数据调研!M4 -> https://www.amazon.com/dp/B07NQ35VDW?psc=1 | L4: =数据调研!N4 -> 387 | M4: =IF(AND(AC6<>0,AC6<>"N.A."),AC6,0) -> 12.98 | N4: =IF(M4<>0,1,0) -> 1 | O4: =IF(N4=1,M4,100000) -> 12.98 | P4: =IF(N4=1,M4,0) -> 12.98 | Q4: =IF(AND(AD6<>"N.A.",AD6<>"< 5"),AD6,0) -> 390 | R4: =IF(Q4<>0,1,0) -> 1 | S4: =IF(R4=1,Q4,10000000) -> 390 | T4: =IF(R4=1,S4,0) -> 390 | U4: =M4 -> 12.98 | V4: =Q4 -> 390 | AA4: US | AB4: B07NQ35VDW | AC4: =VLOOKUP(AB4,A:C,3,0) -> 13.99 | AD4: =VLOOKUP(AB4,A:F,6,0) -> 2550 | AE4: =VLOOKUP(AB4,A:B,2,0) -> Eagloo | AF4: =VLOOKUP(AB4,A:H,8,0) -> 79 | AG4: =VLOOKUP(AB4,A:E,5,0) -> 764 | AH4: =VLOOKUP(AB4,A:I,9,0) -> 4 | AI4: =VLOOKUP(AB4,A:K,11,0) -> https://www.amazon.com/dp/B07NQ35VDW?psc=1 | AJ4: =VLOOKUP(AB4,A:L,12,0) -> 387 | AK4: 一两年的店铺，主营宠物类用品，该产品占据50%以上的销售份额 | AM4: 防逃生、可调、反光带、造型简约、13-18in
A5: =数据调研!L5 -> B078G6MKTN | B5: =数据调研!C5 -> BWOGUE | C5: =数据调研!D5 -> 10.49 | D5: =数据调研!E5 -> Pet Supplies | E5: =数据调研!F5 -> 921 | F5: =数据调研!G5 -> 2220 | G5: =数据调研!H5 -> 23287.8 | H5: =数据调研!I5 -> 743 | I5: =数据调研!J5 -> 4.7 | J5: =数据调研!K5 -> FBA | K5: =数据调研!M5 -> https://www.amazon.com/dp/B078G6MKTN?psc=1 | L5: =数据调研!N5 -> 459 | M5: =IF(AND(AC7<>0,AC7<>"N.A."),AC7,0) -> 10.99 | N5: =IF(M5<>0,1,0) -> 1 | O5: =IF(N5=1,M5,100000) -> 10.99 | P5: =IF(N5=1,M5,0) -> 10.99 | Q5: =IF(AND(AD7<>"N.A.",AD7<>"< 5"),AD7,0) -> 270 | R5: =IF(Q5<>0,1,0) -> 1 | S5: =IF(R5=1,Q5,10000000) -> 270 | T5: =IF(R5=1,S5,0) -> 270 | U5: =M5 -> 10.99 | V5: =Q5 -> 270 | AA5: US | AB5: B07MKQFJSP | AC5: =VLOOKUP(AB5,A:C,3,0) -> 13.99 | AD5: =VLOOKUP(AB5,A:F,6,0) -> 960 | AE5: =VLOOKUP(AB5,A:B,2,0) -> PUPTECK | AF5: =VLOOKUP(AB5,A:H,8,0) -> 13 | AG5: =VLOOKUP(AB5,A:E,5,0) -> 2511 | AH5: =VLOOKUP(AB5,A:I,9,0) -> 4.8 | AI5: =VLOOKUP(AB5,A:K,11,0) -> https://www.amazon.com/dp/B07MKQFJSP?psc=1 | AJ5: =VLOOKUP(AB5,A:L,12,0) -> 96 | AK5: 两年多的大店，专注宠物类用品 | AM5: 带子清新时尚、防逃生、造型简约、多颜色变体
A6: =数据调研!L6 -> B000OGRDK0 | B6: =数据调研!C6 -> PetSafe | C6: =数据调研!D6 -> 4.79 | D6: =数据调研!E6 -> Pet Supplies | E6: =数据调研!F6 -> 1174 | F6: =数据调研!G6 -> 1830 | G6: =数据调研!H6 -> 8765.7 | H6: =数据调研!I6 -> 1616 | I6: =数据调研!J6 -> 4.4 | J6: =数据调研!K6 -> AMZ | K6: =数据调研!M6 -> https://www.amazon.com/dp/B000OGRDK0?psc=1 | L6: =数据调研!N6 -> 4374 | M6: =IF(AND(AC8<>0,AC8<>"N.A."),AC8,0) -> 12.99 | N6: =IF(M6<>0,1,0) -> 1 | O6: =IF(N6=1,M6,100000) -> 12.99 | P6: =IF(N6=1,M6,0) -> 12.99 | Q6: =IF(AND(AD8<>"N.A.",AD8<>"< 5"),AD8,0) -> 360 | R6: =IF(Q6<>0,1,0) -> 1 | S6: =IF(R6=1,Q6,10000000) -> 360 | T6: =IF(R6=1,S6,0) -> 360 | U6: =M6 -> 12.99 | V6: =Q6 -> 360 | AA6: US | AB6: B07MZR3MDT | AC6: =VLOOKUP(AB6,A:C,3,0) -> 12.98 | AD6: =VLOOKUP(AB6,A:F,6,0) -> 390 | AE6: =VLOOKUP(AB6,A:B,2,0) -> Rabbitgoo | AF6: =VLOOKUP(AB6,A:H,8,0) -> 28 | AG6: =VLOOKUP(AB6,A:E,5,0) -> 6553 | AH6: =VLOOKUP(AB6,A:I,9,0) -> 3.7 | AI6: =VLOOKUP(AB6,A:K,11,0) -> https://www.amazon.com/dp/B07MZR3MDT?psc=1 | AJ6: =VLOOKUP(AB6,A:L,12,0) -> 48 | AK6: 大账号、卖家居宠物类产品 | AM6: 防逃生、可调、反光带、造型简约、13-18in、多色
A7: =数据调研!L7 -> B07MKQFJSP | B7: =数据调研!C7 -> PUPTECK | C7: =数据调研!D7 -> 13.99 | D7: =数据调研!E7 -> Pet Supplies | E7: =数据调研!F7 -> 2511 | F7: =数据调研!G7 -> 960 | G7: =数据调研!H7 -> 13430.4 | H7: =数据调研!I7 -> 13 | I7: =数据调研!J7 -> 4.8 | J7: =数据调研!K7 -> FBA | K7: =数据调研!M7 -> https://www.amazon.com/dp/B07MKQFJSP?psc=1 | L7: =数据调研!N7 -> 96 | M7: =IF(AND(AC9<>0,AC9<>"N.A."),AC9,0) -> 11.99 | N7: =IF(M7<>0,1,0) -> 1 | O7: =IF(N7=1,M7,100000) -> 11.99 | P7: =IF(N7=1,M7,0) -> 11.99 | Q7: =IF(AND(AD9<>"N.A.",AD9<>"< 5"),AD9,0) -> 514 | R7: =IF(Q7<>0,1,0) -> 1 | S7: =IF(R7=1,Q7,10000000) -> 514 | T7: =IF(R7=1,S7,0) -> 514 | U7: =M7 -> 11.99 | V7: =Q7 -> 514 | AA7: US | AB7: B07GFBQ4H6 | AC7: =VLOOKUP(AB7,A:C,3,0) -> 10.99 | AD7: =VLOOKUP(AB7,A:F,6,0) -> 270 | AE7: =VLOOKUP(AB7,A:B,2,0) -> GAUTERF | AF7: =VLOOKUP(AB7,A:H,8,0) -> 601 | AG7: =VLOOKUP(AB7,A:E,5,0) -> 9013 | AH7: =VLOOKUP(AB7,A:I,9,0) -> 4.2 | AI7: =VLOOKUP(AB7,A:K,11,0) -> https://www.amazon.com/dp/B07GFBQ4H6?psc=1 | AJ7: =VLOOKUP(AB7,A:L,12,0) -> 364 | AK7: 1年店铺，专卖宠物背带产品 | AM7: 防逃生、可调、反光带、造型简约、多色
A8: =数据调研!L8 -> B07MKQFJSP | B8: =数据调研!C8 -> PUPTECK | C8: =数据调研!D8 -> 13.99 | D8: =数据调研!E8 -> Pet Supplies | E8: =数据调研!F8 -> 2921 | F8: =数据调研!G8 -> 840 | G8: =数据调研!H8 -> 11751.6 | H8: =数据调研!I8 -> 13 | I8: =数据调研!J8 -> 4.8 | J8: =数据调研!K8 -> FBA | K8: =数据调研!M8 -> https://www.amazon.com/dp/B07MKQFJSP?psc=1 | L8: =数据调研!N8 -> 96 | M8: =IF(AND(AC10<>0,AC10<>"N.A."),AC10,0) -> 9.99 | N8: =IF(M8<>0,1,0) -> 1 | O8: =IF(N8=1,M8,100000) -> 9.99 | P8: =IF(N8=1,M8,0) -> 9.99 | Q8: =IF(AND(AD10<>"N.A.",AD10<>"< 5"),AD10,0) -> 102 | R8: =IF(Q8<>0,1,0) -> 1 | S8: =IF(R8=1,Q8,10000000) -> 102 | T8: =IF(R8=1,S8,0) -> 102 | U8: =M8 -> 9.99 | V8: =Q8 -> 102 | AA8: US | AB8: B074MWRZ5Y | AC8: =VLOOKUP(AB8,A:C,3,0) -> 12.99 | AD8: =VLOOKUP(AB8,A:F,6,0) -> 360 | AE8: =VLOOKUP(AB8,A:B,2,0) -> PUPTECK | AF8: =VLOOKUP(AB8,A:H,8,0) -> 944 | AG8: =VLOOKUP(AB8,A:E,5,0) -> 6727 | AH8: =VLOOKUP(AB8,A:I,9,0) -> 3.6 | AI8: =VLOOKUP(AB8,A:K,11,0) -> https://www.amazon.com/dp/B074MWRZ5Y?psc=1 | AJ8: =VLOOKUP(AB8,A:L,12,0) -> 1080 | AK8: 两年多的大店，专注宠物类用品 | AM8: 防逃生、可调、舒适
A9: =数据调研!L9 -> B07GFBW7JT | B9: =数据调研!C9 -> GAUTERF | C9: =数据调研!D9 -> 10.99 | D9: =数据调研!E9 -> Pet Supplies | E9: =数据调研!F9 -> 6044 | F9: =数据调研!G9 -> 420 | G9: =数据调研!H9 -> 4615.8 | H9: =数据调研!I9 -> 601 | I9: =数据调研!J9 -> 4.2 | J9: =数据调研!K9 -> FBA | K9: =数据调研!M9 -> https://www.amazon.com/dp/B07GFBW7JT?psc=1 | L9: =数据调研!N9 -> 256 | M9: =IF(AND(AC11<>0,AC11<>"N.A."),AC11,0) -> 9.99 | N9: =IF(M9<>0,1,0) -> 1 | O9: =IF(N9=1,M9,100000) -> 9.99 | P9: =IF(N9=1,M9,0) -> 9.99 | Q9: =IF(AND(AD11<>"N.A.",AD11<>"< 5"),AD11,0) -> 89 | R9: =IF(Q9<>0,1,0) -> 1 | S9: =IF(R9=1,Q9,10000000) -> 89 | T9: =IF(R9=1,S9,0) -> 89 | U9: =M9 -> 9.99 | V9: =Q9 -> 89 | AA9: UK | AB9: B07B49LNW9 | AC9: 11.99 | AD9: 514 | AE9: BINGPET | AF9: 228 | AG9: 821 | AH9: 4 | AI9: 点此 | AJ9: 715 | AK9: 宠物类店铺 | AM9: 防逃生、可调、舒适
A10: =数据调研!L10 -> B07MZR3MDT | B10: =数据调研!C10 -> Rabbitgoo | C10: =数据调研!D10 -> 12.98 | D10: =数据调研!E10 -> Pet Supplies | E10: =数据调研!F10 -> 6553 | F10: =数据调研!G10 -> 390 | G10: =数据调研!H10 -> 5062.2 | H10: =数据调研!I10 -> 28 | I10: =数据调研!J10 -> 3.7 | J10: =数据调研!K10 -> FBA | K10: =数据调研!M10 -> https://www.amazon.com/dp/B07MZR3MDT?psc=1 | L10: =数据调研!N10 -> 48 | M10: =IF(AND(AC12<>0,AC12<>"N.A."),AC12,0) -> 11.99 | N10: =IF(M10<>0,1,0) -> 1 | O10: =IF(N10=1,M10,100000) -> 11.99 | P10: =IF(N10=1,M10,0) -> 11.99 | Q10: =IF(AND(AD12<>"N.A.",AD12<>"< 5"),AD12,0) -> 124 | R10: =IF(Q10<>0,1,0) -> 1 | S10: =IF(R10=1,Q10,10000000) -> 124 | T10: =IF(R10=1,S10,0) -> 124 | U10: =M10 -> 11.99 | V10: =Q10 -> 124 | AA10: UK | AB10: B07GSJJ2X6 | AC10: 9.99 | AD10: 102 | AE10: SCENEREAL | AF10: 31 | AG10: 4821 | AH10: 4 | AI10: 点此 | AJ10: 16 | AK10: 宠物类店铺 | AM10: 防逃生、可调、舒适
A11: =数据调研!L11 -> B07MZR3MDT | B11: =数据调研!C11 -> Rabbitgoo | C11: =数据调研!D11 -> 12.98 | D11: =数据调研!E11 -> Pet Supplies | E11: =数据调研!F11 -> 6553 | F11: =数据调研!G11 -> 390 | G11: =数据调研!H11 -> 5062.2 | H11: =数据调研!I11 -> 28 | I11: =数据调研!J11 -> 3.7 | J11: =数据调研!K11 -> FBA | K11: =数据调研!M11 -> https://www.amazon.com/dp/B07MZR3MDT?psc=1 | L11: =数据调研!N11 -> 48 | M11: =IF(AND(AC13<>0,AC13<>"N.A."),AC13,0) -> 0 | N11: =IF(M11<>0,1,0) -> 0 | O11: =IF(N11=1,M11,100000) -> 100000 | P11: =IF(N11=1,M11,0) -> 0 | Q11: =IF(AND(AD13<>"N.A.",AD13<>"< 5"),AD13,0) -> 0 | R11: =IF(Q11<>0,1,0) -> 0 | S11: =IF(R11=1,Q11,10000000) -> 10000000 | T11: =IF(R11=1,S11,0) -> 0 | U11: =M11 -> 0 | V11: =Q11 -> 0 | AA11: UK | AB11: B07R8Y1DLY | AC11: 9.99 | AD11: 89 | AE11: EXPAWLORER | AF11: 10 | AG11: 9220 | AH11: 4.8 | AI11: 点此 | AJ11: 712 | AK11: 宠物类店铺，卖得好的产品是定制项圈 | AM11: 防逃生、可调、舒适，胸围: 29-35.6cm, 颈围:20.3-24.1cm
A12: =数据调研!L12 -> B074MWRZ5Y | B12: =数据调研!C12 -> PUPTECK | C12: =数据调研!D12 -> 12.99 | D12: =数据调研!E12 -> Pet Supplies | E12: =数据调研!F12 -> 6727 | F12: =数据调研!G12 -> 360 | G12: =数据调研!H12 -> 4676.4 | H12: =数据调研!I12 -> 944 | I12: =数据调研!J12 -> 3.6 | J12: =数据调研!K12 -> FBA | K12: =数据调研!M12 -> https://www.amazon.com/dp/B074MWRZ5Y?psc=1 | L12: =数据调研!N12 -> 1080 | M12: =IF(AND(#REF!<>0,#REF!<>"N.A."),#REF!,0) -> #REF! | N12: =IF(M12<>0,1,0) -> #REF! | O12: =IF(N12=1,M12,100000) -> #REF! | P12: =IF(N12=1,M12,0) -> #REF! | Q12: =IF(AND(#REF!<>"N.A.",#REF!<>"< 5"),#REF!,0) -> #REF! | R12: =IF(Q12<>0,1,0) -> #REF! | S12: =IF(R12=1,Q12,10000000) -> #REF! | T12: =IF(R12=1,S12,0) -> #REF! | U12: =M12 -> #REF! | V12: =Q12 -> #REF! | AA12: UK | AB12: B07G43RT89 | AC12: 11.99 | AD12: 124 | AE12: HOMIMP | AF12: 22 | AG12: 3730 | AH12: 4.1 | AI12: 点此 | AJ12: 407 | AK12: 一年左右的新店铺，主卖宠物类产品，值得借鉴 | AM12: 普通款，老款产品，双D型扣
A13: =数据调研!L13 -> B07MDLYQR7 | B13: =数据调研!C13 -> INVENHO | C13: =数据调研!D13 -> 10.99 | D13: =数据调研!E13 -> Pet Supplies | E13: =数据调研!F13 -> 7043 | F13: =数据调研!G13 -> 360 | G13: =数据调研!H13 -> 3956.4 | H13: =数据调研!I13 -> 124 | I13: =数据调研!J13 -> 4.3 | J13: =数据调研!K13 -> FBA | K13: =数据调研!M13 -> https://www.amazon.com/dp/B07MDLYQR7?psc=1 | L13: =数据调研!N13 -> 556 | M13: =IF(AND(#REF!<>0,#REF!<>"N.A."),#REF!,0) -> #REF! | N13: =IF(M13<>0,1,0) -> #REF! | O13: =IF(N13=1,M13,100000) -> #REF! | P13: =IF(N13=1,M13,0) -> #REF! | Q13: =IF(AND(#REF!<>"N.A.",#REF!<>"< 5"),#REF!,0) -> #REF! | R13: =IF(Q13<>0,1,0) -> #REF! | S13: =IF(R13=1,Q13,10000000) -> #REF! | T13: =IF(R13=1,S13,0) -> #REF! | U13: =M13 -> #REF! | V13: =Q13 -> #REF! | X13: 客户潜在需求分析 | AH13: 痛点分析
A14: =数据调研!L14 -> B07MDLYQR7 | B14: =数据调研!C14 -> INVENHO | C14: =数据调研!D14 -> 10.99 | D14: =数据调研!E14 -> Pet Supplies | E14: =数据调研!F14 -> 7043 | F14: =数据调研!G14 -> 360 | G14: =数据调研!H14 -> 3956.4 | H14: =数据调研!I14 -> 124 | I14: =数据调研!J14 -> 4.3 | J14: =数据调研!K14 -> FBA | K14: =数据调研!M14 -> https://www.amazon.com/dp/B07MDLYQR7?psc=1 | L14: =数据调研!N14 -> 556 | M14: =IF(AND(#REF!<>0,#REF!<>"N.A."),#REF!,0) -> #REF! | N14: =IF(M14<>0,1,0) -> #REF! | O14: =IF(N14=1,M14,100000) -> #REF! | P14: =IF(N14=1,M14,0) -> #REF! | Q14: =IF(AND(#REF!<>"N.A.",#REF!<>"< 5"),#REF!,0) -> #REF! | R14: =IF(Q14<>0,1,0) -> #REF! | S14: =IF(R14=1,Q14,10000000) -> #REF! | T14: =IF(R14=1,S14,0) -> #REF! | U14: =M14 -> #REF! | V14: =Q14 -> #REF!
A15: =数据调研!L15 -> B00M0V7UVE | B15: =数据调研!C15 -> Best Pet Supplies, Inc. | C15: =数据调研!D15 -> 12.99 | D15: =数据调研!E15 -> Pet Supplies | E15: =数据调研!F15 -> 7965 | F15: =数据调研!G15 -> 300 | G15: =数据调研!H15 -> 3897 | H15: =数据调研!I15 -> 4515 | I15: =数据调研!J15 -> 4.3 | J15: =数据调研!K15 -> AMZ | K15: =数据调研!M15 -> https://www.amazon.com/dp/B00M0V7UVE?psc=1 | L15: =数据调研!N15 -> 1921 | M15: =IF(AND(#REF!<>0,#REF!<>"N.A."),#REF!,0) -> #REF! | N15: =IF(M15<>0,1,0) -> #REF! | O15: =IF(N15=1,M15,100000) -> #REF! | P15: =IF(N15=1,M15,0) -> #REF! | Q15: =IF(AND(#REF!<>"N.A.",#REF!<>"< 5"),#REF!,0) -> #REF! | R15: =IF(Q15<>0,1,0) -> #REF! | S15: =IF(R15=1,Q15,10000000) -> #REF! | T15: =IF(R15=1,S15,0) -> #REF! | U15: =M15 -> #REF! | V15: =Q15 -> #REF! | X15: 序号 | Y15: 需求描述 | AC15: 次数 | AD15: 对策 | AH15: 序号 | AI15: 描述 | AL15: 比例 | AM15: 解决对策
A16: =数据调研!L16 -> B07GFBQ4H6 | B16: =数据调研!C16 -> GAUTERF | C16: =数据调研!D16 -> 10.99 | D16: =数据调研!E16 -> Pet Supplies | E16: =数据调研!F16 -> 9013 | F16: =数据调研!G16 -> 270 | G16: =数据调研!H16 -> 2967.3 | H16: =数据调研!I16 -> 601 | I16: =数据调研!J16 -> 4.2 | J16: =数据调研!K16 -> FBA | K16: =数据调研!M16 -> https://www.amazon.com/dp/B07GFBQ4H6?psc=1 | L16: =数据调研!N16 -> 364 | M16: =IF(AND(#REF!<>0,#REF!<>"N.A."),#REF!,0) -> #REF! | N16: =IF(M16<>0,1,0) -> #REF! | O16: =IF(N16=1,M16,100000) -> #REF! | P16: =IF(N16=1,M16,0) -> #REF! | Q16: =IF(AND(#REF!<>"N.A.",#REF!<>"< 5"),#REF!,0) -> #REF! | R16: =IF(Q16<>0,1,0) -> #REF! | S16: =IF(R16=1,Q16,10000000) -> #REF! | T16: =IF(R16=1,S16,0) -> #REF! | U16: =M16 -> #REF! | V16: =Q16 -> #REF! | X16: 1 | Y16: 需要能更好的调整背带长度 | AC16: 4 | AH16: 1 | AI16: 猫容易逃脱出去 | AL16: 0.56 | AM16: 改变穿戴方式
A17: =数据调研!L17 -> B01MY4O0CE | B17: =数据调研!C17 -> PUPTECK | C17: =数据调研!D17 -> 9.99 | D17: =数据调研!E17 -> Pet Supplies | E17: =数据调研!F17 -> 9685 | F17: =数据调研!G17 -> 240 | G17: =数据调研!H17 -> 2397.6 | H17: =数据调研!I17 -> 614 | I17: =数据调研!J17 -> 4.2 | J17: =数据调研!K17 -> FBA | K17: =数据调研!M17 -> https://www.amazon.com/dp/B01MY4O0CE?psc=1 | L17: =数据调研!N17 -> 795 | M17: =IF(AND(#REF!<>0,#REF!<>"N.A."),#REF!,0) -> #REF! | N17: =IF(M17<>0,1,0) -> #REF! | O17: =IF(N17=1,M17,100000) -> #REF! | P17: =IF(N17=1,M17,0) -> #REF! | Q17: =IF(AND(#REF!<>"N.A.",#REF!<>"< 5"),#REF!,0) -> #REF! | R17: =IF(Q17<>0,1,0) -> #REF! | S17: =IF(R17=1,Q17,10000000) -> #REF! | T17: =IF(R17=1,S17,0) -> #REF! | U17: =M17 -> #REF! | V17: =Q17 -> #REF! | X17: 2 | Y17: 希望更薄 | AC17: 2 | AH17: 2 | AI17: 尺寸不合适 | AL17: 0.17 | AM17: 改为尺寸可调节
A18: =数据调研!L18 -> B07MKTGM95 | B18: =数据调研!C18 -> INVENHO | C18: =数据调研!D18 -> 9.99 | D18: =数据调研!E18 -> Pet Supplies | E18: =数据调研!F18 -> 10023 | F18: =数据调研!G18 -> 240 | G18: =数据调研!H18 -> 2397.6 | H18: =数据调研!I18 -> 124 | I18: =数据调研!J18 -> 4.3 | J18: =数据调研!K18 -> FBA | K18: =数据调研!M18 -> https://www.amazon.com/dp/B07MKTGM95?psc=1 | L18: =数据调研!N18 -> 556 | M18: =IF(AND(#REF!<>0,#REF!<>"N.A."),#REF!,0) -> #REF! | N18: =IF(M18<>0,1,0) -> #REF! | O18: =IF(N18=1,M18,100000) -> #REF! | P18: =IF(N18=1,M18,0) -> #REF! | Q18: =IF(AND(#REF!<>"N.A.",#REF!<>"< 5"),#REF!,0) -> #REF! | R18: =IF(Q18<>0,1,0) -> #REF! | S18: =IF(R18=1,Q18,10000000) -> #REF! | T18: =IF(R18=1,S18,0) -> #REF! | U18: =M18 -> #REF! | V18: =Q18 -> #REF! | X18: 3 | Y18: 舒适度是首要的 | AC18: 1 | AH18: 3 | AI18: 背带太重 | AL18: 0.06 | AM18: 减轻背带重量
A19: =数据调研!L19 -> B007KAX8DO | B19: =数据调研!C19 -> Kitty Holster | C19: =数据调研!D19 -> 24.95 | D19: =数据调研!E19 -> Pet Supplies | E19: =数据调研!F19 -> 11080 | F19: =数据调研!G19 -> 210 | G19: =数据调研!H19 -> 5239.5 | H19: =数据调研!I19 -> 1428 | I19: =数据调研!J19 -> 4.3 | J19: =数据调研!K19 -> FBA | K19: =数据调研!M19 -> https://www.amazon.com/dp/B007KAX8DO?psc=1 | L19: =数据调研!N19 -> 2527 | M19: =IF(AND(#REF!<>0,#REF!<>"N.A."),#REF!,0) -> #REF! | N19: =IF(M19<>0,1,0) -> #REF! | O19: =IF(N19=1,M19,100000) -> #REF! | P19: =IF(N19=1,M19,0) -> #REF! | Q19: =IF(AND(#REF!<>"N.A.",#REF!<>"< 5"),#REF!,0) -> #REF! | R19: =IF(Q19<>0,1,0) -> #REF! | S19: =IF(R19=1,Q19,10000000) -> #REF! | T19: =IF(R19=1,S19,0) -> #REF! | U19: =M19 -> #REF! | V19: =Q19 -> #REF! | X19: 4 | AH19: 4 | AI19: 太厚、太热、不喜欢尼龙粘扣 | AL19: 0.07 | AM19: 减轻背带重量
A20: =数据调研!L20 -> B07F8RY3C6 | B20: =数据调研!C20 -> SCENEREAL | C20: =数据调研!D20 -> 13.99 | D20: =数据调研!E20 -> Pet Supplies | E20: =数据调研!F20 -> 10702 | F20: =数据调研!G20 -> 210 | G20: =数据调研!H20 -> 2937.9 | H20: =数据调研!I20 -> 67 | I20: =数据调研!J20 -> 3.9 | J20: =数据调研!K20 -> FBA | K20: =数据调研!M20 -> https://www.amazon.com/dp/B07F8RY3C6?psc=1 | L20: =数据调研!N20 -> 272 | M20: =IF(AND(AC21<>0,AC21<>"N.A."),AC21,0) -> 0 | N20: =IF(M20<>0,1,0) -> 0 | O20: =IF(N20=1,M20,100000) -> 100000 | P20: =IF(N20=1,M20,0) -> 0 | Q20: =IF(AND(#REF!<>"N.A.",#REF!<>"< 5"),#REF!,0) -> #REF! | R20: =IF(Q20<>0,1,0) -> #REF! | S20: =IF(R20=1,Q20,10000000) -> #REF! | T20: =IF(R20=1,S20,0) -> #REF! | U20: =M20 -> 0 | V20: =Q20 -> #REF! | X20: 5 | AH20: 5
A21: =数据调研!L21 -> B001OMD5ZA | B21: =数据调研!C21 -> PetSafe | C21: =数据调研!D21 -> 14.95 | D21: =数据调研!E21 -> Amazon Best Sellers Rank: | E21: =数据调研!F21 -> N.A. | F21: =数据调研!G21 -> 210 | G21: =数据调研!H21 -> 3139.5 | H21: =数据调研!I21 -> 2543 | I21: =数据调研!J21 -> 3.9 | J21: =数据调研!K21 -> AMZ | K21: =数据调研!M21 -> https://www.amazon.com/dp/B001OMD5ZA?psc=1 | L21: =数据调研!N21 -> 4229 | M21: =IF(AND(#REF!<>0,#REF!<>"N.A."),#REF!,0) -> #REF! | N21: =IF(M21<>0,1,0) -> #REF! | O21: =IF(N21=1,M21,100000) -> #REF! | P21: =IF(N21=1,M21,0) -> #REF! | Q21: =IF(AND(#REF!<>"N.A.",#REF!<>"< 5"),#REF!,0) -> #REF! | R21: =IF(Q21<>0,1,0) -> #REF! | S21: =IF(R21=1,Q21,10000000) -> #REF! | T21: =IF(R21=1,S21,0) -> #REF! | U21: =M21 -> #REF! | V21: =Q21 -> #REF! | X21: 6 | AH21: 6
A22: =数据调研!L22 -> B077XY1CBC | B22: =数据调研!C22 -> Yizhi Miaow | C22: =数据调研!D22 -> 14.49 | D22: =数据调研!E22 -> Pet Supplies | E22: =数据调研!F22 -> 12619 | F22: =数据调研!G22 -> 180 | G22: =数据调研!H22 -> 2608.2 | H22: =数据调研!I22 -> 263 | I22: =数据调研!J22 -> 4 | J22: =数据调研!K22 -> FBA | K22: =数据调研!M22 -> https://www.amazon.com/dp/B077XY1CBC?psc=1 | L22: =数据调研!N22 -> 533 | M22: =IF(AND(#REF!<>0,#REF!<>"N.A."),#REF!,0) -> #REF! | N22: =IF(M22<>0,1,0) -> #REF! | O22: =IF(N22=1,M22,100000) -> #REF! | P22: =IF(N22=1,M22,0) -> #REF! | Q22: =IF(AND(#REF!<>"N.A.",#REF!<>"< 5"),#REF!,0) -> #REF! | R22: =IF(Q22<>0,1,0) -> #REF! | S22: =IF(R22=1,Q22,10000000) -> #REF! | T22: =IF(R22=1,S22,0) -> #REF! | U22: =M22 -> #REF! | V22: =Q22 -> #REF! | Z22: 竞品总结
A23: =数据调研!L23 -> B07DWPTT9S | B23: =数据调研!C23 -> OFPUPPY | C23: =数据调研!D23 -> 9.99 | D23: =数据调研!E23 -> Pet Supplies | E23: =数据调研!F23 -> 98482 | F23: =数据调研!G23 -> 180 | G23: =数据调研!H23 -> 1798.2 | H23: =数据调研!I23 -> 14 | I23: =数据调研!J23 -> 3.9 | J23: =数据调研!K23 -> FBA | K23: =数据调研!M23 -> https://www.amazon.com/dp/B07DWPTT9S?psc=1 | L23: =数据调研!N23 -> 309 | M23: =IF(AND(#REF!<>0,#REF!<>"N.A."),#REF!,0) -> #REF! | N23: =IF(M23<>0,1,0) -> #REF! | O23: =IF(N23=1,M23,100000) -> #REF! | P23: =IF(N23=1,M23,0) -> #REF! | Q23: =IF(AND(#REF!<>"N.A.",#REF!<>"< 5"),#REF!,0) -> #REF! | R23: =IF(Q23<>0,1,0) -> #REF! | S23: =IF(R23=1,Q23,10000000) -> #REF! | T23: =IF(R23=1,S23,0) -> #REF! | U23: =M23 -> #REF! | V23: =Q23 -> #REF!
A24: =数据调研!L24 -> B07MMHDWTC | B24: =数据调研!C24 -> voopet | C24: =数据调研!D24 -> 10.99 | D24: =数据调研!E24 -> Pet Supplies | E24: =数据调研!F24 -> 140925 | F24: =数据调研!G24 -> 180 | G24: =数据调研!H24 -> 1978.2 | H24: =数据调研!I24 -> 2 | I24: =数据调研!J24 -> 5 | J24: =数据调研!K24 -> FBA | K24: =数据调研!M24 -> https://www.amazon.com/dp/B07MMHDWTC?psc=1 | L24: =数据调研!N24 -> 1235 | M24: =IF(AND(#REF!<>0,#REF!<>"N.A."),#REF!,0) -> #REF! | N24: =IF(M24<>0,1,0) -> #REF! | O24: =IF(N24=1,M24,100000) -> #REF! | P24: =IF(N24=1,M24,0) -> #REF! | Q24: =IF(AND(#REF!<>"N.A.",#REF!<>"< 5"),#REF!,0) -> #REF! | R24: =IF(Q24<>0,1,0) -> #REF! | S24: =IF(R24=1,Q24,10000000) -> #REF! | T24: =IF(R24=1,S24,0) -> #REF! | U24: =M24 -> #REF! | V24: =Q24 -> #REF! | Z24: 该款产品属于生命周期比较长的，目前市面上的产品存在严重的质量问题，如果能够想办法解决这些质量问题，那么会达到很高的销量。
A25: =数据调研!L25 -> B018S3APEG | B25: =数据调研!C25 -> Mellow Shirt | C25: =数据调研!D25 -> 25.99 | D25: =数据调研!E25 -> Pet Supplies | E25: =数据调研!F25 -> 12670 | F25: =数据调研!G25 -> 180 | G25: =数据调研!H25 -> 4678.2 | H25: =数据调研!I25 -> 1611 | I25: =数据调研!J25 -> 3.5 | J25: =数据调研!K25 -> FBA | K25: =数据调研!M25 -> https://www.amazon.com/dp/B018S3APEG?psc=1 | L25: =数据调研!N25 -> 1235 | M25: =IF(AND(#REF!<>0,#REF!<>"N.A."),#REF!,0) -> #REF! | N25: =IF(M25<>0,1,0) -> #REF! | O25: =IF(N25=1,M25,100000) -> #REF! | P25: =IF(N25=1,M25,0) -> #REF! | Q25: =IF(AND(#REF!<>"N.A.",#REF!<>"< 5"),#REF!,0) -> #REF! | R25: =IF(Q25<>0,1,0) -> #REF! | S25: =IF(R25=1,Q25,10000000) -> #REF! | T25: =IF(R25=1,S25,0) -> #REF! | U25: =M25 -> #REF! | V25: =Q25 -> #REF!
A26: =数据调研!L26 -> B003WRG9O4 | B26: =数据调研!C26 -> Coastal Pet | C26: =数据调研!D26 -> 8.14 | D26: =数据调研!E26 -> Pet Supplies | E26: =数据调研!F26 -> 13278 | F26: =数据调研!G26 -> 180 | G26: =数据调研!H26 -> 1465.2 | H26: =数据调研!I26 -> 106 | I26: =数据调研!J26 -> 4.4 | J26: =数据调研!K26 -> FBA | K26: =数据调研!M26 -> https://www.amazon.com/dp/B003WRG9O4?psc=1 | L26: =数据调研!N26 -> 980 | M26: =IF(AND(#REF!<>0,#REF!<>"N.A."),#REF!,0) -> #REF! | N26: =IF(M26<>0,1,0) -> #REF! | O26: =IF(N26=1,M26,100000) -> #REF! | P26: =IF(N26=1,M26,0) -> #REF! | Q26: =IF(AND(#REF!<>"N.A.",#REF!<>"< 5"),#REF!,0) -> #REF! | R26: =IF(Q26<>0,1,0) -> #REF! | S26: =IF(R26=1,Q26,10000000) -> #REF! | T26: =IF(R26=1,S26,0) -> #REF! | U26: =M26 -> #REF! | V26: =Q26 -> #REF!
A27: =数据调研!L27 -> B07P74ZSXS | B27: =数据调研!C27 -> Rosestola | C27: =数据调研!D27 -> 8.99 | D27: =数据调研!E27 -> Pet Supplies | E27: =数据调研!F27 -> 130055 | F27: =数据调研!G27 -> 180 | G27: =数据调研!H27 -> 1618.2 | H27: =数据调研!I27 -> 5 | I27: =数据调研!J27 -> 5 | J27: =数据调研!K27 -> FBA | K27: =数据调研!M27 -> https://www.amazon.com/dp/B07P74ZSXS?psc=1 | L27: =数据调研!N27 -> 980 | M27: =IF(AND(#REF!<>0,#REF!<>"N.A."),#REF!,0) -> #REF! | N27: =IF(M27<>0,1,0) -> #REF! | O27: =IF(N27=1,M27,100000) -> #REF! | P27: =IF(N27=1,M27,0) -> #REF! | Q27: =IF(AND(#REF!<>"N.A.",#REF!<>"< 5"),#REF!,0) -> #REF! | R27: =IF(Q27<>0,1,0) -> #REF! | S27: =IF(R27=1,Q27,10000000) -> #REF! | T27: =IF(R27=1,S27,0) -> #REF! | U27: =M27 -> #REF! | V27: =Q27 -> #REF!
A28: =数据调研!L28 -> B01CY48OIO | B28: =数据调研!C28 -> EliteField | C28: =数据调研!D28 -> 29.99 | D28: =数据调研!E28 -> Pet Supplies | E28: =数据调研!F28 -> 12784 | F28: =数据调研!G28 -> 180 | G28: =数据调研!H28 -> 5398.2 | H28: =数据调研!I28 -> 534 | I28: =数据调研!J28 -> 4.3 | J28: =数据调研!K28 -> FBA | K28: =数据调研!M28 -> https://www.amazon.com/dp/B01CY48OIO?psc=1 | L28: =数据调研!N28 -> 1045 | M28: =IF(AND(#REF!<>0,#REF!<>"N.A."),#REF!,0) -> #REF! | N28: =IF(M28<>0,1,0) -> #REF! | O28: =IF(N28=1,M28,100000) -> #REF! | P28: =IF(N28=1,M28,0) -> #REF! | Q28: =IF(AND(#REF!<>"N.A.",#REF!<>"< 5"),#REF!,0) -> #REF! | R28: =IF(Q28<>0,1,0) -> #REF! | S28: =IF(R28=1,Q28,10000000) -> #REF! | T28: =IF(R28=1,S28,0) -> #REF! | U28: =M28 -> #REF! | V28: =Q28 -> #REF!
A29: =数据调研!L29 -> B07J4W6KW2 | B29: =数据调研!C29 -> Best Pet Supplies, Inc. | C29: =数据调研!D29 -> 13.99 | D29: =数据调研!E29 -> Pet Supplies | E29: =数据调研!F29 -> 16620 | F29: =数据调研!G29 -> 150 | G29: =数据调研!H29 -> 2098.5 | H29: =数据调研!I29 -> 1529 | I29: =数据调研!J29 -> 4.4 | J29: =数据调研!K29 -> AMZ | K29: =数据调研!M29 -> https://www.amazon.com/dp/B07J4W6KW2?psc=1 | L29: =数据调研!N29 -> 2186 | M29: =IF(AND(#REF!<>0,#REF!<>"N.A."),#REF!,0) -> #REF! | N29: =IF(M29<>0,1,0) -> #REF! | O29: =IF(N29=1,M29,100000) -> #REF! | P29: =IF(N29=1,M29,0) -> #REF! | Q29: =IF(AND(#REF!<>"N.A.",#REF!<>"< 5"),#REF!,0) -> #REF! | R29: =IF(Q29<>0,1,0) -> #REF! | S29: =IF(R29=1,Q29,10000000) -> #REF! | T29: =IF(R29=1,S29,0) -> #REF! | U29: =M29 -> #REF! | V29: =Q29 -> #REF!
A30: =数据调研!L30 -> B07LGS8M36 | B30: =数据调研!C30 -> Kamots Beauty | C30: =数据调研!D30 -> 11.48 | D30: =数据调研!E30 -> Pet Supplies | E30: =数据调研!F30 -> 17750 | F30: =数据调研!G30 -> 120 | G30: =数据调研!H30 -> 1377.6 | H30: =数据调研!I30 -> 41 | I30: =数据调研!J30 -> 3.9 | J30: =数据调研!K30 -> FBA | K30: =数据调研!M30 -> https://www.amazon.com/dp/B07LGS8M36?psc=1 | L30: =数据调研!N30 -> 159 | M30: =IF(AND(AB23<>0,AB23<>"N.A."),AB23,0) -> 0 | N30: =IF(M30<>0,1,0) -> 0 | O30: =IF(N30=1,M30,100000) -> 100000 | P30: =IF(N30=1,M30,0) -> 0 | Q30: =IF(AND(AC23<>"N.A.",AC23<>"< 5"),AC23,0) -> 0 | R30: =IF(Q30<>0,1,0) -> 0 | S30: =IF(R30=1,Q30,10000000) -> 10000000 | T30: =IF(R30=1,S30,0) -> 0 | U30: =M30 -> 0 | V30: =Q30 -> 0
A31: =数据调研!L31 -> B07PNFDG8P | B31: =数据调研!C31 -> BINGPET | C31: =数据调研!D31 -> 12.99 | D31: =数据调研!E31 -> Pet Supplies | E31: =数据调研!F31 -> 19836 | F31: =数据调研!G31 -> 120 | G31: =数据调研!H31 -> 1558.8 | H31: =数据调研!I31 -> 12 | I31: =数据调研!J31 -> 4.2 | J31: =数据调研!K31 -> FBA | K31: =数据调研!M31 -> https://www.amazon.com/dp/B07PNFDG8P?psc=1 | L31: =数据调研!N31 -> 150 | M31: =IF(AND(AB24<>0,AB24<>"N.A."),AB24,0) -> 0 | N31: =IF(M31<>0,1,0) -> 0 | O31: =IF(N31=1,M31,100000) -> 100000 | P31: =IF(N31=1,M31,0) -> 0 | Q31: =IF(AND(AC24<>"N.A.",AC24<>"< 5"),AC24,0) -> 0 | R31: =IF(Q31<>0,1,0) -> 0 | S31: =IF(R31=1,Q31,10000000) -> 10000000 | T31: =IF(R31=1,S31,0) -> 0 | U31: =M31 -> 0 | V31: =Q31 -> 0
A32: =数据调研!L32 -> B07LGS8M36 | B32: =数据调研!C32 -> Kamots Beauty | C32: =数据调研!D32 -> 11.48 | D32: =数据调研!E32 -> Pet Supplies | E32: =数据调研!F32 -> 17750 | F32: =数据调研!G32 -> 120 | G32: =数据调研!H32 -> 1377.6 | H32: =数据调研!I32 -> 41 | I32: =数据调研!J32 -> 3.9 | J32: =数据调研!K32 -> FBA | K32: =数据调研!M32 -> https://www.amazon.com/dp/B07LGS8M36?psc=1 | L32: =数据调研!N32 -> 159 | M32: =IF(AND(AB25<>0,AB25<>"N.A."),AB25,0) -> 0 | N32: =IF(M32<>0,1,0) -> 0 | O32: =IF(N32=1,M32,100000) -> 100000 | P32: =IF(N32=1,M32,0) -> 0 | Q32: =IF(AND(AC25<>"N.A.",AC25<>"< 5"),AC25,0) -> 0 | R32: =IF(Q32<>0,1,0) -> 0 | S32: =IF(R32=1,Q32,10000000) -> 10000000 | T32: =IF(R32=1,S32,0) -> 0 | U32: =M32 -> 0 | V32: =Q32 -> 0
A33: =数据调研!L33 -> B0753J3RBC | B33: =数据调研!C33 -> Rella Home | C33: =数据调研!D33 -> 7.99 | D33: =数据调研!E33 -> Pet Supplies | E33: =数据调研!F33 -> 18783 | F33: =数据调研!G33 -> 120 | G33: =数据调研!H33 -> 958.8 | H33: =数据调研!I33 -> 88 | I33: =数据调研!J33 -> 4.1 | J33: =数据调研!K33 -> FBA | K33: =数据调研!M33 -> https://www.amazon.com/dp/B0753J3RBC?psc=1 | L33: =数据调研!N33 -> 473 | M33: =IF(AND(AB26<>0,AB26<>"N.A."),AB26,0) -> 0 | N33: =IF(M33<>0,1,0) -> 0 | O33: =IF(N33=1,M33,100000) -> 100000 | P33: =IF(N33=1,M33,0) -> 0 | Q33: =IF(AND(AC26<>"N.A.",AC26<>"< 5"),AC26,0) -> 0 | R33: =IF(Q33<>0,1,0) -> 0 | S33: =IF(R33=1,Q33,10000000) -> 10000000 | T33: =IF(R33=1,S33,0) -> 0 | U33: =M33 -> 0 | V33: =Q33 -> 0
A34: =数据调研!L34 -> B07NXCHNW8 | B34: =数据调研!C34 -> PUPTECK | C34: =数据调研!D34 -> 11.99 | D34: =数据调研!E34 -> Pet Supplies | E34: =数据调研!F34 -> 17359 | F34: =数据调研!G34 -> 120 | G34: =数据调研!H34 -> 1438.8 | H34: =数据调研!I34 -> 4 | I34: =数据调研!J34 -> 3.5 | J34: =数据调研!K34 -> FBA | K34: =数据调研!M34 -> https://www.amazon.com/dp/B07NXCHNW8?psc=1 | L34: =数据调研!N34 -> 674 | M34: =IF(AND(AB27<>0,AB27<>"N.A."),AB27,0) -> 0 | N34: =IF(M34<>0,1,0) -> 0 | O34: =IF(N34=1,M34,100000) -> 100000 | P34: =IF(N34=1,M34,0) -> 0 | Q34: =IF(AND(AC27<>"N.A.",AC27<>"< 5"),AC27,0) -> 0 | R34: =IF(Q34<>0,1,0) -> 0 | S34: =IF(R34=1,Q34,10000000) -> 10000000 | T34: =IF(R34=1,S34,0) -> 0 | U34: =M34 -> 0 | V34: =Q34 -> 0
A35: =数据调研!L35 -> B07QYYDH4T | B35: =数据调研!C35 -> NEEDOON | C35: =数据调研!D35 -> 10.99 | D35: =数据调研!E35 -> Beauty & Personal Care | E35: =数据调研!F35 -> 133666 | F35: =数据调研!G35 -> 120 | G35: =数据调研!H35 -> 1318.8 | H35: =数据调研!I35 -> 3 | I35: =数据调研!J35 -> 4 | J35: =数据调研!K35 -> FBA | K35: =数据调研!M35 -> https://www.amazon.com/dp/B07QYYDH4T?psc=1 | L35: =数据调研!N35 -> 27 | M35: =IF(AND(AB28<>0,AB28<>"N.A."),AB28,0) -> 0 | N35: =IF(M35<>0,1,0) -> 0 | O35: =IF(N35=1,M35,100000) -> 100000 | P35: =IF(N35=1,M35,0) -> 0 | Q35: =IF(AND(AC28<>"N.A.",AC28<>"< 5"),AC28,0) -> 0 | R35: =IF(Q35<>0,1,0) -> 0 | S35: =IF(R35=1,Q35,10000000) -> 10000000 | T35: =IF(R35=1,S35,0) -> 0 | U35: =M35 -> 0 | V35: =Q35 -> 0
A36: =数据调研!L36 -> B07CMQLWF4 | B36: =数据调研!C36 -> Stock Show | C36: =数据调研!D36 -> 16.99 | D36: =数据调研!E36 -> Pet Supplies | E36: =数据调研!F36 -> 211183 | F36: =数据调研!G36 -> 120 | G36: =数据调研!H36 -> 2038.8 | H36: =数据调研!I36 -> 31 | I36: =数据调研!J36 -> 4.2 | J36: =数据调研!K36 -> FBA | K36: =数据调研!M36 -> https://www.amazon.com/dp/B07CMQLWF4?psc=1 | L36: =数据调研!N36 -> 346 | M36: =IF(AND(AB29<>0,AB29<>"N.A."),AB29,0) -> 0 | N36: =IF(M36<>0,1,0) -> 0 | O36: =IF(N36=1,M36,100000) -> 100000 | P36: =IF(N36=1,M36,0) -> 0 | Q36: =IF(AND(AC29<>"N.A.",AC29<>"< 5"),AC29,0) -> 0 | R36: =IF(Q36<>0,1,0) -> 0 | S36: =IF(R36=1,Q36,10000000) -> 10000000 | T36: =IF(R36=1,S36,0) -> 0 | U36: =M36 -> 0 | V36: =Q36 -> 0
A37: =数据调研!L37 -> B07LGS8M36 | B37: =数据调研!C37 -> Kamots Beauty | C37: =数据调研!D37 -> 11.48 | D37: =数据调研!E37 -> Pet Supplies | E37: =数据调研!F37 -> 17750 | F37: =数据调研!G37 -> 120 | G37: =数据调研!H37 -> 1377.6 | H37: =数据调研!I37 -> 41 | I37: =数据调研!J37 -> 3.9 | J37: =数据调研!K37 -> FBA | K37: =数据调研!M37 -> https://www.amazon.com/dp/B07LGS8M36?psc=1 | L37: =数据调研!N37 -> 159 | M37: =IF(AND(AB30<>0,AB30<>"N.A."),AB30,0) -> 0 | N37: =IF(M37<>0,1,0) -> 0 | O37: =IF(N37=1,M37,100000) -> 100000 | P37: =IF(N37=1,M37,0) -> 0 | Q37: =IF(AND(AC30<>"N.A.",AC30<>"< 5"),AC30,0) -> 0 | R37: =IF(Q37<>0,1,0) -> 0 | S37: =IF(R37=1,Q37,10000000) -> 10000000 | T37: =IF(R37=1,S37,0) -> 0 | U37: =M37 -> 0 | V37: =Q37 -> 0
A38: =数据调研!L38 -> B018DDFJTM | B38: =数据调研!C38 -> EcoBark | C38: =数据调研!D38 -> 14.99 | D38: =数据调研!E38 -> Pet Supplies | E38: =数据调研!F38 -> 17257 | F38: =数据调研!G38 -> 120 | G38: =数据调研!H38 -> 1798.8 | H38: =数据调研!I38 -> 3544 | I38: =数据调研!J38 -> 4.4 | J38: =数据调研!K38 -> FBA | K38: =数据调研!M38 -> https://www.amazon.com/dp/B018DDFJTM?psc=1 | L38: =数据调研!N38 -> 1329 | M38: =IF(AND(AC40<>0,AC40<>"N.A."),AC40,0) -> 0 | N38: =IF(M38<>0,1,0) -> 0 | O38: =IF(N38=1,M38,100000) -> 100000 | P38: =IF(N38=1,M38,0) -> 0 | Q38: =IF(AND(AD40<>"N.A.",AD40<>"< 5"),AD40,0) -> 0 | R38: =IF(Q38<>0,1,0) -> 0 | S38: =IF(R38=1,Q38,10000000) -> 10000000 | T38: =IF(R38=1,S38,0) -> 0 | U38: =M38 -> 0 | V38: =Q38 -> 0
A39: =数据调研!L39 -> B07KP86PG5 | B39: =数据调研!C39 -> Kamots Beauty | C39: =数据调研!D39 -> 11.48 | D39: =数据调研!E39 -> Pet Supplies | E39: =数据调研!F39 -> 17345 | F39: =数据调研!G39 -> 120 | G39: =数据调研!H39 -> 1377.6 | H39: =数据调研!I39 -> 41 | I39: =数据调研!J39 -> 3.9 | J39: =数据调研!K39 -> FBA | K39: =数据调研!M39 -> https://www.amazon.com/dp/B07KP86PG5?psc=1 | L39: =数据调研!N39 -> 164 | M39: =IF(AND(AC41<>0,AC41<>"N.A."),AC41,0) -> 0 | N39: =IF(M39<>0,1,0) -> 0 | O39: =IF(N39=1,M39,100000) -> 100000 | P39: =IF(N39=1,M39,0) -> 0 | Q39: =IF(AND(AD41<>"N.A.",AD41<>"< 5"),AD41,0) -> 0 | R39: =IF(Q39<>0,1,0) -> 0 | S39: =IF(R39=1,Q39,10000000) -> 10000000 | T39: =IF(R39=1,S39,0) -> 0 | U39: =M39 -> 0 | V39: =Q39 -> 0
A40: =数据调研!L40 -> B01M0RBJNA | B40: =数据调研!C40 -> PUPTECK | C40: =数据调研!D40 -> 12.99 | D40: =数据调研!E40 -> Pet Supplies | E40: =数据调研!F40 -> 18486 | F40: =数据调研!G40 -> 120 | G40: =数据调研!H40 -> 1558.8 | H40: =数据调研!I40 -> 1030 | I40: =数据调研!J40 -> 3.9 | J40: =数据调研!K40 -> FBA | K40: =数据调研!M40 -> https://www.amazon.com/dp/B01M0RBJNA?psc=1 | L40: =数据调研!N40 -> 1079 | M40: =IF(AND(AC42<>0,AC42<>"N.A."),AC42,0) -> 0 | N40: =IF(M40<>0,1,0) -> 0 | O40: =IF(N40=1,M40,100000) -> 100000 | P40: =IF(N40=1,M40,0) -> 0 | Q40: =IF(AND(AD42<>"N.A.",AD42<>"< 5"),AD42,0) -> 0 | R40: =IF(Q40<>0,1,0) -> 0 | S40: =IF(R40=1,Q40,10000000) -> 10000000 | T40: =IF(R40=1,S40,0) -> 0 | U40: =M40 -> 0 | V40: =Q40 -> 0
A41: =数据调研!L41 -> B00J63SKF4 | B41: =数据调研!C41 -> Snazzi Pet | C41: =数据调研!D41 -> 11.95 | D41: =数据调研!E41 -> Pet Supplies | E41: =数据调研!F41 -> 20233 | F41: =数据调研!G41 -> 119 | G41: =数据调研!H41 -> 1422.05 | H41: =数据调研!I41 -> 856 | I41: =数据调研!J41 -> 4.6 | J41: =数据调研!K41 -> FBA | K41: =数据调研!M41 -> https://www.amazon.com/dp/B00J63SKF4?psc=1 | L41: =数据调研!N41 -> 1820 | M41: =IF(AND(AC43<>0,AC43<>"N.A."),AC43,0) -> 0 | N41: =IF(M41<>0,1,0) -> 0 | O41: =IF(N41=1,M41,100000) -> 100000 | P41: =IF(N41=1,M41,0) -> 0 | Q41: =IF(AND(AD43<>"N.A.",AD43<>"< 5"),AD43,0) -> 0 | R41: =IF(Q41<>0,1,0) -> 0 | S41: =IF(R41=1,Q41,10000000) -> 10000000 | T41: =IF(R41=1,S41,0) -> 0 | U41: =M41 -> 0 | V41: =Q41 -> 0
A42: =数据调研!L42 -> B074NYZQRB | B42: =数据调研!C42 -> Mihachi | C42: =数据调研!D42 -> 11.99 | D42: =数据调研!E42 -> Pet Supplies | E42: =数据调研!F42 -> 20511 | F42: =数据调研!G42 -> 118 | G42: =数据调研!H42 -> 1414.82 | H42: =数据调研!I42 -> 53 | I42: =数据调研!J42 -> 4.4 | J42: =数据调研!K42 -> FBA | K42: =数据调研!M42 -> https://www.amazon.com/dp/B074NYZQRB?psc=1 | L42: =数据调研!N42 -> 593 | M42: =IF(AND(AC44<>0,AC44<>"N.A."),AC44,0) -> 0 | N42: =IF(M42<>0,1,0) -> 0 | O42: =IF(N42=1,M42,100000) -> 100000 | P42: =IF(N42=1,M42,0) -> 0 | Q42: =IF(AND(AD44<>"N.A.",AD44<>"< 5"),AD44,0) -> 0 | R42: =IF(Q42<>0,1,0) -> 0 | S42: =IF(R42=1,Q42,10000000) -> 10000000 | T42: =IF(R42=1,S42,0) -> 0 | U42: =M42 -> 0 | V42: =Q42 -> 0
A43: =数据调研!L43 -> B07PHXF7VL | B43: =数据调研!C43 -> SENGU | C43: =数据调研!D43 -> 11.99 | D43: =数据调研!E43 -> Pet Supplies | E43: =数据调研!F43 -> 88983 | F43: =数据调研!G43 -> 116 | G43: =数据调研!H43 -> 1390.84 | H43: =数据调研!I43 -> 6 | I43: =数据调研!J43 -> 4.8 | J43: =数据调研!K43 -> FBA | K43: =数据调研!M43 -> https://www.amazon.com/dp/B07PHXF7VL?psc=1 | L43: =数据调研!N43 -> 52 | M43: =IF(AND(AC45<>0,AC45<>"N.A."),AC45,0) -> 0 | N43: =IF(M43<>0,1,0) -> 0 | O43: =IF(N43=1,M43,100000) -> 100000 | P43: =IF(N43=1,M43,0) -> 0 | Q43: =IF(AND(AD45<>"N.A.",AD45<>"< 5"),AD45,0) -> 0 | R43: =IF(Q43<>0,1,0) -> 0 | S43: =IF(R43=1,Q43,10000000) -> 10000000 | T43: =IF(R43=1,S43,0) -> 0 | U43: =M43 -> 0 | V43: =Q43 -> 0
A44: =数据调研!L44 -> B07KD39DKC | B44: =数据调研!C44 -> The Creativehome | C44: =数据调研!D44 -> 11.99 | D44: =数据调研!E44 -> Pet Supplies | E44: =数据调研!F44 -> 21737 | F44: =数据调研!G44 -> 116 | G44: =数据调研!H44 -> 1390.84 | H44: =数据调研!I44 -> 8 | I44: =数据调研!J44 -> 4 | J44: =数据调研!K44 -> FBA | K44: =数据调研!M44 -> https://www.amazon.com/dp/B07KD39DKC?psc=1 | L44: =数据调研!N44 -> 154 | M44: =IF(AND(AC46<>0,AC46<>"N.A."),AC46,0) -> 0 | N44: =IF(M44<>0,1,0) -> 0 | O44: =IF(N44=1,M44,100000) -> 100000 | P44: =IF(N44=1,M44,0) -> 0 | Q44: =IF(AND(AD46<>"N.A.",AD46<>"< 5"),AD46,0) -> 0 | R44: =IF(Q44<>0,1,0) -> 0 | S44: =IF(R44=1,Q44,10000000) -> 10000000 | T44: =IF(R44=1,S44,0) -> 0 | U44: =M44 -> 0 | V44: =Q44 -> 0
A45: =数据调研!L45 -> B0126WHNCW | B45: =数据调研!C45 -> EXPAWLORER | C45: =数据调研!D45 -> 10.99 | D45: =数据调研!E45 -> Pet Supplies | E45: =数据调研!F45 -> 21984 | F45: =数据调研!G45 -> 116 | G45: =数据调研!H45 -> 1274.84 | H45: =数据调研!I45 -> 471 | I45: =数据调研!J45 -> 4.1 | J45: =数据调研!K45 -> FBA | K45: =数据调研!M45 -> https://www.amazon.com/dp/B0126WHNCW?psc=1 | L45: =数据调研!N45 -> 1370 | M45: =IF(AND(AC47<>0,AC47<>"N.A."),AC47,0) -> 0 | N45: =IF(M45<>0,1,0) -> 0 | O45: =IF(N45=1,M45,100000) -> 100000 | P45: =IF(N45=1,M45,0) -> 0 | Q45: =IF(AND(AD47<>"N.A.",AD47<>"< 5"),AD47,0) -> 0 | R45: =IF(Q45<>0,1,0) -> 0 | S45: =IF(R45=1,Q45,10000000) -> 10000000 | T45: =IF(R45=1,S45,0) -> 0 | U45: =M45 -> 0 | V45: =Q45 -> 0
A46: =数据调研!L46 -> B07Q7Z69P3 | B46: =数据调研!C46 -> PUPTECK | C46: =数据调研!D46 -> 14.99 | D46: =数据调研!E46 -> Pet Supplies | E46: =数据调研!F46 -> 23895 | F46: =数据调研!G46 -> 112 | G46: =数据调研!H46 -> 1678.88 | H46: =数据调研!I46 -> 5 | I46: =数据调研!J46 -> 3.8 | J46: =数据调研!K46 -> FBA | K46: =数据调研!M46 -> https://www.amazon.com/dp/B07Q7Z69P3?psc=1 | L46: =数据调研!N46 -> 23 | M46: =IF(AND(AC48<>0,AC48<>"N.A."),AC48,0) -> 0 | N46: =IF(M46<>0,1,0) -> 0 | O46: =IF(N46=1,M46,100000) -> 100000 | P46: =IF(N46=1,M46,0) -> 0 | Q46: =IF(AND(AD48<>"N.A.",AD48<>"< 5"),AD48,0) -> 0 | R46: =IF(Q46<>0,1,0) -> 0 | S46: =IF(R46=1,Q46,10000000) -> 10000000 | T46: =IF(R46=1,S46,0) -> 0 | U46: =M46 -> 0 | V46: =Q46 -> 0
A47: =数据调研!L47 -> B07HCDBL52 | B47: =数据调研!C47 -> Unihubys | C47: =数据调研!D47 -> 13.99 | D47: =数据调研!E47 -> Pet Supplies | E47: =数据调研!F47 -> 24227 | F47: =数据调研!G47 -> 111 | G47: =数据调研!H47 -> 1552.89 | H47: =数据调研!I47 -> 58 | I47: =数据调研!J47 -> 3.9 | J47: =数据调研!K47 -> FBA | K47: =数据调研!M47 -> https://www.amazon.com/dp/B07HCDBL52?psc=1 | L47: =数据调研!N47 -> 211 | M47: =IF(AND(AC49<>0,AC49<>"N.A."),AC49,0) -> 0 | N47: =IF(M47<>0,1,0) -> 0 | O47: =IF(N47=1,M47,100000) -> 100000 | P47: =IF(N47=1,M47,0) -> 0 | Q47: =IF(AND(AD49<>"N.A.",AD49<>"< 5"),AD49,0) -> 0 | R47: =IF(Q47<>0,1,0) -> 0 | S47: =IF(R47=1,Q47,10000000) -> 10000000 | T47: =IF(R47=1,S47,0) -> 0 | U47: =M47 -> 0 | V47: =Q47 -> 0
A48: =数据调研!L48 -> B01J3UZCS2 | B48: =数据调研!C48 -> SELMAI | C48: =数据调研!D48 -> 13.98 | D48: =数据调研!E48 -> Pet Supplies | E48: =数据调研!F48 -> 24122 | F48: =数据调研!G48 -> 111 | G48: =数据调研!H48 -> 1551.78 | H48: =数据调研!I48 -> 361 | I48: =数据调研!J48 -> 4.3 | J48: =数据调研!K48 -> AMZ | K48: =数据调研!M48 -> https://www.amazon.com/dp/B01J3UZCS2?psc=1 | L48: =数据调研!N48 -> 984 | M48: =IF(AND(AC50<>0,AC50<>"N.A."),AC50,0) -> 0 | N48: =IF(M48<>0,1,0) -> 0 | O48: =IF(N48=1,M48,100000) -> 100000 | P48: =IF(N48=1,M48,0) -> 0 | Q48: =IF(AND(AD50<>"N.A.",AD50<>"< 5"),AD50,0) -> 0 | R48: =IF(Q48<>0,1,0) -> 0 | S48: =IF(R48=1,Q48,10000000) -> 10000000 | T48: =IF(R48=1,S48,0) -> 0 | U48: =M48 -> 0 | V48: =Q48 -> 0
A49: =数据调研!L49 -> B07KPT5TD6 | B49: =数据调研!C49 -> BINGPET | C49: =数据调研!D49 -> 12.99 | D49: =数据调研!E49 -> Pet Supplies | E49: =数据调研!F49 -> 24038 | F49: =数据调研!G49 -> 111 | G49: =数据调研!H49 -> 1441.89 | H49: =数据调研!I49 -> 12 | I49: =数据调研!J49 -> 4.2 | J49: =数据调研!K49 -> FBA | K49: =数据调研!M49 -> https://www.amazon.com/dp/B07KPT5TD6?psc=1 | L49: =数据调研!N49 -> 150 | M49: =IF(AND(AC51<>0,AC51<>"N.A."),AC51,0) -> 0 | N49: =IF(M49<>0,1,0) -> 0 | O49: =IF(N49=1,M49,100000) -> 100000 | P49: =IF(N49=1,M49,0) -> 0 | Q49: =IF(AND(AD51<>"N.A.",AD51<>"< 5"),AD51,0) -> 0 | R49: =IF(Q49<>0,1,0) -> 0 | S49: =IF(R49=1,Q49,10000000) -> 10000000 | T49: =IF(R49=1,S49,0) -> 0 | U49: =M49 -> 0 | V49: =Q49 -> 0
... A161: =数据调研!L161 -> 0 | B161: =数据调研!C161 -> 0 | C161: =数据调研!D161 -> 0 | D161: =数据调研!E161 -> 0 | E161: =数据调研!F161 -> 0 | F161: =数据调研!G161 -> 0 | G161: =数据调研!H161 -> 0 | H161: =数据调研!I161 -> 0 | I161: =数据调研!J161 -> 0 | J161: =数据调研!K161 -> 0 | K161: =数据调研!M161 -> 0 | L161: =数据调研!N161 -> 0 | M161: =IF(AND(AC163<>0,AC163<>"N.A."),AC163,0) -> 0 | N161: =IF(M161<>0,1,0) -> 0 | O161: =IF(N161=1,M161,100000) -> 100000 | P161: =IF(N161=1,M161,0) -> 0 | Q161: =IF(AND(AD163<>"N.A.",AD163<>"< 5"),AD163,0) -> 0 | R161: =IF(Q161<>0,1,0) -> 0 | S161: =IF(R161=1,Q161,10000000) -> 10000000 | T161: =IF(R161=1,S161,0) -> 0 | U161: =M161 -> 0 | V161: =Q161 -> 0

Sheet 市场容量分析
A1: Rank | B1: 0-99 | C1: 100-499 | D1: 500-999 | E1: 1000-1999 | F1: 2000-3999 | G1: 4000-5999 | H1: 6000-7999 | I1: 8000-10000 | J1: >10001 | K1: 销量 | L1: 0-300 | M1: 300-500 | N1: 500-800 | O1: 800-1000 | P1: 1000-1500 | Q1: 1500-2000 | R1: 2000-3000 | S1: 3000-4500 | T1: 4500-6000 | U1: 6000-8000 | V1: >8000 | W1: Rank | X1: review | Y1: Re<30 | Z1: Re<30且 0-99 | AA1: Re<30且 100-499 | AB1: Re<30且 500-999 | AC1: Re<30且 1000-1999 | AD1: Re<30且 2000-3999 | AE1: Re<30且 4000-5999 | AF1: Re<30且 6000-7999 | AG1: Re<30且8000-10000 | AH1: Re<30且 10000+ | AI1: 30<review<100 | AJ1: 30<review<100且 0-99 | AK1: 30<review<100且 100-499 | AL1: 30<review<100且 500-999 | AM1: 30<review<100且 1000-1999 | AN1: 30<review<100且 2000-3999 | AO1: 30<review<100且 4000-5999 | AP1: 30<review<100且 6000-7999 | AQ1: 30<review<100且8000-10000 | AR1: 30<review<100且 10000+ | AS1: 100<review<500 | AT1: 100<review<500且 0-99 | AU1: 100<review<500且 100-499 | AV1: 100<review<500且 500-999 | AW1: 100<review<500且 1000-1999 | AX1: 100<review<500且 2000-3999 | AY1: 100<review<500且 4000-5999 | AZ1: 100<review<500且 6000-7999 | BA1: 100<review<500且8000-10000 | BB1: 100<review<500且 10000+ | BC1: 500<review<1000 | BD1: 500<review<1000且 0-99 | BE1: 500<review<1000且 100-499 | BF1: 500<review<1000且 500-999 | BG1: 500<review<1000且 1000-1999 | BH1: 500<review<1000且 2000-3999 | BI1: 500<review<1000且 4000-5999 | BJ1: 500<review<1000且 6000-7999 | BK1: 500<review<1000且8000-10000 | BL1: 500<review<1000且 10000+ | BM1: review>1000 | BN1: 500<review<1000且 0-99 | BO1: 500<review<1000且 100-499 | BP1: 500<review<1000且 500-999 | BQ1: 500<review<1000且 1000-1999 | BR1: 500<review<1000且 2000-3999 | BS1: 500<review<1000且 4000-5999 | BT1: 500<review<1000且 6000-7999 | BU1: 500<review<1000且8000-10000 | BV1: 500<review<1000且 10000+ | BW1: Seller | BX1: AMZ | BY1: AMZ且0-99 | BZ1: AMZ且100-499 | CA1: AMZ且500-999 | CB1: AMZ且1000-1999 | CC1: AMZ且2000-3999 | CD1: AMZ且4000-5999 | CE1: AMZ且6000-7999 | CF1: AMZ且8000-10000 | CG1: AMZ且>10000 | CH1: FBA | CI1: FBA且0-99 | CJ1: FBA且100-499 | CK1: FBA且500-999 | CL1: FBA且1000-1999 | CM1: FBA且2000-3999 | CN1: FBA且4000-5999 | CO1: FBA且6000-7999 | CP1: FBA且8000-10000 | CQ1: FBA且>10000 | CR1: 上架天数 | CS1: 天数<31 | CT1: 天数<31且0-99 | CU1: 天数<31且100-499 | CV1: 天数<31且500-999 | CW1: 天数<31且1000-1999 | CX1: 天数<31且2000-3999 | CY1: 天数<31且4000-5999 | CZ1: 天数<31且6000-7999 | DA1: 天数<31且8000-10000 | DB1: 天数<31且>10001 | DC1: 30<天数<61 | DD1: 30<天数<61且0-99 | DE1: 30<天数<61100-499 | DF1: 30<天数<61且500-999 | DG1: 30<天数<61且1000-1999 | DH1: 30<天数<61且2000-3999 | DI1: 30<天数<61且4000-5999 | DJ1: 30<天数<61且6000-7999 | DK1: 30<天数<61且8000-10000 | DL1: 30<天数<61且>10001 | DM1: 60<天数<91 | DN1: 60<天数<91且0-99 | DO1: 60<天数<91且100-499 | DP1: 60<天数<91且500-999 | DQ1: 60<天数<91且1000-1999 | DR1: 60<天数<91且2000-3999 | DS1: 60<天数<91且4000-5999 | DT1: 60<天数<91且6000-7999 | DU1: 60<天数<91且8000-10000 | DV1: 60<天数<91且>10001 | DW1: 90<天数<181 | DX1: 90<天数<181且0-99 | DY1: 90<天数<181且100-499 | DZ1: 90<天数<181且500-999 | EA1: 90<天数<181且1000-1999 | EB1: 90<天数<181且2000-3999 | EC1: 90<天数<181且4000-5999 | ED1: 90<天数<181且6000-7999 | EE1: 90<天数<181且8000-10000 | EF1: 90<天数<181且>10001 | EG1: 半年以上 | EH1: 半年以上且0-99 | EI1: 半年以上且100-499 | EJ1: 半年以上且500-999 | EK1: 半年以上且1000-1999 | EL1: 半年以上且2000-3999 | EM1: 半年以上且4000-5999 | EN1: 半年以上且6000-7999 | EO1: 半年以上且8000-10000 | EP1: 半年以上且>10001 | EQ1: 市场容量分析
A2: =数据调研!F2 -> 764 | B2: =IF(AND(A2>0,A2<100),1,0) -> 0 | C2: =IF(AND(A2>99,A2<500),1,0) -> 0 | D2: =IF(AND(A2>499,A2<1000),1,0) -> 1 | E2: =IF(AND(A2>999,A2<2000),1,0) -> 0 | F2: =IF(AND(A2>1999,A2<4000),1,0) -> 0 | G2: =IF(AND(A2>3999,A2<6000),1,0) -> 0 | H2: =IF(AND(A2>5999,A2<8000),1,0) -> 0 | I2: =IF(AND(A2>7999,A2<10001),1,0) -> 0 | J2: =IF(A2>10001,1,0) -> 0 | K2: =价格参考!K2 -> 2550 | L2: =IF(AND(K2>0,K2<301),1,0) -> 0 | M2: =IF(AND(K2>300,K2<501),1,0) -> 0 | N2: =IF(AND(K2>500,K2<801),1,0) -> 0 | O2: =IF(AND(K2>800,K2<1001),1,0) -> 0 | P2: =IF(AND(K2>1000,K2<1501),1,0) -> 0 | Q2: =IF(AND(K2>1500,K2<2001),1,0) -> 0 | R2: =IF(AND(K2>2000,K2<3001),1,0) -> 1 | S2: =IF(AND(K2>3000,K2<4501),1,0) -> 0 | T2: =IF(AND(K2>4500,K2<6001),1,0) -> 0 | U2: =IF(AND(K2>6000,K2<8001),1,0) -> 0 | V2: =IF(AND(K2>8000,K2<>"N.A.",K2<>"< 5"),1,0) -> 0 | W2: =IF(A2<>"N.A.",A2,1000000) -> 764 | X2: =数据调研!I2 -> 79 | Y2: =IF(X2<31,1,0) -> 0 | Z2: =IF(AND(Y2=1,B2=1),1,0) -> 0 | AA2: =IF(AND(Y2=1,C2=1),1,0) -> 0 | AB2: =IF(AND(Y2=1,D2=1),1,0) -> 0 | AC2: =IF(AND(Y2=1,E2=1),1,0) -> 0 | AD2: =IF(AND(Y2=1,F2=1),1,0) -> 0 | AE2: =IF(AND(Y2=1,G2=1),1,0) -> 0 | AF2: =IF(AND(Y2=1,H2=1),1,0) -> 0 | AG2: =IF(AND(Y2=1,I2=1),1,0) -> 0 | AH2: =IF(AND(Y2=1,J2=1),1,0) -> 0 | AI2: =IF(AND(X2>30,X2<101),1,0) -> 1 | AJ2: =IF(AND(AI2=1,B2=1),1,0) -> 0 | AK2: =IF(AND(AI2=1,C2=1),1,0) -> 0 | AL2: =IF(AND(AI2=1,D2=1),1,0) -> 1 | AM2: =IF(AND(AI2=1,E2=1),1,0) -> 0 | AN2: =IF(AND(AI2=1,F2=1),1,0) -> 0 | AO2: =IF(AND(AI2=1,G2=1),1,0) -> 0 | AP2: =IF(AND(AI2=1,H2=1),1,0) -> 0 | AQ2: =IF(AND(AI2=1,I2=1),1,0) -> 0 | AR2: =IF(AND(AI2=1,J2=1),1,0) -> 0 | AS2: =IF(AND(X2>100,X2<501),1,0) -> 0 | AT2: =IF(AND(B2=1,AS2=1),1,0) -> 0 | AU2: =IF(AND(C2=1,AS2=1),1,0) -> 0 | AV2: =IF(AND(D2=1,AS2=1),1,0) -> 0 | AW2: =IF(AND(E2=1,AS2=1),1,0) -> 0 | AX2: =IF(AND(F2=1,AS2=1),1,0) -> 0 | AY2: =IF(AND(G2=1,AS2=1),1,0) -> 0 | AZ2: =IF(AND(H2=1,AS2=1),1,0) -> 0 | BA2: =IF(AND(I2=1,AS2=1),1,0) -> 0 | BB2: =IF(AND(J2=1,AS2=1),1,0) -> 0 | BC2: =IF(AND(X2>500,X2<1001),1,0) -> 0 | BD2: =IF(AND(BC2=1,B2=1),1,0) -> 0 | BE2: =IF(AND(BC2=1,C2=1),1,0) -> 0 | BF2: =IF(AND(BC2=1,D2=1),1,0) -> 0 | BG2: =IF(AND(BC2=1,E2=1),1,0) -> 0 | BH2: =IF(AND(BC2=1,F2=1),1,0) -> 0 | BI2: =IF(AND(BC2=1,G2=1),1,0) -> 0 | BJ2: =IF(AND(BC2=1,H2=1),1,0) -> 0 | BK2: =IF(AND(BC2=1,I2=1),1,0) -> 0 | BL2: =IF(AND(BC2=1,J2=1),1,0) -> 0 | BM2: =IF(X2>1001,1,0) -> 0 | BN2: =IF(AND(B2=1,BM2=1),1,0) -> 0 | BO2: =IF(AND(C2=1,BM2=1),1,0) -> 0 | BP2: =IF(AND(D2=1,BM2=1),1,0) -> 0 | BQ2: =IF(AND(E2=1,BM2=1),1,0) -> 0 | BR2: =IF(AND(F2=1,BM2=1),1,0) -> 0 | BS2: =IF(AND(G2=1,BM2=1),1,0) -> 0 | BT2: =IF(AND(H2=1,BM2=1),1,0) -> 0 | BU2: =IF(AND(I2=1,BM2=1),1,0) -> 0 | BV2: =IF(AND(J2=1,BM2=1),1,0) -> 0 | BW2: =数据调研!K2 -> FBA | BX2: =IF(BW2="AMZ",1,0) -> 0 | BY2: =IF(AND(BX2=1,B2=1),1,0) -> 0 | BZ2: =IF(AND(BX2=1,C2=1),1,0) -> 0 | CA2: =IF(AND(BX2=1,D2=1),1,0) -> 0 | CB2: =IF(AND(BX2=1,E2=1),1,0) -> 0 | CC2: =IF(AND(BX2=1,F2=1),1,0) -> 0 | CD2: =IF(AND(BX2=1,G2=1),1,0) -> 0 | CE2: =IF(AND(BX2=1,H2=1),1,0) -> 0 | CF2: =IF(AND(BX2=1,I2=1),1,0) -> 0 | CG2: =IF(AND(BX2=1,J2=1),1,0) -> 0 | CH2: =IF(BW2="FBA",1,0) -> 1 | CI2: =IF(AND(CH2=1,B2=1),1,0) -> 0 | CJ2: =IF(AND(CH2=1,C2=1),1,0) -> 0 | CK2: =IF(AND(CH2=1,D2=1),1,0) -> 1 | CL2: =IF(AND(CH2=1,E2=1),1,0) -> 0 | CM2: =IF(AND(CH2=1,F2=1),1,0) -> 0 | CN2: =IF(AND(CH2=1,G2=1),1,0) -> 0 | CO2: =IF(AND(CH2=1,H2=1),1,0) -> 0 | CP2: =IF(AND(CH2=1,I2=1),1,0) -> 0 | CQ2: =IF(AND(CH2=1,J2=1),1,0) -> 0 | CR2: =数据调研!N2 -> 387 | CS2: =IF(AND(CR2<31,CR2<>0),1,0) -> 0 | CT2: =IF(AND(CS2=1,B2=1),1,0) -> 0 | CU2: =IF(AND(CS2=1,C2=1),1,0) -> 0 | CV2: =IF(AND(CS2=1,D2=1),1,0) -> 0 | CW2: =IF(AND(CS2=1,E2=1),1,0) -> 0 | CX2: =IF(AND(CS2=1,F2=1),1,0) -> 0 | CY2: =IF(AND(CS2=1,G2=1),1,0) -> 0 | CZ2: =IF(AND(CS2=1,H2=1),1,0) -> 0 | DA2: =IF(AND(CS2=1,I2=1),1,0) -> 0 | DB2: =IF(AND(CS2=1,J2=1),1,0) -> 0 | DC2: =IF(AND(CR2>30,CR2<61),1,0) -> 0 | DD2: =IF(AND(DC2=1,B2=1),1,0) -> 0 | DE2: =IF(AND(DC2=1,C2=1),1,0) -> 0 | DF2: =IF(AND(DC2=1,D2=1),1,0) -> 0 | DG2: =IF(AND(DC2=1,E2=1),1,0) -> 0 | DH2: =IF(AND(DC2=1,F2=1),1,0) -> 0 | DI2: =IF(AND(DC2=1,G2=1),1,0) -> 0 | DJ2: =IF(AND(DC2=1,H2=1),1,0) -> 0 | DK2: =IF(AND(DC2=1,I2=1),1,0) -> 0 | DL2: =IF(AND(DC2=1,J2=1),1,0) -> 0 | DM2: =IF(AND(CR2>60,CR2<91),1,0) -> 0 | DN2: =IF(AND(DM2=1,B2=1),1,0) -> 0 | DO2: =IF(AND(DM2=1,C2=1),1,0) -> 0 | DP2: =IF(AND(DM2=1,D2=1),1,0) -> 0 | DQ2: =IF(AND(DM2=1,E2=1),1,0) -> 0 | DR2: =IF(AND(DM2=1,F2=1),1,0) -> 0 | DS2: =IF(AND(DM2=1,G2=1),1,0) -> 0 | DT2: =IF(AND(DM2=1,H2=1),1,0) -> 0 | DU2: =IF(AND(DM2=1,I2=1),1,0) -> 0 | DV2: =IF(AND(DM2=1,J2=1),1,0) -> 0 | DW2: =IF(AND(CR2>90,CR2<181),1,0) -> 0 | DX2: =IF(AND(DW2=1,B2=1),1,0) -> 0 | DY2: =IF(AND(DW2=1,C2=1),1,0) -> 0 | DZ2: =IF(AND(DW2=1,D2=1),1,0) -> 0 | EA2: =IF(AND(DW2=1,E2=1),1,0) -> 0 | EB2: =IF(AND(DW2=1,F2=1),1,0) -> 0 | EC2: =IF(AND(DW2=1,G2=1),1,0) -> 0 | ED2: =IF(AND(DW2=1,H2=1),1,0) -> 0 | EE2: =IF(AND(DW2=1,I2=1),1,0) -> 0 | EF2: =IF(AND(DW2=1,J2=1),1,0) -> 0 | EG2: =IF(CR2>180,1,0) -> 1 | EH2: =IF(AND(EG2=1,B2=1),1,0) -> 0 | EI2: =IF(AND(EG2=1,C2=1),1,0) -> 0 | EJ2: =IF(AND(EG2=1,D2=1),1,0) -> 1 | EK2: =IF(AND(EG2=1,E2=1),1,0) -> 0 | EL2: =IF(AND(EG2=1,F2=1),1,0) -> 0 | EM2: =IF(AND(EG2=1,G2=1),1,0) -> 0 | EN2: =IF(AND(EG2=1,H2=1),1,0) -> 0 | EO2: =IF(AND(EG2=1,I2=1),1,0) -> 0 | EP2: =IF(AND(EG2=1,J2=1),1,0) -> 0
A3: =数据调研!F3 -> 764 | B3: =IF(AND(A3>0,A3<100),1,0) -> 0 | C3: =IF(AND(A3>99,A3<500),1,0) -> 0 | D3: =IF(AND(A3>499,A3<1000),1,0) -> 1 | E3: =IF(AND(A3>999,A3<2000),1,0) -> 0 | F3: =IF(AND(A3>1999,A3<4000),1,0) -> 0 | G3: =IF(AND(A3>3999,A3<6000),1,0) -> 0 | H3: =IF(AND(A3>5999,A3<8000),1,0) -> 0 | I3: =IF(AND(A3>7999,A3<10001),1,0) -> 0 | J3: =IF(A3>10002,1,0) -> 0 | K3: =价格参考!K3 -> 2550 | L3: =IF(AND(K3>0,K3<301),1,0) -> 0 | M3: =IF(AND(K3>300,K3<501),1,0) -> 0 | N3: =IF(AND(K3>500,K3<801),1,0) -> 0 | O3: =IF(AND(K3>800,K3<1001),1,0) -> 0 | P3: =IF(AND(K3>1000,K3<1501),1,0) -> 0 | Q3: =IF(AND(K3>1500,K3<2001),1,0) -> 0 | R3: =IF(AND(K3>2000,K3<3001),1,0) -> 1 | S3: =IF(AND(K3>3000,K3<4501),1,0) -> 0 | T3: =IF(AND(K3>4500,K3<6001),1,0) -> 0 | U3: =IF(AND(K3>6000,K3<8001),1,0) -> 0 | V3: =IF(AND(K3>8000,K3<>"N.A.",K3<>"< 5"),1,0) -> 0 | W3: =IF(A3<>"N.A.",A3,1000000) -> 764 | X3: =数据调研!I3 -> 79 | Y3: =IF(X3<31,1,0) -> 0 | Z3: =IF(AND(Y3=1,B3=1),1,0) -> 0 | AA3: =IF(AND(Y3=1,C3=1),1,0) -> 0 | AB3: =IF(AND(Y3=1,D3=1),1,0) -> 0 | AC3: =IF(AND(Y3=1,E3=1),1,0) -> 0 | AD3: =IF(AND(Y3=1,F3=1),1,0) -> 0 | AE3: =IF(AND(Y3=1,G3=1),1,0) -> 0 | AF3: =IF(AND(Y3=1,H3=1),1,0) -> 0 | AG3: =IF(AND(Y3=1,I3=1),1,0) -> 0 | AH3: =IF(AND(Y3=1,J3=1),1,0) -> 0 | AI3: =IF(AND(X3>30,X3<101),1,0) -> 1 | AJ3: =IF(AND(AI3=1,B3=1),1,0) -> 0 | AK3: =IF(AND(AI3=1,C3=1),1,0) -> 0 | AL3: =IF(AND(AI3=1,D3=1),1,0) -> 1 | AM3: =IF(AND(AI3=1,E3=1),1,0) -> 0 | AN3: =IF(AND(AI3=1,F3=1),1,0) -> 0 | AO3: =IF(AND(AI3=1,G3=1),1,0) -> 0 | AP3: =IF(AND(AI3=1,H3=1),1,0) -> 0 | AQ3: =IF(AND(AI3=1,I3=1),1,0) -> 0 | AR3: =IF(AND(AI3=1,J3=1),1,0) -> 0 | AS3: =IF(AND(X3>100,X3<501),1,0) -> 0 | AT3: =IF(AND(B3=1,AS3=1),1,0) -> 0 | AU3: =IF(AND(C3=1,AS3=1),1,0) -> 0 | AV3: =IF(AND(D3=1,AS3=1),1,0) -> 0 | AW3: =IF(AND(E3=1,AS3=1),1,0) -> 0 | AX3: =IF(AND(F3=1,AS3=1),1,0) -> 0 | AY3: =IF(AND(G3=1,AS3=1),1,0) -> 0 | AZ3: =IF(AND(H3=1,AS3=1),1,0) -> 0 | BA3: =IF(AND(I3=1,AS3=1),1,0) -> 0 | BB3: =IF(AND(J3=1,AS3=1),1,0) -> 0 | BC3: =IF(AND(X3>500,X3<1001),1,0) -> 0 | BD3: =IF(AND(BC3=1,B3=1),1,0) -> 0 | BE3: =IF(AND(BC3=1,C3=1),1,0) -> 0 | BF3: =IF(AND(BC3=1,D3=1),1,0) -> 0 | BG3: =IF(AND(BC3=1,E3=1),1,0) -> 0 | BH3: =IF(AND(BC3=1,F3=1),1,0) -> 0 | BI3: =IF(AND(BC3=1,G3=1),1,0) -> 0 | BJ3: =IF(AND(BC3=1,H3=1),1,0) -> 0 | BK3: =IF(AND(BC3=1,I3=1),1,0) -> 0 | BL3: =IF(AND(BC3=1,J3=1),1,0) -> 0 | BM3: =IF(X3>1001,1,0) -> 0 | BN3: =IF(AND(B3=1,BM3=1),1,0) -> 0 | BO3: =IF(AND(C3=1,BM3=1),1,0) -> 0 | BP3: =IF(AND(D3=1,BM3=1),1,0) -> 0 | BQ3: =IF(AND(E3=1,BM3=1),1,0) -> 0 | BR3: =IF(AND(F3=1,BM3=1),1,0) -> 0 | BS3: =IF(AND(G3=1,BM3=1),1,0) -> 0 | BT3: =IF(AND(H3=1,BM3=1),1,0) -> 0 | BU3: =IF(AND(I3=1,BM3=1),1,0) -> 0 | BV3: =IF(AND(J3=1,BM3=1),1,0) -> 0 | BW3: =数据调研!K3 -> FBA | BX3: =IF(BW3="AMZ",1,0) -> 0 | BY3: =IF(AND(BX3=1,B3=1),1,0) -> 0 | BZ3: =IF(AND(BX3=1,C3=1),1,0) -> 0 | CA3: =IF(AND(BX3=1,D3=1),1,0) -> 0 | CB3: =IF(AND(BX3=1,E3=1),1,0) -> 0 | CC3: =IF(AND(BX3=1,F3=1),1,0) -> 0 | CD3: =IF(AND(BX3=1,G3=1),1,0) -> 0 | CE3: =IF(AND(BX3=1,H3=1),1,0) -> 0 | CF3: =IF(AND(BX3=1,I3=1),1,0) -> 0 | CG3: =IF(AND(BX3=1,J3=1),1,0) -> 0 | CH3: =IF(BW3="FBA",1,0) -> 1 | CI3: =IF(AND(CH3=1,B3=1),1,0) -> 0 | CJ3: =IF(AND(CH3=1,C3=1),1,0) -> 0 | CK3: =IF(AND(CH3=1,D3=1),1,0) -> 1 | CL3: =IF(AND(CH3=1,E3=1),1,0) -> 0 | CM3: =IF(AND(CH3=1,F3=1),1,0) -> 0 | CN3: =IF(AND(CH3=1,G3=1),1,0) -> 0 | CO3: =IF(AND(CH3=1,H3=1),1,0) -> 0 | CP3: =IF(AND(CH3=1,I3=1),1,0) -> 0 | CQ3: =IF(AND(CH3=1,J3=1),1,0) -> 0 | CR3: =数据调研!N3 -> 387 | CS3: =IF(AND(CR3<31,CR3<>0),1,0) -> 0 | CT3: =IF(AND(CS3=1,B3=1),1,0) -> 0 | CU3: =IF(AND(CS3=1,C3=1),1,0) -> 0 | CV3: =IF(AND(CS3=1,D3=1),1,0) -> 0 | CW3: =IF(AND(CS3=1,E3=1),1,0) -> 0 | CX3: =IF(AND(CS3=1,F3=1),1,0) -> 0 | CY3: =IF(AND(CS3=1,G3=1),1,0) -> 0 | CZ3: =IF(AND(CS3=1,H3=1),1,0) -> 0 | DA3: =IF(AND(CS3=1,I3=1),1,0) -> 0 | DB3: =IF(AND(CS3=1,J3=1),1,0) -> 0 | DC3: =IF(AND(CR3>30,CR3<61),1,0) -> 0 | DD3: =IF(AND(DC3=1,B3=1),1,0) -> 0 | DE3: =IF(AND(DC3=1,C3=1),1,0) -> 0 | DF3: =IF(AND(DC3=1,D3=1),1,0) -> 0 | DG3: =IF(AND(DC3=1,E3=1),1,0) -> 0 | DH3: =IF(AND(DC3=1,F3=1),1,0) -> 0 | DI3: =IF(AND(DC3=1,G3=1),1,0) -> 0 | DJ3: =IF(AND(DC3=1,H3=1),1,0) -> 0 | DK3: =IF(AND(DC3=1,I3=1),1,0) -> 0 | DL3: =IF(AND(DC3=1,J3=1),1,0) -> 0 | DM3: =IF(AND(CR3>60,CR3<91),1,0) -> 0 | DN3: =IF(AND(DM3=1,B3=1),1,0) -> 0 | DO3: =IF(AND(DM3=1,C3=1),1,0) -> 0 | DP3: =IF(AND(DM3=1,D3=1),1,0) -> 0 | DQ3: =IF(AND(DM3=1,E3=1),1,0) -> 0 | DR3: =IF(AND(DM3=1,F3=1),1,0) -> 0 | DS3: =IF(AND(DM3=1,G3=1),1,0) -> 0 | DT3: =IF(AND(DM3=1,H3=1),1,0) -> 0 | DU3: =IF(AND(DM3=1,I3=1),1,0) -> 0 | DV3: =IF(AND(DM3=1,J3=1),1,0) -> 0 | DW3: =IF(AND(CR3>90,CR3<181),1,0) -> 0 | DX3: =IF(AND(DW3=1,B3=1),1,0) -> 0 | DY3: =IF(AND(DW3=1,C3=1),1,0) -> 0 | DZ3: =IF(AND(DW3=1,D3=1),1,0) -> 0 | EA3: =IF(AND(DW3=1,E3=1),1,0) -> 0 | EB3: =IF(AND(DW3=1,F3=1),1,0) -> 0 | EC3: =IF(AND(DW3=1,G3=1),1,0) -> 0 | ED3: =IF(AND(DW3=1,H3=1),1,0) -> 0 | EE3: =IF(AND(DW3=1,I3=1),1,0) -> 0 | EF3: =IF(AND(DW3=1,J3=1),1,0) -> 0 | EG3: =IF(CR3>180,1,0) -> 1 | EH3: =IF(AND(EG3=1,B3=1),1,0) -> 0 | EI3: =IF(AND(EG3=1,C3=1),1,0) -> 0 | EJ3: =IF(AND(EG3=1,D3=1),1,0) -> 1 | EK3: =IF(AND(EG3=1,E3=1),1,0) -> 0 | EL3: =IF(AND(EG3=1,F3=1),1,0) -> 0 | EM3: =IF(AND(EG3=1,G3=1),1,0) -> 0 | EN3: =IF(AND(EG3=1,H3=1),1,0) -> 0 | EO3: =IF(AND(EG3=1,I3=1),1,0) -> 0 | EP3: =IF(AND(EG3=1,J3=1),1,0) -> 0 | ER3: 序列 | ES3: 排名 | ET3: 数量 | FE3: 分析依据 1、通过排名分析容量：对提供的listing的排名数据进行整理分类，分为9个排名段，最后一段忽略，即排名大于10000的不考虑。前十页中能进入大类目前10000名的数量越多，那么其市场越大。因为排名跟销量挂钩，个人推荐用排名分析，因为销量是使用软件预估，偏差较大，但是排名亚马逊本身的数据，相对较准。 2、通过销量来分析：获取所提供的listing的销量，对销量进行分段统计。进入高销量段的listing数量越多，市场容量越大。用销量来判断市场容量是最直观的方法，因为销量直接跟消费者的需求量挂钩。 3、当然也可以根据关键词的搜索量来判断市场容量，关键词的搜索量越大，市场容量越大。虽然搜索量不及排名和销量那样来的直接，但是也是分析市场容量的依据。这需要其他关键词工具来辅助，我会在关键词分析一页做详述。 4、市场容量分析最好多维度分析，这样有助于分析的准确性。
A4: =数据调研!F4 -> 764 | B4: =IF(AND(A4>0,A4<100),1,0) -> 0 | C4: =IF(AND(A4>99,A4<500),1,0) -> 0 | D4: =IF(AND(A4>499,A4<1000),1,0) -> 1 | E4: =IF(AND(A4>999,A4<2000),1,0) -> 0 | F4: =IF(AND(A4>1999,A4<4000),1,0) -> 0 | G4: =IF(AND(A4>3999,A4<6000),1,0) -> 0 | H4: =IF(AND(A4>5999,A4<8000),1,0) -> 0 | I4: =IF(AND(A4>7999,A4<10001),1,0) -> 0 | J4: =IF(A4>10002,1,0) -> 0 | K4: =价格参考!K4 -> 2550 | L4: =IF(AND(K4>0,K4<301),1,0) -> 0 | M4: =IF(AND(K4>300,K4<501),1,0) -> 0 | N4: =IF(AND(K4>500,K4<801),1,0) -> 0 | O4: =IF(AND(K4>800,K4<1001),1,0) -> 0 | P4: =IF(AND(K4>1000,K4<1501),1,0) -> 0 | Q4: =IF(AND(K4>1500,K4<2001),1,0) -> 0 | R4: =IF(AND(K4>2000,K4<3001),1,0) -> 1 | S4: =IF(AND(K4>3000,K4<4501),1,0) -> 0 | T4: =IF(AND(K4>4500,K4<6001),1,0) -> 0 | U4: =IF(AND(K4>6000,K4<8001),1,0) -> 0 | V4: =IF(AND(K4>8000,K4<>"N.A.",K4<>"< 5"),1,0) -> 0 | W4: =IF(A4<>"N.A.",A4,1000000) -> 764 | X4: =数据调研!I4 -> 79 | Y4: =IF(X4<31,1,0) -> 0 | Z4: =IF(AND(Y4=1,B4=1),1,0) -> 0 | AA4: =IF(AND(Y4=1,C4=1),1,0) -> 0 | AB4: =IF(AND(Y4=1,D4=1),1,0) -> 0 | AC4: =IF(AND(Y4=1,E4=1),1,0) -> 0 | AD4: =IF(AND(Y4=1,F4=1),1,0) -> 0 | AE4: =IF(AND(Y4=1,G4=1),1,0) -> 0 | AF4: =IF(AND(Y4=1,H4=1),1,0) -> 0 | AG4: =IF(AND(Y4=1,I4=1),1,0) -> 0 | AH4: =IF(AND(Y4=1,J4=1),1,0) -> 0 | AI4: =IF(AND(X4>30,X4<101),1,0) -> 1 | AJ4: =IF(AND(AI4=1,B4=1),1,0) -> 0 | AK4: =IF(AND(AI4=1,C4=1),1,0) -> 0 | AL4: =IF(AND(AI4=1,D4=1),1,0) -> 1 | AM4: =IF(AND(AI4=1,E4=1),1,0) -> 0 | AN4: =IF(AND(AI4=1,F4=1),1,0) -> 0 | AO4: =IF(AND(AI4=1,G4=1),1,0) -> 0 | AP4: =IF(AND(AI4=1,H4=1),1,0) -> 0 | AQ4: =IF(AND(AI4=1,I4=1),1,0) -> 0 | AR4: =IF(AND(AI4=1,J4=1),1,0) -> 0 | AS4: =IF(AND(X4>100,X4<501),1,0) -> 0 | AT4: =IF(AND(B4=1,AS4=1),1,0) -> 0 | AU4: =IF(AND(C4=1,AS4=1),1,0) -> 0 | AV4: =IF(AND(D4=1,AS4=1),1,0) -> 0 | AW4: =IF(AND(E4=1,AS4=1),1,0) -> 0 | AX4: =IF(AND(F4=1,AS4=1),1,0) -> 0 | AY4: =IF(AND(G4=1,AS4=1),1,0) -> 0 | AZ4: =IF(AND(H4=1,AS4=1),1,0) -> 0 | BA4: =IF(AND(I4=1,AS4=1),1,0) -> 0 | BB4: =IF(AND(J4=1,AS4=1),1,0) -> 0 | BC4: =IF(AND(X4>500,X4<1001),1,0) -> 0 | BD4: =IF(AND(BC4=1,B4=1),1,0) -> 0 | BE4: =IF(AND(BC4=1,C4=1),1,0) -> 0 | BF4: =IF(AND(BC4=1,D4=1),1,0) -> 0 | BG4: =IF(AND(BC4=1,E4=1),1,0) -> 0 | BH4: =IF(AND(BC4=1,F4=1),1,0) -> 0 | BI4: =IF(AND(BC4=1,G4=1),1,0) -> 0 | BJ4: =IF(AND(BC4=1,H4=1),1,0) -> 0 | BK4: =IF(AND(BC4=1,I4=1),1,0) -> 0 | BL4: =IF(AND(BC4=1,J4=1),1,0) -> 0 | BM4: =IF(X4>1001,1,0) -> 0 | BN4: =IF(AND(B4=1,BM4=1),1,0) -> 0 | BO4: =IF(AND(C4=1,BM4=1),1,0) -> 0 | BP4: =IF(AND(D4=1,BM4=1),1,0) -> 0 | BQ4: =IF(AND(E4=1,BM4=1),1,0) -> 0 | BR4: =IF(AND(F4=1,BM4=1),1,0) -> 0 | BS4: =IF(AND(G4=1,BM4=1),1,0) -> 0 | BT4: =IF(AND(H4=1,BM4=1),1,0) -> 0 | BU4: =IF(AND(I4=1,BM4=1),1,0) -> 0 | BV4: =IF(AND(J4=1,BM4=1),1,0) -> 0 | BW4: =数据调研!K4 -> FBA | BX4: =IF(BW4="AMZ",1,0) -> 0 | BY4: =IF(AND(BX4=1,B4=1),1,0) -> 0 | BZ4: =IF(AND(BX4=1,C4=1),1,0) -> 0 | CA4: =IF(AND(BX4=1,D4=1),1,0) -> 0 | CB4: =IF(AND(BX4=1,E4=1),1,0) -> 0 | CC4: =IF(AND(BX4=1,F4=1),1,0) -> 0 | CD4: =IF(AND(BX4=1,G4=1),1,0) -> 0 | CE4: =IF(AND(BX4=1,H4=1),1,0) -> 0 | CF4: =IF(AND(BX4=1,I4=1),1,0) -> 0 | CG4: =IF(AND(BX4=1,J4=1),1,0) -> 0 | CH4: =IF(BW4="FBA",1,0) -> 1 | CI4: =IF(AND(CH4=1,B4=1),1,0) -> 0 | CJ4: =IF(AND(CH4=1,C4=1),1,0) -> 0 | CK4: =IF(AND(CH4=1,D4=1),1,0) -> 1 | CL4: =IF(AND(CH4=1,E4=1),1,0) -> 0 | CM4: =IF(AND(CH4=1,F4=1),1,0) -> 0 | CN4: =IF(AND(CH4=1,G4=1),1,0) -> 0 | CO4: =IF(AND(CH4=1,H4=1),1,0) -> 0 | CP4: =IF(AND(CH4=1,I4=1),1,0) -> 0 | CQ4: =IF(AND(CH4=1,J4=1),1,0) -> 0 | CR4: =数据调研!N4 -> 387 | CS4: =IF(AND(CR4<31,CR4<>0),1,0) -> 0 | CT4: =IF(AND(CS4=1,B4=1),1,0) -> 0 | CU4: =IF(AND(CS4=1,C4=1),1,0) -> 0 | CV4: =IF(AND(CS4=1,D4=1),1,0) -> 0 | CW4: =IF(AND(CS4=1,E4=1),1,0) -> 0 | CX4: =IF(AND(CS4=1,F4=1),1,0) -> 0 | CY4: =IF(AND(CS4=1,G4=1),1,0) -> 0 | CZ4: =IF(AND(CS4=1,H4=1),1,0) -> 0 | DA4: =IF(AND(CS4=1,I4=1),1,0) -> 0 | DB4: =IF(AND(CS4=1,J4=1),1,0) -> 0 | DC4: =IF(AND(CR4>30,CR4<61),1,0) -> 0 | DD4: =IF(AND(DC4=1,B4=1),1,0) -> 0 | DE4: =IF(AND(DC4=1,C4=1),1,0) -> 0 | DF4: =IF(AND(DC4=1,D4=1),1,0) -> 0 | DG4: =IF(AND(DC4=1,E4=1),1,0) -> 0 | DH4: =IF(AND(DC4=1,F4=1),1,0) -> 0 | DI4: =IF(AND(DC4=1,G4=1),1,0) -> 0 | DJ4: =IF(AND(DC4=1,H4=1),1,0) -> 0 | DK4: =IF(AND(DC4=1,I4=1),1,0) -> 0 | DL4: =IF(AND(DC4=1,J4=1),1,0) -> 0 | DM4: =IF(AND(CR4>60,CR4<91),1,0) -> 0 | DN4: =IF(AND(DM4=1,B4=1),1,0) -> 0 | DO4: =IF(AND(DM4=1,C4=1),1,0) -> 0 | DP4: =IF(AND(DM4=1,D4=1),1,0) -> 0 | DQ4: =IF(AND(DM4=1,E4=1),1,0) -> 0 | DR4: =IF(AND(DM4=1,F4=1),1,0) -> 0 | DS4: =IF(AND(DM4=1,G4=1),1,0) -> 0 | DT4: =IF(AND(DM4=1,H4=1),1,0) -> 0 | DU4: =IF(AND(DM4=1,I4=1),1,0) -> 0 | DV4: =IF(AND(DM4=1,J4=1),1,0) -> 0 | DW4: =IF(AND(CR4>90,CR4<181),1,0) -> 0 | DX4: =IF(AND(DW4=1,B4=1),1,0) -> 0 | DY4: =IF(AND(DW4=1,C4=1),1,0) -> 0 | DZ4: =IF(AND(DW4=1,D4=1),1,0) -> 0 | EA4: =IF(AND(DW4=1,E4=1),1,0) -> 0 | EB4: =IF(AND(DW4=1,F4=1),1,0) -> 0 | EC4: =IF(AND(DW4=1,G4=1),1,0) -> 0 | ED4: =IF(AND(DW4=1,H4=1),1,0) -> 0 | EE4: =IF(AND(DW4=1,I4=1),1,0) -> 0 | EF4: =IF(AND(DW4=1,J4=1),1,0) -> 0 | EG4: =IF(CR4>180,1,0) -> 1 | EH4: =IF(AND(EG4=1,B4=1),1,0) -> 0 | EI4: =IF(AND(EG4=1,C4=1),1,0) -> 0 | EJ4: =IF(AND(EG4=1,D4=1),1,0) -> 1 | EK4: =IF(AND(EG4=1,E4=1),1,0) -> 0 | EL4: =IF(AND(EG4=1,F4=1),1,0) -> 0 | EM4: =IF(AND(EG4=1,G4=1),1,0) -> 0 | EN4: =IF(AND(EG4=1,H4=1),1,0) -> 0 | EO4: =IF(AND(EG4=1,I4=1),1,0) -> 0 | EP4: =IF(AND(EG4=1,J4=1),1,0) -> 0 | ER4: 1 | ES4: 0-99 | ET4: =B163 -> 0
A5: =数据调研!F5 -> 921 | B5: =IF(AND(A5>0,A5<100),1,0) -> 0 | C5: =IF(AND(A5>99,A5<500),1,0) -> 0 | D5: =IF(AND(A5>499,A5<1000),1,0) -> 1 | E5: =IF(AND(A5>999,A5<2000),1,0) -> 0 | F5: =IF(AND(A5>1999,A5<4000),1,0) -> 0 | G5: =IF(AND(A5>3999,A5<6000),1,0) -> 0 | H5: =IF(AND(A5>5999,A5<8000),1,0) -> 0 | I5: =IF(AND(A5>7999,A5<10001),1,0) -> 0 | J5: =IF(A5>10002,1,0) -> 0 | K5: =价格参考!K5 -> 2220 | L5: =IF(AND(K5>0,K5<301),1,0) -> 0 | M5: =IF(AND(K5>300,K5<501),1,0) -> 0 | N5: =IF(AND(K5>500,K5<801),1,0) -> 0 | O5: =IF(AND(K5>800,K5<1001),1,0) -> 0 | P5: =IF(AND(K5>1000,K5<1501),1,0) -> 0 | Q5: =IF(AND(K5>1500,K5<2001),1,0) -> 0 | R5: =IF(AND(K5>2000,K5<3001),1,0) -> 1 | S5: =IF(AND(K5>3000,K5<4501),1,0) -> 0 | T5: =IF(AND(K5>4500,K5<6001),1,0) -> 0 | U5: =IF(AND(K5>6000,K5<8001),1,0) -> 0 | V5: =IF(AND(K5>8000,K5<>"N.A.",K5<>"< 5"),1,0) -> 0 | W5: =IF(A5<>"N.A.",A5,1000000) -> 921 | X5: =数据调研!I5 -> 743 | Y5: =IF(X5<31,1,0) -> 0 | Z5: =IF(AND(Y5=1,B5=1),1,0) -> 0 | AA5: =IF(AND(Y5=1,C5=1),1,0) -> 0 | AB5: =IF(AND(Y5=1,D5=1),1,0) -> 0 | AC5: =IF(AND(Y5=1,E5=1),1,0) -> 0 | AD5: =IF(AND(Y5=1,F5=1),1,0) -> 0 | AE5: =IF(AND(Y5=1,G5=1),1,0) -> 0 | AF5: =IF(AND(Y5=1,H5=1),1,0) -> 0 | AG5: =IF(AND(Y5=1,I5=1),1,0) -> 0 | AH5: =IF(AND(Y5=1,J5=1),1,0) -> 0 | AI5: =IF(AND(X5>30,X5<101),1,0) -> 0 | AJ5: =IF(AND(AI5=1,B5=1),1,0) -> 0 | AK5: =IF(AND(AI5=1,C5=1),1,0) -> 0 | AL5: =IF(AND(AI5=1,D5=1),1,0) -> 0 | AM5: =IF(AND(AI5=1,E5=1),1,0) -> 0 | AN5: =IF(AND(AI5=1,F5=1),1,0) -> 0 | AO5: =IF(AND(AI5=1,G5=1),1,0) -> 0 | AP5: =IF(AND(AI5=1,H5=1),1,0) -> 0 | AQ5: =IF(AND(AI5=1,I5=1),1,0) -> 0 | AR5: =IF(AND(AI5=1,J5=1),1,0) -> 0 | AS5: =IF(AND(X5>100,X5<501),1,0) -> 0 | AT5: =IF(AND(B5=1,AS5=1),1,0) -> 0 | AU5: =IF(AND(C5=1,AS5=1),1,0) -> 0 | AV5: =IF(AND(D5=1,AS5=1),1,0) -> 0 | AW5: =IF(AND(E5=1,AS5=1),1,0) -> 0 | AX5: =IF(AND(F5=1,AS5=1),1,0) -> 0 | AY5: =IF(AND(G5=1,AS5=1),1,0) -> 0 | AZ5: =IF(AND(H5=1,AS5=1),1,0) -> 0 | BA5: =IF(AND(I5=1,AS5=1),1,0) -> 0 | BB5: =IF(AND(J5=1,AS5=1),1,0) -> 0 | BC5: =IF(AND(X5>500,X5<1001),1,0) -> 1 | BD5: =IF(AND(BC5=1,B5=1),1,0) -> 0 | BE5: =IF(AND(BC5=1,C5=1),1,0) -> 0 | BF5: =IF(AND(BC5=1,D5=1),1,0) -> 1 | BG5: =IF(AND(BC5=1,E5=1),1,0) -> 0 | BH5: =IF(AND(BC5=1,F5=1),1,0) -> 0 | BI5: =IF(AND(BC5=1,G5=1),1,0) -> 0 | BJ5: =IF(AND(BC5=1,H5=1),1,0) -> 0 | BK5: =IF(AND(BC5=1,I5=1),1,0) -> 0 | BL5: =IF(AND(BC5=1,J5=1),1,0) -> 0 | BM5: =IF(X5>1001,1,0) -> 0 | BN5: =IF(AND(B5=1,BM5=1),1,0) -> 0 | BO5: =IF(AND(C5=1,BM5=1),1,0) -> 0 | BP5: =IF(AND(D5=1,BM5=1),1,0) -> 0 | BQ5: =IF(AND(E5=1,BM5=1),1,0) -> 0 | BR5: =IF(AND(F5=1,BM5=1),1,0) -> 0 | BS5: =IF(AND(G5=1,BM5=1),1,0) -> 0 | BT5: =IF(AND(H5=1,BM5=1),1,0) -> 0 | BU5: =IF(AND(I5=1,BM5=1),1,0) -> 0 | BV5: =IF(AND(J5=1,BM5=1),1,0) -> 0 | BW5: =数据调研!K5 -> FBA | BX5: =IF(BW5="AMZ",1,0) -> 0 | BY5: =IF(AND(BX5=1,B5=1),1,0) -> 0 | BZ5: =IF(AND(BX5=1,C5=1),1,0) -> 0 | CA5: =IF(AND(BX5=1,D5=1),1,0) -> 0 | CB5: =IF(AND(BX5=1,E5=1),1,0) -> 0 | CC5: =IF(AND(BX5=1,F5=1),1,0) -> 0 | CD5: =IF(AND(BX5=1,G5=1),1,0) -> 0 | CE5: =IF(AND(BX5=1,H5=1),1,0) -> 0 | CF5: =IF(AND(BX5=1,I5=1),1,0) -> 0 | CG5: =IF(AND(BX5=1,J5=1),1,0) -> 0 | CH5: =IF(BW5="FBA",1,0) -> 1 | CI5: =IF(AND(CH5=1,B5=1),1,0) -> 0 | CJ5: =IF(AND(CH5=1,C5=1),1,0) -> 0 | CK5: =IF(AND(CH5=1,D5=1),1,0) -> 1 | CL5: =IF(AND(CH5=1,E5=1),1,0) -> 0 | CM5: =IF(AND(CH5=1,F5=1),1,0) -> 0 | CN5: =IF(AND(CH5=1,G5=1),1,0) -> 0 | CO5: =IF(AND(CH5=1,H5=1),1,0) -> 0 | CP5: =IF(AND(CH5=1,I5=1),1,0) -> 0 | CQ5: =IF(AND(CH5=1,J5=1),1,0) -> 0 | CR5: =数据调研!N5 -> 459 | CS5: =IF(AND(CR5<31,CR5<>0),1,0) -> 0 | CT5: =IF(AND(CS5=1,B5=1),1,0) -> 0 | CU5: =IF(AND(CS5=1,C5=1),1,0) -> 0 | CV5: =IF(AND(CS5=1,D5=1),1,0) -> 0 | CW5: =IF(AND(CS5=1,E5=1),1,0) -> 0 | CX5: =IF(AND(CS5=1,F5=1),1,0) -> 0 | CY5: =IF(AND(CS5=1,G5=1),1,0) -> 0 | CZ5: =IF(AND(CS5=1,H5=1),1,0) -> 0 | DA5: =IF(AND(CS5=1,I5=1),1,0) -> 0 | DB5: =IF(AND(CS5=1,J5=1),1,0) -> 0 | DC5: =IF(AND(CR5>30,CR5<61),1,0) -> 0 | DD5: =IF(AND(DC5=1,B5=1),1,0) -> 0 | DE5: =IF(AND(DC5=1,C5=1),1,0) -> 0 | DF5: =IF(AND(DC5=1,D5=1),1,0) -> 0 | DG5: =IF(AND(DC5=1,E5=1),1,0) -> 0 | DH5: =IF(AND(DC5=1,F5=1),1,0) -> 0 | DI5: =IF(AND(DC5=1,G5=1),1,0) -> 0 | DJ5: =IF(AND(DC5=1,H5=1),1,0) -> 0 | DK5: =IF(AND(DC5=1,I5=1),1,0) -> 0 | DL5: =IF(AND(DC5=1,J5=1),1,0) -> 0 | DM5: =IF(AND(CR5>60,CR5<91),1,0) -> 0 | DN5: =IF(AND(DM5=1,B5=1),1,0) -> 0 | DO5: =IF(AND(DM5=1,C5=1),1,0) -> 0 | DP5: =IF(AND(DM5=1,D5=1),1,0) -> 0 | DQ5: =IF(AND(DM5=1,E5=1),1,0) -> 0 | DR5: =IF(AND(DM5=1,F5=1),1,0) -> 0 | DS5: =IF(AND(DM5=1,G5=1),1,0) -> 0 | DT5: =IF(AND(DM5=1,H5=1),1,0) -> 0 | DU5: =IF(AND(DM5=1,I5=1),1,0) -> 0 | DV5: =IF(AND(DM5=1,J5=1),1,0) -> 0 | DW5: =IF(AND(CR5>90,CR5<181),1,0) -> 0 | DX5: =IF(AND(DW5=1,B5=1),1,0) -> 0 | DY5: =IF(AND(DW5=1,C5=1),1,0) -> 0 | DZ5: =IF(AND(DW5=1,D5=1),1,0) -> 0 | EA5: =IF(AND(DW5=1,E5=1),1,0) -> 0 | EB5: =IF(AND(DW5=1,F5=1),1,0) -> 0 | EC5: =IF(AND(DW5=1,G5=1),1,0) -> 0 | ED5: =IF(AND(DW5=1,H5=1),1,0) -> 0 | EE5: =IF(AND(DW5=1,I5=1),1,0) -> 0 | EF5: =IF(AND(DW5=1,J5=1),1,0) -> 0 | EG5: =IF(CR5>180,1,0) -> 1 | EH5: =IF(AND(EG5=1,B5=1),1,0) -> 0 | EI5: =IF(AND(EG5=1,C5=1),1,0) -> 0 | EJ5: =IF(AND(EG5=1,D5=1),1,0) -> 1 | EK5: =IF(AND(EG5=1,E5=1),1,0) -> 0 | EL5: =IF(AND(EG5=1,F5=1),1,0) -> 0 | EM5: =IF(AND(EG5=1,G5=1),1,0) -> 0 | EN5: =IF(AND(EG5=1,H5=1),1,0) -> 0 | EO5: =IF(AND(EG5=1,I5=1),1,0) -> 0 | EP5: =IF(AND(EG5=1,J5=1),1,0) -> 0 | ER5: 2 | ES5: 100-499 | ET5: =C163 -> 0
A6: =数据调研!F6 -> 1174 | B6: =IF(AND(A6>0,A6<100),1,0) -> 0 | C6: =IF(AND(A6>99,A6<500),1,0) -> 0 | D6: =IF(AND(A6>499,A6<1000),1,0) -> 0 | E6: =IF(AND(A6>999,A6<2000),1,0) -> 1 | F6: =IF(AND(A6>1999,A6<4000),1,0) -> 0 | G6: =IF(AND(A6>3999,A6<6000),1,0) -> 0 | H6: =IF(AND(A6>5999,A6<8000),1,0) -> 0 | I6: =IF(AND(A6>7999,A6<10001),1,0) -> 0 | J6: =IF(A6>10002,1,0) -> 0 | K6: =价格参考!K6 -> 1830 | L6: =IF(AND(K6>0,K6<301),1,0) -> 0 | M6: =IF(AND(K6>300,K6<501),1,0) -> 0 | N6: =IF(AND(K6>500,K6<801),1,0) -> 0 | O6: =IF(AND(K6>800,K6<1001),1,0) -> 0 | P6: =IF(AND(K6>1000,K6<1501),1,0) -> 0 | Q6: =IF(AND(K6>1500,K6<2001),1,0) -> 1 | R6: =IF(AND(K6>2000,K6<3001),1,0) -> 0 | S6: =IF(AND(K6>3000,K6<4501),1,0) -> 0 | T6: =IF(AND(K6>4500,K6<6001),1,0) -> 0 | U6: =IF(AND(K6>6000,K6<8001),1,0) -> 0 | V6: =IF(AND(K6>8000,K6<>"N.A.",K6<>"< 5"),1,0) -> 0 | W6: =IF(A6<>"N.A.",A6,1000000) -> 1174 | X6: =数据调研!I6 -> 1616 | Y6: =IF(X6<31,1,0) -> 0 | Z6: =IF(AND(Y6=1,B6=1),1,0) -> 0 | AA6: =IF(AND(Y6=1,C6=1),1,0) -> 0 | AB6: =IF(AND(Y6=1,D6=1),1,0) -> 0 | AC6: =IF(AND(Y6=1,E6=1),1,0) -> 0 | AD6: =IF(AND(Y6=1,F6=1),1,0) -> 0 | AE6: =IF(AND(Y6=1,G6=1),1,0) -> 0 | AF6: =IF(AND(Y6=1,H6=1),1,0) -> 0 | AG6: =IF(AND(Y6=1,I6=1),1,0) -> 0 | AH6: =IF(AND(Y6=1,J6=1),1,0) -> 0 | AI6: =IF(AND(X6>30,X6<101),1,0) -> 0 | AJ6: =IF(AND(AI6=1,B6=1),1,0) -> 0 | AK6: =IF(AND(AI6=1,C6=1),1,0) -> 0 | AL6: =IF(AND(AI6=1,D6=1),1,0) -> 0 | AM6: =IF(AND(AI6=1,E6=1),1,0) -> 0 | AN6: =IF(AND(AI6=1,F6=1),1,0) -> 0 | AO6: =IF(AND(AI6=1,G6=1),1,0) -> 0 | AP6: =IF(AND(AI6=1,H6=1),1,0) -> 0 | AQ6: =IF(AND(AI6=1,I6=1),1,0) -> 0 | AR6: =IF(AND(AI6=1,J6=1),1,0) -> 0 | AS6: =IF(AND(X6>100,X6<501),1,0) -> 0 | AT6: =IF(AND(B6=1,AS6=1),1,0) -> 0 | AU6: =IF(AND(C6=1,AS6=1),1,0) -> 0 | AV6: =IF(AND(D6=1,AS6=1),1,0) -> 0 | AW6: =IF(AND(E6=1,AS6=1),1,0) -> 0 | AX6: =IF(AND(F6=1,AS6=1),1,0) -> 0 | AY6: =IF(AND(G6=1,AS6=1),1,0) -> 0 | AZ6: =IF(AND(H6=1,AS6=1),1,0) -> 0 | BA6: =IF(AND(I6=1,AS6=1),1,0) -> 0 | BB6: =IF(AND(J6=1,AS6=1),1,0) -> 0 | BC6: =IF(AND(X6>500,X6<1001),1,0) -> 0 | BD6: =IF(AND(BC6=1,B6=1),1,0) -> 0 | BE6: =IF(AND(BC6=1,C6=1),1,0) -> 0 | BF6: =IF(AND(BC6=1,D6=1),1,0) -> 0 | BG6: =IF(AND(BC6=1,E6=1),1,0) -> 0 | BH6: =IF(AND(BC6=1,F6=1),1,0) -> 0 | BI6: =IF(AND(BC6=1,G6=1),1,0) -> 0 | BJ6: =IF(AND(BC6=1,H6=1),1,0) -> 0 | BK6: =IF(AND(BC6=1,I6=1),1,0) -> 0 | BL6: =IF(AND(BC6=1,J6=1),1,0) -> 0 | BM6: =IF(X6>1001,1,0) -> 1 | BN6: =IF(AND(B6=1,BM6=1),1,0) -> 0 | BO6: =IF(AND(C6=1,BM6=1),1,0) -> 0 | BP6: =IF(AND(D6=1,BM6=1),1,0) -> 0 | BQ6: =IF(AND(E6=1,BM6=1),1,0) -> 1 | BR6: =IF(AND(F6=1,BM6=1),1,0) -> 0 | BS6: =IF(AND(G6=1,BM6=1),1,0) -> 0 | BT6: =IF(AND(H6=1,BM6=1),1,0) -> 0 | BU6: =IF(AND(I6=1,BM6=1),1,0) -> 0 | BV6: =IF(AND(J6=1,BM6=1),1,0) -> 0 | BW6: =数据调研!K6 -> AMZ | BX6: =IF(BW6="AMZ",1,0) -> 1 | BY6: =IF(AND(BX6=1,B6=1),1,0) -> 0 | BZ6: =IF(AND(BX6=1,C6=1),1,0) -> 0 | CA6: =IF(AND(BX6=1,D6=1),1,0) -> 0 | CB6: =IF(AND(BX6=1,E6=1),1,0) -> 1 | CC6: =IF(AND(BX6=1,F6=1),1,0) -> 0 | CD6: =IF(AND(BX6=1,G6=1),1,0) -> 0 | CE6: =IF(AND(BX6=1,H6=1),1,0) -> 0 | CF6: =IF(AND(BX6=1,I6=1),1,0) -> 0 | CG6: =IF(AND(BX6=1,J6=1),1,0) -> 0 | CH6: =IF(BW6="FBA",1,0) -> 0 | CI6: =IF(AND(CH6=1,B6=1),1,0) -> 0 | CJ6: =IF(AND(CH6=1,C6=1),1,0) -> 0 | CK6: =IF(AND(CH6=1,D6=1),1,0) -> 0 | CL6: =IF(AND(CH6=1,E6=1),1,0) -> 0 | CM6: =IF(AND(CH6=1,F6=1),1,0) -> 0 | CN6: =IF(AND(CH6=1,G6=1),1,0) -> 0 | CO6: =IF(AND(CH6=1,H6=1),1,0) -> 0 | CP6: =IF(AND(CH6=1,I6=1),1,0) -> 0 | CQ6: =IF(AND(CH6=1,J6=1),1,0) -> 0 | CR6: =数据调研!N6 -> 4374 | CS6: =IF(AND(CR6<31,CR6<>0),1,0) -> 0 | CT6: =IF(AND(CS6=1,B6=1),1,0) -> 0 | CU6: =IF(AND(CS6=1,C6=1),1,0) -> 0 | CV6: =IF(AND(CS6=1,D6=1),1,0) -> 0 | CW6: =IF(AND(CS6=1,E6=1),1,0) -> 0 | CX6: =IF(AND(CS6=1,F6=1),1,0) -> 0 | CY6: =IF(AND(CS6=1,G6=1),1,0) -> 0 | CZ6: =IF(AND(CS6=1,H6=1),1,0) -> 0 | DA6: =IF(AND(CS6=1,I6=1),1,0) -> 0 | DB6: =IF(AND(CS6=1,J6=1),1,0) -> 0 | DC6: =IF(AND(CR6>30,CR6<61),1,0) -> 0 | DD6: =IF(AND(DC6=1,B6=1),1,0) -> 0 | DE6: =IF(AND(DC6=1,C6=1),1,0) -> 0 | DF6: =IF(AND(DC6=1,D6=1),1,0) -> 0 | DG6: =IF(AND(DC6=1,E6=1),1,0) -> 0 | DH6: =IF(AND(DC6=1,F6=1),1,0) -> 0 | DI6: =IF(AND(DC6=1,G6=1),1,0) -> 0 | DJ6: =IF(AND(DC6=1,H6=1),1,0) -> 0 | DK6: =IF(AND(DC6=1,I6=1),1,0) -> 0 | DL6: =IF(AND(DC6=1,J6=1),1,0) -> 0 | DM6: =IF(AND(CR6>60,CR6<91),1,0) -> 0 | DN6: =IF(AND(DM6=1,B6=1),1,0) -> 0 | DO6: =IF(AND(DM6=1,C6=1),1,0) -> 0 | DP6: =IF(AND(DM6=1,D6=1),1,0) -> 0 | DQ6: =IF(AND(DM6=1,E6=1),1,0) -> 0 | DR6: =IF(AND(DM6=1,F6=1),1,0) -> 0 | DS6: =IF(AND(DM6=1,G6=1),1,0) -> 0 | DT6: =IF(AND(DM6=1,H6=1),1,0) -> 0 | DU6: =IF(AND(DM6=1,I6=1),1,0) -> 0 | DV6: =IF(AND(DM6=1,J6=1),1,0) -> 0 | DW6: =IF(AND(CR6>90,CR6<181),1,0) -> 0 | DX6: =IF(AND(DW6=1,B6=1),1,0) -> 0 | DY6: =IF(AND(DW6=1,C6=1),1,0) -> 0 | DZ6: =IF(AND(DW6=1,D6=1),1,0) -> 0 | EA6: =IF(AND(DW6=1,E6=1),1,0) -> 0 | EB6: =IF(AND(DW6=1,F6=1),1,0) -> 0 | EC6: =IF(AND(DW6=1,G6=1),1,0) -> 0 | ED6: =IF(AND(DW6=1,H6=1),1,0) -> 0 | EE6: =IF(AND(DW6=1,I6=1),1,0) -> 0 | EF6: =IF(AND(DW6=1,J6=1),1,0) -> 0 | EG6: =IF(CR6>180,1,0) -> 1 | EH6: =IF(AND(EG6=1,B6=1),1,0) -> 0 | EI6: =IF(AND(EG6=1,C6=1),1,0) -> 0 | EJ6: =IF(AND(EG6=1,D6=1),1,0) -> 0 | EK6: =IF(AND(EG6=1,E6=1),1,0) -> 1 | EL6: =IF(AND(EG6=1,F6=1),1,0) -> 0 | EM6: =IF(AND(EG6=1,G6=1),1,0) -> 0 | EN6: =IF(AND(EG6=1,H6=1),1,0) -> 0 | EO6: =IF(AND(EG6=1,I6=1),1,0) -> 0 | EP6: =IF(AND(EG6=1,J6=1),1,0) -> 0 | ER6: 3 | ES6: 500-999 | ET6: =D163 -> 4
A7: =数据调研!F7 -> 2511 | B7: =IF(AND(A7>0,A7<100),1,0) -> 0 | C7: =IF(AND(A7>99,A7<500),1,0) -> 0 | D7: =IF(AND(A7>499,A7<1000),1,0) -> 0 | E7: =IF(AND(A7>999,A7<2000),1,0) -> 0 | F7: =IF(AND(A7>1999,A7<4000),1,0) -> 1 | G7: =IF(AND(A7>3999,A7<6000),1,0) -> 0 | H7: =IF(AND(A7>5999,A7<8000),1,0) -> 0 | I7: =IF(AND(A7>7999,A7<10001),1,0) -> 0 | J7: =IF(A7>10002,1,0) -> 0 | K7: =价格参考!K7 -> 960 | L7: =IF(AND(K7>0,K7<301),1,0) -> 0 | M7: =IF(AND(K7>300,K7<501),1,0) -> 0 | N7: =IF(AND(K7>500,K7<801),1,0) -> 0 | O7: =IF(AND(K7>800,K7<1001),1,0) -> 1 | P7: =IF(AND(K7>1000,K7<1501),1,0) -> 0 | Q7: =IF(AND(K7>1500,K7<2001),1,0) -> 0 | R7: =IF(AND(K7>2000,K7<3001),1,0) -> 0 | S7: =IF(AND(K7>3000,K7<4501),1,0) -> 0 | T7: =IF(AND(K7>4500,K7<6001),1,0) -> 0 | U7: =IF(AND(K7>6000,K7<8001),1,0) -> 0 | V7: =IF(AND(K7>8000,K7<>"N.A.",K7<>"< 5"),1,0) -> 0 | W7: =IF(A7<>"N.A.",A7,1000000) -> 2511 | X7: =数据调研!I7 -> 13 | Y7: =IF(X7<31,1,0) -> 1 | Z7: =IF(AND(Y7=1,B7=1),1,0) -> 0 | AA7: =IF(AND(Y7=1,C7=1),1,0) -> 0 | AB7: =IF(AND(Y7=1,D7=1),1,0) -> 0 | AC7: =IF(AND(Y7=1,E7=1),1,0) -> 0 | AD7: =IF(AND(Y7=1,F7=1),1,0) -> 1 | AE7: =IF(AND(Y7=1,G7=1),1,0) -> 0 | AF7: =IF(AND(Y7=1,H7=1),1,0) -> 0 | AG7: =IF(AND(Y7=1,I7=1),1,0) -> 0 | AH7: =IF(AND(Y7=1,J7=1),1,0) -> 0 | AI7: =IF(AND(X7>30,X7<101),1,0) -> 0 | AJ7: =IF(AND(AI7=1,B7=1),1,0) -> 0 | AK7: =IF(AND(AI7=1,C7=1),1,0) -> 0 | AL7: =IF(AND(AI7=1,D7=1),1,0) -> 0 | AM7: =IF(AND(AI7=1,E7=1),1,0) -> 0 | AN7: =IF(AND(AI7=1,F7=1),1,0) -> 0 | AO7: =IF(AND(AI7=1,G7=1),1,0) -> 0 | AP7: =IF(AND(AI7=1,H7=1),1,0) -> 0 | AQ7: =IF(AND(AI7=1,I7=1),1,0) -> 0 | AR7: =IF(AND(AI7=1,J7=1),1,0) -> 0 | AS7: =IF(AND(X7>100,X7<501),1,0) -> 0 | AT7: =IF(AND(B7=1,AS7=1),1,0) -> 0 | AU7: =IF(AND(C7=1,AS7=1),1,0) -> 0 | AV7: =IF(AND(D7=1,AS7=1),1,0) -> 0 | AW7: =IF(AND(E7=1,AS7=1),1,0) -> 0 | AX7: =IF(AND(F7=1,AS7=1),1,0) -> 0 | AY7: =IF(AND(G7=1,AS7=1),1,0) -> 0 | AZ7: =IF(AND(H7=1,AS7=1),1,0) -> 0 | BA7: =IF(AND(I7=1,AS7=1),1,0) -> 0 | BB7: =IF(AND(J7=1,AS7=1),1,0) -> 0 | BC7: =IF(AND(X7>500,X7<1001),1,0) -> 0 | BD7: =IF(AND(BC7=1,B7=1),1,0) -> 0 | BE7: =IF(AND(BC7=1,C7=1),1,0) -> 0 | BF7: =IF(AND(BC7=1,D7=1),1,0) -> 0 | BG7: =IF(AND(BC7=1,E7=1),1,0) -> 0 | BH7: =IF(AND(BC7=1,F7=1),1,0) -> 0 | BI7: =IF(AND(BC7=1,G7=1),1,0) -> 0 | BJ7: =IF(AND(BC7=1,H7=1),1,0) -> 0 | BK7: =IF(AND(BC7=1,I7=1),1,0) -> 0 | BL7: =IF(AND(BC7=1,J7=1),1,0) -> 0 | BM7: =IF(X7>1001,1,0) -> 0 | BN7: =IF(AND(B7=1,BM7=1),1,0) -> 0 | BO7: =IF(AND(C7=1,BM7=1),1,0) -> 0 | BP7: =IF(AND(D7=1,BM7=1),1,0) -> 0 | BQ7: =IF(AND(E7=1,BM7=1),1,0) -> 0 | BR7: =IF(AND(F7=1,BM7=1),1,0) -> 0 | BS7: =IF(AND(G7=1,BM7=1),1,0) -> 0 | BT7: =IF(AND(H7=1,BM7=1),1,0) -> 0 | BU7: =IF(AND(I7=1,BM7=1),1,0) -> 0 | BV7: =IF(AND(J7=1,BM7=1),1,0) -> 0 | BW7: =数据调研!K7 -> FBA | BX7: =IF(BW7="AMZ",1,0) -> 0 | BY7: =IF(AND(BX7=1,B7=1),1,0) -> 0 | BZ7: =IF(AND(BX7=1,C7=1),1,0) -> 0 | CA7: =IF(AND(BX7=1,D7=1),1,0) -> 0 | CB7: =IF(AND(BX7=1,E7=1),1,0) -> 0 | CC7: =IF(AND(BX7=1,F7=1),1,0) -> 0 | CD7: =IF(AND(BX7=1,G7=1),1,0) -> 0 | CE7: =IF(AND(BX7=1,H7=1),1,0) -> 0 | CF7: =IF(AND(BX7=1,I7=1),1,0) -> 0 | CG7: =IF(AND(BX7=1,J7=1),1,0) -> 0 | CH7: =IF(BW7="FBA",1,0) -> 1 | CI7: =IF(AND(CH7=1,B7=1),1,0) -> 0 | CJ7: =IF(AND(CH7=1,C7=1),1,0) -> 0 | CK7: =IF(AND(CH7=1,D7=1),1,0) -> 0 | CL7: =IF(AND(CH7=1,E7=1),1,0) -> 0 | CM7: =IF(AND(CH7=1,F7=1),1,0) -> 1 | CN7: =IF(AND(CH7=1,G7=1),1,0) -> 0 | CO7: =IF(AND(CH7=1,H7=1),1,0) -> 0 | CP7: =IF(AND(CH7=1,I7=1),1,0) -> 0 | CQ7: =IF(AND(CH7=1,J7=1),1,0) -> 0 | CR7: =数据调研!N7 -> 96 | CS7: =IF(AND(CR7<31,CR7<>0),1,0) -> 0 | CT7: =IF(AND(CS7=1,B7=1),1,0) -> 0 | CU7: =IF(AND(CS7=1,C7=1),1,0) -> 0 | CV7: =IF(AND(CS7=1,D7=1),1,0) -> 0 | CW7: =IF(AND(CS7=1,E7=1),1,0) -> 0 | CX7: =IF(AND(CS7=1,F7=1),1,0) -> 0 | CY7: =IF(AND(CS7=1,G7=1),1,0) -> 0 | CZ7: =IF(AND(CS7=1,H7=1),1,0) -> 0 | DA7: =IF(AND(CS7=1,I7=1),1,0) -> 0 | DB7: =IF(AND(CS7=1,J7=1),1,0) -> 0 | DC7: =IF(AND(CR7>30,CR7<61),1,0) -> 0 | DD7: =IF(AND(DC7=1,B7=1),1,0) -> 0 | DE7: =IF(AND(DC7=1,C7=1),1,0) -> 0 | DF7: =IF(AND(DC7=1,D7=1),1,0) -> 0 | DG7: =IF(AND(DC7=1,E7=1),1,0) -> 0 | DH7: =IF(AND(DC7=1,F7=1),1,0) -> 0 | DI7: =IF(AND(DC7=1,G7=1),1,0) -> 0 | DJ7: =IF(AND(DC7=1,H7=1),1,0) -> 0 | DK7: =IF(AND(DC7=1,I7=1),1,0) -> 0 | DL7: =IF(AND(DC7=1,J7=1),1,0) -> 0 | DM7: =IF(AND(CR7>60,CR7<91),1,0) -> 0 | DN7: =IF(AND(DM7=1,B7=1),1,0) -> 0 | DO7: =IF(AND(DM7=1,C7=1),1,0) -> 0 | DP7: =IF(AND(DM7=1,D7=1),1,0) -> 0 | DQ7: =IF(AND(DM7=1,E7=1),1,0) -> 0 | DR7: =IF(AND(DM7=1,F7=1),1,0) -> 0 | DS7: =IF(AND(DM7=1,G7=1),1,0) -> 0 | DT7: =IF(AND(DM7=1,H7=1),1,0) -> 0 | DU7: =IF(AND(DM7=1,I7=1),1,0) -> 0 | DV7: =IF(AND(DM7=1,J7=1),1,0) -> 0 | DW7: =IF(AND(CR7>90,CR7<181),1,0) -> 1 | DX7: =IF(AND(DW7=1,B7=1),1,0) -> 0 | DY7: =IF(AND(DW7=1,C7=1),1,0) -> 0 | DZ7: =IF(AND(DW7=1,D7=1),1,0) -> 0 | EA7: =IF(AND(DW7=1,E7=1),1,0) -> 0 | EB7: =IF(AND(DW7=1,F7=1),1,0) -> 1 | EC7: =IF(AND(DW7=1,G7=1),1,0) -> 0 | ED7: =IF(AND(DW7=1,H7=1),1,0) -> 0 | EE7: =IF(AND(DW7=1,I7=1),1,0) -> 0 | EF7: =IF(AND(DW7=1,J7=1),1,0) -> 0 | EG7: =IF(CR7>180,1,0) -> 0 | EH7: =IF(AND(EG7=1,B7=1),1,0) -> 0 | EI7: =IF(AND(EG7=1,C7=1),1,0) -> 0 | EJ7: =IF(AND(EG7=1,D7=1),1,0) -> 0 | EK7: =IF(AND(EG7=1,E7=1),1,0) -> 0 | EL7: =IF(AND(EG7=1,F7=1),1,0) -> 0 | EM7: =IF(AND(EG7=1,G7=1),1,0) -> 0 | EN7: =IF(AND(EG7=1,H7=1),1,0) -> 0 | EO7: =IF(AND(EG7=1,I7=1),1,0) -> 0 | EP7: =IF(AND(EG7=1,J7=1),1,0) -> 0 | ER7: 4 | ES7: 1000-1999 | ET7: =E163 -> 2
A8: =数据调研!F8 -> 2921 | B8: =IF(AND(A8>0,A8<100),1,0) -> 0 | C8: =IF(AND(A8>99,A8<500),1,0) -> 0 | D8: =IF(AND(A8>499,A8<1000),1,0) -> 0 | E8: =IF(AND(A8>999,A8<2000),1,0) -> 0 | F8: =IF(AND(A8>1999,A8<4000),1,0) -> 1 | G8: =IF(AND(A8>3999,A8<6000),1,0) -> 0 | H8: =IF(AND(A8>5999,A8<8000),1,0) -> 0 | I8: =IF(AND(A8>7999,A8<10001),1,0) -> 0 | J8: =IF(A8>10002,1,0) -> 0 | K8: =价格参考!K8 -> 840 | L8: =IF(AND(K8>0,K8<301),1,0) -> 0 | M8: =IF(AND(K8>300,K8<501),1,0) -> 0 | N8: =IF(AND(K8>500,K8<801),1,0) -> 0 | O8: =IF(AND(K8>800,K8<1001),1,0) -> 1 | P8: =IF(AND(K8>1000,K8<1501),1,0) -> 0 | Q8: =IF(AND(K8>1500,K8<2001),1,0) -> 0 | R8: =IF(AND(K8>2000,K8<3001),1,0) -> 0 | S8: =IF(AND(K8>3000,K8<4501),1,0) -> 0 | T8: =IF(AND(K8>4500,K8<6001),1,0) -> 0 | U8: =IF(AND(K8>6000,K8<8001),1,0) -> 0 | V8: =IF(AND(K8>8000,K8<>"N.A.",K8<>"< 5"),1,0) -> 0 | W8: =IF(A8<>"N.A.",A8,1000000) -> 2921 | X8: =数据调研!I8 -> 13 | Y8: =IF(X8<31,1,0) -> 1 | Z8: =IF(AND(Y8=1,B8=1),1,0) -> 0 | AA8: =IF(AND(Y8=1,C8=1),1,0) -> 0 | AB8: =IF(AND(Y8=1,D8=1),1,0) -> 0 | AC8: =IF(AND(Y8=1,E8=1),1,0) -> 0 | AD8: =IF(AND(Y8=1,F8=1),1,0) -> 1 | AE8: =IF(AND(Y8=1,G8=1),1,0) -> 0 | AF8: =IF(AND(Y8=1,H8=1),1,0) -> 0 | AG8: =IF(AND(Y8=1,I8=1),1,0) -> 0 | AH8: =IF(AND(Y8=1,J8=1),1,0) -> 0 | AI8: =IF(AND(X8>30,X8<101),1,0) -> 0 | AJ8: =IF(AND(AI8=1,B8=1),1,0) -> 0 | AK8: =IF(AND(AI8=1,C8=1),1,0) -> 0 | AL8: =IF(AND(AI8=1,D8=1),1,0) -> 0 | AM8: =IF(AND(AI8=1,E8=1),1,0) -> 0 | AN8: =IF(AND(AI8=1,F8=1),1,0) -> 0 | AO8: =IF(AND(AI8=1,G8=1),1,0) -> 0 | AP8: =IF(AND(AI8=1,H8=1),1,0) -> 0 | AQ8: =IF(AND(AI8=1,I8=1),1,0) -> 0 | AR8: =IF(AND(AI8=1,J8=1),1,0) -> 0 | AS8: =IF(AND(X8>100,X8<501),1,0) -> 0 | AT8: =IF(AND(B8=1,AS8=1),1,0) -> 0 | AU8: =IF(AND(C8=1,AS8=1),1,0) -> 0 | AV8: =IF(AND(D8=1,AS8=1),1,0) -> 0 | AW8: =IF(AND(E8=1,AS8=1),1,0) -> 0 | AX8: =IF(AND(F8=1,AS8=1),1,0) -> 0 | AY8: =IF(AND(G8=1,AS8=1),1,0) -> 0 | AZ8: =IF(AND(H8=1,AS8=1),1,0) -> 0 | BA8: =IF(AND(I8=1,AS8=1),1,0) -> 0 | BB8: =IF(AND(J8=1,AS8=1),1,0) -> 0 | BC8: =IF(AND(X8>500,X8<1001),1,0) -> 0 | BD8: =IF(AND(BC8=1,B8=1),1,0) -> 0 | BE8: =IF(AND(BC8=1,C8=1),1,0) -> 0 | BF8: =IF(AND(BC8=1,D8=1),1,0) -> 0 | BG8: =IF(AND(BC8=1,E8=1),1,0) -> 0 | BH8: =IF(AND(BC8=1,F8=1),1,0) -> 0 | BI8: =IF(AND(BC8=1,G8=1),1,0) -> 0 | BJ8: =IF(AND(BC8=1,H8=1),1,0) -> 0 | BK8: =IF(AND(BC8=1,I8=1),1,0) -> 0 | BL8: =IF(AND(BC8=1,J8=1),1,0) -> 0 | BM8: =IF(X8>1001,1,0) -> 0 | BN8: =IF(AND(B8=1,BM8=1),1,0) -> 0 | BO8: =IF(AND(C8=1,BM8=1),1,0) -> 0 | BP8: =IF(AND(D8=1,BM8=1),1,0) -> 0 | BQ8: =IF(AND(E8=1,BM8=1),1,0) -> 0 | BR8: =IF(AND(F8=1,BM8=1),1,0) -> 0 | BS8: =IF(AND(G8=1,BM8=1),1,0) -> 0 | BT8: =IF(AND(H8=1,BM8=1),1,0) -> 0 | BU8: =IF(AND(I8=1,BM8=1),1,0) -> 0 | BV8: =IF(AND(J8=1,BM8=1),1,0) -> 0 | BW8: =数据调研!K8 -> FBA | BX8: =IF(BW8="AMZ",1,0) -> 0 | BY8: =IF(AND(BX8=1,B8=1),1,0) -> 0 | BZ8: =IF(AND(BX8=1,C8=1),1,0) -> 0 | CA8: =IF(AND(BX8=1,D8=1),1,0) -> 0 | CB8: =IF(AND(BX8=1,E8=1),1,0) -> 0 | CC8: =IF(AND(BX8=1,F8=1),1,0) -> 0 | CD8: =IF(AND(BX8=1,G8=1),1,0) -> 0 | CE8: =IF(AND(BX8=1,H8=1),1,0) -> 0 | CF8: =IF(AND(BX8=1,I8=1),1,0) -> 0 | CG8: =IF(AND(BX8=1,J8=1),1,0) -> 0 | CH8: =IF(BW8="FBA",1,0) -> 1 | CI8: =IF(AND(CH8=1,B8=1),1,0) -> 0 | CJ8: =IF(AND(CH8=1,C8=1),1,0) -> 0 | CK8: =IF(AND(CH8=1,D8=1),1,0) -> 0 | CL8: =IF(AND(CH8=1,E8=1),1,0) -> 0 | CM8: =IF(AND(CH8=1,F8=1),1,0) -> 1 | CN8: =IF(AND(CH8=1,G8=1),1,0) -> 0 | CO8: =IF(AND(CH8=1,H8=1),1,0) -> 0 | CP8: =IF(AND(CH8=1,I8=1),1,0) -> 0 | CQ8: =IF(AND(CH8=1,J8=1),1,0) -> 0 | CR8: =数据调研!N8 -> 96 | CS8: =IF(AND(CR8<31,CR8<>0),1,0) -> 0 | CT8: =IF(AND(CS8=1,B8=1),1,0) -> 0 | CU8: =IF(AND(CS8=1,C8=1),1,0) -> 0 | CV8: =IF(AND(CS8=1,D8=1),1,0) -> 0 | CW8: =IF(AND(CS8=1,E8=1),1,0) -> 0 | CX8: =IF(AND(CS8=1,F8=1),1,0) -> 0 | CY8: =IF(AND(CS8=1,G8=1),1,0) -> 0 | CZ8: =IF(AND(CS8=1,H8=1),1,0) -> 0 | DA8: =IF(AND(CS8=1,I8=1),1,0) -> 0 | DB8: =IF(AND(CS8=1,J8=1),1,0) -> 0 | DC8: =IF(AND(CR8>30,CR8<61),1,0) -> 0 | DD8: =IF(AND(DC8=1,B8=1),1,0) -> 0 | DE8: =IF(AND(DC8=1,C8=1),1,0) -> 0 | DF8: =IF(AND(DC8=1,D8=1),1,0) -> 0 | DG8: =IF(AND(DC8=1,E8=1),1,0) -> 0 | DH8: =IF(AND(DC8=1,F8=1),1,0) -> 0 | DI8: =IF(AND(DC8=1,G8=1),1,0) -> 0 | DJ8: =IF(AND(DC8=1,H8=1),1,0) -> 0 | DK8: =IF(AND(DC8=1,I8=1),1,0) -> 0 | DL8: =IF(AND(DC8=1,J8=1),1,0) -> 0 | DM8: =IF(AND(CR8>60,CR8<91),1,0) -> 0 | DN8: =IF(AND(DM8=1,B8=1),1,0) -> 0 | DO8: =IF(AND(DM8=1,C8=1),1,0) -> 0 | DP8: =IF(AND(DM8=1,D8=1),1,0) -> 0 | DQ8: =IF(AND(DM8=1,E8=1),1,0) -> 0 | DR8: =IF(AND(DM8=1,F8=1),1,0) -> 0 | DS8: =IF(AND(DM8=1,G8=1),1,0) -> 0 | DT8: =IF(AND(DM8=1,H8=1),1,0) -> 0 | DU8: =IF(AND(DM8=1,I8=1),1,0) -> 0 | DV8: =IF(AND(DM8=1,J8=1),1,0) -> 0 | DW8: =IF(AND(CR8>90,CR8<181),1,0) -> 1 | DX8: =IF(AND(DW8=1,B8=1),1,0) -> 0 | DY8: =IF(AND(DW8=1,C8=1),1,0) -> 0 | DZ8: =IF(AND(DW8=1,D8=1),1,0) -> 0 | EA8: =IF(AND(DW8=1,E8=1),1,0) -> 0 | EB8: =IF(AND(DW8=1,F8=1),1,0) -> 1 | EC8: =IF(AND(DW8=1,G8=1),1,0) -> 0 | ED8: =IF(AND(DW8=1,H8=1),1,0) -> 0 | EE8: =IF(AND(DW8=1,I8=1),1,0) -> 0 | EF8: =IF(AND(DW8=1,J8=1),1,0) -> 0 | EG8: =IF(CR8>180,1,0) -> 0 | EH8: =IF(AND(EG8=1,B8=1),1,0) -> 0 | EI8: =IF(AND(EG8=1,C8=1),1,0) -> 0 | EJ8: =IF(AND(EG8=1,D8=1),1,0) -> 0 | EK8: =IF(AND(EG8=1,E8=1),1,0) -> 0 | EL8: =IF(AND(EG8=1,F8=1),1,0) -> 0 | EM8: =IF(AND(EG8=1,G8=1),1,0) -> 0 | EN8: =IF(AND(EG8=1,H8=1),1,0) -> 0 | EO8: =IF(AND(EG8=1,I8=1),1,0) -> 0 | EP8: =IF(AND(EG8=1,J8=1),1,0) -> 0 | ER8: 5 | ES8: 2000-3999 | ET8: =F163 -> 2
A9: =数据调研!F9 -> 6044 | B9: =IF(AND(A9>0,A9<100),1,0) -> 0 | C9: =IF(AND(A9>99,A9<500),1,0) -> 0 | D9: =IF(AND(A9>499,A9<1000),1,0) -> 0 | E9: =IF(AND(A9>999,A9<2000),1,0) -> 0 | F9: =IF(AND(A9>1999,A9<4000),1,0) -> 0 | G9: =IF(AND(A9>3999,A9<6000),1,0) -> 0 | H9: =IF(AND(A9>5999,A9<8000),1,0) -> 1 | I9: =IF(AND(A9>7999,A9<10001),1,0) -> 0 | J9: =IF(A9>10002,1,0) -> 0 | K9: =价格参考!K9 -> 420 | L9: =IF(AND(K9>0,K9<301),1,0) -> 0 | M9: =IF(AND(K9>300,K9<501),1,0) -> 1 | N9: =IF(AND(K9>500,K9<801),1,0) -> 0 | O9: =IF(AND(K9>800,K9<1001),1,0) -> 0 | P9: =IF(AND(K9>1000,K9<1501),1,0) -> 0 | Q9: =IF(AND(K9>1500,K9<2001),1,0) -> 0 | R9: =IF(AND(K9>2000,K9<3001),1,0) -> 0 | S9: =IF(AND(K9>3000,K9<4501),1,0) -> 0 | T9: =IF(AND(K9>4500,K9<6001),1,0) -> 0 | U9: =IF(AND(K9>6000,K9<8001),1,0) -> 0 | V9: =IF(AND(K9>8000,K9<>"N.A.",K9<>"< 5"),1,0) -> 0 | W9: =IF(A9<>"N.A.",A9,1000000) -> 6044 | X9: =数据调研!I9 -> 601 | Y9: =IF(X9<31,1,0) -> 0 | Z9: =IF(AND(Y9=1,B9=1),1,0) -> 0 | AA9: =IF(AND(Y9=1,C9=1),1,0) -> 0 | AB9: =IF(AND(Y9=1,D9=1),1,0) -> 0 | AC9: =IF(AND(Y9=1,E9=1),1,0) -> 0 | AD9: =IF(AND(Y9=1,F9=1),1,0) -> 0 | AE9: =IF(AND(Y9=1,G9=1),1,0) -> 0 | AF9: =IF(AND(Y9=1,H9=1),1,0) -> 0 | AG9: =IF(AND(Y9=1,I9=1),1,0) -> 0 | AH9: =IF(AND(Y9=1,J9=1),1,0) -> 0 | AI9: =IF(AND(X9>30,X9<101),1,0) -> 0 | AJ9: =IF(AND(AI9=1,B9=1),1,0) -> 0 | AK9: =IF(AND(AI9=1,C9=1),1,0) -> 0 | AL9: =IF(AND(AI9=1,D9=1),1,0) -> 0 | AM9: =IF(AND(AI9=1,E9=1),1,0) -> 0 | AN9: =IF(AND(AI9=1,F9=1),1,0) -> 0 | AO9: =IF(AND(AI9=1,G9=1),1,0) -> 0 | AP9: =IF(AND(AI9=1,H9=1),1,0) -> 0 | AQ9: =IF(AND(AI9=1,I9=1),1,0) -> 0 | AR9: =IF(AND(AI9=1,J9=1),1,0) -> 0 | AS9: =IF(AND(X9>100,X9<501),1,0) -> 0 | AT9: =IF(AND(B9=1,AS9=1),1,0) -> 0 | AU9: =IF(AND(C9=1,AS9=1),1,0) -> 0 | AV9: =IF(AND(D9=1,AS9=1),1,0) -> 0 | AW9: =IF(AND(E9=1,AS9=1),1,0) -> 0 | AX9: =IF(AND(F9=1,AS9=1),1,0) -> 0 | AY9: =IF(AND(G9=1,AS9=1),1,0) -> 0 | AZ9: =IF(AND(H9=1,AS9=1),1,0) -> 0 | BA9: =IF(AND(I9=1,AS9=1),1,0) -> 0 | BB9: =IF(AND(J9=1,AS9=1),1,0) -> 0 | BC9: =IF(AND(X9>500,X9<1001),1,0) -> 1 | BD9: =IF(AND(BC9=1,B9=1),1,0) -> 0 | BE9: =IF(AND(BC9=1,C9=1),1,0) -> 0 | BF9: =IF(AND(BC9=1,D9=1),1,0) -> 0 | BG9: =IF(AND(BC9=1,E9=1),1,0) -> 0 | BH9: =IF(AND(BC9=1,F9=1),1,0) -> 0 | BI9: =IF(AND(BC9=1,G9=1),1,0) -> 0 | BJ9: =IF(AND(BC9=1,H9=1),1,0) -> 1 | BK9: =IF(AND(BC9=1,I9=1),1,0) -> 0 | BL9: =IF(AND(BC9=1,J9=1),1,0) -> 0 | BM9: =IF(X9>1001,1,0) -> 0 | BN9: =IF(AND(B9=1,BM9=1),1,0) -> 0 | BO9: =IF(AND(C9=1,BM9=1),1,0) -> 0 | BP9: =IF(AND(D9=1,BM9=1),1,0) -> 0 | BQ9: =IF(AND(E9=1,BM9=1),1,0) -> 0 | BR9: =IF(AND(F9=1,BM9=1),1,0) -> 0 | BS9: =IF(AND(G9=1,BM9=1),1,0) -> 0 | BT9: =IF(AND(H9=1,BM9=1),1,0) -> 0 | BU9: =IF(AND(I9=1,BM9=1),1,0) -> 0 | BV9: =IF(AND(J9=1,BM9=1),1,0) -> 0 | BW9: =数据调研!K9 -> FBA | BX9: =IF(BW9="AMZ",1,0) -> 0 | BY9: =IF(AND(BX9=1,B9=1),1,0) -> 0 | BZ9: =IF(AND(BX9=1,C9=1),1,0) -> 0 | CA9: =IF(AND(BX9=1,D9=1),1,0) -> 0 | CB9: =IF(AND(BX9=1,E9=1),1,0) -> 0 | CC9: =IF(AND(BX9=1,F9=1),1,0) -> 0 | CD9: =IF(AND(BX9=1,G9=1),1,0) -> 0 | CE9: =IF(AND(BX9=1,H9=1),1,0) -> 0 | CF9: =IF(AND(BX9=1,I9=1),1,0) -> 0 | CG9: =IF(AND(BX9=1,J9=1),1,0) -> 0 | CH9: =IF(BW9="FBA",1,0) -> 1 | CI9: =IF(AND(CH9=1,B9=1),1,0) -> 0 | CJ9: =IF(AND(CH9=1,C9=1),1,0) -> 0 | CK9: =IF(AND(CH9=1,D9=1),1,0) -> 0 | CL9: =IF(AND(CH9=1,E9=1),1,0) -> 0 | CM9: =IF(AND(CH9=1,F9=1),1,0) -> 0 | CN9: =IF(AND(CH9=1,G9=1),1,0) -> 0 | CO9: =IF(AND(CH9=1,H9=1),1,0) -> 1 | CP9: =IF(AND(CH9=1,I9=1),1,0) -> 0 | CQ9: =IF(AND(CH9=1,J9=1),1,0) -> 0 | CR9: =数据调研!N9 -> 256 | CS9: =IF(AND(CR9<31,CR9<>0),1,0) -> 0 | CT9: =IF(AND(CS9=1,B9=1),1,0) -> 0 | CU9: =IF(AND(CS9=1,C9=1),1,0) -> 0 | CV9: =IF(AND(CS9=1,D9=1),1,0) -> 0 | CW9: =IF(AND(CS9=1,E9=1),1,0) -> 0 | CX9: =IF(AND(CS9=1,F9=1),1,0) -> 0 | CY9: =IF(AND(CS9=1,G9=1),1,0) -> 0 | CZ9: =IF(AND(CS9=1,H9=1),1,0) -> 0 | DA9: =IF(AND(CS9=1,I9=1),1,0) -> 0 | DB9: =IF(AND(CS9=1,J9=1),1,0) -> 0 | DC9: =IF(AND(CR9>30,CR9<61),1,0) -> 0 | DD9: =IF(AND(DC9=1,B9=1),1,0) -> 0 | DE9: =IF(AND(DC9=1,C9=1),1,0) -> 0 | DF9: =IF(AND(DC9=1,D9=1),1,0) -> 0 | DG9: =IF(AND(DC9=1,E9=1),1,0) -> 0 | DH9: =IF(AND(DC9=1,F9=1),1,0) -> 0 | DI9: =IF(AND(DC9=1,G9=1),1,0) -> 0 | DJ9: =IF(AND(DC9=1,H9=1),1,0) -> 0 | DK9: =IF(AND(DC9=1,I9=1),1,0) -> 0 | DL9: =IF(AND(DC9=1,J9=1),1,0) -> 0 | DM9: =IF(AND(CR9>60,CR9<91),1,0) -> 0 | DN9: =IF(AND(DM9=1,B9=1),1,0) -> 0 | DO9: =IF(AND(DM9=1,C9=1),1,0) -> 0 | DP9: =IF(AND(DM9=1,D9=1),1,0) -> 0 | DQ9: =IF(AND(DM9=1,E9=1),1,0) -> 0 | DR9: =IF(AND(DM9=1,F9=1),1,0) -> 0 | DS9: =IF(AND(DM9=1,G9=1),1,0) -> 0 | DT9: =IF(AND(DM9=1,H9=1),1,0) -> 0 | DU9: =IF(AND(DM9=1,I9=1),1,0) -> 0 | DV9: =IF(AND(DM9=1,J9=1),1,0) -> 0 | DW9: =IF(AND(CR9>90,CR9<181),1,0) -> 0 | DX9: =IF(AND(DW9=1,B9=1),1,0) -> 0 | DY9: =IF(AND(DW9=1,C9=1),1,0) -> 0 | DZ9: =IF(AND(DW9=1,D9=1),1,0) -> 0 | EA9: =IF(AND(DW9=1,E9=1),1,0) -> 0 | EB9: =IF(AND(DW9=1,F9=1),1,0) -> 0 | EC9: =IF(AND(DW9=1,G9=1),1,0) -> 0 | ED9: =IF(AND(DW9=1,H9=1),1,0) -> 0 | EE9: =IF(AND(DW9=1,I9=1),1,0) -> 0 | EF9: =IF(AND(DW9=1,J9=1),1,0) -> 0 | EG9: =IF(CR9>180,1,0) -> 1 | EH9: =IF(AND(EG9=1,B9=1),1,0) -> 0 | EI9: =IF(AND(EG9=1,C9=1),1,0) -> 0 | EJ9: =IF(AND(EG9=1,D9=1),1,0) -> 0 | EK9: =IF(AND(EG9=1,E9=1),1,0) -> 0 | EL9: =IF(AND(EG9=1,F9=1),1,0) -> 0 | EM9: =IF(AND(EG9=1,G9=1),1,0) -> 0 | EN9: =IF(AND(EG9=1,H9=1),1,0) -> 1 | EO9: =IF(AND(EG9=1,I9=1),1,0) -> 0 | EP9: =IF(AND(EG9=1,J9=1),1,0) -> 0 | ER9: 6 | ES9: 4000-5999 | ET9: =G163 -> 0
A10: =数据调研!F10 -> 6553 | B10: =IF(AND(A10>0,A10<100),1,0) -> 0 | C10: =IF(AND(A10>99,A10<500),1,0) -> 0 | D10: =IF(AND(A10>499,A10<1000),1,0) -> 0 | E10: =IF(AND(A10>999,A10<2000),1,0) -> 0 | F10: =IF(AND(A10>1999,A10<4000),1,0) -> 0 | G10: =IF(AND(A10>3999,A10<6000),1,0) -> 0 | H10: =IF(AND(A10>5999,A10<8000),1,0) -> 1 | I10: =IF(AND(A10>7999,A10<10001),1,0) -> 0 | J10: =IF(A10>10002,1,0) -> 0 | K10: =价格参考!K10 -> 390 | L10: =IF(AND(K10>0,K10<301),1,0) -> 0 | M10: =IF(AND(K10>300,K10<501),1,0) -> 1 | N10: =IF(AND(K10>500,K10<801),1,0) -> 0 | O10: =IF(AND(K10>800,K10<1001),1,0) -> 0 | P10: =IF(AND(K10>1000,K10<1501),1,0) -> 0 | Q10: =IF(AND(K10>1500,K10<2001),1,0) -> 0 | R10: =IF(AND(K10>2000,K10<3001),1,0) -> 0 | S10: =IF(AND(K10>3000,K10<4501),1,0) -> 0 | T10: =IF(AND(K10>4500,K10<6001),1,0) -> 0 | U10: =IF(AND(K10>6000,K10<8001),1,0) -> 0 | V10: =IF(AND(K10>8000,K10<>"N.A.",K10<>"< 5"),1,0) -> 0 | W10: =IF(A10<>"N.A.",A10,1000000) -> 6553 | X10: =数据调研!I10 -> 28 | Y10: =IF(X10<31,1,0) -> 1 | Z10: =IF(AND(Y10=1,B10=1),1,0) -> 0 | AA10: =IF(AND(Y10=1,C10=1),1,0) -> 0 | AB10: =IF(AND(Y10=1,D10=1),1,0) -> 0 | AC10: =IF(AND(Y10=1,E10=1),1,0) -> 0 | AD10: =IF(AND(Y10=1,F10=1),1,0) -> 0 | AE10: =IF(AND(Y10=1,G10=1),1,0) -> 0 | AF10: =IF(AND(Y10=1,H10=1),1,0) -> 1 | AG10: =IF(AND(Y10=1,I10=1),1,0) -> 0 | AH10: =IF(AND(Y10=1,J10=1),1,0) -> 0 | AI10: =IF(AND(X10>30,X10<101),1,0) -> 0 | AJ10: =IF(AND(AI10=1,B10=1),1,0) -> 0 | AK10: =IF(AND(AI10=1,C10=1),1,0) -> 0 | AL10: =IF(AND(AI10=1,D10=1),1,0) -> 0 | AM10: =IF(AND(AI10=1,E10=1),1,0) -> 0 | AN10: =IF(AND(AI10=1,F10=1),1,0) -> 0 | AO10: =IF(AND(AI10=1,G10=1),1,0) -> 0 | AP10: =IF(AND(AI10=1,H10=1),1,0) -> 0 | AQ10: =IF(AND(AI10=1,I10=1),1,0) -> 0 | AR10: =IF(AND(AI10=1,J10=1),1,0) -> 0 | AS10: =IF(AND(X10>100,X10<501),1,0) -> 0 | AT10: =IF(AND(B10=1,AS10=1),1,0) -> 0 | AU10: =IF(AND(C10=1,AS10=1),1,0) -> 0 | AV10: =IF(AND(D10=1,AS10=1),1,0) -> 0 | AW10: =IF(AND(E10=1,AS10=1),1,0) -> 0 | AX10: =IF(AND(F10=1,AS10=1),1,0) -> 0 | AY10: =IF(AND(G10=1,AS10=1),1,0) -> 0 | AZ10: =IF(AND(H10=1,AS10=1),1,0) -> 0 | BA10: =IF(AND(I10=1,AS10=1),1,0) -> 0 | BB10: =IF(AND(J10=1,AS10=1),1,0) -> 0 | BC10: =IF(AND(X10>500,X10<1001),1,0) -> 0 | BD10: =IF(AND(BC10=1,B10=1),1,0) -> 0 | BE10: =IF(AND(BC10=1,C10=1),1,0) -> 0 | BF10: =IF(AND(BC10=1,D10=1),1,0) -> 0 | BG10: =IF(AND(BC10=1,E10=1),1,0) -> 0 | BH10: =IF(AND(BC10=1,F10=1),1,0) -> 0 | BI10: =IF(AND(BC10=1,G10=1),1,0) -> 0 | BJ10: =IF(AND(BC10=1,H10=1),1,0) -> 0 | BK10: =IF(AND(BC10=1,I10=1),1,0) -> 0 | BL10: =IF(AND(BC10=1,J10=1),1,0) -> 0 | BM10: =IF(X10>1001,1,0) -> 0 | BN10: =IF(AND(B10=1,BM10=1),1,0) -> 0 | BO10: =IF(AND(C10=1,BM10=1),1,0) -> 0 | BP10: =IF(AND(D10=1,BM10=1),1,0) -> 0 | BQ10: =IF(AND(E10=1,BM10=1),1,0) -> 0 | BR10: =IF(AND(F10=1,BM10=1),1,0) -> 0 | BS10: =IF(AND(G10=1,BM10=1),1,0) -> 0 | BT10: =IF(AND(H10=1,BM10=1),1,0) -> 0 | BU10: =IF(AND(I10=1,BM10=1),1,0) -> 0 | BV10: =IF(AND(J10=1,BM10=1),1,0) -> 0 | BW10: =数据调研!K10 -> FBA | BX10: =IF(BW10="AMZ",1,0) -> 0 | BY10: =IF(AND(BX10=1,B10=1),1,0) -> 0 | BZ10: =IF(AND(BX10=1,C10=1),1,0) -> 0 | CA10: =IF(AND(BX10=1,D10=1),1,0) -> 0 | CB10: =IF(AND(BX10=1,E10=1),1,0) -> 0 | CC10: =IF(AND(BX10=1,F10=1),1,0) -> 0 | CD10: =IF(AND(BX10=1,G10=1),1,0) -> 0 | CE10: =IF(AND(BX10=1,H10=1),1,0) -> 0 | CF10: =IF(AND(BX10=1,I10=1),1,0) -> 0 | CG10: =IF(AND(BX10=1,J10=1),1,0) -> 0 | CH10: =IF(BW10="FBA",1,0) -> 1 | CI10: =IF(AND(CH10=1,B10=1),1,0) -> 0 | CJ10: =IF(AND(CH10=1,C10=1),1,0) -> 0 | CK10: =IF(AND(CH10=1,D10=1),1,0) -> 0 | CL10: =IF(AND(CH10=1,E10=1),1,0) -> 0 | CM10: =IF(AND(CH10=1,F10=1),1,0) -> 0 | CN10: =IF(AND(CH10=1,G10=1),1,0) -> 0 | CO10: =IF(AND(CH10=1,H10=1),1,0) -> 1 | CP10: =IF(AND(CH10=1,I10=1),1,0) -> 0 | CQ10: =IF(AND(CH10=1,J10=1),1,0) -> 0 | CR10: =数据调研!N10 -> 48 | CS10: =IF(AND(CR10<31,CR10<>0),1,0) -> 0 | CT10: =IF(AND(CS10=1,B10=1),1,0) -> 0 | CU10: =IF(AND(CS10=1,C10=1),1,0) -> 0 | CV10: =IF(AND(CS10=1,D10=1),1,0) -> 0 | CW10: =IF(AND(CS10=1,E10=1),1,0) -> 0 | CX10: =IF(AND(CS10=1,F10=1),1,0) -> 0 | CY10: =IF(AND(CS10=1,G10=1),1,0) -> 0 | CZ10: =IF(AND(CS10=1,H10=1),1,0) -> 0 | DA10: =IF(AND(CS10=1,I10=1),1,0) -> 0 | DB10: =IF(AND(CS10=1,J10=1),1,0) -> 0 | DC10: =IF(AND(CR10>30,CR10<61),1,0) -> 1 | DD10: =IF(AND(DC10=1,B10=1),1,0) -> 0 | DE10: =IF(AND(DC10=1,C10=1),1,0) -> 0 | DF10: =IF(AND(DC10=1,D10=1),1,0) -> 0 | DG10: =IF(AND(DC10=1,E10=1),1,0) -> 0 | DH10: =IF(AND(DC10=1,F10=1),1,0) -> 0 | DI10: =IF(AND(DC10=1,G10=1),1,0) -> 0 | DJ10: =IF(AND(DC10=1,H10=1),1,0) -> 1 | DK10: =IF(AND(DC10=1,I10=1),1,0) -> 0 | DL10: =IF(AND(DC10=1,J10=1),1,0) -> 0 | DM10: =IF(AND(CR10>60,CR10<91),1,0) -> 0 | DN10: =IF(AND(DM10=1,B10=1),1,0) -> 0 | DO10: =IF(AND(DM10=1,C10=1),1,0) -> 0 | DP10: =IF(AND(DM10=1,D10=1),1,0) -> 0 | DQ10: =IF(AND(DM10=1,E10=1),1,0) -> 0 | DR10: =IF(AND(DM10=1,F10=1),1,0) -> 0 | DS10: =IF(AND(DM10=1,G10=1),1,0) -> 0 | DT10: =IF(AND(DM10=1,H10=1),1,0) -> 0 | DU10: =IF(AND(DM10=1,I10=1),1,0) -> 0 | DV10: =IF(AND(DM10=1,J10=1),1,0) -> 0 | DW10: =IF(AND(CR10>90,CR10<181),1,0) -> 0 | DX10: =IF(AND(DW10=1,B10=1),1,0) -> 0 | DY10: =IF(AND(DW10=1,C10=1),1,0) -> 0 | DZ10: =IF(AND(DW10=1,D10=1),1,0) -> 0 | EA10: =IF(AND(DW10=1,E10=1),1,0) -> 0 | EB10: =IF(AND(DW10=1,F10=1),1,0) -> 0 | EC10: =IF(AND(DW10=1,G10=1),1,0) -> 0 | ED10: =IF(AND(DW10=1,H10=1),1,0) -> 0 | EE10: =IF(AND(DW10=1,I10=1),1,0) -> 0 | EF10: =IF(AND(DW10=1,J10=1),1,0) -> 0 | EG10: =IF(CR10>180,1,0) -> 0 | EH10: =IF(AND(EG10=1,B10=1),1,0) -> 0 | EI10: =IF(AND(EG10=1,C10=1),1,0) -> 0 | EJ10: =IF(AND(EG10=1,D10=1),1,0) -> 0 | EK10: =IF(AND(EG10=1,E10=1),1,0) -> 0 | EL10: =IF(AND(EG10=1,F10=1),1,0) -> 0 | EM10: =IF(AND(EG10=1,G10=1),1,0) -> 0 | EN10: =IF(AND(EG10=1,H10=1),1,0) -> 0 | EO10: =IF(AND(EG10=1,I10=1),1,0) -> 0 | EP10: =IF(AND(EG10=1,J10=1),1,0) -> 0 | ER10: 7 | ES10: 6000-7999 | ET10: =H163 -> 7
A11: =数据调研!F11 -> 6553 | B11: =IF(AND(A11>0,A11<100),1,0) -> 0 | C11: =IF(AND(A11>99,A11<500),1,0) -> 0 | D11: =IF(AND(A11>499,A11<1000),1,0) -> 0 | E11: =IF(AND(A11>999,A11<2000),1,0) -> 0 | F11: =IF(AND(A11>1999,A11<4000),1,0) -> 0 | G11: =IF(AND(A11>3999,A11<6000),1,0) -> 0 | H11: =IF(AND(A11>5999,A11<8000),1,0) -> 1 | I11: =IF(AND(A11>7999,A11<10001),1,0) -> 0 | J11: =IF(A11>10002,1,0) -> 0 | K11: =价格参考!K11 -> 390 | L11: =IF(AND(K11>0,K11<301),1,0) -> 0 | M11: =IF(AND(K11>300,K11<501),1,0) -> 1 | N11: =IF(AND(K11>500,K11<801),1,0) -> 0 | O11: =IF(AND(K11>800,K11<1001),1,0) -> 0 | P11: =IF(AND(K11>1000,K11<1501),1,0) -> 0 | Q11: =IF(AND(K11>1500,K11<2001),1,0) -> 0 | R11: =IF(AND(K11>2000,K11<3001),1,0) -> 0 | S11: =IF(AND(K11>3000,K11<4501),1,0) -> 0 | T11: =IF(AND(K11>4500,K11<6001),1,0) -> 0 | U11: =IF(AND(K11>6000,K11<8001),1,0) -> 0 | V11: =IF(AND(K11>8000,K11<>"N.A.",K11<>"< 5"),1,0) -> 0 | W11: =IF(A11<>"N.A.",A11,1000000) -> 6553 | X11: =数据调研!I11 -> 28 | Y11: =IF(X11<31,1,0) -> 1 | Z11: =IF(AND(Y11=1,B11=1),1,0) -> 0 | AA11: =IF(AND(Y11=1,C11=1),1,0) -> 0 | AB11: =IF(AND(Y11=1,D11=1),1,0) -> 0 | AC11: =IF(AND(Y11=1,E11=1),1,0) -> 0 | AD11: =IF(AND(Y11=1,F11=1),1,0) -> 0 | AE11: =IF(AND(Y11=1,G11=1),1,0) -> 0 | AF11: =IF(AND(Y11=1,H11=1),1,0) -> 1 | AG11: =IF(AND(Y11=1,I11=1),1,0) -> 0 | AH11: =IF(AND(Y11=1,J11=1),1,0) -> 0 | AI11: =IF(AND(X11>30,X11<101),1,0) -> 0 | AJ11: =IF(AND(AI11=1,B11=1),1,0) -> 0 | AK11: =IF(AND(AI11=1,C11=1),1,0) -> 0 | AL11: =IF(AND(AI11=1,D11=1),1,0) -> 0 | AM11: =IF(AND(AI11=1,E11=1),1,0) -> 0 | AN11: =IF(AND(AI11=1,F11=1),1,0) -> 0 | AO11: =IF(AND(AI11=1,G11=1),1,0) -> 0 | AP11: =IF(AND(AI11=1,H11=1),1,0) -> 0 | AQ11: =IF(AND(AI11=1,I11=1),1,0) -> 0 | AR11: =IF(AND(AI11=1,J11=1),1,0) -> 0 | AS11: =IF(AND(X11>100,X11<501),1,0) -> 0 | AT11: =IF(AND(B11=1,AS11=1),1,0) -> 0 | AU11: =IF(AND(C11=1,AS11=1),1,0) -> 0 | AV11: =IF(AND(D11=1,AS11=1),1,0) -> 0 | AW11: =IF(AND(E11=1,AS11=1),1,0) -> 0 | AX11: =IF(AND(F11=1,AS11=1),1,0) -> 0 | AY11: =IF(AND(G11=1,AS11=1),1,0) -> 0 | AZ11: =IF(AND(H11=1,AS11=1),1,0) -> 0 | BA11: =IF(AND(I11=1,AS11=1),1,0) -> 0 | BB11: =IF(AND(J11=1,AS11=1),1,0) -> 0 | BC11: =IF(AND(X11>500,X11<1001),1,0) -> 0 | BD11: =IF(AND(BC11=1,B11=1),1,0) -> 0 | BE11: =IF(AND(BC11=1,C11=1),1,0) -> 0 | BF11: =IF(AND(BC11=1,D11=1),1,0) -> 0 | BG11: =IF(AND(BC11=1,E11=1),1,0) -> 0 | BH11: =IF(AND(BC11=1,F11=1),1,0) -> 0 | BI11: =IF(AND(BC11=1,G11=1),1,0) -> 0 | BJ11: =IF(AND(BC11=1,H11=1),1,0) -> 0 | BK11: =IF(AND(BC11=1,I11=1),1,0) -> 0 | BL11: =IF(AND(BC11=1,J11=1),1,0) -> 0 | BM11: =IF(X11>1001,1,0) -> 0 | BN11: =IF(AND(B11=1,BM11=1),1,0) -> 0 | BO11: =IF(AND(C11=1,BM11=1),1,0) -> 0 | BP11: =IF(AND(D11=1,BM11=1),1,0) -> 0 | BQ11: =IF(AND(E11=1,BM11=1),1,0) -> 0 | BR11: =IF(AND(F11=1,BM11=1),1,0) -> 0 | BS11: =IF(AND(G11=1,BM11=1),1,0) -> 0 | BT11: =IF(AND(H11=1,BM11=1),1,0) -> 0 | BU11: =IF(AND(I11=1,BM11=1),1,0) -> 0 | BV11: =IF(AND(J11=1,BM11=1),1,0) -> 0 | BW11: =数据调研!K11 -> FBA | BX11: =IF(BW11="AMZ",1,0) -> 0 | BY11: =IF(AND(BX11=1,B11=1),1,0) -> 0 | BZ11: =IF(AND(BX11=1,C11=1),1,0) -> 0 | CA11: =IF(AND(BX11=1,D11=1),1,0) -> 0 | CB11: =IF(AND(BX11=1,E11=1),1,0) -> 0 | CC11: =IF(AND(BX11=1,F11=1),1,0) -> 0 | CD11: =IF(AND(BX11=1,G11=1),1,0) -> 0 | CE11: =IF(AND(BX11=1,H11=1),1,0) -> 0 | CF11: =IF(AND(BX11=1,I11=1),1,0) -> 0 | CG11: =IF(AND(BX11=1,J11=1),1,0) -> 0 | CH11: =IF(BW11="FBA",1,0) -> 1 | CI11: =IF(AND(CH11=1,B11=1),1,0) -> 0 | CJ11: =IF(AND(CH11=1,C11=1),1,0) -> 0 | CK11: =IF(AND(CH11=1,D11=1),1,0) -> 0 | CL11: =IF(AND(CH11=1,E11=1),1,0) -> 0 | CM11: =IF(AND(CH11=1,F11=1),1,0) -> 0 | CN11: =IF(AND(CH11=1,G11=1),1,0) -> 0 | CO11: =IF(AND(CH11=1,H11=1),1,0) -> 1 | CP11: =IF(AND(CH11=1,I11=1),1,0) -> 0 | CQ11: =IF(AND(CH11=1,J11=1),1,0) -> 0 | CR11: =数据调研!N11 -> 48 | CS11: =IF(AND(CR11<31,CR11<>0),1,0) -> 0 | CT11: =IF(AND(CS11=1,B11=1),1,0) -> 0 | CU11: =IF(AND(CS11=1,C11=1),1,0) -> 0 | CV11: =IF(AND(CS11=1,D11=1),1,0) -> 0 | CW11: =IF(AND(CS11=1,E11=1),1,0) -> 0 | CX11: =IF(AND(CS11=1,F11=1),1,0) -> 0 | CY11: =IF(AND(CS11=1,G11=1),1,0) -> 0 | CZ11: =IF(AND(CS11=1,H11=1),1,0) -> 0 | DA11: =IF(AND(CS11=1,I11=1),1,0) -> 0 | DB11: =IF(AND(CS11=1,J11=1),1,0) -> 0 | DC11: =IF(AND(CR11>30,CR11<61),1,0) -> 1 | DD11: =IF(AND(DC11=1,B11=1),1,0) -> 0 | DE11: =IF(AND(DC11=1,C11=1),1,0) -> 0 | DF11: =IF(AND(DC11=1,D11=1),1,0) -> 0 | DG11: =IF(AND(DC11=1,E11=1),1,0) -> 0 | DH11: =IF(AND(DC11=1,F11=1),1,0) -> 0 | DI11: =IF(AND(DC11=1,G11=1),1,0) -> 0 | DJ11: =IF(AND(DC11=1,H11=1),1,0) -> 1 | DK11: =IF(AND(DC11=1,I11=1),1,0) -> 0 | DL11: =IF(AND(DC11=1,J11=1),1,0) -> 0 | DM11: =IF(AND(CR11>60,CR11<91),1,0) -> 0 | DN11: =IF(AND(DM11=1,B11=1),1,0) -> 0 | DO11: =IF(AND(DM11=1,C11=1),1,0) -> 0 | DP11: =IF(AND(DM11=1,D11=1),1,0) -> 0 | DQ11: =IF(AND(DM11=1,E11=1),1,0) -> 0 | DR11: =IF(AND(DM11=1,F11=1),1,0) -> 0 | DS11: =IF(AND(DM11=1,G11=1),1,0) -> 0 | DT11: =IF(AND(DM11=1,H11=1),1,0) -> 0 | DU11: =IF(AND(DM11=1,I11=1),1,0) -> 0 | DV11: =IF(AND(DM11=1,J11=1),1,0) -> 0 | DW11: =IF(AND(CR11>90,CR11<181),1,0) -> 0 | DX11: =IF(AND(DW11=1,B11=1),1,0) -> 0 | DY11: =IF(AND(DW11=1,C11=1),1,0) -> 0 | DZ11: =IF(AND(DW11=1,D11=1),1,0) -> 0 | EA11: =IF(AND(DW11=1,E11=1),1,0) -> 0 | EB11: =IF(AND(DW11=1,F11=1),1,0) -> 0 | EC11: =IF(AND(DW11=1,G11=1),1,0) -> 0 | ED11: =IF(AND(DW11=1,H11=1),1,0) -> 0 | EE11: =IF(AND(DW11=1,I11=1),1,0) -> 0 | EF11: =IF(AND(DW11=1,J11=1),1,0) -> 0 | EG11: =IF(CR11>180,1,0) -> 0 | EH11: =IF(AND(EG11=1,B11=1),1,0) -> 0 | EI11: =IF(AND(EG11=1,C11=1),1,0) -> 0 | EJ11: =IF(AND(EG11=1,D11=1),1,0) -> 0 | EK11: =IF(AND(EG11=1,E11=1),1,0) -> 0 | EL11: =IF(AND(EG11=1,F11=1),1,0) -> 0 | EM11: =IF(AND(EG11=1,G11=1),1,0) -> 0 | EN11: =IF(AND(EG11=1,H11=1),1,0) -> 0 | EO11: =IF(AND(EG11=1,I11=1),1,0) -> 0 | EP11: =IF(AND(EG11=1,J11=1),1,0) -> 0 | ER11: 8 | ES11: 8000-10000 | ET11: =I163 -> 2
A12: =数据调研!F12 -> 6727 | B12: =IF(AND(A12>0,A12<100),1,0) -> 0 | C12: =IF(AND(A12>99,A12<500),1,0) -> 0 | D12: =IF(AND(A12>499,A12<1000),1,0) -> 0 | E12: =IF(AND(A12>999,A12<2000),1,0) -> 0 | F12: =IF(AND(A12>1999,A12<4000),1,0) -> 0 | G12: =IF(AND(A12>3999,A12<6000),1,0) -> 0 | H12: =IF(AND(A12>5999,A12<8000),1,0) -> 1 | I12: =IF(AND(A12>7999,A12<10001),1,0) -> 0 | J12: =IF(A12>10002,1,0) -> 0 | K12: =价格参考!K12 -> 360 | L12: =IF(AND(K12>0,K12<301),1,0) -> 0 | M12: =IF(AND(K12>300,K12<501),1,0) -> 1 | N12: =IF(AND(K12>500,K12<801),1,0) -> 0 | O12: =IF(AND(K12>800,K12<1001),1,0) -> 0 | P12: =IF(AND(K12>1000,K12<1501),1,0) -> 0 | Q12: =IF(AND(K12>1500,K12<2001),1,0) -> 0 | R12: =IF(AND(K12>2000,K12<3001),1,0) -> 0 | S12: =IF(AND(K12>3000,K12<4501),1,0) -> 0 | T12: =IF(AND(K12>4500,K12<6001),1,0) -> 0 | U12: =IF(AND(K12>6000,K12<8001),1,0) -> 0 | V12: =IF(AND(K12>8000,K12<>"N.A.",K12<>"< 5"),1,0) -> 0 | W12: =IF(A12<>"N.A.",A12,1000000) -> 6727 | X12: =数据调研!I12 -> 944 | Y12: =IF(X12<31,1,0) -> 0 | Z12: =IF(AND(Y12=1,B12=1),1,0) -> 0 | AA12: =IF(AND(Y12=1,C12=1),1,0) -> 0 | AB12: =IF(AND(Y12=1,D12=1),1,0) -> 0 | AC12: =IF(AND(Y12=1,E12=1),1,0) -> 0 | AD12: =IF(AND(Y12=1,F12=1),1,0) -> 0 | AE12: =IF(AND(Y12=1,G12=1),1,0) -> 0 | AF12: =IF(AND(Y12=1,H12=1),1,0) -> 0 | AG12: =IF(AND(Y12=1,I12=1),1,0) -> 0 | AH12: =IF(AND(Y12=1,J12=1),1,0) -> 0 | AI12: =IF(AND(X12>30,X12<101),1,0) -> 0 | AJ12: =IF(AND(AI12=1,B12=1),1,0) -> 0 | AK12: =IF(AND(AI12=1,C12=1),1,0) -> 0 | AL12: =IF(AND(AI12=1,D12=1),1,0) -> 0 | AM12: =IF(AND(AI12=1,E12=1),1,0) -> 0 | AN12: =IF(AND(AI12=1,F12=1),1,0) -> 0 | AO12: =IF(AND(AI12=1,G12=1),1,0) -> 0 | AP12: =IF(AND(AI12=1,H12=1),1,0) -> 0 | AQ12: =IF(AND(AI12=1,I12=1),1,0) -> 0 | AR12: =IF(AND(AI12=1,J12=1),1,0) -> 0 | AS12: =IF(AND(X12>100,X12<501),1,0) -> 0 | AT12: =IF(AND(B12=1,AS12=1),1,0) -> 0 | AU12: =IF(AND(C12=1,AS12=1),1,0) -> 0 | AV12: =IF(AND(D12=1,AS12=1),1,0) -> 0 | AW12: =IF(AND(E12=1,AS12=1),1,0) -> 0 | AX12: =IF(AND(F12=1,AS12=1),1,0) -> 0 | AY12: =IF(AND(G12=1,AS12=1),1,0) -> 0 | AZ12: =IF(AND(H12=1,AS12=1),1,0) -> 0 | BA12: =IF(AND(I12=1,AS12=1),1,0) -> 0 | BB12: =IF(AND(J12=1,AS12=1),1,0) -> 0 | BC12: =IF(AND(X12>500,X12<1001),1,0) -> 1 | BD12: =IF(AND(BC12=1,B12=1),1,0) -> 0 | BE12: =IF(AND(BC12=1,C12=1),1,0) -> 0 | BF12: =IF(AND(BC12=1,D12=1),1,0) -> 0 | BG12: =IF(AND(BC12=1,E12=1),1,0) -> 0 | BH12: =IF(AND(BC12=1,F12=1),1,0) -> 0 | BI12: =IF(AND(BC12=1,G12=1),1,0) -> 0 | BJ12: =IF(AND(BC12=1,H12=1),1,0) -> 1 | BK12: =IF(AND(BC12=1,I12=1),1,0) -> 0 | BL12: =IF(AND(BC12=1,J12=1),1,0) -> 0 | BM12: =IF(X12>1001,1,0) -> 0 | BN12: =IF(AND(B12=1,BM12=1),1,0) -> 0 | BO12: =IF(AND(C12=1,BM12=1),1,0) -> 0 | BP12: =IF(AND(D12=1,BM12=1),1,0) -> 0 | BQ12: =IF(AND(E12=1,BM12=1),1,0) -> 0 | BR12: =IF(AND(F12=1,BM12=1),1,0) -> 0 | BS12: =IF(AND(G12=1,BM12=1),1,0) -> 0 | BT12: =IF(AND(H12=1,BM12=1),1,0) -> 0 | BU12: =IF(AND(I12=1,BM12=1),1,0) -> 0 | BV12: =IF(AND(J12=1,BM12=1),1,0) -> 0 | BW12: =数据调研!K12 -> FBA | BX12: =IF(BW12="AMZ",1,0) -> 0 | BY12: =IF(AND(BX12=1,B12=1),1,0) -> 0 | BZ12: =IF(AND(BX12=1,C12=1),1,0) -> 0 | CA12: =IF(AND(BX12=1,D12=1),1,0) -> 0 | CB12: =IF(AND(BX12=1,E12=1),1,0) -> 0 | CC12: =IF(AND(BX12=1,F12=1),1,0) -> 0 | CD12: =IF(AND(BX12=1,G12=1),1,0) -> 0 | CE12: =IF(AND(BX12=1,H12=1),1,0) -> 0 | CF12: =IF(AND(BX12=1,I12=1),1,0) -> 0 | CG12: =IF(AND(BX12=1,J12=1),1,0) -> 0 | CH12: =IF(BW12="FBA",1,0) -> 1 | CI12: =IF(AND(CH12=1,B12=1),1,0) -> 0 | CJ12: =IF(AND(CH12=1,C12=1),1,0) -> 0 | CK12: =IF(AND(CH12=1,D12=1),1,0) -> 0 | CL12: =IF(AND(CH12=1,E12=1),1,0) -> 0 | CM12: =IF(AND(CH12=1,F12=1),1,0) -> 0 | CN12: =IF(AND(CH12=1,G12=1),1,0) -> 0 | CO12: =IF(AND(CH12=1,H12=1),1,0) -> 1 | CP12: =IF(AND(CH12=1,I12=1),1,0) -> 0 | CQ12: =IF(AND(CH12=1,J12=1),1,0) -> 0 | CR12: =数据调研!N12 -> 1080 | CS12: =IF(AND(CR12<31,CR12<>0),1,0) -> 0 | CT12: =IF(AND(CS12=1,B12=1),1,0) -> 0 | CU12: =IF(AND(CS12=1,C12=1),1,0) -> 0 | CV12: =IF(AND(CS12=1,D12=1),1,0) -> 0 | CW12: =IF(AND(CS12=1,E12=1),1,0) -> 0 | CX12: =IF(AND(CS12=1,F12=1),1,0) -> 0 | CY12: =IF(AND(CS12=1,G12=1),1,0) -> 0 | CZ12: =IF(AND(CS12=1,H12=1),1,0) -> 0 | DA12: =IF(AND(CS12=1,I12=1),1,0) -> 0 | DB12: =IF(AND(CS12=1,J12=1),1,0) -> 0 | DC12: =IF(AND(CR12>30,CR12<61),1,0) -> 0 | DD12: =IF(AND(DC12=1,B12=1),1,0) -> 0 | DE12: =IF(AND(DC12=1,C12=1),1,0) -> 0 | DF12: =IF(AND(DC12=1,D12=1),1,0) -> 0 | DG12: =IF(AND(DC12=1,E12=1),1,0) -> 0 | DH12: =IF(AND(DC12=1,F12=1),1,0) -> 0 | DI12: =IF(AND(DC12=1,G12=1),1,0) -> 0 | DJ12: =IF(AND(DC12=1,H12=1),1,0) -> 0 | DK12: =IF(AND(DC12=1,I12=1),1,0) -> 0 | DL12: =IF(AND(DC12=1,J12=1),1,0) -> 0 | DM12: =IF(AND(CR12>60,CR12<91),1,0) -> 0 | DN12: =IF(AND(DM12=1,B12=1),1,0) -> 0 | DO12: =IF(AND(DM12=1,C12=1),1,0) -> 0 | DP12: =IF(AND(DM12=1,D12=1),1,0) -> 0 | DQ12: =IF(AND(DM12=1,E12=1),1,0) -> 0 | DR12: =IF(AND(DM12=1,F12=1),1,0) -> 0 | DS12: =IF(AND(DM12=1,G12=1),1,0) -> 0 | DT12: =IF(AND(DM12=1,H12=1),1,0) -> 0 | DU12: =IF(AND(DM12=1,I12=1),1,0) -> 0 | DV12: =IF(AND(DM12=1,J12=1),1,0) -> 0 | DW12: =IF(AND(CR12>90,CR12<181),1,0) -> 0 | DX12: =IF(AND(DW12=1,B12=1),1,0) -> 0 | DY12: =IF(AND(DW12=1,C12=1),1,0) -> 0 | DZ12: =IF(AND(DW12=1,D12=1),1,0) -> 0 | EA12: =IF(AND(DW12=1,E12=1),1,0) -> 0 | EB12: =IF(AND(DW12=1,F12=1),1,0) -> 0 | EC12: =IF(AND(DW12=1,G12=1),1,0) -> 0 | ED12: =IF(AND(DW12=1,H12=1),1,0) -> 0 | EE12: =IF(AND(DW12=1,I12=1),1,0) -> 0 | EF12: =IF(AND(DW12=1,J12=1),1,0) -> 0 | EG12: =IF(CR12>180,1,0) -> 1 | EH12: =IF(AND(EG12=1,B12=1),1,0) -> 0 | EI12: =IF(AND(EG12=1,C12=1),1,0) -> 0 | EJ12: =IF(AND(EG12=1,D12=1),1,0) -> 0 | EK12: =IF(AND(EG12=1,E12=1),1,0) -> 0 | EL12: =IF(AND(EG12=1,F12=1),1,0) -> 0 | EM12: =IF(AND(EG12=1,G12=1),1,0) -> 0 | EN12: =IF(AND(EG12=1,H12=1),1,0) -> 1 | EO12: =IF(AND(EG12=1,I12=1),1,0) -> 0 | EP12: =IF(AND(EG12=1,J12=1),1,0) -> 0 | ER12: 9 | ES12: >10001 | ET12: =J163 -> 124
A13: =数据调研!F13 -> 7043 | B13: =IF(AND(A13>0,A13<100),1,0) -> 0 | C13: =IF(AND(A13>99,A13<500),1,0) -> 0 | D13: =IF(AND(A13>499,A13<1000),1,0) -> 0 | E13: =IF(AND(A13>999,A13<2000),1,0) -> 0 | F13: =IF(AND(A13>1999,A13<4000),1,0) -> 0 | G13: =IF(AND(A13>3999,A13<6000),1,0) -> 0 | H13: =IF(AND(A13>5999,A13<8000),1,0) -> 1 | I13: =IF(AND(A13>7999,A13<10001),1,0) -> 0 | J13: =IF(A13>10002,1,0) -> 0 | K13: =价格参考!K13 -> 360 | L13: =IF(AND(K13>0,K13<301),1,0) -> 0 | M13: =IF(AND(K13>300,K13<501),1,0) -> 1 | N13: =IF(AND(K13>500,K13<801),1,0) -> 0 | O13: =IF(AND(K13>800,K13<1001),1,0) -> 0 | P13: =IF(AND(K13>1000,K13<1501),1,0) -> 0 | Q13: =IF(AND(K13>1500,K13<2001),1,0) -> 0 | R13: =IF(AND(K13>2000,K13<3001),1,0) -> 0 | S13: =IF(AND(K13>3000,K13<4501),1,0) -> 0 | T13: =IF(AND(K13>4500,K13<6001),1,0) -> 0 | U13: =IF(AND(K13>6000,K13<8001),1,0) -> 0 | V13: =IF(AND(K13>8000,K13<>"N.A.",K13<>"< 5"),1,0) -> 0 | W13: =IF(A13<>"N.A.",A13,1000000) -> 7043 | X13: =数据调研!I13 -> 124 | Y13: =IF(X13<31,1,0) -> 0 | Z13: =IF(AND(Y13=1,B13=1),1,0) -> 0 | AA13: =IF(AND(Y13=1,C13=1),1,0) -> 0 | AB13: =IF(AND(Y13=1,D13=1),1,0) -> 0 | AC13: =IF(AND(Y13=1,E13=1),1,0) -> 0 | AD13: =IF(AND(Y13=1,F13=1),1,0) -> 0 | AE13: =IF(AND(Y13=1,G13=1),1,0) -> 0 | AF13: =IF(AND(Y13=1,H13=1),1,0) -> 0 | AG13: =IF(AND(Y13=1,I13=1),1,0) -> 0 | AH13: =IF(AND(Y13=1,J13=1),1,0) -> 0 | AI13: =IF(AND(X13>30,X13<101),1,0) -> 0 | AJ13: =IF(AND(AI13=1,B13=1),1,0) -> 0 | AK13: =IF(AND(AI13=1,C13=1),1,0) -> 0 | AL13: =IF(AND(AI13=1,D13=1),1,0) -> 0 | AM13: =IF(AND(AI13=1,E13=1),1,0) -> 0 | AN13: =IF(AND(AI13=1,F13=1),1,0) -> 0 | AO13: =IF(AND(AI13=1,G13=1),1,0) -> 0 | AP13: =IF(AND(AI13=1,H13=1),1,0) -> 0 | AQ13: =IF(AND(AI13=1,I13=1),1,0) -> 0 | AR13: =IF(AND(AI13=1,J13=1),1,0) -> 0 | AS13: =IF(AND(X13>100,X13<501),1,0) -> 1 | AT13: =IF(AND(B13=1,AS13=1),1,0) -> 0 | AU13: =IF(AND(C13=1,AS13=1),1,0) -> 0 | AV13: =IF(AND(D13=1,AS13=1),1,0) -> 0 | AW13: =IF(AND(E13=1,AS13=1),1,0) -> 0 | AX13: =IF(AND(F13=1,AS13=1),1,0) -> 0 | AY13: =IF(AND(G13=1,AS13=1),1,0) -> 0 | AZ13: =IF(AND(H13=1,AS13=1),1,0) -> 1 | BA13: =IF(AND(I13=1,AS13=1),1,0) -> 0 | BB13: =IF(AND(J13=1,AS13=1),1,0) -> 0 | BC13: =IF(AND(X13>500,X13<1001),1,0) -> 0 | BD13: =IF(AND(BC13=1,B13=1),1,0) -> 0 | BE13: =IF(AND(BC13=1,C13=1),1,0) -> 0 | BF13: =IF(AND(BC13=1,D13=1),1,0) -> 0 | BG13: =IF(AND(BC13=1,E13=1),1,0) -> 0 | BH13: =IF(AND(BC13=1,F13=1),1,0) -> 0 | BI13: =IF(AND(BC13=1,G13=1),1,0) -> 0 | BJ13: =IF(AND(BC13=1,H13=1),1,0) -> 0 | BK13: =IF(AND(BC13=1,I13=1),1,0) -> 0 | BL13: =IF(AND(BC13=1,J13=1),1,0) -> 0 | BM13: =IF(X13>1001,1,0) -> 0 | BN13: =IF(AND(B13=1,BM13=1),1,0) -> 0 | BO13: =IF(AND(C13=1,BM13=1),1,0) -> 0 | BP13: =IF(AND(D13=1,BM13=1),1,0) -> 0 | BQ13: =IF(AND(E13=1,BM13=1),1,0) -> 0 | BR13: =IF(AND(F13=1,BM13=1),1,0) -> 0 | BS13: =IF(AND(G13=1,BM13=1),1,0) -> 0 | BT13: =IF(AND(H13=1,BM13=1),1,0) -> 0 | BU13: =IF(AND(I13=1,BM13=1),1,0) -> 0 | BV13: =IF(AND(J13=1,BM13=1),1,0) -> 0 | BW13: =数据调研!K13 -> FBA | BX13: =IF(BW13="AMZ",1,0) -> 0 | BY13: =IF(AND(BX13=1,B13=1),1,0) -> 0 | BZ13: =IF(AND(BX13=1,C13=1),1,0) -> 0 | CA13: =IF(AND(BX13=1,D13=1),1,0) -> 0 | CB13: =IF(AND(BX13=1,E13=1),1,0) -> 0 | CC13: =IF(AND(BX13=1,F13=1),1,0) -> 0 | CD13: =IF(AND(BX13=1,G13=1),1,0) -> 0 | CE13: =IF(AND(BX13=1,H13=1),1,0) -> 0 | CF13: =IF(AND(BX13=1,I13=1),1,0) -> 0 | CG13: =IF(AND(BX13=1,J13=1),1,0) -> 0 | CH13: =IF(BW13="FBA",1,0) -> 1 | CI13: =IF(AND(CH13=1,B13=1),1,0) -> 0 | CJ13: =IF(AND(CH13=1,C13=1),1,0) -> 0 | CK13: =IF(AND(CH13=1,D13=1),1,0) -> 0 | CL13: =IF(AND(CH13=1,E13=1),1,0) -> 0 | CM13: =IF(AND(CH13=1,F13=1),1,0) -> 0 | CN13: =IF(AND(CH13=1,G13=1),1,0) -> 0 | CO13: =IF(AND(CH13=1,H13=1),1,0) -> 1 | CP13: =IF(AND(CH13=1,I13=1),1,0) -> 0 | CQ13: =IF(AND(CH13=1,J13=1),1,0) -> 0 | CR13: =数据调研!N13 -> 556 | CS13: =IF(AND(CR13<31,CR13<>0),1,0) -> 0 | CT13: =IF(AND(CS13=1,B13=1),1,0) -> 0 | CU13: =IF(AND(CS13=1,C13=1),1,0) -> 0 | CV13: =IF(AND(CS13=1,D13=1),1,0) -> 0 | CW13: =IF(AND(CS13=1,E13=1),1,0) -> 0 | CX13: =IF(AND(CS13=1,F13=1),1,0) -> 0 | CY13: =IF(AND(CS13=1,G13=1),1,0) -> 0 | CZ13: =IF(AND(CS13=1,H13=1),1,0) -> 0 | DA13: =IF(AND(CS13=1,I13=1),1,0) -> 0 | DB13: =IF(AND(CS13=1,J13=1),1,0) -> 0 | DC13: =IF(AND(CR13>30,CR13<61),1,0) -> 0 | DD13: =IF(AND(DC13=1,B13=1),1,0) -> 0 | DE13: =IF(AND(DC13=1,C13=1),1,0) -> 0 | DF13: =IF(AND(DC13=1,D13=1),1,0) -> 0 | DG13: =IF(AND(DC13=1,E13=1),1,0) -> 0 | DH13: =IF(AND(DC13=1,F13=1),1,0) -> 0 | DI13: =IF(AND(DC13=1,G13=1),1,0) -> 0 | DJ13: =IF(AND(DC13=1,H13=1),1,0) -> 0 | DK13: =IF(AND(DC13=1,I13=1),1,0) -> 0 | DL13: =IF(AND(DC13=1,J13=1),1,0) -> 0 | DM13: =IF(AND(CR13>60,CR13<91),1,0) -> 0 | DN13: =IF(AND(DM13=1,B13=1),1,0) -> 0 | DO13: =IF(AND(DM13=1,C13=1),1,0) -> 0 | DP13: =IF(AND(DM13=1,D13=1),1,0) -> 0 | DQ13: =IF(AND(DM13=1,E13=1),1,0) -> 0 | DR13: =IF(AND(DM13=1,F13=1),1,0) -> 0 | DS13: =IF(AND(DM13=1,G13=1),1,0) -> 0 | DT13: =IF(AND(DM13=1,H13=1),1,0) -> 0 | DU13: =IF(AND(DM13=1,I13=1),1,0) -> 0 | DV13: =IF(AND(DM13=1,J13=1),1,0) -> 0 | DW13: =IF(AND(CR13>90,CR13<181),1,0) -> 0 | DX13: =IF(AND(DW13=1,B13=1),1,0) -> 0 | DY13: =IF(AND(DW13=1,C13=1),1,0) -> 0 | DZ13: =IF(AND(DW13=1,D13=1),1,0) -> 0 | EA13: =IF(AND(DW13=1,E13=1),1,0) -> 0 | EB13: =IF(AND(DW13=1,F13=1),1,0) -> 0 | EC13: =IF(AND(DW13=1,G13=1),1,0) -> 0 | ED13: =IF(AND(DW13=1,H13=1),1,0) -> 0 | EE13: =IF(AND(DW13=1,I13=1),1,0) -> 0 | EF13: =IF(AND(DW13=1,J13=1),1,0) -> 0 | EG13: =IF(CR13>180,1,0) -> 1 | EH13: =IF(AND(EG13=1,B13=1),1,0) -> 0 | EI13: =IF(AND(EG13=1,C13=1),1,0) -> 0 | EJ13: =IF(AND(EG13=1,D13=1),1,0) -> 0 | EK13: =IF(AND(EG13=1,E13=1),1,0) -> 0 | EL13: =IF(AND(EG13=1,F13=1),1,0) -> 0 | EM13: =IF(AND(EG13=1,G13=1),1,0) -> 0 | EN13: =IF(AND(EG13=1,H13=1),1,0) -> 1 | EO13: =IF(AND(EG13=1,I13=1),1,0) -> 0 | EP13: =IF(AND(EG13=1,J13=1),1,0) -> 0 | ES13: 合计 | ET13: =SUM(ET4:ET12) -> 141
A14: =数据调研!F14 -> 7043 | B14: =IF(AND(A14>0,A14<100),1,0) -> 0 | C14: =IF(AND(A14>99,A14<500),1,0) -> 0 | D14: =IF(AND(A14>499,A14<1000),1,0) -> 0 | E14: =IF(AND(A14>999,A14<2000),1,0) -> 0 | F14: =IF(AND(A14>1999,A14<4000),1,0) -> 0 | G14: =IF(AND(A14>3999,A14<6000),1,0) -> 0 | H14: =IF(AND(A14>5999,A14<8000),1,0) -> 1 | I14: =IF(AND(A14>7999,A14<10001),1,0) -> 0 | J14: =IF(A14>10002,1,0) -> 0 | K14: =价格参考!K14 -> 360 | L14: =IF(AND(K14>0,K14<301),1,0) -> 0 | M14: =IF(AND(K14>300,K14<501),1,0) -> 1 | N14: =IF(AND(K14>500,K14<801),1,0) -> 0 | O14: =IF(AND(K14>800,K14<1001),1,0) -> 0 | P14: =IF(AND(K14>1000,K14<1501),1,0) -> 0 | Q14: =IF(AND(K14>1500,K14<2001),1,0) -> 0 | R14: =IF(AND(K14>2000,K14<3001),1,0) -> 0 | S14: =IF(AND(K14>3000,K14<4501),1,0) -> 0 | T14: =IF(AND(K14>4500,K14<6001),1,0) -> 0 | U14: =IF(AND(K14>6000,K14<8001),1,0) -> 0 | V14: =IF(AND(K14>8000,K14<>"N.A.",K14<>"< 5"),1,0) -> 0 | W14: =IF(A14<>"N.A.",A14,1000000) -> 7043 | X14: =数据调研!I14 -> 124 | Y14: =IF(X14<31,1,0) -> 0 | Z14: =IF(AND(Y14=1,B14=1),1,0) -> 0 | AA14: =IF(AND(Y14=1,C14=1),1,0) -> 0 | AB14: =IF(AND(Y14=1,D14=1),1,0) -> 0 | AC14: =IF(AND(Y14=1,E14=1),1,0) -> 0 | AD14: =IF(AND(Y14=1,F14=1),1,0) -> 0 | AE14: =IF(AND(Y14=1,G14=1),1,0) -> 0 | AF14: =IF(AND(Y14=1,H14=1),1,0) -> 0 | AG14: =IF(AND(Y14=1,I14=1),1,0) -> 0 | AH14: =IF(AND(Y14=1,J14=1),1,0) -> 0 | AI14: =IF(AND(X14>30,X14<101),1,0) -> 0 | AJ14: =IF(AND(AI14=1,B14=1),1,0) -> 0 | AK14: =IF(AND(AI14=1,C14=1),1,0) -> 0 | AL14: =IF(AND(AI14=1,D14=1),1,0) -> 0 | AM14: =IF(AND(AI14=1,E14=1),1,0) -> 0 | AN14: =IF(AND(AI14=1,F14=1),1,0) -> 0 | AO14: =IF(AND(AI14=1,G14=1),1,0) -> 0 | AP14: =IF(AND(AI14=1,H14=1),1,0) -> 0 | AQ14: =IF(AND(AI14=1,I14=1),1,0) -> 0 | AR14: =IF(AND(AI14=1,J14=1),1,0) -> 0 | AS14: =IF(AND(X14>100,X14<501),1,0) -> 1 | AT14: =IF(AND(B14=1,AS14=1),1,0) -> 0 | AU14: =IF(AND(C14=1,AS14=1),1,0) -> 0 | AV14: =IF(AND(D14=1,AS14=1),1,0) -> 0 | AW14: =IF(AND(E14=1,AS14=1),1,0) -> 0 | AX14: =IF(AND(F14=1,AS14=1),1,0) -> 0 | AY14: =IF(AND(G14=1,AS14=1),1,0) -> 0 | AZ14: =IF(AND(H14=1,AS14=1),1,0) -> 1 | BA14: =IF(AND(I14=1,AS14=1),1,0) -> 0 | BB14: =IF(AND(J14=1,AS14=1),1,0) -> 0 | BC14: =IF(AND(X14>500,X14<1001),1,0) -> 0 | BD14: =IF(AND(BC14=1,B14=1),1,0) -> 0 | BE14: =IF(AND(BC14=1,C14=1),1,0) -> 0 | BF14: =IF(AND(BC14=1,D14=1),1,0) -> 0 | BG14: =IF(AND(BC14=1,E14=1),1,0) -> 0 | BH14: =IF(AND(BC14=1,F14=1),1,0) -> 0 | BI14: =IF(AND(BC14=1,G14=1),1,0) -> 0 | BJ14: =IF(AND(BC14=1,H14=1),1,0) -> 0 | BK14: =IF(AND(BC14=1,I14=1),1,0) -> 0 | BL14: =IF(AND(BC14=1,J14=1),1,0) -> 0 | BM14: =IF(X14>1001,1,0) -> 0 | BN14: =IF(AND(B14=1,BM14=1),1,0) -> 0 | BO14: =IF(AND(C14=1,BM14=1),1,0) -> 0 | BP14: =IF(AND(D14=1,BM14=1),1,0) -> 0 | BQ14: =IF(AND(E14=1,BM14=1),1,0) -> 0 | BR14: =IF(AND(F14=1,BM14=1),1,0) -> 0 | BS14: =IF(AND(G14=1,BM14=1),1,0) -> 0 | BT14: =IF(AND(H14=1,BM14=1),1,0) -> 0 | BU14: =IF(AND(I14=1,BM14=1),1,0) -> 0 | BV14: =IF(AND(J14=1,BM14=1),1,0) -> 0 | BW14: =数据调研!K14 -> FBA | BX14: =IF(BW14="AMZ",1,0) -> 0 | BY14: =IF(AND(BX14=1,B14=1),1,0) -> 0 | BZ14: =IF(AND(BX14=1,C14=1),1,0) -> 0 | CA14: =IF(AND(BX14=1,D14=1),1,0) -> 0 | CB14: =IF(AND(BX14=1,E14=1),1,0) -> 0 | CC14: =IF(AND(BX14=1,F14=1),1,0) -> 0 | CD14: =IF(AND(BX14=1,G14=1),1,0) -> 0 | CE14: =IF(AND(BX14=1,H14=1),1,0) -> 0 | CF14: =IF(AND(BX14=1,I14=1),1,0) -> 0 | CG14: =IF(AND(BX14=1,J14=1),1,0) -> 0 | CH14: =IF(BW14="FBA",1,0) -> 1 | CI14: =IF(AND(CH14=1,B14=1),1,0) -> 0 | CJ14: =IF(AND(CH14=1,C14=1),1,0) -> 0 | CK14: =IF(AND(CH14=1,D14=1),1,0) -> 0 | CL14: =IF(AND(CH14=1,E14=1),1,0) -> 0 | CM14: =IF(AND(CH14=1,F14=1),1,0) -> 0 | CN14: =IF(AND(CH14=1,G14=1),1,0) -> 0 | CO14: =IF(AND(CH14=1,H14=1),1,0) -> 1 | CP14: =IF(AND(CH14=1,I14=1),1,0) -> 0 | CQ14: =IF(AND(CH14=1,J14=1),1,0) -> 0 | CR14: =数据调研!N14 -> 556 | CS14: =IF(AND(CR14<31,CR14<>0),1,0) -> 0 | CT14: =IF(AND(CS14=1,B14=1),1,0) -> 0 | CU14: =IF(AND(CS14=1,C14=1),1,0) -> 0 | CV14: =IF(AND(CS14=1,D14=1),1,0) -> 0 | CW14: =IF(AND(CS14=1,E14=1),1,0) -> 0 | CX14: =IF(AND(CS14=1,F14=1),1,0) -> 0 | CY14: =IF(AND(CS14=1,G14=1),1,0) -> 0 | CZ14: =IF(AND(CS14=1,H14=1),1,0) -> 0 | DA14: =IF(AND(CS14=1,I14=1),1,0) -> 0 | DB14: =IF(AND(CS14=1,J14=1),1,0) -> 0 | DC14: =IF(AND(CR14>30,CR14<61),1,0) -> 0 | DD14: =IF(AND(DC14=1,B14=1),1,0) -> 0 | DE14: =IF(AND(DC14=1,C14=1),1,0) -> 0 | DF14: =IF(AND(DC14=1,D14=1),1,0) -> 0 | DG14: =IF(AND(DC14=1,E14=1),1,0) -> 0 | DH14: =IF(AND(DC14=1,F14=1),1,0) -> 0 | DI14: =IF(AND(DC14=1,G14=1),1,0) -> 0 | DJ14: =IF(AND(DC14=1,H14=1),1,0) -> 0 | DK14: =IF(AND(DC14=1,I14=1),1,0) -> 0 | DL14: =IF(AND(DC14=1,J14=1),1,0) -> 0 | DM14: =IF(AND(CR14>60,CR14<91),1,0) -> 0 | DN14: =IF(AND(DM14=1,B14=1),1,0) -> 0 | DO14: =IF(AND(DM14=1,C14=1),1,0) -> 0 | DP14: =IF(AND(DM14=1,D14=1),1,0) -> 0 | DQ14: =IF(AND(DM14=1,E14=1),1,0) -> 0 | DR14: =IF(AND(DM14=1,F14=1),1,0) -> 0 | DS14: =IF(AND(DM14=1,G14=1),1,0) -> 0 | DT14: =IF(AND(DM14=1,H14=1),1,0) -> 0 | DU14: =IF(AND(DM14=1,I14=1),1,0) -> 0 | DV14: =IF(AND(DM14=1,J14=1),1,0) -> 0 | DW14: =IF(AND(CR14>90,CR14<181),1,0) -> 0 | DX14: =IF(AND(DW14=1,B14=1),1,0) -> 0 | DY14: =IF(AND(DW14=1,C14=1),1,0) -> 0 | DZ14: =IF(AND(DW14=1,D14=1),1,0) -> 0 | EA14: =IF(AND(DW14=1,E14=1),1,0) -> 0 | EB14: =IF(AND(DW14=1,F14=1),1,0) -> 0 | EC14: =IF(AND(DW14=1,G14=1),1,0) -> 0 | ED14: =IF(AND(DW14=1,H14=1),1,0) -> 0 | EE14: =IF(AND(DW14=1,I14=1),1,0) -> 0 | EF14: =IF(AND(DW14=1,J14=1),1,0) -> 0 | EG14: =IF(CR14>180,1,0) -> 1 | EH14: =IF(AND(EG14=1,B14=1),1,0) -> 0 | EI14: =IF(AND(EG14=1,C14=1),1,0) -> 0 | EJ14: =IF(AND(EG14=1,D14=1),1,0) -> 0 | EK14: =IF(AND(EG14=1,E14=1),1,0) -> 0 | EL14: =IF(AND(EG14=1,F14=1),1,0) -> 0 | EM14: =IF(AND(EG14=1,G14=1),1,0) -> 0 | EN14: =IF(AND(EG14=1,H14=1),1,0) -> 1 | EO14: =IF(AND(EG14=1,I14=1),1,0) -> 0 | EP14: =IF(AND(EG14=1,J14=1),1,0) -> 0
A15: =数据调研!F15 -> 7965 | B15: =IF(AND(A15>0,A15<100),1,0) -> 0 | C15: =IF(AND(A15>99,A15<500),1,0) -> 0 | D15: =IF(AND(A15>499,A15<1000),1,0) -> 0 | E15: =IF(AND(A15>999,A15<2000),1,0) -> 0 | F15: =IF(AND(A15>1999,A15<4000),1,0) -> 0 | G15: =IF(AND(A15>3999,A15<6000),1,0) -> 0 | H15: =IF(AND(A15>5999,A15<8000),1,0) -> 1 | I15: =IF(AND(A15>7999,A15<10001),1,0) -> 0 | J15: =IF(A15>10002,1,0) -> 0 | K15: =价格参考!K15 -> 300 | L15: =IF(AND(K15>0,K15<301),1,0) -> 1 | M15: =IF(AND(K15>300,K15<501),1,0) -> 0 | N15: =IF(AND(K15>500,K15<801),1,0) -> 0 | O15: =IF(AND(K15>800,K15<1001),1,0) -> 0 | P15: =IF(AND(K15>1000,K15<1501),1,0) -> 0 | Q15: =IF(AND(K15>1500,K15<2001),1,0) -> 0 | R15: =IF(AND(K15>2000,K15<3001),1,0) -> 0 | S15: =IF(AND(K15>3000,K15<4501),1,0) -> 0 | T15: =IF(AND(K15>4500,K15<6001),1,0) -> 0 | U15: =IF(AND(K15>6000,K15<8001),1,0) -> 0 | V15: =IF(AND(K15>8000,K15<>"N.A.",K15<>"< 5"),1,0) -> 0 | W15: =IF(A15<>"N.A.",A15,1000000) -> 7965 | X15: =数据调研!I15 -> 4515 | Y15: =IF(X15<31,1,0) -> 0 | Z15: =IF(AND(Y15=1,B15=1),1,0) -> 0 | AA15: =IF(AND(Y15=1,C15=1),1,0) -> 0 | AB15: =IF(AND(Y15=1,D15=1),1,0) -> 0 | AC15: =IF(AND(Y15=1,E15=1),1,0) -> 0 | AD15: =IF(AND(Y15=1,F15=1),1,0) -> 0 | AE15: =IF(AND(Y15=1,G15=1),1,0) -> 0 | AF15: =IF(AND(Y15=1,H15=1),1,0) -> 0 | AG15: =IF(AND(Y15=1,I15=1),1,0) -> 0 | AH15: =IF(AND(Y15=1,J15=1),1,0) -> 0 | AI15: =IF(AND(X15>30,X15<101),1,0) -> 0 | AJ15: =IF(AND(AI15=1,B15=1),1,0) -> 0 | AK15: =IF(AND(AI15=1,C15=1),1,0) -> 0 | AL15: =IF(AND(AI15=1,D15=1),1,0) -> 0 | AM15: =IF(AND(AI15=1,E15=1),1,0) -> 0 | AN15: =IF(AND(AI15=1,F15=1),1,0) -> 0 | AO15: =IF(AND(AI15=1,G15=1),1,0) -> 0 | AP15: =IF(AND(AI15=1,H15=1),1,0) -> 0 | AQ15: =IF(AND(AI15=1,I15=1),1,0) -> 0 | AR15: =IF(AND(AI15=1,J15=1),1,0) -> 0 | AS15: =IF(AND(X15>100,X15<501),1,0) -> 0 | AT15: =IF(AND(B15=1,AS15=1),1,0) -> 0 | AU15: =IF(AND(C15=1,AS15=1),1,0) -> 0 | AV15: =IF(AND(D15=1,AS15=1),1,0) -> 0 | AW15: =IF(AND(E15=1,AS15=1),1,0) -> 0 | AX15: =IF(AND(F15=1,AS15=1),1,0) -> 0 | AY15: =IF(AND(G15=1,AS15=1),1,0) -> 0 | AZ15: =IF(AND(H15=1,AS15=1),1,0) -> 0 | BA15: =IF(AND(I15=1,AS15=1),1,0) -> 0 | BB15: =IF(AND(J15=1,AS15=1),1,0) -> 0 | BC15: =IF(AND(X15>500,X15<1001),1,0) -> 0 | BD15: =IF(AND(BC15=1,B15=1),1,0) -> 0 | BE15: =IF(AND(BC15=1,C15=1),1,0) -> 0 | BF15: =IF(AND(BC15=1,D15=1),1,0) -> 0 | BG15: =IF(AND(BC15=1,E15=1),1,0) -> 0 | BH15: =IF(AND(BC15=1,F15=1),1,0) -> 0 | BI15: =IF(AND(BC15=1,G15=1),1,0) -> 0 | BJ15: =IF(AND(BC15=1,H15=1),1,0) -> 0 | BK15: =IF(AND(BC15=1,I15=1),1,0) -> 0 | BL15: =IF(AND(BC15=1,J15=1),1,0) -> 0 | BM15: =IF(X15>1001,1,0) -> 1 | BN15: =IF(AND(B15=1,BM15=1),1,0) -> 0 | BO15: =IF(AND(C15=1,BM15=1),1,0) -> 0 | BP15: =IF(AND(D15=1,BM15=1),1,0) -> 0 | BQ15: =IF(AND(E15=1,BM15=1),1,0) -> 0 | BR15: =IF(AND(F15=1,BM15=1),1,0) -> 0 | BS15: =IF(AND(G15=1,BM15=1),1,0) -> 0 | BT15: =IF(AND(H15=1,BM15=1),1,0) -> 1 | BU15: =IF(AND(I15=1,BM15=1),1,0) -> 0 | BV15: =IF(AND(J15=1,BM15=1),1,0) -> 0 | BW15: =数据调研!K15 -> AMZ | BX15: =IF(BW15="AMZ",1,0) -> 1 | BY15: =IF(AND(BX15=1,B15=1),1,0) -> 0 | BZ15: =IF(AND(BX15=1,C15=1),1,0) -> 0 | CA15: =IF(AND(BX15=1,D15=1),1,0) -> 0 | CB15: =IF(AND(BX15=1,E15=1),1,0) -> 0 | CC15: =IF(AND(BX15=1,F15=1),1,0) -> 0 | CD15: =IF(AND(BX15=1,G15=1),1,0) -> 0 | CE15: =IF(AND(BX15=1,H15=1),1,0) -> 1 | CF15: =IF(AND(BX15=1,I15=1),1,0) -> 0 | CG15: =IF(AND(BX15=1,J15=1),1,0) -> 0 | CH15: =IF(BW15="FBA",1,0) -> 0 | CI15: =IF(AND(CH15=1,B15=1),1,0) -> 0 | CJ15: =IF(AND(CH15=1,C15=1),1,0) -> 0 | CK15: =IF(AND(CH15=1,D15=1),1,0) -> 0 | CL15: =IF(AND(CH15=1,E15=1),1,0) -> 0 | CM15: =IF(AND(CH15=1,F15=1),1,0) -> 0 | CN15: =IF(AND(CH15=1,G15=1),1,0) -> 0 | CO15: =IF(AND(CH15=1,H15=1),1,0) -> 0 | CP15: =IF(AND(CH15=1,I15=1),1,0) -> 0 | CQ15: =IF(AND(CH15=1,J15=1),1,0) -> 0 | CR15: =数据调研!N15 -> 1921 | CS15: =IF(AND(CR15<31,CR15<>0),1,0) -> 0 | CT15: =IF(AND(CS15=1,B15=1),1,0) -> 0 | CU15: =IF(AND(CS15=1,C15=1),1,0) -> 0 | CV15: =IF(AND(CS15=1,D15=1),1,0) -> 0 | CW15: =IF(AND(CS15=1,E15=1),1,0) -> 0 | CX15: =IF(AND(CS15=1,F15=1),1,0) -> 0 | CY15: =IF(AND(CS15=1,G15=1),1,0) -> 0 | CZ15: =IF(AND(CS15=1,H15=1),1,0) -> 0 | DA15: =IF(AND(CS15=1,I15=1),1,0) -> 0 | DB15: =IF(AND(CS15=1,J15=1),1,0) -> 0 | DC15: =IF(AND(CR15>30,CR15<61),1,0) -> 0 | DD15: =IF(AND(DC15=1,B15=1),1,0) -> 0 | DE15: =IF(AND(DC15=1,C15=1),1,0) -> 0 | DF15: =IF(AND(DC15=1,D15=1),1,0) -> 0 | DG15: =IF(AND(DC15=1,E15=1),1,0) -> 0 | DH15: =IF(AND(DC15=1,F15=1),1,0) -> 0 | DI15: =IF(AND(DC15=1,G15=1),1,0) -> 0 | DJ15: =IF(AND(DC15=1,H15=1),1,0) -> 0 | DK15: =IF(AND(DC15=1,I15=1),1,0) -> 0 | DL15: =IF(AND(DC15=1,J15=1),1,0) -> 0 | DM15: =IF(AND(CR15>60,CR15<91),1,0) -> 0 | DN15: =IF(AND(DM15=1,B15=1),1,0) -> 0 | DO15: =IF(AND(DM15=1,C15=1),1,0) -> 0 | DP15: =IF(AND(DM15=1,D15=1),1,0) -> 0 | DQ15: =IF(AND(DM15=1,E15=1),1,0) -> 0 | DR15: =IF(AND(DM15=1,F15=1),1,0) -> 0 | DS15: =IF(AND(DM15=1,G15=1),1,0) -> 0 | DT15: =IF(AND(DM15=1,H15=1),1,0) -> 0 | DU15: =IF(AND(DM15=1,I15=1),1,0) -> 0 | DV15: =IF(AND(DM15=1,J15=1),1,0) -> 0 | DW15: =IF(AND(CR15>90,CR15<181),1,0) -> 0 | DX15: =IF(AND(DW15=1,B15=1),1,0) -> 0 | DY15: =IF(AND(DW15=1,C15=1),1,0) -> 0 | DZ15: =IF(AND(DW15=1,D15=1),1,0) -> 0 | EA15: =IF(AND(DW15=1,E15=1),1,0) -> 0 | EB15: =IF(AND(DW15=1,F15=1),1,0) -> 0 | EC15: =IF(AND(DW15=1,G15=1),1,0) -> 0 | ED15: =IF(AND(DW15=1,H15=1),1,0) -> 0 | EE15: =IF(AND(DW15=1,I15=1),1,0) -> 0 | EF15: =IF(AND(DW15=1,J15=1),1,0) -> 0 | EG15: =IF(CR15>180,1,0) -> 1 | EH15: =IF(AND(EG15=1,B15=1),1,0) -> 0 | EI15: =IF(AND(EG15=1,C15=1),1,0) -> 0 | EJ15: =IF(AND(EG15=1,D15=1),1,0) -> 0 | EK15: =IF(AND(EG15=1,E15=1),1,0) -> 0 | EL15: =IF(AND(EG15=1,F15=1),1,0) -> 0 | EM15: =IF(AND(EG15=1,G15=1),1,0) -> 0 | EN15: =IF(AND(EG15=1,H15=1),1,0) -> 1 | EO15: =IF(AND(EG15=1,I15=1),1,0) -> 0 | EP15: =IF(AND(EG15=1,J15=1),1,0) -> 0
A16: =数据调研!F16 -> 9013 | B16: =IF(AND(A16>0,A16<100),1,0) -> 0 | C16: =IF(AND(A16>99,A16<500),1,0) -> 0 | D16: =IF(AND(A16>499,A16<1000),1,0) -> 0 | E16: =IF(AND(A16>999,A16<2000),1,0) -> 0 | F16: =IF(AND(A16>1999,A16<4000),1,0) -> 0 | G16: =IF(AND(A16>3999,A16<6000),1,0) -> 0 | H16: =IF(AND(A16>5999,A16<8000),1,0) -> 0 | I16: =IF(AND(A16>7999,A16<10001),1,0) -> 1 | J16: =IF(A16>10002,1,0) -> 0 | K16: =价格参考!K16 -> 270 | L16: =IF(AND(K16>0,K16<301),1,0) -> 1 | M16: =IF(AND(K16>300,K16<501),1,0) -> 0 | N16: =IF(AND(K16>500,K16<801),1,0) -> 0 | O16: =IF(AND(K16>800,K16<1001),1,0) -> 0 | P16: =IF(AND(K16>1000,K16<1501),1,0) -> 0 | Q16: =IF(AND(K16>1500,K16<2001),1,0) -> 0 | R16: =IF(AND(K16>2000,K16<3001),1,0) -> 0 | S16: =IF(AND(K16>3000,K16<4501),1,0) -> 0 | T16: =IF(AND(K16>4500,K16<6001),1,0) -> 0 | U16: =IF(AND(K16>6000,K16<8001),1,0) -> 0 | V16: =IF(AND(K16>8000,K16<>"N.A.",K16<>"< 5"),1,0) -> 0 | W16: =IF(A16<>"N.A.",A16,1000000) -> 9013 | X16: =数据调研!I16 -> 601 | Y16: =IF(X16<31,1,0) -> 0 | Z16: =IF(AND(Y16=1,B16=1),1,0) -> 0 | AA16: =IF(AND(Y16=1,C16=1),1,0) -> 0 | AB16: =IF(AND(Y16=1,D16=1),1,0) -> 0 | AC16: =IF(AND(Y16=1,E16=1),1,0) -> 0 | AD16: =IF(AND(Y16=1,F16=1),1,0) -> 0 | AE16: =IF(AND(Y16=1,G16=1),1,0) -> 0 | AF16: =IF(AND(Y16=1,H16=1),1,0) -> 0 | AG16: =IF(AND(Y16=1,I16=1),1,0) -> 0 | AH16: =IF(AND(Y16=1,J16=1),1,0) -> 0 | AI16: =IF(AND(X16>30,X16<101),1,0) -> 0 | AJ16: =IF(AND(AI16=1,B16=1),1,0) -> 0 | AK16: =IF(AND(AI16=1,C16=1),1,0) -> 0 | AL16: =IF(AND(AI16=1,D16=1),1,0) -> 0 | AM16: =IF(AND(AI16=1,E16=1),1,0) -> 0 | AN16: =IF(AND(AI16=1,F16=1),1,0) -> 0 | AO16: =IF(AND(AI16=1,G16=1),1,0) -> 0 | AP16: =IF(AND(AI16=1,H16=1),1,0) -> 0 | AQ16: =IF(AND(AI16=1,I16=1),1,0) -> 0 | AR16: =IF(AND(AI16=1,J16=1),1,0) -> 0 | AS16: =IF(AND(X16>100,X16<501),1,0) -> 0 | AT16: =IF(AND(B16=1,AS16=1),1,0) -> 0 | AU16: =IF(AND(C16=1,AS16=1),1,0) -> 0 | AV16: =IF(AND(D16=1,AS16=1),1,0) -> 0 | AW16: =IF(AND(E16=1,AS16=1),1,0) -> 0 | AX16: =IF(AND(F16=1,AS16=1),1,0) -> 0 | AY16: =IF(AND(G16=1,AS16=1),1,0) -> 0 | AZ16: =IF(AND(H16=1,AS16=1),1,0) -> 0 | BA16: =IF(AND(I16=1,AS16=1),1,0) -> 0 | BB16: =IF(AND(J16=1,AS16=1),1,0) -> 0 | BC16: =IF(AND(X16>500,X16<1001),1,0) -> 1 | BD16: =IF(AND(BC16=1,B16=1),1,0) -> 0 | BE16: =IF(AND(BC16=1,C16=1),1,0) -> 0 | BF16: =IF(AND(BC16=1,D16=1),1,0) -> 0 | BG16: =IF(AND(BC16=1,E16=1),1,0) -> 0 | BH16: =IF(AND(BC16=1,F16=1),1,0) -> 0 | BI16: =IF(AND(BC16=1,G16=1),1,0) -> 0 | BJ16: =IF(AND(BC16=1,H16=1),1,0) -> 0 | BK16: =IF(AND(BC16=1,I16=1),1,0) -> 1 | BL16: =IF(AND(BC16=1,J16=1),1,0) -> 0 | BM16: =IF(X16>1001,1,0) -> 0 | BN16: =IF(AND(B16=1,BM16=1),1,0) -> 0 | BO16: =IF(AND(C16=1,BM16=1),1,0) -> 0 | BP16: =IF(AND(D16=1,BM16=1),1,0) -> 0 | BQ16: =IF(AND(E16=1,BM16=1),1,0) -> 0 | BR16: =IF(AND(F16=1,BM16=1),1,0) -> 0 | BS16: =IF(AND(G16=1,BM16=1),1,0) -> 0 | BT16: =IF(AND(H16=1,BM16=1),1,0) -> 0 | BU16: =IF(AND(I16=1,BM16=1),1,0) -> 0 | BV16: =IF(AND(J16=1,BM16=1),1,0) -> 0 | BW16: =数据调研!K16 -> FBA | BX16: =IF(BW16="AMZ",1,0) -> 0 | BY16: =IF(AND(BX16=1,B16=1),1,0) -> 0 | BZ16: =IF(AND(BX16=1,C16=1),1,0) -> 0 | CA16: =IF(AND(BX16=1,D16=1),1,0) -> 0 | CB16: =IF(AND(BX16=1,E16=1),1,0) -> 0 | CC16: =IF(AND(BX16=1,F16=1),1,0) -> 0 | CD16: =IF(AND(BX16=1,G16=1),1,0) -> 0 | CE16: =IF(AND(BX16=1,H16=1),1,0) -> 0 | CF16: =IF(AND(BX16=1,I16=1),1,0) -> 0 | CG16: =IF(AND(BX16=1,J16=1),1,0) -> 0 | CH16: =IF(BW16="FBA",1,0) -> 1 | CI16: =IF(AND(CH16=1,B16=1),1,0) -> 0 | CJ16: =IF(AND(CH16=1,C16=1),1,0) -> 0 | CK16: =IF(AND(CH16=1,D16=1),1,0) -> 0 | CL16: =IF(AND(CH16=1,E16=1),1,0) -> 0 | CM16: =IF(AND(CH16=1,F16=1),1,0) -> 0 | CN16: =IF(AND(CH16=1,G16=1),1,0) -> 0 | CO16: =IF(AND(CH16=1,H16=1),1,0) -> 0 | CP16: =IF(AND(CH16=1,I16=1),1,0) -> 1 | CQ16: =IF(AND(CH16=1,J16=1),1,0) -> 0 | CR16: =数据调研!N16 -> 364 | CS16: =IF(AND(CR16<31,CR16<>0),1,0) -> 0 | CT16: =IF(AND(CS16=1,B16=1),1,0) -> 0 | CU16: =IF(AND(CS16=1,C16=1),1,0) -> 0 | CV16: =IF(AND(CS16=1,D16=1),1,0) -> 0 | CW16: =IF(AND(CS16=1,E16=1),1,0) -> 0 | CX16: =IF(AND(CS16=1,F16=1),1,0) -> 0 | CY16: =IF(AND(CS16=1,G16=1),1,0) -> 0 | CZ16: =IF(AND(CS16=1,H16=1),1,0) -> 0 | DA16: =IF(AND(CS16=1,I16=1),1,0) -> 0 | DB16: =IF(AND(CS16=1,J16=1),1,0) -> 0 | DC16: =IF(AND(CR16>30,CR16<61),1,0) -> 0 | DD16: =IF(AND(DC16=1,B16=1),1,0) -> 0 | DE16: =IF(AND(DC16=1,C16=1),1,0) -> 0 | DF16: =IF(AND(DC16=1,D16=1),1,0) -> 0 | DG16: =IF(AND(DC16=1,E16=1),1,0) -> 0 | DH16: =IF(AND(DC16=1,F16=1),1,0) -> 0 | DI16: =IF(AND(DC16=1,G16=1),1,0) -> 0 | DJ16: =IF(AND(DC16=1,H16=1),1,0) -> 0 | DK16: =IF(AND(DC16=1,I16=1),1,0) -> 0 | DL16: =IF(AND(DC16=1,J16=1),1,0) -> 0 | DM16: =IF(AND(CR16>60,CR16<91),1,0) -> 0 | DN16: =IF(AND(DM16=1,B16=1),1,0) -> 0 | DO16: =IF(AND(DM16=1,C16=1),1,0) -> 0 | DP16: =IF(AND(DM16=1,D16=1),1,0) -> 0 | DQ16: =IF(AND(DM16=1,E16=1),1,0) -> 0 | DR16: =IF(AND(DM16=1,F16=1),1,0) -> 0 | DS16: =IF(AND(DM16=1,G16=1),1,0) -> 0 | DT16: =IF(AND(DM16=1,H16=1),1,0) -> 0 | DU16: =IF(AND(DM16=1,I16=1),1,0) -> 0 | DV16: =IF(AND(DM16=1,J16=1),1,0) -> 0 | DW16: =IF(AND(CR16>90,CR16<181),1,0) -> 0 | DX16: =IF(AND(DW16=1,B16=1),1,0) -> 0 | DY16: =IF(AND(DW16=1,C16=1),1,0) -> 0 | DZ16: =IF(AND(DW16=1,D16=1),1,0) -> 0 | EA16: =IF(AND(DW16=1,E16=1),1,0) -> 0 | EB16: =IF(AND(DW16=1,F16=1),1,0) -> 0 | EC16: =IF(AND(DW16=1,G16=1),1,0) -> 0 | ED16: =IF(AND(DW16=1,H16=1),1,0) -> 0 | EE16: =IF(AND(DW16=1,I16=1),1,0) -> 0 | EF16: =IF(AND(DW16=1,J16=1),1,0) -> 0 | EG16: =IF(CR16>180,1,0) -> 1 | EH16: =IF(AND(EG16=1,B16=1),1,0) -> 0 | EI16: =IF(AND(EG16=1,C16=1),1,0) -> 0 | EJ16: =IF(AND(EG16=1,D16=1),1,0) -> 0 | EK16: =IF(AND(EG16=1,E16=1),1,0) -> 0 | EL16: =IF(AND(EG16=1,F16=1),1,0) -> 0 | EM16: =IF(AND(EG16=1,G16=1),1,0) -> 0 | EN16: =IF(AND(EG16=1,H16=1),1,0) -> 0 | EO16: =IF(AND(EG16=1,I16=1),1,0) -> 1 | EP16: =IF(AND(EG16=1,J16=1),1,0) -> 0 | ER16: 序列 | ES16: 销量 | ET16: 数量
A17: =数据调研!F17 -> 9685 | B17: =IF(AND(A17>0,A17<100),1,0) -> 0 | C17: =IF(AND(A17>99,A17<500),1,0) -> 0 | D17: =IF(AND(A17>499,A17<1000),1,0) -> 0 | E17: =IF(AND(A17>999,A17<2000),1,0) -> 0 | F17: =IF(AND(A17>1999,A17<4000),1,0) -> 0 | G17: =IF(AND(A17>3999,A17<6000),1,0) -> 0 | H17: =IF(AND(A17>5999,A17<8000),1,0) -> 0 | I17: =IF(AND(A17>7999,A17<10001),1,0) -> 1 | J17: =IF(A17>10002,1,0) -> 0 | K17: =价格参考!K17 -> 240 | L17: =IF(AND(K17>0,K17<301),1,0) -> 1 | M17: =IF(AND(K17>300,K17<501),1,0) -> 0 | N17: =IF(AND(K17>500,K17<801),1,0) -> 0 | O17: =IF(AND(K17>800,K17<1001),1,0) -> 0 | P17: =IF(AND(K17>1000,K17<1501),1,0) -> 0 | Q17: =IF(AND(K17>1500,K17<2001),1,0) -> 0 | R17: =IF(AND(K17>2000,K17<3001),1,0) -> 0 | S17: =IF(AND(K17>3000,K17<4501),1,0) -> 0 | T17: =IF(AND(K17>4500,K17<6001),1,0) -> 0 | U17: =IF(AND(K17>6000,K17<8001),1,0) -> 0 | V17: =IF(AND(K17>8000,K17<>"N.A.",K17<>"< 5"),1,0) -> 0 | W17: =IF(A17<>"N.A.",A17,1000000) -> 9685 | X17: =数据调研!I17 -> 614 | Y17: =IF(X17<31,1,0) -> 0 | Z17: =IF(AND(Y17=1,B17=1),1,0) -> 0 | AA17: =IF(AND(Y17=1,C17=1),1,0) -> 0 | AB17: =IF(AND(Y17=1,D17=1),1,0) -> 0 | AC17: =IF(AND(Y17=1,E17=1),1,0) -> 0 | AD17: =IF(AND(Y17=1,F17=1),1,0) -> 0 | AE17: =IF(AND(Y17=1,G17=1),1,0) -> 0 | AF17: =IF(AND(Y17=1,H17=1),1,0) -> 0 | AG17: =IF(AND(Y17=1,I17=1),1,0) -> 0 | AH17: =IF(AND(Y17=1,J17=1),1,0) -> 0 | AI17: =IF(AND(X17>30,X17<101),1,0) -> 0 | AJ17: =IF(AND(AI17=1,B17=1),1,0) -> 0 | AK17: =IF(AND(AI17=1,C17=1),1,0) -> 0 | AL17: =IF(AND(AI17=1,D17=1),1,0) -> 0 | AM17: =IF(AND(AI17=1,E17=1),1,0) -> 0 | AN17: =IF(AND(AI17=1,F17=1),1,0) -> 0 | AO17: =IF(AND(AI17=1,G17=1),1,0) -> 0 | AP17: =IF(AND(AI17=1,H17=1),1,0) -> 0 | AQ17: =IF(AND(AI17=1,I17=1),1,0) -> 0 | AR17: =IF(AND(AI17=1,J17=1),1,0) -> 0 | AS17: =IF(AND(X17>100,X17<501),1,0) -> 0 | AT17: =IF(AND(B17=1,AS17=1),1,0) -> 0 | AU17: =IF(AND(C17=1,AS17=1),1,0) -> 0 | AV17: =IF(AND(D17=1,AS17=1),1,0) -> 0 | AW17: =IF(AND(E17=1,AS17=1),1,0) -> 0 | AX17: =IF(AND(F17=1,AS17=1),1,0) -> 0 | AY17: =IF(AND(G17=1,AS17=1),1,0) -> 0 | AZ17: =IF(AND(H17=1,AS17=1),1,0) -> 0 | BA17: =IF(AND(I17=1,AS17=1),1,0) -> 0 | BB17: =IF(AND(J17=1,AS17=1),1,0) -> 0 | BC17: =IF(AND(X17>500,X17<1001),1,0) -> 1 | BD17: =IF(AND(BC17=1,B17=1),1,0) -> 0 | BE17: =IF(AND(BC17=1,C17=1),1,0) -> 0 | BF17: =IF(AND(BC17=1,D17=1),1,0) -> 0 | BG17: =IF(AND(BC17=1,E17=1),1,0) -> 0 | BH17: =IF(AND(BC17=1,F17=1),1,0) -> 0 | BI17: =IF(AND(BC17=1,G17=1),1,0) -> 0 | BJ17: =IF(AND(BC17=1,H17=1),1,0) -> 0 | BK17: =IF(AND(BC17=1,I17=1),1,0) -> 1 | BL17: =IF(AND(BC17=1,J17=1),1,0) -> 0 | BM17: =IF(X17>1001,1,0) -> 0 | BN17: =IF(AND(B17=1,BM17=1),1,0) -> 0 | BO17: =IF(AND(C17=1,BM17=1),1,0) -> 0 | BP17: =IF(AND(D17=1,BM17=1),1,0) -> 0 | BQ17: =IF(AND(E17=1,BM17=1),1,0) -> 0 | BR17: =IF(AND(F17=1,BM17=1),1,0) -> 0 | BS17: =IF(AND(G17=1,BM17=1),1,0) -> 0 | BT17: =IF(AND(H17=1,BM17=1),1,0) -> 0 | BU17: =IF(AND(I17=1,BM17=1),1,0) -> 0 | BV17: =IF(AND(J17=1,BM17=1),1,0) -> 0 | BW17: =数据调研!K17 -> FBA | BX17: =IF(BW17="AMZ",1,0) -> 0 | BY17: =IF(AND(BX17=1,B17=1),1,0) -> 0 | BZ17: =IF(AND(BX17=1,C17=1),1,0) -> 0 | CA17: =IF(AND(BX17=1,D17=1),1,0) -> 0 | CB17: =IF(AND(BX17=1,E17=1),1,0) -> 0 | CC17: =IF(AND(BX17=1,F17=1),1,0) -> 0 | CD17: =IF(AND(BX17=1,G17=1),1,0) -> 0 | CE17: =IF(AND(BX17=1,H17=1),1,0) -> 0 | CF17: =IF(AND(BX17=1,I17=1),1,0) -> 0 | CG17: =IF(AND(BX17=1,J17=1),1,0) -> 0 | CH17: =IF(BW17="FBA",1,0) -> 1 | CI17: =IF(AND(CH17=1,B17=1),1,0) -> 0 | CJ17: =IF(AND(CH17=1,C17=1),1,0) -> 0 | CK17: =IF(AND(CH17=1,D17=1),1,0) -> 0 | CL17: =IF(AND(CH17=1,E17=1),1,0) -> 0 | CM17: =IF(AND(CH17=1,F17=1),1,0) -> 0 | CN17: =IF(AND(CH17=1,G17=1),1,0) -> 0 | CO17: =IF(AND(CH17=1,H17=1),1,0) -> 0 | CP17: =IF(AND(CH17=1,I17=1),1,0) -> 1 | CQ17: =IF(AND(CH17=1,J17=1),1,0) -> 0 | CR17: =数据调研!N17 -> 795 | CS17: =IF(AND(CR17<31,CR17<>0),1,0) -> 0 | CT17: =IF(AND(CS17=1,B17=1),1,0) -> 0 | CU17: =IF(AND(CS17=1,C17=1),1,0) -> 0 | CV17: =IF(AND(CS17=1,D17=1),1,0) -> 0 | CW17: =IF(AND(CS17=1,E17=1),1,0) -> 0 | CX17: =IF(AND(CS17=1,F17=1),1,0) -> 0 | CY17: =IF(AND(CS17=1,G17=1),1,0) -> 0 | CZ17: =IF(AND(CS17=1,H17=1),1,0) -> 0 | DA17: =IF(AND(CS17=1,I17=1),1,0) -> 0 | DB17: =IF(AND(CS17=1,J17=1),1,0) -> 0 | DC17: =IF(AND(CR17>30,CR17<61),1,0) -> 0 | DD17: =IF(AND(DC17=1,B17=1),1,0) -> 0 | DE17: =IF(AND(DC17=1,C17=1),1,0) -> 0 | DF17: =IF(AND(DC17=1,D17=1),1,0) -> 0 | DG17: =IF(AND(DC17=1,E17=1),1,0) -> 0 | DH17: =IF(AND(DC17=1,F17=1),1,0) -> 0 | DI17: =IF(AND(DC17=1,G17=1),1,0) -> 0 | DJ17: =IF(AND(DC17=1,H17=1),1,0) -> 0 | DK17: =IF(AND(DC17=1,I17=1),1,0) -> 0 | DL17: =IF(AND(DC17=1,J17=1),1,0) -> 0 | DM17: =IF(AND(CR17>60,CR17<91),1,0) -> 0 | DN17: =IF(AND(DM17=1,B17=1),1,0) -> 0 | DO17: =IF(AND(DM17=1,C17=1),1,0) -> 0 | DP17: =IF(AND(DM17=1,D17=1),1,0) -> 0 | DQ17: =IF(AND(DM17=1,E17=1),1,0) -> 0 | DR17: =IF(AND(DM17=1,F17=1),1,0) -> 0 | DS17: =IF(AND(DM17=1,G17=1),1,0) -> 0 | DT17: =IF(AND(DM17=1,H17=1),1,0) -> 0 | DU17: =IF(AND(DM17=1,I17=1),1,0) -> 0 | DV17: =IF(AND(DM17=1,J17=1),1,0) -> 0 | DW17: =IF(AND(CR17>90,CR17<181),1,0) -> 0 | DX17: =IF(AND(DW17=1,B17=1),1,0) -> 0 | DY17: =IF(AND(DW17=1,C17=1),1,0) -> 0 | DZ17: =IF(AND(DW17=1,D17=1),1,0) -> 0 | EA17: =IF(AND(DW17=1,E17=1),1,0) -> 0 | EB17: =IF(AND(DW17=1,F17=1),1,0) -> 0 | EC17: =IF(AND(DW17=1,G17=1),1,0) -> 0 | ED17: =IF(AND(DW17=1,H17=1),1,0) -> 0 | EE17: =IF(AND(DW17=1,I17=1),1,0) -> 0 | EF17: =IF(AND(DW17=1,J17=1),1,0) -> 0 | EG17: =IF(CR17>180,1,0) -> 1 | EH17: =IF(AND(EG17=1,B17=1),1,0) -> 0 | EI17: =IF(AND(EG17=1,C17=1),1,0) -> 0 | EJ17: =IF(AND(EG17=1,D17=1),1,0) -> 0 | EK17: =IF(AND(EG17=1,E17=1),1,0) -> 0 | EL17: =IF(AND(EG17=1,F17=1),1,0) -> 0 | EM17: =IF(AND(EG17=1,G17=1),1,0) -> 0 | EN17: =IF(AND(EG17=1,H17=1),1,0) -> 0 | EO17: =IF(AND(EG17=1,I17=1),1,0) -> 1 | EP17: =IF(AND(EG17=1,J17=1),1,0) -> 0 | ER17: 1 | ES17: 0-300 | ET17: =L163 -> 128
A18: =数据调研!F18 -> 10023 | B18: =IF(AND(A18>0,A18<100),1,0) -> 0 | C18: =IF(AND(A18>99,A18<500),1,0) -> 0 | D18: =IF(AND(A18>499,A18<1000),1,0) -> 0 | E18: =IF(AND(A18>999,A18<2000),1,0) -> 0 | F18: =IF(AND(A18>1999,A18<4000),1,0) -> 0 | G18: =IF(AND(A18>3999,A18<6000),1,0) -> 0 | H18: =IF(AND(A18>5999,A18<8000),1,0) -> 0 | I18: =IF(AND(A18>7999,A18<10001),1,0) -> 0 | J18: =IF(A18>10002,1,0) -> 1 | K18: =价格参考!K18 -> 240 | L18: =IF(AND(K18>0,K18<301),1,0) -> 1 | M18: =IF(AND(K18>300,K18<501),1,0) -> 0 | N18: =IF(AND(K18>500,K18<801),1,0) -> 0 | O18: =IF(AND(K18>800,K18<1001),1,0) -> 0 | P18: =IF(AND(K18>1000,K18<1501),1,0) -> 0 | Q18: =IF(AND(K18>1500,K18<2001),1,0) -> 0 | R18: =IF(AND(K18>2000,K18<3001),1,0) -> 0 | S18: =IF(AND(K18>3000,K18<4501),1,0) -> 0 | T18: =IF(AND(K18>4500,K18<6001),1,0) -> 0 | U18: =IF(AND(K18>6000,K18<8001),1,0) -> 0 | V18: =IF(AND(K18>8000,K18<>"N.A.",K18<>"< 5"),1,0) -> 0 | W18: =IF(A18<>"N.A.",A18,1000000) -> 10023 | X18: =数据调研!I18 -> 124 | Y18: =IF(X18<31,1,0) -> 0 | Z18: =IF(AND(Y18=1,B18=1),1,0) -> 0 | AA18: =IF(AND(Y18=1,C18=1),1,0) -> 0 | AB18: =IF(AND(Y18=1,D18=1),1,0) -> 0 | AC18: =IF(AND(Y18=1,E18=1),1,0) -> 0 | AD18: =IF(AND(Y18=1,F18=1),1,0) -> 0 | AE18: =IF(AND(Y18=1,G18=1),1,0) -> 0 | AF18: =IF(AND(Y18=1,H18=1),1,0) -> 0 | AG18: =IF(AND(Y18=1,I18=1),1,0) -> 0 | AH18: =IF(AND(Y18=1,J18=1),1,0) -> 0 | AI18: =IF(AND(X18>30,X18<101),1,0) -> 0 | AJ18: =IF(AND(AI18=1,B18=1),1,0) -> 0 | AK18: =IF(AND(AI18=1,C18=1),1,0) -> 0 | AL18: =IF(AND(AI18=1,D18=1),1,0) -> 0 | AM18: =IF(AND(AI18=1,E18=1),1,0) -> 0 | AN18: =IF(AND(AI18=1,F18=1),1,0) -> 0 | AO18: =IF(AND(AI18=1,G18=1),1,0) -> 0 | AP18: =IF(AND(AI18=1,H18=1),1,0) -> 0 | AQ18: =IF(AND(AI18=1,I18=1),1,0) -> 0 | AR18: =IF(AND(AI18=1,J18=1),1,0) -> 0 | AS18: =IF(AND(X18>100,X18<501),1,0) -> 1 | AT18: =IF(AND(B18=1,AS18=1),1,0) -> 0 | AU18: =IF(AND(C18=1,AS18=1),1,0) -> 0 | AV18: =IF(AND(D18=1,AS18=1),1,0) -> 0 | AW18: =IF(AND(E18=1,AS18=1),1,0) -> 0 | AX18: =IF(AND(F18=1,AS18=1),1,0) -> 0 | AY18: =IF(AND(G18=1,AS18=1),1,0) -> 0 | AZ18: =IF(AND(H18=1,AS18=1),1,0) -> 0 | BA18: =IF(AND(I18=1,AS18=1),1,0) -> 0 | BB18: =IF(AND(J18=1,AS18=1),1,0) -> 1 | BC18: =IF(AND(X18>500,X18<1001),1,0) -> 0 | BD18: =IF(AND(BC18=1,B18=1),1,0) -> 0 | BE18: =IF(AND(BC18=1,C18=1),1,0) -> 0 | BF18: =IF(AND(BC18=1,D18=1),1,0) -> 0 | BG18: =IF(AND(BC18=1,E18=1),1,0) -> 0 | BH18: =IF(AND(BC18=1,F18=1),1,0) -> 0 | BI18: =IF(AND(BC18=1,G18=1),1,0) -> 0 | BJ18: =IF(AND(BC18=1,H18=1),1,0) -> 0 | BK18: =IF(AND(BC18=1,I18=1),1,0) -> 0 | BL18: =IF(AND(BC18=1,J18=1),1,0) -> 0 | BM18: =IF(X18>1001,1,0) -> 0 | BN18: =IF(AND(B18=1,BM18=1),1,0) -> 0 | BO18: =IF(AND(C18=1,BM18=1),1,0) -> 0 | BP18: =IF(AND(D18=1,BM18=1),1,0) -> 0 | BQ18: =IF(AND(E18=1,BM18=1),1,0) -> 0 | BR18: =IF(AND(F18=1,BM18=1),1,0) -> 0 | BS18: =IF(AND(G18=1,BM18=1),1,0) -> 0 | BT18: =IF(AND(H18=1,BM18=1),1,0) -> 0 | BU18: =IF(AND(I18=1,BM18=1),1,0) -> 0 | BV18: =IF(AND(J18=1,BM18=1),1,0) -> 0 | BW18: =数据调研!K18 -> FBA | BX18: =IF(BW18="AMZ",1,0) -> 0 | BY18: =IF(AND(BX18=1,B18=1),1,0) -> 0 | BZ18: =IF(AND(BX18=1,C18=1),1,0) -> 0 | CA18: =IF(AND(BX18=1,D18=1),1,0) -> 0 | CB18: =IF(AND(BX18=1,E18=1),1,0) -> 0 | CC18: =IF(AND(BX18=1,F18=1),1,0) -> 0 | CD18: =IF(AND(BX18=1,G18=1),1,0) -> 0 | CE18: =IF(AND(BX18=1,H18=1),1,0) -> 0 | CF18: =IF(AND(BX18=1,I18=1),1,0) -> 0 | CG18: =IF(AND(BX18=1,J18=1),1,0) -> 0 | CH18: =IF(BW18="FBA",1,0) -> 1 | CI18: =IF(AND(CH18=1,B18=1),1,0) -> 0 | CJ18: =IF(AND(CH18=1,C18=1),1,0) -> 0 | CK18: =IF(AND(CH18=1,D18=1),1,0) -> 0 | CL18: =IF(AND(CH18=1,E18=1),1,0) -> 0 | CM18: =IF(AND(CH18=1,F18=1),1,0) -> 0 | CN18: =IF(AND(CH18=1,G18=1),1,0) -> 0 | CO18: =IF(AND(CH18=1,H18=1),1,0) -> 0 | CP18: =IF(AND(CH18=1,I18=1),1,0) -> 0 | CQ18: =IF(AND(CH18=1,J18=1),1,0) -> 1 | CR18: =数据调研!N18 -> 556 | CS18: =IF(AND(CR18<31,CR18<>0),1,0) -> 0 | CT18: =IF(AND(CS18=1,B18=1),1,0) -> 0 | CU18: =IF(AND(CS18=1,C18=1),1,0) -> 0 | CV18: =IF(AND(CS18=1,D18=1),1,0) -> 0 | CW18: =IF(AND(CS18=1,E18=1),1,0) -> 0 | CX18: =IF(AND(CS18=1,F18=1),1,0) -> 0 | CY18: =IF(AND(CS18=1,G18=1),1,0) -> 0 | CZ18: =IF(AND(CS18=1,H18=1),1,0) -> 0 | DA18: =IF(AND(CS18=1,I18=1),1,0) -> 0 | DB18: =IF(AND(CS18=1,J18=1),1,0) -> 0 | DC18: =IF(AND(CR18>30,CR18<61),1,0) -> 0 | DD18: =IF(AND(DC18=1,B18=1),1,0) -> 0 | DE18: =IF(AND(DC18=1,C18=1),1,0) -> 0 | DF18: =IF(AND(DC18=1,D18=1),1,0) -> 0 | DG18: =IF(AND(DC18=1,E18=1),1,0) -> 0 | DH18: =IF(AND(DC18=1,F18=1),1,0) -> 0 | DI18: =IF(AND(DC18=1,G18=1),1,0) -> 0 | DJ18: =IF(AND(DC18=1,H18=1),1,0) -> 0 | DK18: =IF(AND(DC18=1,I18=1),1,0) -> 0 | DL18: =IF(AND(DC18=1,J18=1),1,0) -> 0 | DM18: =IF(AND(CR18>60,CR18<91),1,0) -> 0 | DN18: =IF(AND(DM18=1,B18=1),1,0) -> 0 | DO18: =IF(AND(DM18=1,C18=1),1,0) -> 0 | DP18: =IF(AND(DM18=1,D18=1),1,0) -> 0 | DQ18: =IF(AND(DM18=1,E18=1),1,0) -> 0 | DR18: =IF(AND(DM18=1,F18=1),1,0) -> 0 | DS18: =IF(AND(DM18=1,G18=1),1,0) -> 0 | DT18: =IF(AND(DM18=1,H18=1),1,0) -> 0 | DU18: =IF(AND(DM18=1,I18=1),1,0) -> 0 | DV18: =IF(AND(DM18=1,J18=1),1,0) -> 0 | DW18: =IF(AND(CR18>90,CR18<181),1,0) -> 0 | DX18: =IF(AND(DW18=1,B18=1),1,0) -> 0 | DY18: =IF(AND(DW18=1,C18=1),1,0) -> 0 | DZ18: =IF(AND(DW18=1,D18=1),1,0) -> 0 | EA18: =IF(AND(DW18=1,E18=1),1,0) -> 0 | EB18: =IF(AND(DW18=1,F18=1),1,0) -> 0 | EC18: =IF(AND(DW18=1,G18=1),1,0) -> 0 | ED18: =IF(AND(DW18=1,H18=1),1,0) -> 0 | EE18: =IF(AND(DW18=1,I18=1),1,0) -> 0 | EF18: =IF(AND(DW18=1,J18=1),1,0) -> 0 | EG18: =IF(CR18>180,1,0) -> 1 | EH18: =IF(AND(EG18=1,B18=1),1,0) -> 0 | EI18: =IF(AND(EG18=1,C18=1),1,0) -> 0 | EJ18: =IF(AND(EG18=1,D18=1),1,0) -> 0 | EK18: =IF(AND(EG18=1,E18=1),1,0) -> 0 | EL18: =IF(AND(EG18=1,F18=1),1,0) -> 0 | EM18: =IF(AND(EG18=1,G18=1),1,0) -> 0 | EN18: =IF(AND(EG18=1,H18=1),1,0) -> 0 | EO18: =IF(AND(EG18=1,I18=1),1,0) -> 0 | EP18: =IF(AND(EG18=1,J18=1),1,0) -> 1 | ER18: 2 | ES18: 300-500 | ET18: =M163 -> 6
A19: =数据调研!F19 -> 11080 | B19: =IF(AND(A19>0,A19<100),1,0) -> 0 | C19: =IF(AND(A19>99,A19<500),1,0) -> 0 | D19: =IF(AND(A19>499,A19<1000),1,0) -> 0 | E19: =IF(AND(A19>999,A19<2000),1,0) -> 0 | F19: =IF(AND(A19>1999,A19<4000),1,0) -> 0 | G19: =IF(AND(A19>3999,A19<6000),1,0) -> 0 | H19: =IF(AND(A19>5999,A19<8000),1,0) -> 0 | I19: =IF(AND(A19>7999,A19<10001),1,0) -> 0 | J19: =IF(A19>10002,1,0) -> 1 | K19: =价格参考!K19 -> 210 | L19: =IF(AND(K19>0,K19<301),1,0) -> 1 | M19: =IF(AND(K19>300,K19<501),1,0) -> 0 | N19: =IF(AND(K19>500,K19<801),1,0) -> 0 | O19: =IF(AND(K19>800,K19<1001),1,0) -> 0 | P19: =IF(AND(K19>1000,K19<1501),1,0) -> 0 | Q19: =IF(AND(K19>1500,K19<2001),1,0) -> 0 | R19: =IF(AND(K19>2000,K19<3001),1,0) -> 0 | S19: =IF(AND(K19>3000,K19<4501),1,0) -> 0 | T19: =IF(AND(K19>4500,K19<6001),1,0) -> 0 | U19: =IF(AND(K19>6000,K19<8001),1,0) -> 0 | V19: =IF(AND(K19>8000,K19<>"N.A.",K19<>"< 5"),1,0) -> 0 | W19: =IF(A19<>"N.A.",A19,1000000) -> 11080 | X19: =数据调研!I19 -> 1428 | Y19: =IF(X19<31,1,0) -> 0 | Z19: =IF(AND(Y19=1,B19=1),1,0) -> 0 | AA19: =IF(AND(Y19=1,C19=1),1,0) -> 0 | AB19: =IF(AND(Y19=1,D19=1),1,0) -> 0 | AC19: =IF(AND(Y19=1,E19=1),1,0) -> 0 | AD19: =IF(AND(Y19=1,F19=1),1,0) -> 0 | AE19: =IF(AND(Y19=1,G19=1),1,0) -> 0 | AF19: =IF(AND(Y19=1,H19=1),1,0) -> 0 | AG19: =IF(AND(Y19=1,I19=1),1,0) -> 0 | AH19: =IF(AND(Y19=1,J19=1),1,0) -> 0 | AI19: =IF(AND(X19>30,X19<101),1,0) -> 0 | AJ19: =IF(AND(AI19=1,B19=1),1,0) -> 0 | AK19: =IF(AND(AI19=1,C19=1),1,0) -> 0 | AL19: =IF(AND(AI19=1,D19=1),1,0) -> 0 | AM19: =IF(AND(AI19=1,E19=1),1,0) -> 0 | AN19: =IF(AND(AI19=1,F19=1),1,0) -> 0 | AO19: =IF(AND(AI19=1,G19=1),1,0) -> 0 | AP19: =IF(AND(AI19=1,H19=1),1,0) -> 0 | AQ19: =IF(AND(AI19=1,I19=1),1,0) -> 0 | AR19: =IF(AND(AI19=1,J19=1),1,0) -> 0 | AS19: =IF(AND(X19>100,X19<501),1,0) -> 0 | AT19: =IF(AND(B19=1,AS19=1),1,0) -> 0 | AU19: =IF(AND(C19=1,AS19=1),1,0) -> 0 | AV19: =IF(AND(D19=1,AS19=1),1,0) -> 0 | AW19: =IF(AND(E19=1,AS19=1),1,0) -> 0 | AX19: =IF(AND(F19=1,AS19=1),1,0) -> 0 | AY19: =IF(AND(G19=1,AS19=1),1,0) -> 0 | AZ19: =IF(AND(H19=1,AS19=1),1,0) -> 0 | BA19: =IF(AND(I19=1,AS19=1),1,0) -> 0 | BB19: =IF(AND(J19=1,AS19=1),1,0) -> 0 | BC19: =IF(AND(X19>500,X19<1001),1,0) -> 0 | BD19: =IF(AND(BC19=1,B19=1),1,0) -> 0 | BE19: =IF(AND(BC19=1,C19=1),1,0) -> 0 | BF19: =IF(AND(BC19=1,D19=1),1,0) -> 0 | BG19: =IF(AND(BC19=1,E19=1),1,0) -> 0 | BH19: =IF(AND(BC19=1,F19=1),1,0) -> 0 | BI19: =IF(AND(BC19=1,G19=1),1,0) -> 0 | BJ19: =IF(AND(BC19=1,H19=1),1,0) -> 0 | BK19: =IF(AND(BC19=1,I19=1),1,0) -> 0 | BL19: =IF(AND(BC19=1,J19=1),1,0) -> 0 | BM19: =IF(X19>1001,1,0) -> 1 | BN19: =IF(AND(B19=1,BM19=1),1,0) -> 0 | BO19: =IF(AND(C19=1,BM19=1),1,0) -> 0 | BP19: =IF(AND(D19=1,BM19=1),1,0) -> 0 | BQ19: =IF(AND(E19=1,BM19=1),1,0) -> 0 | BR19: =IF(AND(F19=1,BM19=1),1,0) -> 0 | BS19: =IF(AND(G19=1,BM19=1),1,0) -> 0 | BT19: =IF(AND(H19=1,BM19=1),1,0) -> 0 | BU19: =IF(AND(I19=1,BM19=1),1,0) -> 0 | BV19: =IF(AND(J19=1,BM19=1),1,0) -> 1 | BW19: =数据调研!K19 -> FBA | BX19: =IF(BW19="AMZ",1,0) -> 0 | BY19: =IF(AND(BX19=1,B19=1),1,0) -> 0 | BZ19: =IF(AND(BX19=1,C19=1),1,0) -> 0 | CA19: =IF(AND(BX19=1,D19=1),1,0) -> 0 | CB19: =IF(AND(BX19=1,E19=1),1,0) -> 0 | CC19: =IF(AND(BX19=1,F19=1),1,0) -> 0 | CD19: =IF(AND(BX19=1,G19=1),1,0) -> 0 | CE19: =IF(AND(BX19=1,H19=1),1,0) -> 0 | CF19: =IF(AND(BX19=1,I19=1),1,0) -> 0 | CG19: =IF(AND(BX19=1,J19=1),1,0) -> 0 | CH19: =IF(BW19="FBA",1,0) -> 1 | CI19: =IF(AND(CH19=1,B19=1),1,0) -> 0 | CJ19: =IF(AND(CH19=1,C19=1),1,0) -> 0 | CK19: =IF(AND(CH19=1,D19=1),1,0) -> 0 | CL19: =IF(AND(CH19=1,E19=1),1,0) -> 0 | CM19: =IF(AND(CH19=1,F19=1),1,0) -> 0 | CN19: =IF(AND(CH19=1,G19=1),1,0) -> 0 | CO19: =IF(AND(CH19=1,H19=1),1,0) -> 0 | CP19: =IF(AND(CH19=1,I19=1),1,0) -> 0 | CQ19: =IF(AND(CH19=1,J19=1),1,0) -> 1 | CR19: =数据调研!N19 -> 2527 | CS19: =IF(AND(CR19<31,CR19<>0),1,0) -> 0 | CT19: =IF(AND(CS19=1,B19=1),1,0) -> 0 | CU19: =IF(AND(CS19=1,C19=1),1,0) -> 0 | CV19: =IF(AND(CS19=1,D19=1),1,0) -> 0 | CW19: =IF(AND(CS19=1,E19=1),1,0) -> 0 | CX19: =IF(AND(CS19=1,F19=1),1,0) -> 0 | CY19: =IF(AND(CS19=1,G19=1),1,0) -> 0 | CZ19: =IF(AND(CS19=1,H19=1),1,0) -> 0 | DA19: =IF(AND(CS19=1,I19=1),1,0) -> 0 | DB19: =IF(AND(CS19=1,J19=1),1,0) -> 0 | DC19: =IF(AND(CR19>30,CR19<61),1,0) -> 0 | DD19: =IF(AND(DC19=1,B19=1),1,0) -> 0 | DE19: =IF(AND(DC19=1,C19=1),1,0) -> 0 | DF19: =IF(AND(DC19=1,D19=1),1,0) -> 0 | DG19: =IF(AND(DC19=1,E19=1),1,0) -> 0 | DH19: =IF(AND(DC19=1,F19=1),1,0) -> 0 | DI19: =IF(AND(DC19=1,G19=1),1,0) -> 0 | DJ19: =IF(AND(DC19=1,H19=1),1,0) -> 0 | DK19: =IF(AND(DC19=1,I19=1),1,0) -> 0 | DL19: =IF(AND(DC19=1,J19=1),1,0) -> 0 | DM19: =IF(AND(CR19>60,CR19<91),1,0) -> 0 | DN19: =IF(AND(DM19=1,B19=1),1,0) -> 0 | DO19: =IF(AND(DM19=1,C19=1),1,0) -> 0 | DP19: =IF(AND(DM19=1,D19=1),1,0) -> 0 | DQ19: =IF(AND(DM19=1,E19=1),1,0) -> 0 | DR19: =IF(AND(DM19=1,F19=1),1,0) -> 0 | DS19: =IF(AND(DM19=1,G19=1),1,0) -> 0 | DT19: =IF(AND(DM19=1,H19=1),1,0) -> 0 | DU19: =IF(AND(DM19=1,I19=1),1,0) -> 0 | DV19: =IF(AND(DM19=1,J19=1),1,0) -> 0 | DW19: =IF(AND(CR19>90,CR19<181),1,0) -> 0 | DX19: =IF(AND(DW19=1,B19=1),1,0) -> 0 | DY19: =IF(AND(DW19=1,C19=1),1,0) -> 0 | DZ19: =IF(AND(DW19=1,D19=1),1,0) -> 0 | EA19: =IF(AND(DW19=1,E19=1),1,0) -> 0 | EB19: =IF(AND(DW19=1,F19=1),1,0) -> 0 | EC19: =IF(AND(DW19=1,G19=1),1,0) -> 0 | ED19: =IF(AND(DW19=1,H19=1),1,0) -> 0 | EE19: =IF(AND(DW19=1,I19=1),1,0) -> 0 | EF19: =IF(AND(DW19=1,J19=1),1,0) -> 0 | EG19: =IF(CR19>180,1,0) -> 1 | EH19: =IF(AND(EG19=1,B19=1),1,0) -> 0 | EI19: =IF(AND(EG19=1,C19=1),1,0) -> 0 | EJ19: =IF(AND(EG19=1,D19=1),1,0) -> 0 | EK19: =IF(AND(EG19=1,E19=1),1,0) -> 0 | EL19: =IF(AND(EG19=1,F19=1),1,0) -> 0 | EM19: =IF(AND(EG19=1,G19=1),1,0) -> 0 | EN19: =IF(AND(EG19=1,H19=1),1,0) -> 0 | EO19: =IF(AND(EG19=1,I19=1),1,0) -> 0 | EP19: =IF(AND(EG19=1,J19=1),1,0) -> 1 | ER19: 3 | ES19: 500-800 | ET19: =N163 -> 0
A20: =数据调研!F20 -> 10702 | B20: =IF(AND(A20>0,A20<100),1,0) -> 0 | C20: =IF(AND(A20>99,A20<500),1,0) -> 0 | D20: =IF(AND(A20>499,A20<1000),1,0) -> 0 | E20: =IF(AND(A20>999,A20<2000),1,0) -> 0 | F20: =IF(AND(A20>1999,A20<4000),1,0) -> 0 | G20: =IF(AND(A20>3999,A20<6000),1,0) -> 0 | H20: =IF(AND(A20>5999,A20<8000),1,0) -> 0 | I20: =IF(AND(A20>7999,A20<10001),1,0) -> 0 | J20: =IF(A20>10002,1,0) -> 1 | K20: =价格参考!K20 -> 210 | L20: =IF(AND(K20>0,K20<301),1,0) -> 1 | M20: =IF(AND(K20>300,K20<501),1,0) -> 0 | N20: =IF(AND(K20>500,K20<801),1,0) -> 0 | O20: =IF(AND(K20>800,K20<1001),1,0) -> 0 | P20: =IF(AND(K20>1000,K20<1501),1,0) -> 0 | Q20: =IF(AND(K20>1500,K20<2001),1,0) -> 0 | R20: =IF(AND(K20>2000,K20<3001),1,0) -> 0 | S20: =IF(AND(K20>3000,K20<4501),1,0) -> 0 | T20: =IF(AND(K20>4500,K20<6001),1,0) -> 0 | U20: =IF(AND(K20>6000,K20<8001),1,0) -> 0 | V20: =IF(AND(K20>8000,K20<>"N.A.",K20<>"< 5"),1,0) -> 0 | W20: =IF(A20<>"N.A.",A20,1000000) -> 10702 | X20: =数据调研!I20 -> 67 | Y20: =IF(X20<31,1,0) -> 0 | Z20: =IF(AND(Y20=1,B20=1),1,0) -> 0 | AA20: =IF(AND(Y20=1,C20=1),1,0) -> 0 | AB20: =IF(AND(Y20=1,D20=1),1,0) -> 0 | AC20: =IF(AND(Y20=1,E20=1),1,0) -> 0 | AD20: =IF(AND(Y20=1,F20=1),1,0) -> 0 | AE20: =IF(AND(Y20=1,G20=1),1,0) -> 0 | AF20: =IF(AND(Y20=1,H20=1),1,0) -> 0 | AG20: =IF(AND(Y20=1,I20=1),1,0) -> 0 | AH20: =IF(AND(Y20=1,J20=1),1,0) -> 0 | AI20: =IF(AND(X20>30,X20<101),1,0) -> 1 | AJ20: =IF(AND(AI20=1,B20=1),1,0) -> 0 | AK20: =IF(AND(AI20=1,C20=1),1,0) -> 0 | AL20: =IF(AND(AI20=1,D20=1),1,0) -> 0 | AM20: =IF(AND(AI20=1,E20=1),1,0) -> 0 | AN20: =IF(AND(AI20=1,F20=1),1,0) -> 0 | AO20: =IF(AND(AI20=1,G20=1),1,0) -> 0 | AP20: =IF(AND(AI20=1,H20=1),1,0) -> 0 | AQ20: =IF(AND(AI20=1,I20=1),1,0) -> 0 | AR20: =IF(AND(AI20=1,J20=1),1,0) -> 1 | AS20: =IF(AND(X20>100,X20<501),1,0) -> 0 | AT20: =IF(AND(B20=1,AS20=1),1,0) -> 0 | AU20: =IF(AND(C20=1,AS20=1),1,0) -> 0 | AV20: =IF(AND(D20=1,AS20=1),1,0) -> 0 | AW20: =IF(AND(E20=1,AS20=1),1,0) -> 0 | AX20: =IF(AND(F20=1,AS20=1),1,0) -> 0 | AY20: =IF(AND(G20=1,AS20=1),1,0) -> 0 | AZ20: =IF(AND(H20=1,AS20=1),1,0) -> 0 | BA20: =IF(AND(I20=1,AS20=1),1,0) -> 0 | BB20: =IF(AND(J20=1,AS20=1),1,0) -> 0 | BC20: =IF(AND(X20>500,X20<1001),1,0) -> 0 | BD20: =IF(AND(BC20=1,B20=1),1,0) -> 0 | BE20: =IF(AND(BC20=1,C20=1),1,0) -> 0 | BF20: =IF(AND(BC20=1,D20=1),1,0) -> 0 | BG20: =IF(AND(BC20=1,E20=1),1,0) -> 0 | BH20: =IF(AND(BC20=1,F20=1),1,0) -> 0 | BI20: =IF(AND(BC20=1,G20=1),1,0) -> 0 | BJ20: =IF(AND(BC20=1,H20=1),1,0) -> 0 | BK20: =IF(AND(BC20=1,I20=1),1,0) -> 0 | BL20: =IF(AND(BC20=1,J20=1),1,0) -> 0 | BM20: =IF(X20>1001,1,0) -> 0 | BN20: =IF(AND(B20=1,BM20=1),1,0) -> 0 | BO20: =IF(AND(C20=1,BM20=1),1,0) -> 0 | BP20: =IF(AND(D20=1,BM20=1),1,0) -> 0 | BQ20: =IF(AND(E20=1,BM20=1),1,0) -> 0 | BR20: =IF(AND(F20=1,BM20=1),1,0) -> 0 | BS20: =IF(AND(G20=1,BM20=1),1,0) -> 0 | BT20: =IF(AND(H20=1,BM20=1),1,0) -> 0 | BU20: =IF(AND(I20=1,BM20=1),1,0) -> 0 | BV20: =IF(AND(J20=1,BM20=1),1,0) -> 0 | BW20: =数据调研!K20 -> FBA | BX20: =IF(BW20="AMZ",1,0) -> 0 | BY20: =IF(AND(BX20=1,B20=1),1,0) -> 0 | BZ20: =IF(AND(BX20=1,C20=1),1,0) -> 0 | CA20: =IF(AND(BX20=1,D20=1),1,0) -> 0 | CB20: =IF(AND(BX20=1,E20=1),1,0) -> 0 | CC20: =IF(AND(BX20=1,F20=1),1,0) -> 0 | CD20: =IF(AND(BX20=1,G20=1),1,0) -> 0 | CE20: =IF(AND(BX20=1,H20=1),1,0) -> 0 | CF20: =IF(AND(BX20=1,I20=1),1,0) -> 0 | CG20: =IF(AND(BX20=1,J20=1),1,0) -> 0 | CH20: =IF(BW20="FBA",1,0) -> 1 | CI20: =IF(AND(CH20=1,B20=1),1,0) -> 0 | CJ20: =IF(AND(CH20=1,C20=1),1,0) -> 0 | CK20: =IF(AND(CH20=1,D20=1),1,0) -> 0 | CL20: =IF(AND(CH20=1,E20=1),1,0) -> 0 | CM20: =IF(AND(CH20=1,F20=1),1,0) -> 0 | CN20: =IF(AND(CH20=1,G20=1),1,0) -> 0 | CO20: =IF(AND(CH20=1,H20=1),1,0) -> 0 | CP20: =IF(AND(CH20=1,I20=1),1,0) -> 0 | CQ20: =IF(AND(CH20=1,J20=1),1,0) -> 1 | CR20: =数据调研!N20 -> 272 | CS20: =IF(AND(CR20<31,CR20<>0),1,0) -> 0 | CT20: =IF(AND(CS20=1,B20=1),1,0) -> 0 | CU20: =IF(AND(CS20=1,C20=1),1,0) -> 0 | CV20: =IF(AND(CS20=1,D20=1),1,0) -> 0 | CW20: =IF(AND(CS20=1,E20=1),1,0) -> 0 | CX20: =IF(AND(CS20=1,F20=1),1,0) -> 0 | CY20: =IF(AND(CS20=1,G20=1),1,0) -> 0 | CZ20: =IF(AND(CS20=1,H20=1),1,0) -> 0 | DA20: =IF(AND(CS20=1,I20=1),1,0) -> 0 | DB20: =IF(AND(CS20=1,J20=1),1,0) -> 0 | DC20: =IF(AND(CR20>30,CR20<61),1,0) -> 0 | DD20: =IF(AND(DC20=1,B20=1),1,0) -> 0 | DE20: =IF(AND(DC20=1,C20=1),1,0) -> 0 | DF20: =IF(AND(DC20=1,D20=1),1,0) -> 0 | DG20: =IF(AND(DC20=1,E20=1),1,0) -> 0 | DH20: =IF(AND(DC20=1,F20=1),1,0) -> 0 | DI20: =IF(AND(DC20=1,G20=1),1,0) -> 0 | DJ20: =IF(AND(DC20=1,H20=1),1,0) -> 0 | DK20: =IF(AND(DC20=1,I20=1),1,0) -> 0 | DL20: =IF(AND(DC20=1,J20=1),1,0) -> 0 | DM20: =IF(AND(CR20>60,CR20<91),1,0) -> 0 | DN20: =IF(AND(DM20=1,B20=1),1,0) -> 0 | DO20: =IF(AND(DM20=1,C20=1),1,0) -> 0 | DP20: =IF(AND(DM20=1,D20=1),1,0) -> 0 | DQ20: =IF(AND(DM20=1,E20=1),1,0) -> 0 | DR20: =IF(AND(DM20=1,F20=1),1,0) -> 0 | DS20: =IF(AND(DM20=1,G20=1),1,0) -> 0 | DT20: =IF(AND(DM20=1,H20=1),1,0) -> 0 | DU20: =IF(AND(DM20=1,I20=1),1,0) -> 0 | DV20: =IF(AND(DM20=1,J20=1),1,0) -> 0 | DW20: =IF(AND(CR20>90,CR20<181),1,0) -> 0 | DX20: =IF(AND(DW20=1,B20=1),1,0) -> 0 | DY20: =IF(AND(DW20=1,C20=1),1,0) -> 0 | DZ20: =IF(AND(DW20=1,D20=1),1,0) -> 0 | EA20: =IF(AND(DW20=1,E20=1),1,0) -> 0 | EB20: =IF(AND(DW20=1,F20=1),1,0) -> 0 | EC20: =IF(AND(DW20=1,G20=1),1,0) -> 0 | ED20: =IF(AND(DW20=1,H20=1),1,0) -> 0 | EE20: =IF(AND(DW20=1,I20=1),1,0) -> 0 | EF20: =IF(AND(DW20=1,J20=1),1,0) -> 0 | EG20: =IF(CR20>180,1,0) -> 1 | EH20: =IF(AND(EG20=1,B20=1),1,0) -> 0 | EI20: =IF(AND(EG20=1,C20=1),1,0) -> 0 | EJ20: =IF(AND(EG20=1,D20=1),1,0) -> 0 | EK20: =IF(AND(EG20=1,E20=1),1,0) -> 0 | EL20: =IF(AND(EG20=1,F20=1),1,0) -> 0 | EM20: =IF(AND(EG20=1,G20=1),1,0) -> 0 | EN20: =IF(AND(EG20=1,H20=1),1,0) -> 0 | EO20: =IF(AND(EG20=1,I20=1),1,0) -> 0 | EP20: =IF(AND(EG20=1,J20=1),1,0) -> 1 | ER20: 4 | ES20: 800-1000 | ET20: =O163 -> 2
A21: =数据调研!F21 -> N.A. | B21: =IF(AND(A21>0,A21<100),1,0) -> 0 | C21: =IF(AND(A21>99,A21<500),1,0) -> 0 | D21: =IF(AND(A21>499,A21<1000),1,0) -> 0 | E21: =IF(AND(A21>999,A21<2000),1,0) -> 0 | F21: =IF(AND(A21>1999,A21<4000),1,0) -> 0 | G21: =IF(AND(A21>3999,A21<6000),1,0) -> 0 | H21: =IF(AND(A21>5999,A21<8000),1,0) -> 0 | I21: =IF(AND(A21>7999,A21<10001),1,0) -> 0 | J21: =IF(A21>10002,1,0) -> 1 | K21: =价格参考!K21 -> 210 | L21: =IF(AND(K21>0,K21<301),1,0) -> 1 | M21: =IF(AND(K21>300,K21<501),1,0) -> 0 | N21: =IF(AND(K21>500,K21<801),1,0) -> 0 | O21: =IF(AND(K21>800,K21<1001),1,0) -> 0 | P21: =IF(AND(K21>1000,K21<1501),1,0) -> 0 | Q21: =IF(AND(K21>1500,K21<2001),1,0) -> 0 | R21: =IF(AND(K21>2000,K21<3001),1,0) -> 0 | S21: =IF(AND(K21>3000,K21<4501),1,0) -> 0 | T21: =IF(AND(K21>4500,K21<6001),1,0) -> 0 | U21: =IF(AND(K21>6000,K21<8001),1,0) -> 0 | V21: =IF(AND(K21>8000,K21<>"N.A.",K21<>"< 5"),1,0) -> 0 | W21: =IF(A21<>"N.A.",A21,1000000) -> 1000000 | X21: =数据调研!I21 -> 2543 | Y21: =IF(X21<31,1,0) -> 0 | Z21: =IF(AND(Y21=1,B21=1),1,0) -> 0 | AA21: =IF(AND(Y21=1,C21=1),1,0) -> 0 | AB21: =IF(AND(Y21=1,D21=1),1,0) -> 0 | AC21: =IF(AND(Y21=1,E21=1),1,0) -> 0 | AD21: =IF(AND(Y21=1,F21=1),1,0) -> 0 | AE21: =IF(AND(Y21=1,G21=1),1,0) -> 0 | AF21: =IF(AND(Y21=1,H21=1),1,0) -> 0 | AG21: =IF(AND(Y21=1,I21=1),1,0) -> 0 | AH21: =IF(AND(Y21=1,J21=1),1,0) -> 0 | AI21: =IF(AND(X21>30,X21<101),1,0) -> 0 | AJ21: =IF(AND(AI21=1,B21=1),1,0) -> 0 | AK21: =IF(AND(AI21=1,C21=1),1,0) -> 0 | AL21: =IF(AND(AI21=1,D21=1),1,0) -> 0 | AM21: =IF(AND(AI21=1,E21=1),1,0) -> 0 | AN21: =IF(AND(AI21=1,F21=1),1,0) -> 0 | AO21: =IF(AND(AI21=1,G21=1),1,0) -> 0 | AP21: =IF(AND(AI21=1,H21=1),1,0) -> 0 | AQ21: =IF(AND(AI21=1,I21=1),1,0) -> 0 | AR21: =IF(AND(AI21=1,J21=1),1,0) -> 0 | AS21: =IF(AND(X21>100,X21<501),1,0) -> 0 | AT21: =IF(AND(B21=1,AS21=1),1,0) -> 0 | AU21: =IF(AND(C21=1,AS21=1),1,0) -> 0 | AV21: =IF(AND(D21=1,AS21=1),1,0) -> 0 | AW21: =IF(AND(E21=1,AS21=1),1,0) -> 0 | AX21: =IF(AND(F21=1,AS21=1),1,0) -> 0 | AY21: =IF(AND(G21=1,AS21=1),1,0) -> 0 | AZ21: =IF(AND(H21=1,AS21=1),1,0) -> 0 | BA21: =IF(AND(I21=1,AS21=1),1,0) -> 0 | BB21: =IF(AND(J21=1,AS21=1),1,0) -> 0 | BC21: =IF(AND(X21>500,X21<1001),1,0) -> 0 | BD21: =IF(AND(BC21=1,B21=1),1,0) -> 0 | BE21: =IF(AND(BC21=1,C21=1),1,0) -> 0 | BF21: =IF(AND(BC21=1,D21=1),1,0) -> 0 | BG21: =IF(AND(BC21=1,E21=1),1,0) -> 0 | BH21: =IF(AND(BC21=1,F21=1),1,0) -> 0 | BI21: =IF(AND(BC21=1,G21=1),1,0) -> 0 | BJ21: =IF(AND(BC21=1,H21=1),1,0) -> 0 | BK21: =IF(AND(BC21=1,I21=1),1,0) -> 0 | BL21: =IF(AND(BC21=1,J21=1),1,0) -> 0 | BM21: =IF(X21>1001,1,0) -> 1 | BN21: =IF(AND(B21=1,BM21=1),1,0) -> 0 | BO21: =IF(AND(C21=1,BM21=1),1,0) -> 0 | BP21: =IF(AND(D21=1,BM21=1),1,0) -> 0 | BQ21: =IF(AND(E21=1,BM21=1),1,0) -> 0 | BR21: =IF(AND(F21=1,BM21=1),1,0) -> 0 | BS21: =IF(AND(G21=1,BM21=1),1,0) -> 0 | BT21: =IF(AND(H21=1,BM21=1),1,0) -> 0 | BU21: =IF(AND(I21=1,BM21=1),1,0) -> 0 | BV21: =IF(AND(J21=1,BM21=1),1,0) -> 1 | BW21: =数据调研!K21 -> AMZ | BX21: =IF(BW21="AMZ",1,0) -> 1 | BY21: =IF(AND(BX21=1,B21=1),1,0) -> 0 | BZ21: =IF(AND(BX21=1,C21=1),1,0) -> 0 | CA21: =IF(AND(BX21=1,D21=1),1,0) -> 0 | CB21: =IF(AND(BX21=1,E21=1),1,0) -> 0 | CC21: =IF(AND(BX21=1,F21=1),1,0) -> 0 | CD21: =IF(AND(BX21=1,G21=1),1,0) -> 0 | CE21: =IF(AND(BX21=1,H21=1),1,0) -> 0 | CF21: =IF(AND(BX21=1,I21=1),1,0) -> 0 | CG21: =IF(AND(BX21=1,J21=1),1,0) -> 1 | CH21: =IF(BW21="FBA",1,0) -> 0 | CI21: =IF(AND(CH21=1,B21=1),1,0) -> 0 | CJ21: =IF(AND(CH21=1,C21=1),1,0) -> 0 | CK21: =IF(AND(CH21=1,D21=1),1,0) -> 0 | CL21: =IF(AND(CH21=1,E21=1),1,0) -> 0 | CM21: =IF(AND(CH21=1,F21=1),1,0) -> 0 | CN21: =IF(AND(CH21=1,G21=1),1,0) -> 0 | CO21: =IF(AND(CH21=1,H21=1),1,0) -> 0 | CP21: =IF(AND(CH21=1,I21=1),1,0) -> 0 | CQ21: =IF(AND(CH21=1,J21=1),1,0) -> 0 | CR21: =数据调研!N21 -> 4229 | CS21: =IF(AND(CR21<31,CR21<>0),1,0) -> 0 | CT21: =IF(AND(CS21=1,B21=1),1,0) -> 0 | CU21: =IF(AND(CS21=1,C21=1),1,0) -> 0 | CV21: =IF(AND(CS21=1,D21=1),1,0) -> 0 | CW21: =IF(AND(CS21=1,E21=1),1,0) -> 0 | CX21: =IF(AND(CS21=1,F21=1),1,0) -> 0 | CY21: =IF(AND(CS21=1,G21=1),1,0) -> 0 | CZ21: =IF(AND(CS21=1,H21=1),1,0) -> 0 | DA21: =IF(AND(CS21=1,I21=1),1,0) -> 0 | DB21: =IF(AND(CS21=1,J21=1),1,0) -> 0 | DC21: =IF(AND(CR21>30,CR21<61),1,0) -> 0 | DD21: =IF(AND(DC21=1,B21=1),1,0) -> 0 | DE21: =IF(AND(DC21=1,C21=1),1,0) -> 0 | DF21: =IF(AND(DC21=1,D21=1),1,0) -> 0 | DG21: =IF(AND(DC21=1,E21=1),1,0) -> 0 | DH21: =IF(AND(DC21=1,F21=1),1,0) -> 0 | DI21: =IF(AND(DC21=1,G21=1),1,0) -> 0 | DJ21: =IF(AND(DC21=1,H21=1),1,0) -> 0 | DK21: =IF(AND(DC21=1,I21=1),1,0) -> 0 | DL21: =IF(AND(DC21=1,J21=1),1,0) -> 0 | DM21: =IF(AND(CR21>60,CR21<91),1,0) -> 0 | DN21: =IF(AND(DM21=1,B21=1),1,0) -> 0 | DO21: =IF(AND(DM21=1,C21=1),1,0) -> 0 | DP21: =IF(AND(DM21=1,D21=1),1,0) -> 0 | DQ21: =IF(AND(DM21=1,E21=1),1,0) -> 0 | DR21: =IF(AND(DM21=1,F21=1),1,0) -> 0 | DS21: =IF(AND(DM21=1,G21=1),1,0) -> 0 | DT21: =IF(AND(DM21=1,H21=1),1,0) -> 0 | DU21: =IF(AND(DM21=1,I21=1),1,0) -> 0 | DV21: =IF(AND(DM21=1,J21=1),1,0) -> 0 | DW21: =IF(AND(CR21>90,CR21<181),1,0) -> 0 | DX21: =IF(AND(DW21=1,B21=1),1,0) -> 0 | DY21: =IF(AND(DW21=1,C21=1),1,0) -> 0 | DZ21: =IF(AND(DW21=1,D21=1),1,0) -> 0 | EA21: =IF(AND(DW21=1,E21=1),1,0) -> 0 | EB21: =IF(AND(DW21=1,F21=1),1,0) -> 0 | EC21: =IF(AND(DW21=1,G21=1),1,0) -> 0 | ED21: =IF(AND(DW21=1,H21=1),1,0) -> 0 | EE21: =IF(AND(DW21=1,I21=1),1,0) -> 0 | EF21: =IF(AND(DW21=1,J21=1),1,0) -> 0 | EG21: =IF(CR21>180,1,0) -> 1 | EH21: =IF(AND(EG21=1,B21=1),1,0) -> 0 | EI21: =IF(AND(EG21=1,C21=1),1,0) -> 0 | EJ21: =IF(AND(EG21=1,D21=1),1,0) -> 0 | EK21: =IF(AND(EG21=1,E21=1),1,0) -> 0 | EL21: =IF(AND(EG21=1,F21=1),1,0) -> 0 | EM21: =IF(AND(EG21=1,G21=1),1,0) -> 0 | EN21: =IF(AND(EG21=1,H21=1),1,0) -> 0 | EO21: =IF(AND(EG21=1,I21=1),1,0) -> 0 | EP21: =IF(AND(EG21=1,J21=1),1,0) -> 1 | ER21: 5 | ES21: 1000-1500 | ET21: =P163 -> 0
