Workbook

Sheet 运营推广计划表
B2: 亚马逊新品利润预算表 | J2: 单个头程计算表
B3: 料号 | D3: SKU | F3: 产品排名目标 | G3: Top 300 | H3: Top120 | J3: 外箱尺寸（inch） | K3: =K4/2.54 -> 0 | L3: =L4/2.54 -> 0 | M3: =M4/2.54 -> 0
B4: 品名 | D4: ASIN | F4: 产品销量目标 | G4: 10单/天 | H4: 20单/天 | J4: 外箱尺寸（cm）
B5: 原币 | C5: 美元 | D5: 汇率 | E5: =_xlfn.IFS(C5="美元",K31,C5="欧元",K32,C5="英镑",K33) -> 7.15 | F5: 预计达成时间 | G5: 第2个月 | H5: 第4个月 | J5: 体积 | K5: =K4*L4*M4 -> 0
B6: 币别 | C6: 人民币（元） | J6: 重量（kg）
B7: 销售期间 | D7: 推广期 | F7: 盈利期 | G7: 总合计 | H7: 备注 | J7: 体积重 | K7: =K5/6000 -> 0 | L7: =K5/5000 -> 0 | M7: =K5/6000 -> 0
B8: 类目 产品链接 | D8: 第1月 | E8: 第2月 | F8: 第3月及以后 | J8: 物流价格/kg
B9: 收入 | C9: 刷单数量 | D9: 33 | E9: 5 | F9: 8 | G9: =SUM(D9:F9) -> 46 | H9: 预估刷单单量 | J9: 单个运费 | K9: =IF(K7>$K$6,K7*K8,$K$6*K8) -> 0 | L9: =IF(L7>$K$6,L7*L8,$K$6*L8) -> 0 | M9: =IF(M7>$K$6,M7*M8,$K$6*M8) -> 0
C10: 正常销量 | D10: =SUM(首批与返单囤货数量预测表!G3:G32) -> 115 | E10: =SUM(首批与返单囤货数量预测表!G33:G62) -> 266 | F10: =SUM(首批与返单囤货数量预测表!G63:G92) -> 488 | G10: =SUM(D10:F10) -> 869 | H10: 预估正常销量（不包含刷单单量），需要通过囤货计划中的销量预估，公式会自动汇总 | J10: 单项数量 | K10: 1
C11: 汇总销量 | D11: =D9+D10 -> 148 | E11: =E9+E10 -> 271 | F11: =F9+F10 -> 496 | G11: =SUM(D11:F11) -> 915 | H11: 预估销量（包含刷单单量） | J11: 单个头程 | K11: =K9/K10 -> 0 | L11: =L9/K10 -> 0 | M11: =M9/K10 -> 0
C12: 不含税售价（人民币） | D12: =D16/(1+D13) -> 278.7785 | E12: =E16/(1+E13) -> 285.9285 | F12: =F16/(1+F13) -> 293.0785 | H12: product sales价格 | K12: 空运 | L12: 红单 | M12: 海运
C13: 销售税率 | D13: =IF($C$5="美元",0,20%) -> 0 | E13: =IF($C$5="美元",0,20%) -> 0 | F13: =IF($C$5="美元",0,20%) -> 0 | H13: product sales tax税率，欧洲站20%，美国站0% | J13: 产品包装信息
C14: 含税售价(美元或其他货币） | D14: 38.99 | E14: 39.99 | F14: 40.99 | H14: 亚马逊上的售价 | J14: 彩盒尺寸（cm)
C15: 汇率 | D15: =$E$5 -> 7.15 | E15: =$E$5 -> 7.15 | F15: =$E$5 -> 7.15 | J15: 包裹重量(KG) | K15: 0.76
C16: 含税售价（人民币） | D16: =D14*D15 -> 278.7785 | E16: =E14*E15 -> 285.9285 | F16: =F14*F15 -> 293.0785
C17: 退款率 | D17: ='毛利测算表-US'!$C$29 -> 0.05 | E17: ='毛利测算表-US'!$C$29 -> 0.05 | F17: ='毛利测算表-US'!$C$29 -> 0.05 | H17: 预估退款率 | J17: 各费用占比
C18: 不含税销售额（人民币） | D18: =D11*D12 -> 41259.218 | E18: =E11*E12 -> 77486.624 | F18: =F11*F12 -> 145366.94 | G18: =SUM(D18:F18) -> 264112.78 | J18: 阶段 | K18: 第1月 | L18: 第2月 | M18: 第3月及以后
C19: 含税销售额（人民币） | D19: =D16*D11 -> 41259.218 | E19: =E16*E11 -> 77486.624 | F19: =F16*F11 -> 145366.94 | G19: =SUM(D19:F19) -> 264112.78 | J19: 营销占比 | K19: =D37 -> 0.28497335 | L19: =E37 -> 0.16004001 | M19: =F37 -> 0.08538668
B20: 成本 | C20: 产品成本单价（人民币） | D20: ='毛利测算表-US'!$C$19 -> 75 | E20: ='毛利测算表-US'!$C$19 -> 75 | F20: ='毛利测算表-US'!$C$19 -> 75 | J20: 站内促销营销比 | K20: =D29/D19 -> 0.20077199 | L20: =E29/E19 -> 0.10750188 | M20: =F29/F19 -> 0.045855087
C21: 总成本（人民币） | D21: =D11*D20 -> 11100 | E21: =E11*E20 -> 20325 | F21: =F11*F20 -> 37200 | G21: =SUM(D21:F21) -> 68625 | J21: 站外营销比 | K21: =(D47+D48)/D19 -> 0.17590384 | L21: =(E47+E48)/E19 -> 0.015766255 | M21: =(F47+F48)/F19 -> 0.013505535
B22: 毛利 | C22: 毛利额（人民币） | D22: =D18-D21 -> 30159.218 | E22: =E18-E21 -> 57161.624 | F22: =F18-F21 -> 108166.94 | G22: =SUM(D22:F22) -> 195487.78 | H22: 不含税销售额减去产品总成本 | J22: 成本比 | K22: =D21/D19 -> 0.26903079 | L22: =E21/E19 -> 0.26230334 | M22: =F21/F19 -> 0.25590413
C23: 毛利率 | D23: =D22/D18 -> 0.73096921 | E23: =E22/E18 -> 0.73769666 | F23: =F22/F18 -> 0.74409587 | G23: =SUM(D22:F22)/SUM(D18:F18) -> 0.74016782 | J23: 物流费用比例 | K23: =D45/D19 -> 0.039099141 | L23: =E45/E19 -> 0.038121418 | M23: =F45/F19 -> 0.037191401
B24: 站内促销费用 | C24: LD次数 | D24: 0 | E24: 0 | F24: 0 | H24: 每月预计秒杀次数 | J24: 佣金比 | K24: =D39 -> 0.15 | L24: =E39 -> 0.15 | M24: =F39 -> 0.15
C25: 7DD次数 | D25: 0 | E25: 0 | F25: 0 | H25: 每月预计7天促销次数 | J25: FBA配送费比 | K25: =D42/D19 -> 0.16337522 | L25: =E42/E19 -> 0.15928982 | M25: =F42/F19 -> 0.15540376
C26: Coupon | D26: 0.2 | E26: 0.2 | F26: 0.1 | H26: 优惠券的优惠金额数或者百分比 | J26: 其他费用 | K26: 0.02 | L26: 0.02 | M26: 0.02
C27: Coupon Rate（使用率） | D27: 0.7 | E27: 0.5 | F27: 0.4 | H27: 优惠券使用率=Coupon兑换数/总订单,第一次制作的时候需要预估，有两周的数据后可以实际计算； | J27: 退款 | K27: =D17 -> 0.05 | L27: =E17 -> 0.05 | M27: =F17 -> 0.05
C28: Prime Discount（折扣） | D28: 0.05 | E28: 0 | F28: 0 | H28: 会员专项折扣百分比 | J28: 净利率 | K28: =1-SUM(K19:K27) -> -0.35315435 | L28: =1-SUM(L19:L27) -> 0.03697728 | M28: =1-SUM(M19:M27) -> 0.18675341
C29: 总计（人民币） | D29: =IF(D26>0.8,(D24*$K$37+D25*$L$37+D26*D27*D11+D28*D14*D11+0.6*D11*D27)*D15,(D24*$K$37+D25*$L$37+D26*D14*D27*D11+D28*D14*D11+0.6*D11*D27)*D15) -> 8283.6954 | E29: =IF(E26>0.8,(E24*$K$37+E25*$L$37+E26*E27*E11+E28*E14*E11+0.6*E11*E27)*E15,(E24*$K$37+E25*$L$37+E26*E14*E27*E11+E28*E14*E11+0.6*E11*E27)*E15) -> 8329.9574 | F29: =IF(F26>0.8,(F24*$K$37+F25*$L$37+F26*F27*F11+F28*F14*F11+0.6*F11*F27)*F15,(F24*$K$37+F25*$L$37+F26*F14*F27*F11+F28*F14*F11+0.6*F11*F27)*F15) -> 6665.8134 | G29: =SUM(D29:F29) -> 23279.466 | H29: 请注意修改个站点LD,7DD的价格，参考右下方的价格信息
B30: 站内预估数据 | C30: CPC（预估）(美元或其他货币） | D30: 2 | E30: 1.6 | F30: 1.4 | H30: 参考类似产品历史数据或者卖家精灵，对CPC值做预估 | J30: 汇率
C31: 转化率（预估） | D31: 0.09 | E31: 0.1 | F31: 0.12 | H31: 结合后台商品探测器的类目关键词转化率和产品本身，对产品做出转化率预估 | J31: US | K31: 7.15
C32: 广告订单成本（每单）(美元或其他货币） | D32: =D30/D31 -> 22.222222 | E32: =E30/E31 -> 16 | F32: =F30/F31 -> 11.666667 | H32: 每个广告订单所需要的广告费 | J32: EU | K32: 7.45
C33: 广告订单占比（预估） | D33: 0.5 | E33: 0.4 | F33: 0.3 | H33: 整月广告订单占比的预估值 | J33: UK | K33: 8.66
C34: 广告订单营销比（Acos） | D34: =D32/D14 -> 0.56994671 | E34: =E32/E14 -> 0.40010003 | F34: =F32/F14 -> 0.28462227
B35: 费用 | C35: 站内推广费（人民币） | D35: =D16*D11*D37 -> 11757.778 | E35: =E16*E11*E37 -> 12400.96 | F35: =F16*F11*F37 -> 12412.4 | G35: =SUM(D35:F35) -> 36571.138 | J35: 站内促销费用明细（当地货币）
C36: 站内推广费（美金） | D36: =D35/$D$15 -> 1644.4444 | E36: =E35/$D$15 -> 1734.4 | F36: =F35/$D$15 -> 1736 | G36: =SUM(D36:F36) -> 5114.8444 | J36: 站点 | K36: LD | L36: 7DD
C37: 营销占比 | D37: =D34*D33 -> 0.28497335 | E37: =E34*E33 -> 0.16004001 | F37: =F34*F33 -> 0.08538668 | H37: 广告营销比=ACOS*广告订单占比 | J37: US | K37: 150 | L37: 300
C38: 平台佣金（人民币） | D38: =D16*D11*D39 -> 6188.8827 | E38: =E16*E11*E39 -> 11622.994 | F38: =F16*F11*F39 -> 21805.04 | G38: =SUM(D38:F38) -> 39616.917 | J38: DE | K38: 35 | L38: 70
C39: 平台佣金比例 | D39: 0.15 | E39: 0.15 | F39: 0.15 | J39: UK | K39: 25 | L39: 50
C40: FBA配送费（美元或其他货币） | D40: 6.37 | E40: =D40 -> 6.37 | F40: =E40 -> 6.37 | J40: IT/FR/ES | K40: 20 | L40: 40
C41: FBA配送费（人民币） | D41: =D40*D15 -> 45.5455 | E41: =E40*E15 -> 45.5455 | F41: =F40*F15 -> 45.5455 | H41: 单个产品FBA配送费
C42: FBA配送费（总）（人民币） | D42: =D41*D11 -> 6740.734 | E42: =E41*E11 -> 12342.831 | F42: =F41*F11 -> 22590.568 | G42: =SUM(D42:F42) -> 41674.132
C43: 平台及其他费用 | D43: =ROUND(D19*2%,2) -> 825.18 | E43: =ROUND(E19*2%,2) -> 1549.73 | F43: =ROUND(F19*2%,2) -> 2907.34 | G43: =SUM(D43:F43) -> 5282.25 | H43: 包含站内订阅、仓储、弃置等，可以按照2%计算
C44: 单个头程及海外仓费(人民币） | D44: 10.9 | E44: =D44 -> 10.9 | F44: =E44 -> 10.9 | H44: 单个产品头程及海外仓费，头程费按以下方法预估
C45: 头程及海外仓费（总） | D45: =D44*D11 -> 1613.2 | E45: =E44*E11 -> 2953.9 | F45: =F44*F11 -> 5406.4 | G45: =SUM(D45:F45) -> 9973.5
C46: 测评佣金（红包，人民币） | D46: =1400/30 -> 46.666667 | E46: 70 | F46: 70 | H46: 单个产品营销佣金（红包）
C47: 测评费用（总） | D47: =((D14*0.15+D40)*D15+D20+D44+D46)*D9 -> 7257.6551 | E47: =((E14*0.15+E40)*E15+E20+E44+E46)*E9 -> 1221.6739 | F47: =((F14*0.15+F40)*F15+F20+F44+F46)*F9 -> 1963.2582 | G47: =SUM(D47:F47) -> 10442.587
C48: 站外红人等推广费及其他报销（人民币） | D48: 0 | E48: 0 | F48: 0 | G48: =SUM(D48:F48) -> 0 | H48: 站外所有推广费及报销费用
C49: 费用总额 | D49: =D48+D47+D45+D43+D42+D38+D35+D29+D17*D19 -> 44730.086 | E49: =E48+E47+E45+E43+E42+E38+E35+E29+E17*E19 -> 54296.376 | F49: =F48+F47+F45+F43+F42+F38+F35+F29+F17*F19 -> 81019.167 | G49: =G48+G47+G45+G43+G42+G38+G35+G29+G17*G19 -> 166839.99
C50: 总费用占比 | D50: =D49/D18 -> 1.0841235 | E50: =E49/E18 -> 0.70071935 | F50: =F49/F18 -> 0.55734247 | G50: =G49/G18 -> 0.63169981
B51: 利润 | C51: 净毛利额（人民币） | D51: =D22-D49 -> -14570.868 | E51: =E22-E49 -> 2865.2471 | F51: =F22-F49 -> 27147.769 | G51: =SUM(D51:F51) -> 15442.148
C52: 净毛利率 | D52: =D51/D18 -> -0.35315424 | E52: =E51/E18 -> 0.036977312 | F52: =F51/F18 -> 0.1867534 | G52: =G51/G18 -> 0.058468009
B54: 填表说明： | C54: 绿底为必填项，非绿底的是自动计算项，欧洲站的销售税率设定为20%，美国站销售税率设定为0%。
C55: 头程费预估：先核算出各种物流方式的单位头程费，再测算每个阶段红单比重、空派比重、海运比重，最后核算出相应阶段的综合单位头程费。 公式：单位综合头程费=单位红单头程费*红单比重+单位空运头程费*空运比重+单位海运头程费*海运比重。（红单比重+空运比重+海运比重=1）
C56: 销售价格预估：平台订单价格按同类同级别产品的市场价估算。
B58: 总结 | C58: 月份 | D58: 月销量 | E58: 月销售额（RMB） | F58: 广告费 | G58: 广销比 | H58: 净利润（RMB)
C59: 第1个月 | D59: =D10 -> 115 | E59: =D19 -> 41259.218 | F59: =D35 -> 11757.778 | G59: =D37 -> 0.28497335 | H59: =D51 -> -14570.868
C60: 第2个月 | D60: =E10 -> 266 | E60: =E19 -> 77486.624 | F60: =E35 -> 12400.96 | G60: =E37 -> 0.16004001 | H60: =E51 -> 2865.2471
C61: 第3个月 | D61: =F10 -> 488 | E61: =F19 -> 145366.94 | F61: =F35 -> 12412.4 | G61: =F37 -> 0.08538668 | H61: =F51 -> 27147.769
E72: 欢迎扫码联系顾问咨询详情

Sheet 首批与返单囤货数量预测表
B2: 日期 | C2: 月份 | D2: 周 | E2: 天数 | F2: 客单价 | G2: 日总单量 （预计） | H2: 当前库存 | I2: 预计剩余库存 | J2: 到货库存 | L2: 13周销量计划
B3: 44622 | C3: 第一月 | D3: 第一周 | E3: 1 | F3: 39.97 | G3: =VLOOKUP(D3,L:N,3,0) -> 2 | H3: =M21 -> 400 | I3: =H3-G3 -> 398 | L3: 销售时间 | M3: 预计达到排名 | N3: 日销 | O3: 下单总量
B4: 44623 | C4: 第一月 | D4: 第一周 | E4: 2 | F4: 39.97 | G4: =VLOOKUP(D4,L:N,3,0) -> 2 | H4: =IF(I3<0,0,I3) -> 398 | I4: =IF(H4-G4+J4<0,0,H4-G4+J4) -> 396 | L4: 第一周 | M4: 600 | N4: 2 | O4: =N4*7 -> 14
B5: 44624 | C5: 第一月 | D5: 第一周 | E5: 3 | F5: 39.97 | G5: =VLOOKUP(D5,L:N,3,0) -> 2 | H5: =IF(I4<0,0,I4) -> 396 | I5: =IF(H5-G5+J5<0,0,H5-G5+J5) -> 394 | L5: 第二周 | M5: 520 | N5: 4 | O5: =N5*7 -> 28
B6: 44625 | C6: 第一月 | D6: 第一周 | E6: 4 | F6: 39.97 | G6: =VLOOKUP(D6,L:N,3,0) -> 2 | H6: =IF(I5<0,0,I5) -> 394 | I6: =IF(H6-G6+J6<0,0,H6-G6+J6) -> 392 | L6: 第三周 | M6: 460 | N6: 4 | O6: =N6*7 -> 28
B7: 44626 | C7: 第一月 | D7: 第一周 | E7: 5 | F7: 39.97 | G7: =VLOOKUP(D7,L:N,3,0) -> 2 | H7: =IF(I6<0,0,I6) -> 392 | I7: =IF(H7-G7+J7<0,0,H7-G7+J7) -> 390 | L7: 第四周 | M7: 410 | N7: 5 | O7: =N7*7 -> 35
B8: 44627 | C8: 第一月 | D8: 第一周 | E8: 6 | F8: 39.97 | G8: =VLOOKUP(D8,L:N,3,0) -> 2 | H8: =IF(I7<0,0,I7) -> 390 | I8: =IF(H8-G8+J8<0,0,H8-G8+J8) -> 388 | L8: 第五周 | M8: 380 | N8: 5 | O8: =N8*7 -> 35
B9: 44628 | C9: 第一月 | D9: 第一周 | E9: 7 | F9: 39.97 | G9: =VLOOKUP(D9,L:N,3,0) -> 2 | H9: =IF(I8<0,0,I8) -> 388 | I9: =IF(H9-G9+J9<0,0,H9-G9+J9) -> 386 | L9: 第六周 | M9: 350 | N9: 7 | O9: =N9*7 -> 49
B10: 44629 | C10: 第一月 | D10: 第二周 | E10: 8 | F10: 39.97 | G10: =VLOOKUP(D10,L:N,3,0) -> 4 | H10: =IF(I9<0,0,I9) -> 386 | I10: =IF(H10-G10+J10<0,0,H10-G10+J10) -> 382 | L10: 第七周 | M10: 300 | N10: 9 | O10: =N10*7 -> 63
B11: 44630 | C11: 第一月 | D11: 第二周 | E11: 9 | F11: 39.97 | G11: =VLOOKUP(D11,L:N,3,0) -> 4 | H11: =IF(I10<0,0,I10) -> 382 | I11: =IF(H11-G11+J11<0,0,H11-G11+J11) -> 378 | L11: 第八周 | M11: 280 | N11: 11 | O11: =N11*7 -> 77
B12: 44631 | C12: 第一月 | D12: 第二周 | E12: 10 | F12: 39.97 | G12: =VLOOKUP(D12,L:N,3,0) -> 4 | H12: =IF(I11<0,0,I11) -> 378 | I12: =IF(H12-G12+J12<0,0,H12-G12+J12) -> 374 | L12: 第九周 | M12: 210 | N12: 13 | O12: =N12*7 -> 91
B13: 44632 | C13: 第一月 | D13: 第二周 | E13: 11 | F13: 39.97 | G13: =VLOOKUP(D13,L:N,3,0) -> 4 | H13: =IF(I12<0,0,I12) -> 374 | I13: =IF(H13-G13+J13<0,0,H13-G13+J13) -> 370 | L13: 第十周 | M13: 180 | N13: 15 | O13: =N13*7 -> 105
B14: 44633 | C14: 第一月 | D14: 第二周 | E14: 12 | F14: 39.97 | G14: =VLOOKUP(D14,L:N,3,0) -> 4 | H14: =IF(I13<0,0,I13) -> 370 | I14: =IF(H14-G14+J14<0,0,H14-G14+J14) -> 366 | L14: 第十一周 | M14: 150 | N14: 16 | O14: =N14*7 -> 112
B15: 44634 | C15: 第一月 | D15: 第二周 | E15: 13 | F15: 39.97 | G15: =VLOOKUP(D15,L:N,3,0) -> 4 | H15: =IF(I14<0,0,I14) -> 366 | I15: =IF(H15-G15+J15<0,0,H15-G15+J15) -> 362 | L15: 第十二周 | M15: 150 | N15: 16 | O15: =N15*7 -> 112
B16: 44635 | C16: 第一月 | D16: 第二周 | E16: 14 | F16: 39.97 | G16: =VLOOKUP(D16,L:N,3,0) -> 4 | H16: =IF(I15<0,0,I15) -> 362 | I16: =IF(H16-G16+J16<0,0,H16-G16+J16) -> 358 | L16: 第十三周 | M16: 120 | N16: 20 | O16: =N16*7 -> 140
B17: 44636 | C17: 第一月 | D17: 第三周 | E17: 15 | F17: 39.97 | G17: =VLOOKUP(D17,L:N,3,0) -> 4 | H17: =IF(I16<0,0,I16) -> 358 | I17: =IF(H17-G17+J17<0,0,H17-G17+J17) -> 354 | L17: 汇总 | O17: =SUM(O4:O16) -> 889
B18: 44637 | C18: 第一月 | D18: 第三周 | E18: 16 | F18: 39.97 | G18: =VLOOKUP(D18,L:N,3,0) -> 4 | H18: =IF(I17<0,0,I17) -> 354 | I18: =IF(H18-G18+J18<0,0,H18-G18+J18) -> 350
B19: 44638 | C19: 第一月 | D19: 第三周 | E19: 17 | F19: 39.97 | G19: =VLOOKUP(D19,L:N,3,0) -> 4 | H19: =IF(I18<0,0,I18) -> 350 | I19: =IF(H19-G19+J19<0,0,H19-G19+J19) -> 346 | L19: 首批+返单下单计划
B20: 44639 | C20: 第一月 | D20: 第三周 | E20: 18 | F20: 39.97 | G20: =VLOOKUP(D20,L:N,3,0) -> 4 | H20: =IF(I19<0,0,I19) -> 346 | I20: =IF(H20-G20+J20<0,0,H20-G20+J20) -> 342 | L20: 批次 | M20: 下单量 | N20: 物流时效 | O20: 物流渠道 | P20: 产品交期 | Q20: 下单时间 | R20: 付款金额 | S20: 交货时间 | T20: 国内离港时间 | U20: 到货时间
B21: 44640 | C21: 第一月 | D21: 第三周 | E21: 19 | F21: 39.97 | G21: =VLOOKUP(D21,L:N,3,0) -> 4 | H21: =IF(I20<0,0,I20) -> 342 | I21: =IF(H21-G21+J21<0,0,H21-G21+J21) -> 338 | L21: 首批 | M21: 400 | N21: =_xlfn.IFS(O21=$L$29,$M$29,O21=$L$30,$M$30,O21=$L$31,$M$31,O21=$L$32,$M$32,O21=$L$33,$M$33) -> 40 | O21: 慢船时效 | P21: =$M$27 -> 30 | Q21: 44910 | R21: =M21*$M$28 -> 27600 | S21: =P21+Q21 -> 44940 | T21: =S21+M35 -> 44947 | U21: =T21+N21 -> 44987
B22: 44641 | C22: 第一月 | D22: 第三周 | E22: 20 | F22: 39.97 | G22: =VLOOKUP(D22,L:N,3,0) -> 4 | H22: =IF(I21<0,0,I21) -> 338 | I22: =IF(H22-G22+J22<0,0,H22-G22+J22) -> 334 | L22: 返单 | M22: 200 | N22: =_xlfn.IFS(O22=$L$29,$M$29,O22=$L$30,$M$30,O22=$L$31,$M$31,O22=$L$32,$M$32,O22=$L$33,$M$33) -> 40 | O22: 慢船时效 | P22: =$M$27 -> 30 | Q22: =S22-P22 -> 44606 | R22: =M22*$M$28 -> 13800 | S22: =T22-M35 -> 44636 | T22: =U22-N22 -> 44643 | U22: =B64 -> 44683
B23: 44642 | C23: 第一月 | D23: 第三周 | E23: 21 | F23: 39.97 | G23: =VLOOKUP(D23,L:N,3,0) -> 4 | H23: =IF(I22<0,0,I22) -> 334 | I23: =IF(H23-G23+J23<0,0,H23-G23+J23) -> 330 | L23: 第三批 | M23: 300 | N23: =_xlfn.IFS(O23=$L$29,$M$29,O23=$L$30,$M$30,O23=$L$31,$M$31,O23=$L$32,$M$32,O23=$L$33,$M$33) -> 40 | O23: 慢船时效 | P23: =$M$27 -> 30 | Q23: =S23-P23 -> 44626 | R23: =M23*$M$28 -> 20700 | S23: =T23-M38 -> 44656 | T23: =U23-N23 -> 44656 | U23: =B77 -> 44696
B24: 44643 | C24: 第一月 | D24: 第四周 | E24: 22 | F24: 39.97 | G24: =VLOOKUP(D24,L:N,3,0) -> 5 | H24: =IF(I23<0,0,I23) -> 330 | I24: =IF(H24-G24+J24<0,0,H24-G24+J24) -> 325 | L24: 第四批 | N24: =_xlfn.IFS(O24=$L$29,$M$29,O24=$L$30,$M$30,O24=$L$31,$M$31,O24=$L$32,$M$32,O24=$L$33,$M$33) -> 40 | O24: 慢船时效 | P24: =$M$27 -> 30 | Q24: =S24-P24 -> -70 | R24: =M24*$M$28 -> 0 | S24: =T24-M39 -> -40 | T24: =U24-N24 -> -40
B25: 44644 | C25: 第一月 | D25: 第四周 | E25: 23 | F25: 39.97 | G25: =VLOOKUP(D25,L:N,3,0) -> 5 | H25: =IF(I24<0,0,I24) -> 325 | I25: =IF(H25-G25+J25<0,0,H25-G25+J25) -> 320
B26: 44645 | C26: 第一月 | D26: 第四周 | E26: 24 | F26: 39.97 | G26: =VLOOKUP(D26,L:N,3,0) -> 5 | H26: =IF(I25<0,0,I25) -> 320 | I26: =IF(H26-G26+J26<0,0,H26-G26+J26) -> 315 | L26: 基础信息
B27: 44646 | C27: 第一月 | D27: 第四周 | E27: 25 | F27: 39.97 | G27: =VLOOKUP(D27,L:N,3,0) -> 5 | H27: =IF(I26<0,0,I26) -> 315 | I27: =IF(H27-G27+J27<0,0,H27-G27+J27) -> 310 | L27: 产品交期/天 | M27: 30 | N27: 天
B28: 44647 | C28: 第一月 | D28: 第四周 | E28: 26 | F28: 39.97 | G28: =VLOOKUP(D28,L:N,3,0) -> 5 | H28: =IF(I27<0,0,I27) -> 310 | I28: =IF(H28-G28+J28<0,0,H28-G28+J28) -> 305 | L28: 成本 | M28: 69 | N28: 人民币
B29: 44648 | C29: 第一月 | D29: 第四周 | E29: 27 | F29: 39.97 | G29: =VLOOKUP(D29,L:N,3,0) -> 5 | H29: =IF(I28<0,0,I28) -> 305 | I29: =IF(H29-G29+J29<0,0,H29-G29+J29) -> 300 | L29: 快递时效 | M29: 20 | N29: 天
B30: 44649 | C30: 第一月 | D30: 第四周 | E30: 28 | F30: 39.97 | G30: =VLOOKUP(D30,L:N,3,0) -> 5 | H30: =IF(I29<0,0,I29) -> 300 | I30: =IF(H30-G30+J30<0,0,H30-G30+J30) -> 295 | L30: 快船时效 | M30: 30 | N30: 天
B31: 44650 | C31: 第一月 | D31: 第五周 | E31: 29 | F31: 39.97 | G31: =VLOOKUP(D31,L:N,3,0) -> 5 | H31: =IF(I30<0,0,I30) -> 295 | I31: =IF(H31-G31+J31<0,0,H31-G31+J31) -> 290 | L31: 慢船时效 | M31: 40 | N31: 天
B32: 44651 | C32: 第一月 | D32: 第五周 | E32: 30 | F32: 39.97 | G32: =VLOOKUP(D32,L:N,3,0) -> 5 | H32: =IF(I31<0,0,I31) -> 290 | I32: =IF(H32-G32+J32<0,0,H32-G32+J32) -> 285 | L32: 空运时效 | M32: 20 | N32: 天 | P32: 欢迎扫码联系顾问咨询详情
B33: 44652 | C33: 第二月 | D33: 第五周 | E33: 31 | F33: 39.97 | G33: =VLOOKUP(D33,L:N,3,0) -> 5 | H33: =IF(I32<0,0,I32) -> 285 | I33: =IF(H33-G33+J33<0,0,H33-G33+J33) -> 280 | L33: 卡航 | M33: 40 | N33: 天
B34: 44653 | C34: 第二月 | D34: 第五周 | E34: 32 | F34: 39.97 | G34: =VLOOKUP(D34,L:N,3,0) -> 5 | H34: =IF(I33<0,0,I33) -> 280 | I34: =IF(H34-G34+J34<0,0,H34-G34+J34) -> 275 | L34: 单次补货维持天数 | M34: 60 | N34: 天
B35: 44654 | C35: 第二月 | D35: 第五周 | E35: 33 | F35: 39.97 | G35: =VLOOKUP(D35,L:N,3,0) -> 5 | H35: =IF(I34<0,0,I34) -> 275 | I35: =IF(H35-G35+J35<0,0,H35-G35+J35) -> 270 | L35: 交货后国内处理时间 | M35: 7 | N35: 天
B36: 44655 | C36: 第二月 | D36: 第五周 | E36: 34 | F36: 39.97 | G36: =VLOOKUP(D36,L:N,3,0) -> 5 | H36: =IF(I35<0,0,I35) -> 270 | I36: =IF(H36-G36+J36<0,0,H36-G36+J36) -> 265
B37: 44656 | C37: 第二月 | D37: 第五周 | E37: 35 | F37: 39.97 | G37: =VLOOKUP(D37,L:N,3,0) -> 5 | H37: =IF(I36<0,0,I36) -> 265 | I37: =IF(H37-G37+J37<0,0,H37-G37+J37) -> 260
B38: 44657 | C38: 第二月 | D38: 第六周 | E38: 36 | F38: 39.97 | G38: =VLOOKUP(D38,L:N,3,0) -> 7 | H38: =IF(I37<0,0,I37) -> 260 | I38: =IF(H38-G38+J38<0,0,H38-G38+J38) -> 253
B39: 44658 | C39: 第二月 | D39: 第六周 | E39: 37 | F39: 39.97 | G39: =VLOOKUP(D39,L:N,3,0) -> 7 | H39: =IF(I38<0,0,I38) -> 253 | I39: =IF(H39-G39+J39<0,0,H39-G39+J39) -> 246
B40: 44659 | C40: 第二月 | D40: 第六周 | E40: 38 | F40: 39.97 | G40: =VLOOKUP(D40,L:N,3,0) -> 7 | H40: =IF(I39<0,0,I39) -> 246 | I40: =IF(H40-G40+J40<0,0,H40-G40+J40) -> 239
B41: 44660 | C41: 第二月 | D41: 第六周 | E41: 39 | F41: 39.97 | G41: =VLOOKUP(D41,L:N,3,0) -> 7 | H41: =IF(I40<0,0,I40) -> 239 | I41: =IF(H41-G41+J41<0,0,H41-G41+J41) -> 232
B42: 44661 | C42: 第二月 | D42: 第六周 | E42: 40 | F42: 39.97 | G42: =VLOOKUP(D42,L:N,3,0) -> 7 | H42: =IF(I41<0,0,I41) -> 232 | I42: =IF(H42-G42+J42<0,0,H42-G42+J42) -> 225
B43: 44662 | C43: 第二月 | D43: 第六周 | E43: 41 | F43: 39.97 | G43: =VLOOKUP(D43,L:N,3,0) -> 7 | H43: =IF(I42<0,0,I42) -> 225 | I43: =IF(H43-G43+J43<0,0,H43-G43+J43) -> 218
B44: 44663 | C44: 第二月 | D44: 第六周 | E44: 42 | F44: 39.97 | G44: =VLOOKUP(D44,L:N,3,0) -> 7 | H44: =IF(I43<0,0,I43) -> 218 | I44: =IF(H44-G44+J44<0,0,H44-G44+J44) -> 211
B45: 44664 | C45: 第二月 | D45: 第七周 | E45: 43 | F45: 39.97 | G45: =VLOOKUP(D45,L:N,3,0) -> 9 | H45: =IF(I44<0,0,I44) -> 211 | I45: =IF(H45-G45+J45<0,0,H45-G45+J45) -> 202
B46: 44665 | C46: 第二月 | D46: 第七周 | E46: 44 | F46: 39.97 | G46: =VLOOKUP(D46,L:N,3,0) -> 9 | H46: =IF(I45<0,0,I45) -> 202 | I46: =IF(H46-G46+J46<0,0,H46-G46+J46) -> 193
B47: 44666 | C47: 第二月 | D47: 第七周 | E47: 45 | F47: 39.97 | G47: =VLOOKUP(D47,L:N,3,0) -> 9 | H47: =IF(I46<0,0,I46) -> 193 | I47: =IF(H47-G47+J47<0,0,H47-G47+J47) -> 184
... B63: 44682 | C63: 第三月 | D63: 第九周 | E63: 61 | F63: 39.97 | G63: =VLOOKUP(D63,L:N,3,0) -> 13 | H63: =IF(I62<0,0,I62) -> 19 | I63: =IF(H63-G63+J63<0,0,H63-G63+J63) -> 6
B64: 44683 | C64: 第三月 | D64: 第九周 | E64: 62 | F64: 39.97 | G64: =VLOOKUP(D64,L:N,3,0) -> 13 | H64: =IF(I63<0,0,I63) -> 6 | I64: =IF(H64-G64+J64<0,0,H64-G64+J64) -> 193 | J64: 200
B65: 44684 | C65: 第三月 | D65: 第九周 | E65: 63 | F65: 39.97 | G65: =VLOOKUP(D65,L:N,3,0) -> 13 | H65: =IF(I64<0,0,I64) -> 193 | I65: =IF(H65-G65+J65<0,0,H65-G65+J65) -> 180
B66: 44685 | C66: 第三月 | D66: 第十周 | E66: 64 | F66: 39.97 | G66: =VLOOKUP(D66,L:N,3,0) -> 15 | H66: =IF(I65<0,0,I65) -> 180 | I66: =IF(H66-G66+J66<0,0,H66-G66+J66) -> 165
B67: 44686 | C67: 第三月 | D67: 第十周 | E67: 65 | F67: 39.97 | G67: =VLOOKUP(D67,L:N,3,0) -> 15 | H67: =IF(I66<0,0,I66) -> 165 | I67: =IF(H67-G67+J67<0,0,H67-G67+J67) -> 150
B68: 44687 | C68: 第三月 | D68: 第十周 | E68: 66 | F68: 39.97 | G68: =VLOOKUP(D68,L:N,3,0) -> 15 | H68: =IF(I67<0,0,I67) -> 150 | I68: =IF(H68-G68+J68<0,0,H68-G68+J68) -> 135
B69: 44688 | C69: 第三月 | D69: 第十周 | E69: 67 | F69: 39.97 | G69: =VLOOKUP(D69,L:N,3,0) -> 15 | H69: =IF(I68<0,0,I68) -> 135 | I69: =IF(H69-G69+J69<0,0,H69-G69+J69) -> 120
B70: 44689 | C70: 第三月 | D70: 第十周 | E70: 68 | F70: 39.97 | G70: =VLOOKUP(D70,L:N,3,0) -> 15 | H70: =IF(I69<0,0,I69) -> 120 | I70: =IF(H70-G70+J70<0,0,H70-G70+J70) -> 105
B71: 44690 | C71: 第三月 | D71: 第十周 | E71: 69 | F71: 39.97 | G71: =VLOOKUP(D71,L:N,3,0) -> 15 | H71: =IF(I70<0,0,I70) -> 105 | I71: =IF(H71-G71+J71<0,0,H71-G71+J71) -> 90
B72: 44691 | C72: 第三月 | D72: 第十周 | E72: 70 | F72: 39.97 | G72: =VLOOKUP(D72,L:N,3,0) -> 15 | H72: =IF(I71<0,0,I71) -> 90 | I72: =IF(H72-G72+J72<0,0,H72-G72+J72) -> 75
B73: 44692 | C73: 第三月 | D73: 第十一周 | E73: 71 | F73: 39.97 | G73: =VLOOKUP(D73,L:N,3,0) -> 16 | H73: =IF(I72<0,0,I72) -> 75 | I73: =IF(H73-G73+J73<0,0,H73-G73+J73) -> 59
B74: 44693 | C74: 第三月 | D74: 第十一周 | E74: 72 | F74: 39.97 | G74: =VLOOKUP(D74,L:N,3,0) -> 16 | H74: =IF(I73<0,0,I73) -> 59 | I74: =IF(H74-G74+J74<0,0,H74-G74+J74) -> 43
B75: 44694 | C75: 第三月 | D75: 第十一周 | E75: 73 | F75: 39.97 | G75: =VLOOKUP(D75,L:N,3,0) -> 16 | H75: =IF(I74<0,0,I74) -> 43 | I75: =IF(H75-G75+J75<0,0,H75-G75+J75) -> 27
B76: 44695 | C76: 第三月 | D76: 第十一周 | E76: 74 | F76: 39.97 | G76: =VLOOKUP(D76,L:N,3,0) -> 16 | H76: =IF(I75<0,0,I75) -> 27 | I76: =IF(H76-G76+J76<0,0,H76-G76+J76) -> 11
B77: 44696 | C77: 第三月 | D77: 第十一周 | E77: 75 | F77: 39.97 | G77: =VLOOKUP(D77,L:N,3,0) -> 16 | H77: =IF(I76<0,0,I76) -> 11 | I77: =IF(H77-G77+J77<0,0,H77-G77+J77) -> 295 | J77: 300
B78: 44697 | C78: 第三月 | D78: 第十一周 | E78: 76 | F78: 39.97 | G78: =VLOOKUP(D78,L:N,3,0) -> 16 | H78: =IF(I77<0,0,I77) -> 295 | I78: =IF(H78-G78+J78<0,0,H78-G78+J78) -> 279
B79: 44698 | C79: 第三月 | D79: 第十一周 | E79: 77 | F79: 39.97 | G79: =VLOOKUP(D79,L:N,3,0) -> 16 | H79: =IF(I78<0,0,I78) -> 279 | I79: =IF(H79-G79+J79<0,0,H79-G79+J79) -> 263
B80: 44699 | C80: 第三月 | D80: 第十二周 | E80: 78 | F80: 39.97 | G80: =VLOOKUP(D80,L:N,3,0) -> 16 | H80: =IF(I79<0,0,I79) -> 263 | I80: =IF(H80-G80+J80<0,0,H80-G80+J80) -> 247
B81: 44700 | C81: 第三月 | D81: 第十二周 | E81: 79 | F81: 39.97 | G81: =VLOOKUP(D81,L:N,3,0) -> 16 | H81: =IF(I80<0,0,I80) -> 247 | I81: =IF(H81-G81+J81<0,0,H81-G81+J81) -> 231
B82: 44701 | C82: 第三月 | D82: 第十二周 | E82: 80 | F82: 39.97 | G82: =VLOOKUP(D82,L:N,3,0) -> 16 | H82: =IF(I81<0,0,I81) -> 231 | I82: =IF(H82-G82+J82<0,0,H82-G82+J82) -> 215
B83: 44702 | C83: 第三月 | D83: 第十二周 | E83: 81 | F83: 39.97 | G83: =VLOOKUP(D83,L:N,3,0) -> 16 | H83: =IF(I82<0,0,I82) -> 215 | I83: =IF(H83-G83+J83<0,0,H83-G83+J83) -> 199
B84: 44703 | C84: 第三月 | D84: 第十二周 | E84: 82 | F84: 39.97 | G84: =VLOOKUP(D84,L:N,3,0) -> 16 | H84: =IF(I83<0,0,I83) -> 199 | I84: =IF(H84-G84+J84<0,0,H84-G84+J84) -> 183
B85: 44704 | C85: 第三月 | D85: 第十二周 | E85: 83 | F85: 39.97 | G85: =VLOOKUP(D85,L:N,3,0) -> 16 | H85: =IF(I84<0,0,I84) -> 183 | I85: =IF(H85-G85+J85<0,0,H85-G85+J85) -> 167
B86: 44705 | C86: 第三月 | D86: 第十二周 | E86: 84 | F86: 39.97 | G86: =VLOOKUP(D86,L:N,3,0) -> 16 | H86: =IF(I85<0,0,I85) -> 167 | I86: =IF(H86-G86+J86<0,0,H86-G86+J86) -> 151
B87: 44706 | C87: 第三月 | D87: 第十三周 | E87: 85 | F87: 39.97 | G87: =VLOOKUP(D87,L:N,3,0) -> 20 | H87: =IF(I86<0,0,I86) -> 151 | I87: =IF(H87-G87+J87<0,0,H87-G87+J87) -> 131
B88: 44707 | C88: 第三月 | D88: 第十三周 | E88: 86 | F88: 39.97 | G88: =VLOOKUP(D88,L:N,3,0) -> 20 | H88: =IF(I87<0,0,I87) -> 131 | I88: =IF(H88-G88+J88<0,0,H88-G88+J88) -> 111
B89: 44708 | C89: 第三月 | D89: 第十三周 | E89: 87 | F89: 39.97 | G89: =VLOOKUP(D89,L:N,3,0) -> 20 | H89: =IF(I88<0,0,I88) -> 111 | I89: =IF(H89-G89+J89<0,0,H89-G89+J89) -> 91
... B92: 44711 | C92: 第三月 | D92: 第十三周 | E92: 90 | F92: 39.97 | G92: =VLOOKUP(D92,L:N,3,0) -> 20 | H92: =IF(I91<0,0,I91) -> 51 | I92: =IF(H92-G92+J92<0,0,H92-G92+J92) -> 31

Sheet 毛利测算表-US
B2: 1 | C2: 利润核算表（海运） | Q2: 利润核算表（空运） | W2: 利润核算表（快递）
B3: 售价阶梯 | C3: 成本结构 | N3: 利润 | O3: 毛利率 | T3: 利润 | U3: 毛利率 | Z3: 利润 | AA3: 毛利率
C4: 采购成本 | D4: 采购占比 | E4: 头程运费 | F4: 头程占比 | G4: FBA费用 | H4: 交易佣金 | I4: 仓租（淡/旺） | J4: 广告费用 | K4: 汇率折损 | L4: 退款费用 | M4: VAT税 | Q4: 采购占比 | R4: 头程运费 | S4: 头程占比 | W4: 采购占比 | X4: 头程运输 | Y4: 头程占比
B5: =B6-$B$2 -> 32.99 | C5: =$E$19 -> 10.48951 | D5: =C5/B5*100% -> 0.31796031 | E5: =$E$20 -> 1.53 | F5: =E5/B5*100% -> 0.04637769 | G5: =$C$36 -> 6.37 | H5: =B5*0.15 -> 4.9485 | I5: 0 | J5: =B5*0.2 -> 6.598 | K5: =B5*0.03 -> 0.9897 | L5: =B5*$C$29 -> 1.6495 | M5: 0 | N5: =B5-C5-E5-G5-H5-J5-K5-L5-I5-M5 -> 0.41478951 | O5: =N5/B5 -> 0.012573189 | Q5: =C5/B5*100% -> 0.31796031 | R5: =$E$21 -> 4.7290909 | S5: =R5/B5*100% -> 0.14334922 | T5: =B5-C5-R5-G5-H5-J5-K5-L5-I5-M5 -> -2.7843014 | U5: =T5/B5 -> -0.084398345 | W5: =C5/B5*100% -> 0.31796031 | X5: =$E$22 -> 5.5636364 | Y5: =X5/B5*100% -> 0.16864615 | Z5: =B5-C5-X5-G5-H5-J5-K5-L5-I5-M5 -> -3.6188469 | AA5: =Z5/B5 -> -0.10969527
B6: =B7-$B$2 -> 33.99 | C6: =$E$19 -> 10.48951 | D6: =C6/B6*100% -> 0.30860578 | E6: =$E$20 -> 1.53 | F6: =E6/B6*100% -> 0.045013239 | G6: =$C$36 -> 6.37 | H6: =B6*0.15 -> 5.0985 | I6: 0 | J6: =B6*0.2 -> 6.798 | K6: =B6*0.03 -> 1.0197 | L6: =B6*$C$29 -> 1.6995 | M6: 0 | N6: =B6-C6-E6-G6-H6-J6-K6-L6-I6-M6 -> 0.98478951 | O6: =N6/B6 -> 0.028972919 | Q6: =C6/B6*100% -> 0.30860578 | R6: =$E$21 -> 4.7290909 | S6: =R6/B6*100% -> 0.13913183 | T6: =B6-C6-R6-G6-H6-J6-K6-L6-I6-M6 -> -2.2143014 | U6: =T6/B6 -> -0.065145672 | W6: =C6/B6*100% -> 0.30860578 | X6: =$E$22 -> 5.5636364 | Y6: =X6/B6*100% -> 0.16368451 | Z6: =B6-C6-X6-G6-H6-J6-K6-L6-I6-M6 -> -3.0488469 | AA6: =Z6/B6 -> -0.089698348
B7: =B8-$B$2 -> 34.99 | C7: =$E$19 -> 10.48951 | D7: =C7/B7*100% -> 0.29978595 | E7: =$E$20 -> 1.53 | F7: =E7/B7*100% -> 0.043726779 | G7: =$C$36 -> 6.37 | H7: =B7*0.15 -> 5.2485 | I7: 0 | J7: =B7*0.2 -> 6.998 | K7: =B7*0.03 -> 1.0497 | L7: =B7*$C$29 -> 1.7495 | M7: 0 | N7: =B7-C7-E7-G7-H7-J7-K7-L7-I7-M7 -> 1.5547895 | O7: =N7/B7 -> 0.044435253 | Q7: =C7/B7*100% -> 0.29978595 | R7: =$E$21 -> 4.7290909 | S7: =R7/B7*100% -> 0.1351555 | T7: =B7-C7-R7-G7-H7-J7-K7-L7-I7-M7 -> -1.6443014 | U7: =T7/B7 -> -0.046993467 | W7: =C7/B7*100% -> 0.29978595 | X7: =$E$22 -> 5.5636364 | Y7: =X7/B7*100% -> 0.15900647 | Z7: =B7-C7-X7-G7-H7-J7-K7-L7-I7-M7 -> -2.4788469 | AA7: =Z7/B7 -> -0.070844437
B8: =B9-$B$2 -> 35.99 | C8: =$E$19 -> 10.48951 | D8: =C8/B8*100% -> 0.29145625 | E8: =$E$20 -> 1.53 | F8: =E8/B8*100% -> 0.042511809 | G8: =$C$36 -> 6.37 | H8: =B8*0.15 -> 5.3985 | I8: 0 | J8: =B8*0.2 -> 7.198 | K8: =B8*0.03 -> 1.0797 | L8: =B8*$C$29 -> 1.7995 | M8: 0 | N8: =B8-C8-E8-G8-H8-J8-K8-L8-I8-M8 -> 2.1247895 | O8: =N8/B8 -> 0.05903833 | Q8: =C8/B8*100% -> 0.29145625 | R8: =$E$21 -> 4.7290909 | S8: =R8/B8*100% -> 0.13140014 | T8: =B8-C8-R8-G8-H8-J8-K8-L8-I8-M8 -> -1.0743014 | U8: =T8/B8 -> -0.029849997 | W8: =C8/B8*100% -> 0.29145625 | X8: =$E$22 -> 5.5636364 | Y8: =X8/B8*100% -> 0.1545884 | Z8: =B8-C8-X8-G8-H8-J8-K8-L8-I8-M8 -> -1.9088469 | AA8: =Z8/B8 -> -0.053038257
B9: =B17 -> 36.99 | C9: =$E$19 -> 10.48951 | D9: =C9/B9*100% -> 0.28357693 | E9: =$E$20 -> 1.53 | F9: =E9/B9*100% -> 0.04136253 | G9: =$C$36 -> 6.37 | H9: =B9*0.15 -> 5.5485 | I9: 0 | J9: =B9*0.2 -> 7.398 | K9: =B9*0.03 -> 1.1097 | L9: =B9*$C$29 -> 1.8495 | M9: 0 | N9: =B9-C9-E9-G9-H9-J9-K9-L9-I9-M9 -> 2.6947895 | O9: =N9/B9 -> 0.072851839 | Q9: =C9/B9*100% -> 0.28357693 | R9: =$E$21 -> 4.7290909 | S9: =R9/B9*100% -> 0.12784782 | T9: =B9-C9-R9-G9-H9-J9-K9-L9-I9-M9 -> -0.5043014 | U9: =T9/B9 -> -0.013633452 | W9: =C9/B9*100% -> 0.28357693 | X9: =$E$22 -> 5.5636364 | Y9: =X9/B9*100% -> 0.1504092 | Z9: =B9-C9-X9-G9-H9-J9-K9-L9-I9-M9 -> -1.3388469 | AA9: =Z9/B9 -> -0.036194832
B10: =B9+$B$2 -> 37.99 | C10: =$E$19 -> 10.48951 | D10: =C10/B10*100% -> 0.27611241 | E10: =$E$20 -> 1.53 | F10: =E10/B10*100% -> 0.040273756 | G10: =$C$36 -> 6.37 | H10: =B10*0.15 -> 5.6985 | I10: 0 | J10: =B10*0.2 -> 7.598 | K10: =B10*0.03 -> 1.1397 | L10: =B10*$C$29 -> 1.8995 | M10: 0 | N10: =B10-C10-E10-G10-H10-J10-K10-L10-I10-M10 -> 3.2647895 | O10: =N10/B10 -> 0.085938129 | Q10: =C10/B10*100% -> 0.27611241 | R10: =$E$21 -> 4.7290909 | S10: =R10/B10*100% -> 0.12448252 | T10: =B10-C10-R10-G10-H10-J10-K10-L10-I10-M10 -> 0.065698601 | U10: =T10/B10 -> 0.0017293657 | W10: =C10/B10*100% -> 0.27611241 | X10: =$E$22 -> 5.5636364 | Y10: =X10/B10*100% -> 0.14645002 | Z10: =B10-C10-X10-G10-H10-J10-K10-L10-I10-M10 -> -0.76884685 | AA10: =Z10/B10 -> -0.020238138
B11: =B10+$B$2 -> 38.99 | C11: =$E$19 -> 10.48951 | D11: =C11/B11*100% -> 0.26903079 | E11: =$E$20 -> 1.53 | F11: =E11/B11*100% -> 0.039240831 | G11: =$C$36 -> 6.37 | H11: =B11*0.15 -> 5.8485 | I11: 0 | J11: =B11*0.2 -> 7.798 | K11: =B11*0.03 -> 1.1697 | L11: =B11*$C$29 -> 1.9495 | M11: 0 | N11: =B11-C11-E11-G11-H11-J11-K11-L11-I11-M11 -> 3.8347895 | O11: =N11/B11 -> 0.098353155 | Q11: =C11/B11*100% -> 0.26903079 | R11: =$E$21 -> 4.7290909 | S11: =R11/B11*100% -> 0.12128984 | T11: =B11-C11-R11-G11-H11-J11-K11-L11-I11-M11 -> 0.6356986 | U11: =T11/B11 -> 0.016304145 | W11: =C11/B11*100% -> 0.26903079 | X11: =$E$22 -> 5.5636364 | Y11: =X11/B11*100% -> 0.14269393 | Z11: =B11-C11-X11-G11-H11-J11-K11-L11-I11-M11 -> -0.19884685 | AA11: =Z11/B11 -> -0.0050999449
B12: =B11+$B$2 -> 39.99 | C12: =$E$19 -> 10.48951 | D12: =C12/B12*100% -> 0.26230334 | E12: =$E$20 -> 1.53 | F12: =E12/B12*100% -> 0.038259565 | G12: =$C$36 -> 6.37 | H12: =B12*0.15 -> 5.9985 | I12: 0 | J12: =B12*0.2 -> 7.998 | K12: =B12*0.03 -> 1.1997 | L12: =B12*$C$29 -> 1.9995 | M12: 0 | N12: =B12-C12-E12-G12-H12-J12-K12-L12-I12-M12 -> 4.4047895 | O12: =N12/B12 -> 0.11014727 | Q12: =C12/B12*100% -> 0.26230334 | R12: =$E$21 -> 4.7290909 | S12: =R12/B12*100% -> 0.11825684 | T12: =B12-C12-R12-G12-H12-J12-K12-L12-I12-M12 -> 1.2056986 | U12: =T12/B12 -> 0.030150003 | W12: =C12/B12*100% -> 0.26230334 | X12: =$E$22 -> 5.5636364 | Y12: =X12/B12*100% -> 0.13912569 | Z12: =B12-C12-X12-G12-H12-J12-K12-L12-I12-M12 -> 0.37115315 | AA12: =Z12/B12 -> 0.009281149
B13: =B12+$B$2 -> 40.99 | C13: =$E$19 -> 10.48951 | D13: =C13/B13*100% -> 0.25590413 | E13: =$E$20 -> 1.53 | F13: =E13/B13*100% -> 0.037326177 | G13: =$C$36 -> 6.37 | H13: =B13*0.15 -> 6.1485 | I13: 0 | J13: =B13*0.2 -> 8.198 | K13: =B13*0.03 -> 1.2297 | L13: =B13*$C$29 -> 2.0495 | M13: 0 | N13: =B13-C13-E13-G13-H13-J13-K13-L13-I13-M13 -> 4.9747895 | O13: =N13/B13 -> 0.12136593 | Q13: =C13/B13*100% -> 0.25590413 | R13: =$E$21 -> 4.7290909 | S13: =R13/B13*100% -> 0.11537182 | T13: =B13-C13-R13-G13-H13-J13-K13-L13-I13-M13 -> 1.7756986 | U13: =T13/B13 -> 0.043320288 | W13: =C13/B13*100% -> 0.25590413 | X13: =$E$22 -> 5.5636364 | Y13: =X13/B13*100% -> 0.13573155 | Z13: =B13-C13-X13-G13-H13-J13-K13-L13-I13-M13 -> 0.94115315 | AA13: =Z13/B13 -> 0.022960555
B14: =B13+$B$2 -> 41.99 | C14: =$E$19 -> 10.48951 | D14: =C14/B14*100% -> 0.24980973 | E14: =$E$20 -> 1.53 | F14: =E14/B14*100% -> 0.036437247 | G14: =$C$36 -> 6.37 | H14: =B14*0.15 -> 6.2985 | I14: 0 | J14: =B14*0.2 -> 8.398 | K14: =B14*0.03 -> 1.2597 | L14: =B14*$C$29 -> 2.0995 | M14: 0 | N14: =B14-C14-E14-G14-H14-J14-K14-L14-I14-M14 -> 5.5447895 | O14: =N14/B14 -> 0.13205024 | Q14: =C14/B14*100% -> 0.24980973 | R14: =$E$21 -> 4.7290909 | S14: =R14/B14*100% -> 0.11262422 | T14: =B14-C14-R14-G14-H14-J14-K14-L14-I14-M14 -> 2.3456986 | U14: =T14/B14 -> 0.055863267 | W14: =C14/B14*100% -> 0.24980973 | X14: =$E$22 -> 5.5636364 | Y14: =X14/B14*100% -> 0.13249908 | Z14: =B14-C14-X14-G14-H14-J14-K14-L14-I14-M14 -> 1.5111531 | AA14: =Z14/B14 -> 0.035988405
B16: 设定售价
B17: 36.99
C18: 人民币 | E18: 美金
B19: 采购成本 | C19: 75 | E19: =C19/$C$23 -> 10.48951
B20: 海运成本 | C20: =MAX(C28*C32,C27*C32) -> 10.9395 | E20: =C20/$C$23 -> 1.53
B21: 空派成本 | C21: =MAX(C27*C33,C28*C33) -> 33.813 | E21: =C21/$C$23 -> 4.7290909
B22: DHL成本 | C22: =MAX(C34*C27,C34*C28) -> 39.78 | E22: =C22/$C$23 -> 5.5636364
B23: 汇率 | C23: 7.15
B24: 长 | C24: 25.5 | E24: 厘米
B25: 宽 | C25: 19.5 | E25: 厘米
B26: 高 | C26: 12 | E26: 厘米 | K26: 欢迎扫码联系顾问咨询详情
B27: 产品实重 | C27: 0.81 | E27: 千克
B28: 海运体积重 | C28: =C24*C25*C26/6000 -> 0.9945 | E28: 千克
B29: 预估退款率 | C29: 0.05
B31: 渠道 | C31: 实时价格
B32: 海运价格 | C32: 11 | E32: 元/KG
B33: 空派价格 | C33: 34 | E33: 元/KG
B34: UPS快递价格 | C34: 40 | E34: 元/KG
B36: FBA配送费 | C36: 6.37

Sheet 毛利测算表-UK
B2: 1 | C2: 利润核算表（海运） | Q2: 利润核算表（空运） | W2: 利润核算表（快船）
B3: 售价阶梯 | C3: 成本结构 | N3: 利润 | O3: 毛利率 | T3: 利润 | U3: 毛利率 | Z3: 利润 | AA3: 毛利率
C4: 采购成本 | D4: 采购占比 | E4: 头程运费 | F4: 头程占比 | G4: FBA费用 | H4: 交易佣金 | I4: 仓租（淡/旺） | J4: 广告费用 | K4: 汇率折损 | L4: 退款费用 | M4: VAT税 | Q4: 采购占比 | R4: 头程运费 | S4: 头程占比 | W4: 采购占比 | X4: 头程运输 | Y4: 头程占比
B5: =B6-$B$2 -> 32.99 | C5: =$E$19 -> 8.6605081 | D5: =C5/B5*100% -> 0.26251919 | E5: =$E$20 -> 0.86128753 | F5: =E5/B5*100% -> 0.026107533 | G5: =$C$36 -> 2.82 | H5: =B5*0.15 -> 4.9485 | I5: 0 | J5: =B5*0.1 -> 3.299 | K5: =B5*0.03 -> 0.9897 | L5: =B5*$C$29 -> 1.6495 | M5: =(B5-J5)/1.2*0.2 -> 4.9485 | N5: =B5-C5-E5-G5-H5-J5-K5-L5-I5-M5 -> 4.8130044 | O5: =N5/B5 -> 0.14589283 | Q5: =C5/B5*100% -> 0.26251919 | R5: =$E$21 -> 4.1915993 | S5: =R5/B5*100% -> 0.12705666 | T5: =B5-C5-R5-G5-H5-J5-K5-L5-I5-M5 -> 1.4826926 | U5: =T5/B5 -> 0.044943698 | W5: =C5/B5*100% -> 0.26251919 | X5: =$E$22 -> 1.9522517 | Y5: =X5/B5*100% -> 0.059177076 | Z5: =B5-C5-X5-G5-H5-J5-K5-L5-I5-M5 -> 3.7220402 | AA5: =Z5/B5 -> 0.11282329
B6: =B7-$B$2 -> 33.99 | C6: =$E$19 -> 8.6605081 | D6: =C6/B6*100% -> 0.25479577 | E6: =$E$20 -> 0.86128753 | F6: =E6/B6*100% -> 0.025339439 | G6: =$C$36 -> 2.82 | H6: =B6*0.15 -> 5.0985 | I6: 0 | J6: =B6*0.1 -> 3.399 | K6: =B6*0.03 -> 1.0197 | L6: =B6*$C$29 -> 1.6995 | M6: =(B6-J6)/1.2*0.2 -> 5.0985 | N6: =B6-C6-E6-G6-H6-J6-K6-L6-I6-M6 -> 5.3330044 | O6: =N6/B6 -> 0.15689922 | Q6: =C6/B6*100% -> 0.25479577 | R6: =$E$21 -> 4.1915993 | S6: =R6/B6*100% -> 0.1233186 | T6: =B6-C6-R6-G6-H6-J6-K6-L6-I6-M6 -> 2.0026926 | U6: =T6/B6 -> 0.058920053 | W6: =C6/B6*100% -> 0.25479577 | X6: =$E$22 -> 1.9522517 | Y6: =X6/B6*100% -> 0.057436062 | Z6: =B6-C6-X6-G6-H6-J6-K6-L6-I6-M6 -> 4.2420402 | AA6: =Z6/B6 -> 0.12480259
B7: =B8-$B$2 -> 34.99 | C7: =$E$19 -> 8.6605081 | D7: =C7/B7*100% -> 0.24751381 | E7: =$E$20 -> 0.86128753 | F7: =E7/B7*100% -> 0.024615248 | G7: =$C$36 -> 2.82 | H7: =B7*0.15 -> 5.2485 | I7: 0 | J7: =B7*0.1 -> 3.499 | K7: =B7*0.03 -> 1.0497 | L7: =B7*$C$29 -> 1.7495 | M7: =(B7-J7)/1.2*0.2 -> 5.2485 | N7: =B7-C7-E7-G7-H7-J7-K7-L7-I7-M7 -> 5.8530044 | O7: =N7/B7 -> 0.16727649 | Q7: =C7/B7*100% -> 0.24751381 | R7: =$E$21 -> 4.1915993 | S7: =R7/B7*100% -> 0.11979421 | T7: =B7-C7-R7-G7-H7-J7-K7-L7-I7-M7 -> 2.5226926 | U7: =T7/B7 -> 0.072097531 | W7: =C7/B7*100% -> 0.24751381 | X7: =$E$22 -> 1.9522517 | Y7: =X7/B7*100% -> 0.055794562 | Z7: =B7-C7-X7-G7-H7-J7-K7-L7-I7-M7 -> 4.7620402 | AA7: =Z7/B7 -> 0.13609718
B8: =B9-$B$2 -> 35.99 | C8: =$E$19 -> 8.6605081 | D8: =C8/B8*100% -> 0.24063651 | E8: =$E$20 -> 0.86128753 | F8: =E8/B8*100% -> 0.023931301 | G8: =$C$36 -> 2.82 | H8: =B8*0.15 -> 5.3985 | I8: 0 | J8: =B8*0.1 -> 3.599 | K8: =B8*0.03 -> 1.0797 | L8: =B8*$C$29 -> 1.7995 | M8: =(B8-J8)/1.2*0.2 -> 5.3985 | N8: =B8-C8-E8-G8-H8-J8-K8-L8-I8-M8 -> 6.3730044 | O8: =N8/B8 -> 0.17707709 | Q8: =C8/B8*100% -> 0.24063651 | R8: =$E$21 -> 4.1915993 | S8: =R8/B8*100% -> 0.11646567 | T8: =B8-C8-R8-G8-H8-J8-K8-L8-I8-M8 -> 3.0426926 | U8: =T8/B8 -> 0.084542723 | W8: =C8/B8*100% -> 0.24063651 | X8: =$E$22 -> 1.9522517 | Y8: =X8/B8*100% -> 0.054244283 | Z8: =B8-C8-X8-G8-H8-J8-K8-L8-I8-M8 -> 5.2820402 | AA8: =Z8/B8 -> 0.14676411
B9: =B17 -> 36.99 | C9: =$E$19 -> 8.6605081 | D9: =C9/B9*100% -> 0.23413106 | E9: =$E$20 -> 0.86128753 | F9: =E9/B9*100% -> 0.023284334 | G9: =$C$36 -> 2.82 | H9: =B9*0.15 -> 5.5485 | I9: 0 | J9: =B9*0.1 -> 3.699 | K9: =B9*0.03 -> 1.1097 | L9: =B9*$C$29 -> 1.8495 | M9: =(B9-J9)/1.2*0.2 -> 5.5485 | N9: =B9-C9-E9-G9-H9-J9-K9-L9-I9-M9 -> 6.8930044 | O9: =N9/B9 -> 0.18634778 | Q9: =C9/B9*100% -> 0.23413106 | R9: =$E$21 -> 4.1915993 | S9: =R9/B9*100% -> 0.11331709 | T9: =B9-C9-R9-G9-H9-J9-K9-L9-I9-M9 -> 3.5626926 | U9: =T9/B9 -> 0.096315021 | W9: =C9/B9*100% -> 0.23413106 | X9: =$E$22 -> 1.9522517 | Y9: =X9/B9*100% -> 0.052777825 | Z9: =B9-C9-X9-G9-H9-J9-K9-L9-I9-M9 -> 5.8020402 | AA9: =Z9/B9 -> 0.15685429
B10: =B9+$B$2 -> 37.99 | C10: =$E$19 -> 8.6605081 | D10: =C10/B10*100% -> 0.2279681 | E10: =$E$20 -> 0.86128753 | F10: =E10/B10*100% -> 0.022671427 | G10: =$C$36 -> 2.82 | H10: =B10*0.15 -> 5.6985 | I10: 0 | J10: =B10*0.1 -> 3.799 | K10: =B10*0.03 -> 1.1397 | L10: =B10*$C$29 -> 1.8995 | M10: =(B10-J10)/1.2*0.2 -> 5.6985 | N10: =B10-C10-E10-G10-H10-J10-K10-L10-I10-M10 -> 7.4130044 | O10: =N10/B10 -> 0.19513041 | Q10: =C10/B10*100% -> 0.2279681 | R10: =$E$21 -> 4.1915993 | S10: =R10/B10*100% -> 0.11033428 | T10: =B10-C10-R10-G10-H10-J10-K10-L10-I10-M10 -> 4.0826926 | U10: =T10/B10 -> 0.10746756 | W10: =C10/B10*100% -> 0.2279681 | X10: =$E$22 -> 1.9522517 | Y10: =X10/B10*100% -> 0.051388569 | Z10: =B10-C10-X10-G10-H10-J10-K10-L10-I10-M10 -> 6.3220402 | AA10: =Z10/B10 -> 0.16641327
B11: =B10+$B$2 -> 38.99 | C11: =$E$19 -> 8.6605081 | D11: =C11/B11*100% -> 0.22212126 | E11: =$E$20 -> 0.86128753 | F11: =E11/B11*100% -> 0.02208996 | G11: =$C$36 -> 2.82 | H11: =B11*0.15 -> 5.8485 | I11: 0 | J11: =B11*0.1 -> 3.899 | K11: =B11*0.03 -> 1.1697 | L11: =B11*$C$29 -> 1.9495 | M11: =(B11-J11)/1.2*0.2 -> 5.8485 | N11: =B11-C11-E11-G11-H11-J11-K11-L11-I11-M11 -> 7.9330044 | O11: =N11/B11 -> 0.20346254 | Q11: =C11/B11*100% -> 0.22212126 | R11: =$E$21 -> 4.1915993 | S11: =R11/B11*100% -> 0.10750447 | T11: =B11-C11-R11-G11-H11-J11-K11-L11-I11-M11 -> 4.6026926 | U11: =T11/B11 -> 0.11804803 | W11: =C11/B11*100% -> 0.22212126 | X11: =$E$22 -> 1.9522517 | Y11: =X11/B11*100% -> 0.050070575 | Z11: =B11-C11-X11-G11-H11-J11-K11-L11-I11-M11 -> 6.8420402 | AA11: =Z11/B11 -> 0.17548192
B12: =B11+$B$2 -> 39.99 | C12: =$E$19 -> 8.6605081 | D12: =C12/B12*100% -> 0.21656684 | E12: =$E$20 -> 0.86128753 | F12: =E12/B12*100% -> 0.021537573 | G12: =$C$36 -> 2.82 | H12: =B12*0.15 -> 5.9985 | I12: 0 | J12: =B12*0.1 -> 3.999 | K12: =B12*0.03 -> 1.1997 | L12: =B12*$C$29 -> 1.9995 | M12: =(B12-J12)/1.2*0.2 -> 5.9985 | N12: =B12-C12-E12-G12-H12-J12-K12-L12-I12-M12 -> 8.4530044 | O12: =N12/B12 -> 0.21137795 | Q12: =C12/B12*100% -> 0.21656684 | R12: =$E$21 -> 4.1915993 | S12: =R12/B12*100% -> 0.10481619 | T12: =B12-C12-R12-G12-H12-J12-K12-L12-I12-M12 -> 5.1226926 | U12: =T12/B12 -> 0.12809934 | W12: =C12/B12*100% -> 0.21656684 | X12: =$E$22 -> 1.9522517 | Y12: =X12/B12*100% -> 0.048818498 | Z12: =B12-C12-X12-G12-H12-J12-K12-L12-I12-M12 -> 7.3620402 | AA12: =Z12/B12 -> 0.18409703
B13: =B12+$B$2 -> 40.99 | C13: =$E$19 -> 8.6605081 | D13: =C13/B13*100% -> 0.21128344 | E13: =$E$20 -> 0.86128753 | F13: =E13/B13*100% -> 0.021012138 | G13: =$C$36 -> 2.82 | H13: =B13*0.15 -> 6.1485 | I13: 0 | J13: =B13*0.1 -> 4.099 | K13: =B13*0.03 -> 1.2297 | L13: =B13*$C$29 -> 2.0495 | M13: =(B13-J13)/1.2*0.2 -> 6.1485 | N13: =B13-C13-E13-G13-H13-J13-K13-L13-I13-M13 -> 8.9730044 | O13: =N13/B13 -> 0.21890716 | Q13: =C13/B13*100% -> 0.21128344 | R13: =$E$21 -> 4.1915993 | S13: =R13/B13*100% -> 0.10225907 | T13: =B13-C13-R13-G13-H13-J13-K13-L13-I13-M13 -> 5.6426926 | U13: =T13/B13 -> 0.13766022 | W13: =C13/B13*100% -> 0.21128344 | X13: =$E$22 -> 1.9522517 | Y13: =X13/B13*100% -> 0.047627512 | Z13: =B13-C13-X13-G13-H13-J13-K13-L13-I13-M13 -> 7.8820402 | AA13: =Z13/B13 -> 0.19229178
B14: =B13+$B$2 -> 41.99 | C14: =$E$19 -> 8.6605081 | D14: =C14/B14*100% -> 0.20625168 | E14: =$E$20 -> 0.86128753 | F14: =E14/B14*100% -> 0.02051173 | G14: =$C$36 -> 2.82 | H14: =B14*0.15 -> 6.2985 | I14: 0 | J14: =B14*0.1 -> 4.199 | K14: =B14*0.03 -> 1.2597 | L14: =B14*$C$29 -> 2.0995 | M14: =(B14-J14)/1.2*0.2 -> 6.2985 | N14: =B14-C14-E14-G14-H14-J14-K14-L14-I14-M14 -> 9.4930044 | O14: =N14/B14 -> 0.22607774 | Q14: =C14/B14*100% -> 0.20625168 | R14: =$E$21 -> 4.1915993 | S14: =R14/B14*100% -> 0.099823751 | T14: =B14-C14-R14-G14-H14-J14-K14-L14-I14-M14 -> 6.1626926 | U14: =T14/B14 -> 0.14676572 | W14: =C14/B14*100% -> 0.20625168 | X14: =$E$22 -> 1.9522517 | Y14: =X14/B14*100% -> 0.046493254 | Z14: =B14-C14-X14-G14-H14-J14-K14-L14-I14-M14 -> 8.4020402 | AA14: =Z14/B14 -> 0.20009622
B16: 设定售价
B17: 36.99
C18: 人民币 | E18: 英镑
B19: 采购成本 | C19: 75 | E19: =C19/$C$23 -> 8.6605081
B20: 海运成本 | C20: =MAX(C28*C32,C27*C32) -> 7.45875 | E20: =C20/$C$23 -> 0.86128753
B21: 空派成本 | C21: =MAX(C27*C33,C28*C33) -> 36.29925 | E21: =C21/$C$23 -> 4.1915993
B22: DHL成本 | C22: =MAX(C34*C27,C34*C28) -> 16.9065 | E22: =C22/$C$23 -> 1.9522517
B23: 汇率 | C23: 8.66
B24: 长 | C24: 25.5 | E24: 厘米
B25: 宽 | C25: 19.5 | E25: 厘米
B26: 高 | C26: 12 | E26: 厘米
B27: 产品实重 | C27: 0.81 | E27: 千克
B28: 海运体积重 | C28: =C24*C25*C26/6000 -> 0.9945 | E28: 千克
B29: 预估退款率 | C29: 0.05
B31: 渠道 | C31: 实时价格
B32: 海运价格 | C32: 7.5 | E32: 元/KG
B33: 空派价格 | C33: 36.5 | E33: 元/KG
B34: 卡航价格 | C34: 17 | E34: 元/KG
B36: FBA配送费 | C36: 2.82

Sheet 毛利测算表-DE
B2: 1 | C2: 利润核算表（海运） | Q2: 利润核算表（空运） | W2: 利润核算表（快船）
B3: 售价阶梯 | C3: 成本结构 | N3: 利润 | O3: 毛利率 | T3: 利润 | U3: 毛利率 | Z3: 利润 | AA3: 毛利率
C4: 采购成本 | D4: 采购占比 | E4: 头程运费 | F4: 头程占比 | G4: FBA费用 | H4: 交易佣金 | I4: 仓租（淡/旺） | J4: 广告费用 | K4: 汇率折损 | L4: 退款费用 | M4: VAT税 | Q4: 采购占比 | R4: 头程运费 | S4: 头程占比 | W4: 采购占比 | X4: 头程运输 | Y4: 头程占比
B5: =B6-$B$2 -> 32.99 | C5: =$E$19 -> 10.067114 | D5: =C5/B5*100% -> 0.30515654 | E5: =$E$20 -> 2.002349 | F5: =E5/B5*100% -> 0.060695635 | G5: =$C$36 -> 3.7 | H5: =B5*0.15 -> 4.9485 | I5: 0 | J5: =B5*0.1 -> 3.299 | K5: =B5*0.03 -> 0.9897 | L5: =B5*$C$29 -> 1.6495 | M5: =(B5-J5)/1.19*0.19 -> 4.7405798 | N5: =B5-C5-E5-G5-H5-J5-K5-L5-I5-M5 -> 1.5932571 | O5: =N5/B5 -> 0.048295152 | Q5: =C5/B5*100% -> 0.30515654 | R5: =$E$21 -> 4.4051678 | S5: =R5/B5*100% -> 0.1335304 | T5: =B5-C5-R5-G5-H5-J5-K5-L5-I5-M5 -> -0.80956171 | U5: =T5/B5 -> -0.024539609 | W5: =C5/B5*100% -> 0.30515654 | X5: =$E$22 -> 2.4695638 | Y5: =X5/B5*100% -> 0.07485795 | Z5: =B5-C5-X5-G5-H5-J5-K5-L5-I5-M5 -> 1.1260423 | AA5: =Z5/B5 -> 0.034132838
B6: =B7-$B$2 -> 33.99 | C6: =$E$19 -> 10.067114 | D6: =C6/B6*100% -> 0.2961787 | E6: =$E$20 -> 2.002349 | F6: =E6/B6*100% -> 0.058909944 | G6: =$C$36 -> 3.7 | H6: =B6*0.15 -> 5.0985 | I6: 0 | J6: =B6*0.1 -> 3.399 | K6: =B6*0.03 -> 1.0197 | L6: =B6*$C$29 -> 1.6995 | M6: =(B6-J6)/1.19*0.19 -> 4.8842773 | N6: =B6-C6-E6-G6-H6-J6-K6-L6-I6-M6 -> 2.1195596 | O6: =N6/B6 -> 0.062358329 | Q6: =C6/B6*100% -> 0.2961787 | R6: =$E$21 -> 4.4051678 | S6: =R6/B6*100% -> 0.12960188 | T6: =B6-C6-R6-G6-H6-J6-K6-L6-I6-M6 -> -0.28325919 | U6: =T6/B6 -> -0.0083336037 | W6: =C6/B6*100% -> 0.2961787 | X6: =$E$22 -> 2.4695638 | Y6: =X6/B6*100% -> 0.072655597 | Z6: =B6-C6-X6-G6-H6-J6-K6-L6-I6-M6 -> 1.6523448 | AA6: =Z6/B6 -> 0.048612675
B7: =B8-$B$2 -> 34.99 | C7: =$E$19 -> 10.067114 | D7: =C7/B7*100% -> 0.28771404 | E7: =$E$20 -> 2.002349 | F7: =E7/B7*100% -> 0.057226322 | G7: =$C$36 -> 3.7 | H7: =B7*0.15 -> 5.2485 | I7: 0 | J7: =B7*0.1 -> 3.499 | K7: =B7*0.03 -> 1.0497 | L7: =B7*$C$29 -> 1.7495 | M7: =(B7-J7)/1.19*0.19 -> 5.0279748 | N7: =B7-C7-E7-G7-H7-J7-K7-L7-I7-M7 -> 2.6458621 | O7: =N7/B7 -> 0.075617666 | Q7: =C7/B7*100% -> 0.28771404 | R7: =$E$21 -> 4.4051678 | S7: =R7/B7*100% -> 0.12589791 | T7: =B7-C7-R7-G7-H7-J7-K7-L7-I7-M7 -> 0.24304333 | U7: =T7/B7 -> 0.0069460798 | W7: =C7/B7*100% -> 0.28771404 | X7: =$E$22 -> 2.4695638 | Y7: =X7/B7*100% -> 0.07057913 | Z7: =B7-C7-X7-G7-H7-J7-K7-L7-I7-M7 -> 2.1786474 | AA7: =Z7/B7 -> 0.062264857
B8: =B9-$B$2 -> 35.99 | C8: =$E$19 -> 10.067114 | D8: =C8/B8*100% -> 0.27971976 | E8: =$E$20 -> 2.002349 | F8: =E8/B8*100% -> 0.05563626 | G8: =$C$36 -> 3.7 | H8: =B8*0.15 -> 5.3985 | I8: 0 | J8: =B8*0.1 -> 3.599 | K8: =B8*0.03 -> 1.0797 | L8: =B8*$C$29 -> 1.7995 | M8: =(B8-J8)/1.19*0.19 -> 5.1716723 | N8: =B8-C8-E8-G8-H8-J8-K8-L8-I8-M8 -> 3.1721646 | O8: =N8/B8 -> 0.088140168 | Q8: =C8/B8*100% -> 0.27971976 | R8: =$E$21 -> 4.4051678 | S8: =R8/B8*100% -> 0.12239977 | T8: =B8-C8-R8-G8-H8-J8-K8-L8-I8-M8 -> 0.76934585 | U8: =T8/B8 -> 0.021376656 | W8: =C8/B8*100% -> 0.27971976 | X8: =$E$22 -> 2.4695638 | Y8: =X8/B8*100% -> 0.068618054 | Z8: =B8-C8-X8-G8-H8-J8-K8-L8-I8-M8 -> 2.7049499 | AA8: =Z8/B8 -> 0.075158374
B9: =B17 -> 36.99 | C9: =$E$19 -> 10.067114 | D9: =C9/B9*100% -> 0.27215772 | E9: =$E$20 -> 2.002349 | F9: =E9/B9*100% -> 0.054132171 | G9: =$C$36 -> 3.7 | H9: =B9*0.15 -> 5.5485 | I9: 0 | J9: =B9*0.1 -> 3.699 | K9: =B9*0.03 -> 1.1097 | L9: =B9*$C$29 -> 1.8495 | M9: =(B9-J9)/1.19*0.19 -> 5.3153697 | N9: =B9-C9-E9-G9-H9-J9-K9-L9-I9-M9 -> 3.6984672 | O9: =N9/B9 -> 0.099985595 | Q9: =C9/B9*100% -> 0.27215772 | R9: =$E$21 -> 4.4051678 | S9: =R9/B9*100% -> 0.11909078 | T9: =B9-C9-R9-G9-H9-J9-K9-L9-I9-M9 -> 1.2956484 | U9: =T9/B9 -> 0.03502699 | W9: =C9/B9*100% -> 0.27215772 | X9: =$E$22 -> 2.4695638 | Y9: =X9/B9*100% -> 0.06676301 | Z9: =B9-C9-X9-G9-H9-J9-K9-L9-I9-M9 -> 3.2312524 | AA9: =Z9/B9 -> 0.087354755
B10: =B9+$B$2 -> 37.99 | C10: =$E$19 -> 10.067114 | D10: =C10/B10*100% -> 0.26499379 | E10: =$E$20 -> 2.002349 | F10: =E10/B10*100% -> 0.052707265 | G10: =$C$36 -> 3.7 | H10: =B10*0.15 -> 5.6985 | I10: 0 | J10: =B10*0.1 -> 3.799 | K10: =B10*0.03 -> 1.1397 | L10: =B10*$C$29 -> 1.8995 | M10: =(B10-J10)/1.19*0.19 -> 5.4590672 | N10: =B10-C10-E10-G10-H10-J10-K10-L10-I10-M10 -> 4.2247697 | O10: =N10/B10 -> 0.11120741 | Q10: =C10/B10*100% -> 0.26499379 | R10: =$E$21 -> 4.4051678 | S10: =R10/B10*100% -> 0.11595598 | T10: =B10-C10-R10-G10-H10-J10-K10-L10-I10-M10 -> 1.8219509 | U10: =T10/B10 -> 0.047958697 | W10: =C10/B10*100% -> 0.26499379 | X10: =$E$22 -> 2.4695638 | Y10: =X10/B10*100% -> 0.065005627 | Z10: =B10-C10-X10-G10-H10-J10-K10-L10-I10-M10 -> 3.7575549 | AA10: =Z10/B10 -> 0.098909053
B11: =B10+$B$2 -> 38.99 | C11: =$E$19 -> 10.067114 | D11: =C11/B11*100% -> 0.25819734 | E11: =$E$20 -> 2.002349 | F11: =E11/B11*100% -> 0.05135545 | G11: =$C$36 -> 3.7 | H11: =B11*0.15 -> 5.8485 | I11: 0 | J11: =B11*0.1 -> 3.899 | K11: =B11*0.03 -> 1.1697 | L11: =B11*$C$29 -> 1.9495 | M11: =(B11-J11)/1.19*0.19 -> 5.6027647 | N11: =B11-C11-E11-G11-H11-J11-K11-L11-I11-M11 -> 4.7510722 | O11: =N11/B11 -> 0.12185361 | Q11: =C11/B11*100% -> 0.25819734 | R11: =$E$21 -> 4.4051678 | S11: =R11/B11*100% -> 0.11298199 | T11: =B11-C11-R11-G11-H11-J11-K11-L11-I11-M11 -> 2.3482534 | U11: =T11/B11 -> 0.060227069 | W11: =C11/B11*100% -> 0.25819734 | X11: =$E$22 -> 2.4695638 | Y11: =X11/B11*100% -> 0.063338388 | Z11: =B11-C11-X11-G11-H11-J11-K11-L11-I11-M11 -> 4.2838574 | AA11: =Z11/B11 -> 0.10987067
B12: =B11+$B$2 -> 39.99 | C12: =$E$19 -> 10.067114 | D12: =C12/B12*100% -> 0.25174079 | E12: =$E$20 -> 2.002349 | F12: =E12/B12*100% -> 0.050071243 | G12: =$C$36 -> 3.7 | H12: =B12*0.15 -> 5.9985 | I12: 0 | J12: =B12*0.1 -> 3.999 | K12: =B12*0.03 -> 1.1997 | L12: =B12*$C$29 -> 1.9995 | M12: =(B12-J12)/1.19*0.19 -> 5.7464622 | N12: =B12-C12-E12-G12-H12-J12-K12-L12-I12-M12 -> 5.2773747 | O12: =N12/B12 -> 0.13196736 | Q12: =C12/B12*100% -> 0.25174079 | R12: =$E$21 -> 4.4051678 | S12: =R12/B12*100% -> 0.11015673 | T12: =B12-C12-R12-G12-H12-J12-K12-L12-I12-M12 -> 2.8745559 | U12: =T12/B12 -> 0.071881869 | W12: =C12/B12*100% -> 0.25174079 | X12: =$E$22 -> 2.4695638 | Y12: =X12/B12*100% -> 0.061754533 | Z12: =B12-C12-X12-G12-H12-J12-K12-L12-I12-M12 -> 4.81016 | AA12: =Z12/B12 -> 0.12028407
B13: =B12+$B$2 -> 40.99 | C13: =$E$19 -> 10.067114 | D13: =C13/B13*100% -> 0.24559927 | E13: =$E$20 -> 2.002349 | F13: =E13/B13*100% -> 0.048849695 | G13: =$C$36 -> 3.7 | H13: =B13*0.15 -> 6.1485 | I13: 0 | J13: =B13*0.1 -> 4.099 | K13: =B13*0.03 -> 1.2297 | L13: =B13*$C$29 -> 2.0495 | M13: =(B13-J13)/1.19*0.19 -> 5.8901597 | N13: =B13-C13-E13-G13-H13-J13-K13-L13-I13-M13 -> 5.8036772 | O13: =N13/B13 -> 0.14158764 | Q13: =C13/B13*100% -> 0.24559927 | R13: =$E$21 -> 4.4051678 | S13: =R13/B13*100% -> 0.10746933 | T13: =B13-C13-R13-G13-H13-J13-K13-L13-I13-M13 -> 3.4008585 | U13: =T13/B13 -> 0.082968003 | W13: =C13/B13*100% -> 0.24559927 | X13: =$E$22 -> 2.4695638 | Y13: =X13/B13*100% -> 0.060247957 | Z13: =B13-C13-X13-G13-H13-J13-K13-L13-I13-M13 -> 5.3364625 | AA13: =Z13/B13 -> 0.13018938
B14: =B13+$B$2 -> 41.99 | C14: =$E$19 -> 10.067114 | D14: =C14/B14*100% -> 0.23975028 | E14: =$E$20 -> 2.002349 | F14: =E14/B14*100% -> 0.04768633 | G14: =$C$36 -> 3.7 | H14: =B14*0.15 -> 6.2985 | I14: 0 | J14: =B14*0.1 -> 4.199 | K14: =B14*0.03 -> 1.2597 | L14: =B14*$C$29 -> 2.0995 | M14: =(B14-J14)/1.19*0.19 -> 6.0338571 | N14: =B14-C14-E14-G14-H14-J14-K14-L14-I14-M14 -> 6.3299798 | O14: =N14/B14 -> 0.1507497 | Q14: =C14/B14*100% -> 0.23975028 | R14: =$E$21 -> 4.4051678 | S14: =R14/B14*100% -> 0.10490993 | T14: =B14-C14-R14-G14-H14-J14-K14-L14-I14-M14 -> 3.927161 | U14: =T14/B14 -> 0.093526101 | W14: =C14/B14*100% -> 0.23975028 | X14: =$E$22 -> 2.4695638 | Y14: =X14/B14*100% -> 0.05881314 | Z14: =B14-C14-X14-G14-H14-J14-K14-L14-I14-M14 -> 5.862765 | AA14: =Z14/B14 -> 0.13962289
B16: 设定售价
B17: 36.99
C18: 人民币 | E18: 欧罗
B19: 采购成本 | C19: 75 | E19: =C19/$C$23 -> 10.067114
B20: 海运成本 | C20: =MAX(C28*C32,C27*C32) -> 14.9175 | E20: =C20/$C$23 -> 2.002349
B21: 空派成本 | C21: =MAX(C27*C33,C28*C33) -> 32.8185 | E21: =C21/$C$23 -> 4.4051678
B22: DHL成本 | C22: =MAX(C34*C27,C34*C28) -> 18.39825 | E22: =C22/$C$23 -> 2.4695638
B23: 汇率 | C23: 7.45
B24: 长 | C24: 25.5 | E24: 厘米
B25: 宽 | C25: 19.5 | E25: 厘米
B26: 高 | C26: 12 | E26: 厘米
B27: 产品实重 | C27: 0.81 | E27: 千克
B28: 海运体积重 | C28: =C24*C25*C26/6000 -> 0.9945 | E28: 千克
B29: 预估退款率 | C29: 0.05
B31: 渠道 | C31: 实时价格
B32: 海运价格 | C32: 15 | E32: 元/KG
B33: 空派价格 | C33: 33 | E33: 元/KG
B34: 卡航价格 | C34: 18.5 | E34: 元/KG
B36: FBA配送费 | C36: 3.7

Sheet 毛利测算表-IT
B2: 1 | C2: 利润核算表（海运） | Q2: 利润核算表（空运） | W2: 利润核算表（快船）
B3: 售价阶梯 | C3: 成本结构 | N3: 利润 | O3: 毛利率 | T3: 利润 | U3: 毛利率 | Z3: 利润 | AA3: 毛利率
C4: 采购成本 | D4: 采购占比 | E4: 头程运费 | F4: 头程占比 | G4: FBA费用 | H4: 交易佣金 | I4: 仓租（淡/旺） | J4: 广告费用 | K4: 汇率折损 | L4: 退款费用 | M4: VAT税 | Q4: 采购占比 | R4: 头程运费 | S4: 头程占比 | W4: 采购占比 | X4: 头程运输 | Y4: 头程占比
B5: =B6-$B$2 -> 35.99 | C5: =$E$19 -> 10.067114 | D5: =C5/B5*100% -> 0.27971976 | E5: =$E$20 -> 2.002349 | F5: =E5/B5*100% -> 0.05563626 | G5: =$C$36 -> 4.92 | H5: =B5*0.15 -> 5.3985 | I5: 0 | J5: =B5*0.1 -> 3.599 | K5: =B5*0.03 -> 1.0797 | L5: =B5*$C$29 -> 1.7995 | M5: =(B5-J5)/1.22*0.22 -> 5.841 | N5: =B5-C5-E5-G5-H5-J5-K5-L5-I5-M5 -> 1.2828369 | O5: =N5/B5 -> 0.03564426 | Q5: =C5/B5*100% -> 0.27971976 | R5: =$E$21 -> 4.9391275 | S5: =R5/B5*100% -> 0.13723611 | T5: =B5-C5-R5-G5-H5-J5-K5-L5-I5-M5 -> -1.6539416 | U5: =T5/B5 -> -0.045955588 | W5: =C5/B5*100% -> 0.27971976 | X5: =$E$22 -> 2.8700336 | Y5: =X5/B5*100% -> 0.079745306 | Z5: =B5-C5-X5-G5-H5-J5-K5-L5-I5-M5 -> 0.41515235 | AA5: =Z5/B5 -> 0.011535214
B6: =B7-$B$2 -> 36.99 | C6: =$E$19 -> 10.067114 | D6: =C6/B6*100% -> 0.27215772 | E6: =$E$20 -> 2.002349 | F6: =E6/B6*100% -> 0.054132171 | G6: =$C$36 -> 4.92 | H6: =B6*0.15 -> 5.5485 | I6: 0 | J6: =B6*0.1 -> 3.699 | K6: =B6*0.03 -> 1.1097 | L6: =B6*$C$29 -> 1.8495 | M6: =(B6-J6)/1.22*0.22 -> 6.0032951 | N6: =B6-C6-E6-G6-H6-J6-K6-L6-I6-M6 -> 1.7905418 | O6: =N6/B6 -> 0.048406105 | Q6: =C6/B6*100% -> 0.27215772 | R6: =$E$21 -> 4.9391275 | S6: =R6/B6*100% -> 0.13352602 | T6: =B6-C6-R6-G6-H6-J6-K6-L6-I6-M6 -> -1.1462367 | U6: =T6/B6 -> -0.030987745 | W6: =C6/B6*100% -> 0.27215772 | X6: =$E$22 -> 2.8700336 | Y6: =X6/B6*100% -> 0.077589445 | Z6: =B6-C6-X6-G6-H6-J6-K6-L6-I6-M6 -> 0.92285727 | AA6: =Z6/B6 -> 0.024948831
B7: =B8-$B$2 -> 37.99 | C7: =$E$19 -> 10.067114 | D7: =C7/B7*100% -> 0.26499379 | E7: =$E$20 -> 2.002349 | F7: =E7/B7*100% -> 0.052707265 | G7: =$C$36 -> 4.92 | H7: =B7*0.15 -> 5.6985 | I7: 0 | J7: =B7*0.1 -> 3.799 | K7: =B7*0.03 -> 1.1397 | L7: =B7*$C$29 -> 1.8995 | M7: =(B7-J7)/1.22*0.22 -> 6.1655902 | N7: =B7-C7-E7-G7-H7-J7-K7-L7-I7-M7 -> 2.2982467 | O7: =N7/B7 -> 0.060496098 | Q7: =C7/B7*100% -> 0.26499379 | R7: =$E$21 -> 4.9391275 | S7: =R7/B7*100% -> 0.13001125 | T7: =B7-C7-R7-G7-H7-J7-K7-L7-I7-M7 -> -0.63853177 | U7: =T7/B7 -> -0.016807891 | W7: =C7/B7*100% -> 0.26499379 | X7: =$E$22 -> 2.8700336 | Y7: =X7/B7*100% -> 0.07554708 | Z7: =B7-C7-X7-G7-H7-J7-K7-L7-I7-M7 -> 1.4305622 | AA7: =Z7/B7 -> 0.037656283
B8: =B9-$B$2 -> 38.99 | C8: =$E$19 -> 10.067114 | D8: =C8/B8*100% -> 0.25819734 | E8: =$E$20 -> 2.002349 | F8: =E8/B8*100% -> 0.05135545 | G8: =$C$36 -> 4.92 | H8: =B8*0.15 -> 5.8485 | I8: 0 | J8: =B8*0.1 -> 3.899 | K8: =B8*0.03 -> 1.1697 | L8: =B8*$C$29 -> 1.9495 | M8: =(B8-J8)/1.22*0.22 -> 6.3278852 | N8: =B8-C8-E8-G8-H8-J8-K8-L8-I8-M8 -> 2.8059517 | O8: =N8/B8 -> 0.071965931 | Q8: =C8/B8*100% -> 0.25819734 | R8: =$E$21 -> 4.9391275 | S8: =R8/B8*100% -> 0.12667678 | T8: =B8-C8-R8-G8-H8-J8-K8-L8-I8-M8 -> -0.13082686 | U8: =T8/B8 -> -0.0033553951 | W8: =C8/B8*100% -> 0.25819734 | X8: =$E$22 -> 2.8700336 | Y8: =X8/B8*100% -> 0.073609478 | Z8: =B8-C8-X8-G8-H8-J8-K8-L8-I8-M8 -> 1.9382671 | AA8: =Z8/B8 -> 0.049711903
B9: =B17 -> 39.99 | C9: =$E$19 -> 10.067114 | D9: =C9/B9*100% -> 0.25174079 | E9: =$E$20 -> 2.002349 | F9: =E9/B9*100% -> 0.050071243 | G9: =$C$36 -> 4.92 | H9: =B9*0.15 -> 5.9985 | I9: 0 | J9: =B9*0.1 -> 3.999 | K9: =B9*0.03 -> 1.1997 | L9: =B9*$C$29 -> 1.9995 | M9: =(B9-J9)/1.22*0.22 -> 6.4901803 | N9: =B9-C9-E9-G9-H9-J9-K9-L9-I9-M9 -> 3.3136566 | O9: =N9/B9 -> 0.08286213 | Q9: =C9/B9*100% -> 0.25174079 | R9: =$E$21 -> 4.9391275 | S9: =R9/B9*100% -> 0.12350907 | T9: =B9-C9-R9-G9-H9-J9-K9-L9-I9-M9 -> 0.37687806 | U9: =T9/B9 -> 0.0094243076 | W9: =C9/B9*100% -> 0.25174079 | X9: =$E$22 -> 2.8700336 | Y9: =X9/B9*100% -> 0.071768781 | Z9: =B9-C9-X9-G9-H9-J9-K9-L9-I9-M9 -> 2.445972 | AA9: =Z9/B9 -> 0.061164592
B10: =B9+$B$2 -> 40.99 | C10: =$E$19 -> 10.067114 | D10: =C10/B10*100% -> 0.24559927 | E10: =$E$20 -> 2.002349 | F10: =E10/B10*100% -> 0.048849695 | G10: =$C$36 -> 4.92 | H10: =B10*0.15 -> 6.1485 | I10: 0 | J10: =B10*0.1 -> 4.099 | K10: =B10*0.03 -> 1.2297 | L10: =B10*$C$29 -> 2.0495 | M10: =(B10-J10)/1.22*0.22 -> 6.6524754 | N10: =B10-C10-E10-G10-H10-J10-K10-L10-I10-M10 -> 3.8213615 | O10: =N10/B10 -> 0.093226677 | Q10: =C10/B10*100% -> 0.24559927 | R10: =$E$21 -> 4.9391275 | S10: =R10/B10*100% -> 0.12049591 | T10: =B10-C10-R10-G10-H10-J10-K10-L10-I10-M10 -> 0.88458298 | U10: =T10/B10 -> 0.021580458 | W10: =C10/B10*100% -> 0.24559927 | X10: =$E$22 -> 2.8700336 | Y10: =X10/B10*100% -> 0.070017896 | Z10: =B10-C10-X10-G10-H10-J10-K10-L10-I10-M10 -> 2.9536769 | AA10: =Z10/B10 -> 0.072058476
B11: =B10+$B$2 -> 41.99 | C11: =$E$19 -> 10.067114 | D11: =C11/B11*100% -> 0.23975028 | E11: =$E$20 -> 2.002349 | F11: =E11/B11*100% -> 0.04768633 | G11: =$C$36 -> 4.92 | H11: =B11*0.15 -> 6.2985 | I11: 0 | J11: =B11*0.1 -> 4.199 | K11: =B11*0.03 -> 1.2597 | L11: =B11*$C$29 -> 2.0995 | M11: =(B11-J11)/1.22*0.22 -> 6.8147705 | N11: =B11-C11-E11-G11-H11-J11-K11-L11-I11-M11 -> 4.3290664 | O11: =N11/B11 -> 0.10309756 | Q11: =C11/B11*100% -> 0.23975028 | R11: =$E$21 -> 4.9391275 | S11: =R11/B11*100% -> 0.11762628 | T11: =B11-C11-R11-G11-H11-J11-K11-L11-I11-M11 -> 1.3922879 | U11: =T11/B11 -> 0.033157607 | W11: =C11/B11*100% -> 0.23975028 | X11: =$E$22 -> 2.8700336 | Y11: =X11/B11*100% -> 0.068350406 | Z11: =B11-C11-X11-G11-H11-J11-K11-L11-I11-M11 -> 3.4613819 | AA11: =Z11/B11 -> 0.082433481
B12: =B11+$B$2 -> 42.99 | C12: =$E$19 -> 10.067114 | D12: =C12/B12*100% -> 0.23417339 | E12: =$E$20 -> 2.002349 | F12: =E12/B12*100% -> 0.046577088 | G12: =$C$36 -> 4.92 | H12: =B12*0.15 -> 6.4485 | I12: 0 | J12: =B12*0.1 -> 4.299 | K12: =B12*0.03 -> 1.2897 | L12: =B12*$C$29 -> 2.1495 | M12: =(B12-J12)/1.22*0.22 -> 6.9770656 | N12: =B12-C12-E12-G12-H12-J12-K12-L12-I12-M12 -> 4.8367713 | O12: =N12/B12 -> 0.11250922 | Q12: =C12/B12*100% -> 0.23417339 | R12: =$E$21 -> 4.9391275 | S12: =R12/B12*100% -> 0.11489015 | T12: =B12-C12-R12-G12-H12-J12-K12-L12-I12-M12 -> 1.8999928 | U12: =T12/B12 -> 0.044196158 | W12: =C12/B12*100% -> 0.23417339 | X12: =$E$22 -> 2.8700336 | Y12: =X12/B12*100% -> 0.066760492 | Z12: =B12-C12-X12-G12-H12-J12-K12-L12-I12-M12 -> 3.9690868 | AA12: =Z12/B12 -> 0.092325815
B13: =B12+$B$2 -> 43.99 | C13: =$E$19 -> 10.067114 | D13: =C13/B13*100% -> 0.22885006 | E13: =$E$20 -> 2.002349 | F13: =E13/B13*100% -> 0.045518277 | G13: =$C$36 -> 4.92 | H13: =B13*0.15 -> 6.5985 | I13: 0 | J13: =B13*0.1 -> 4.399 | K13: =B13*0.03 -> 1.3197 | L13: =B13*$C$29 -> 2.1995 | M13: =(B13-J13)/1.22*0.22 -> 7.1393607 | N13: =B13-C13-E13-G13-H13-J13-K13-L13-I13-M13 -> 5.3444763 | O13: =N13/B13 -> 0.12149298 | Q13: =C13/B13*100% -> 0.22885006 | R13: =$E$21 -> 4.9391275 | S13: =R13/B13*100% -> 0.11227842 | T13: =B13-C13-R13-G13-H13-J13-K13-L13-I13-M13 -> 2.4076977 | U13: =T13/B13 -> 0.054732842 | W13: =C13/B13*100% -> 0.22885006 | X13: =$E$22 -> 2.8700336 | Y13: =X13/B13*100% -> 0.065242863 | Z13: =B13-C13-X13-G13-H13-J13-K13-L13-I13-M13 -> 4.4767917 | AA13: =Z13/B13 -> 0.10176839
B14: =B13+$B$2 -> 44.99 | C14: =$E$19 -> 10.067114 | D14: =C14/B14*100% -> 0.22376337 | E14: =$E$20 -> 2.002349 | F14: =E14/B14*100% -> 0.044506535 | G14: =$C$36 -> 4.92 | H14: =B14*0.15 -> 6.7485 | I14: 0 | J14: =B14*0.1 -> 4.499 | K14: =B14*0.03 -> 1.3497 | L14: =B14*$C$29 -> 2.2495 | M14: =(B14-J14)/1.22*0.22 -> 7.3016557 | N14: =B14-C14-E14-G14-H14-J14-K14-L14-I14-M14 -> 5.8521812 | O14: =N14/B14 -> 0.13007738 | Q14: =C14/B14*100% -> 0.22376337 | R14: =$E$21 -> 4.9391275 | S14: =R14/B14*100% -> 0.10978279 | T14: =B14-C14-R14-G14-H14-J14-K14-L14-I14-M14 -> 2.9154027 | U14: =T14/B14 -> 0.064801126 | W14: =C14/B14*100% -> 0.22376337 | X14: =$E$22 -> 2.8700336 | Y14: =X14/B14*100% -> 0.0637927 | Z14: =B14-C14-X14-G14-H14-J14-K14-L14-I14-M14 -> 4.9844966 | AA14: =Z14/B14 -> 0.11079121
B16: 设定售价
B17: 39.99
C18: 人民币 | E18: 欧罗
B19: 采购成本 | C19: 75 | E19: =C19/$C$23 -> 10.067114
B20: 海运成本 | C20: =MAX(C28*C32,C27*C32) -> 14.9175 | E20: =C20/$C$23 -> 2.002349
B21: 空派成本 | C21: =MAX(C27*C33,C28*C33) -> 36.7965 | E21: =C21/$C$23 -> 4.9391275
B22: DHL成本 | C22: =MAX(C34*C27,C34*C28) -> 21.38175 | E22: =C22/$C$23 -> 2.8700336
B23: 汇率 | C23: 7.45
B24: 长 | C24: 25.5 | E24: 厘米
B25: 宽 | C25: 19.5 | E25: 厘米
B26: 高 | C26: 12 | E26: 厘米
B27: 产品实重 | C27: 0.81 | E27: 千克
B28: 海运体积重 | C28: =C24*C25*C26/6000 -> 0.9945 | E28: 千克
B29: 预估退款率 | C29: 0.05
B31: 渠道 | C31: 实时价格
B32: 海运价格 | C32: 15 | E32: 元/KG
B33: 空派价格 | C33: 37 | E33: 元/KG
B34: 卡航价格 | C34: 21.5 | E34: 元/KG
B36: FBA配送费 | C36: 4.92

Sheet 毛利测算表-ES
B2: 1 | C2: 利润核算表（海运） | Q2: 利润核算表（空运） | W2: 利润核算表（快船）
B3: 售价阶梯 | C3: 成本结构 | N3: 利润 | O3: 毛利率 | T3: 利润 | U3: 毛利率 | Z3: 利润 | AA3: 毛利率
C4: 采购成本 | D4: 采购占比 | E4: 头程运费 | F4: 头程占比 | G4: FBA费用 | H4: 交易佣金 | I4: 仓租（淡/旺） | J4: 广告费用 | K4: 汇率折损 | L4: 退款费用 | M4: VAT税 | Q4: 采购占比 | R4: 头程运费 | S4: 头程占比 | W4: 采购占比 | X4: 头程运输 | Y4: 头程占比
B5: =B6-$B$2 -> 35.99 | C5: =$E$19 -> 10.067114 | D5: =C5/B5*100% -> 0.27971976 | E5: =$E$20 -> 2.002349 | F5: =E5/B5*100% -> 0.05563626 | G5: =$C$36 -> 4.16 | H5: =B5*0.15 -> 5.3985 | I5: 0 | J5: =B5*0.1 -> 3.599 | K5: =B5*0.03 -> 1.0797 | L5: =B5*$C$29 -> 1.7995 | M5: =(B5-J5)/1.21*0.21 -> 5.6215785 | N5: =B5-C5-E5-G5-H5-J5-K5-L5-I5-M5 -> 2.2622584 | O5: =N5/B5 -> 0.062857972 | Q5: =C5/B5*100% -> 0.27971976 | R5: =$E$21 -> 4.9391275 | S5: =R5/B5*100% -> 0.13723611 | T5: =B5-C5-R5-G5-H5-J5-K5-L5-I5-M5 -> -0.67452012 | U5: =T5/B5 -> -0.018741876 | W5: =C5/B5*100% -> 0.27971976 | X5: =$E$22 -> 2.8700336 | Y5: =X5/B5*100% -> 0.079745306 | Z5: =B5-C5-X5-G5-H5-J5-K5-L5-I5-M5 -> 1.3945738 | AA5: =Z5/B5 -> 0.038748926
B6: =B7-$B$2 -> 36.99 | C6: =$E$19 -> 10.067114 | D6: =C6/B6*100% -> 0.27215772 | E6: =$E$20 -> 2.002349 | F6: =E6/B6*100% -> 0.054132171 | G6: =$C$36 -> 4.16 | H6: =B6*0.15 -> 5.5485 | I6: 0 | J6: =B6*0.1 -> 3.699 | K6: =B6*0.03 -> 1.1097 | L6: =B6*$C$29 -> 1.8495 | M6: =(B6-J6)/1.21*0.21 -> 5.7777769 | N6: =B6-C6-E6-G6-H6-J6-K6-L6-I6-M6 -> 2.7760601 | O6: =N6/B6 -> 0.075048934 | Q6: =C6/B6*100% -> 0.27215772 | R6: =$E$21 -> 4.9391275 | S6: =R6/B6*100% -> 0.13352602 | T6: =B6-C6-R6-G6-H6-J6-K6-L6-I6-M6 -> -0.16071847 | U6: =T6/B6 -> -0.0043449167 | W6: =C6/B6*100% -> 0.27215772 | X6: =$E$22 -> 2.8700336 | Y6: =X6/B6*100% -> 0.077589445 | Z6: =B6-C6-X6-G6-H6-J6-K6-L6-I6-M6 -> 1.9083755 | AA6: =Z6/B6 -> 0.05159166
B7: =B8-$B$2 -> 37.99 | C7: =$E$19 -> 10.067114 | D7: =C7/B7*100% -> 0.26499379 | E7: =$E$20 -> 2.002349 | F7: =E7/B7*100% -> 0.052707265 | G7: =$C$36 -> 4.16 | H7: =B7*0.15 -> 5.6985 | I7: 0 | J7: =B7*0.1 -> 3.799 | K7: =B7*0.03 -> 1.1397 | L7: =B7*$C$29 -> 1.8995 | M7: =(B7-J7)/1.21*0.21 -> 5.9339752 | N7: =B7-C7-E7-G7-H7-J7-K7-L7-I7-M7 -> 3.2898617 | O7: =N7/B7 -> 0.086598097 | Q7: =C7/B7*100% -> 0.26499379 | R7: =$E$21 -> 4.9391275 | S7: =R7/B7*100% -> 0.13001125 | T7: =B7-C7-R7-G7-H7-J7-K7-L7-I7-M7 -> 0.35308318 | U7: =T7/B7 -> 0.0092941085 | W7: =C7/B7*100% -> 0.26499379 | X7: =$E$22 -> 2.8700336 | Y7: =X7/B7*100% -> 0.07554708 | Z7: =B7-C7-X7-G7-H7-J7-K7-L7-I7-M7 -> 2.4221771 | AA7: =Z7/B7 -> 0.063758282
B8: =B9-$B$2 -> 38.99 | C8: =$E$19 -> 10.067114 | D8: =C8/B8*100% -> 0.25819734 | E8: =$E$20 -> 2.002349 | F8: =E8/B8*100% -> 0.05135545 | G8: =$C$36 -> 4.16 | H8: =B8*0.15 -> 5.8485 | I8: 0 | J8: =B8*0.1 -> 3.899 | K8: =B8*0.03 -> 1.1697 | L8: =B8*$C$29 -> 1.9495 | M8: =(B8-J8)/1.21*0.21 -> 6.0901736 | N8: =B8-C8-E8-G8-H8-J8-K8-L8-I8-M8 -> 3.8036634 | O8: =N8/B8 -> 0.097554844 | Q8: =C8/B8*100% -> 0.25819734 | R8: =$E$21 -> 4.9391275 | S8: =R8/B8*100% -> 0.12667678 | T8: =B8-C8-R8-G8-H8-J8-K8-L8-I8-M8 -> 0.86688484 | U8: =T8/B8 -> 0.022233517 | W8: =C8/B8*100% -> 0.25819734 | X8: =$E$22 -> 2.8700336 | Y8: =X8/B8*100% -> 0.073609478 | Z8: =B8-C8-X8-G8-H8-J8-K8-L8-I8-M8 -> 2.9359788 | AA8: =Z8/B8 -> 0.075300815
B9: =B17 -> 39.99 | C9: =$E$19 -> 10.067114 | D9: =C9/B9*100% -> 0.25174079 | E9: =$E$20 -> 2.002349 | F9: =E9/B9*100% -> 0.050071243 | G9: =$C$36 -> 4.16 | H9: =B9*0.15 -> 5.9985 | I9: 0 | J9: =B9*0.1 -> 3.999 | K9: =B9*0.03 -> 1.1997 | L9: =B9*$C$29 -> 1.9995 | M9: =(B9-J9)/1.21*0.21 -> 6.2463719 | N9: =B9-C9-E9-G9-H9-J9-K9-L9-I9-M9 -> 4.317465 | O9: =N9/B9 -> 0.10796362 | Q9: =C9/B9*100% -> 0.25174079 | R9: =$E$21 -> 4.9391275 | S9: =R9/B9*100% -> 0.12350907 | T9: =B9-C9-R9-G9-H9-J9-K9-L9-I9-M9 -> 1.3806865 | U9: =T9/B9 -> 0.034525794 | W9: =C9/B9*100% -> 0.25174079 | X9: =$E$22 -> 2.8700336 | Y9: =X9/B9*100% -> 0.071768781 | Z9: =B9-C9-X9-G9-H9-J9-K9-L9-I9-M9 -> 3.4497804 | AA9: =Z9/B9 -> 0.086266078
B10: =B9+$B$2 -> 40.99 | C10: =$E$19 -> 10.067114 | D10: =C10/B10*100% -> 0.24559927 | E10: =$E$20 -> 2.002349 | F10: =E10/B10*100% -> 0.048849695 | G10: =$C$36 -> 4.16 | H10: =B10*0.15 -> 6.1485 | I10: 0 | J10: =B10*0.1 -> 4.099 | K10: =B10*0.03 -> 1.2297 | L10: =B10*$C$29 -> 2.0495 | M10: =(B10-J10)/1.21*0.21 -> 6.4025702 | N10: =B10-C10-E10-G10-H10-J10-K10-L10-I10-M10 -> 4.8312667 | O10: =N10/B10 -> 0.11786452 | Q10: =C10/B10*100% -> 0.24559927 | R10: =$E$21 -> 4.9391275 | S10: =R10/B10*100% -> 0.12049591 | T10: =B10-C10-R10-G10-H10-J10-K10-L10-I10-M10 -> 1.8944881 | U10: =T10/B10 -> 0.046218301 | W10: =C10/B10*100% -> 0.24559927 | X10: =$E$22 -> 2.8700336 | Y10: =X10/B10*100% -> 0.070017896 | Z10: =B10-C10-X10-G10-H10-J10-K10-L10-I10-M10 -> 3.9635821 | AA10: =Z10/B10 -> 0.096696319
B11: =B10+$B$2 -> 41.99 | C11: =$E$19 -> 10.067114 | D11: =C11/B11*100% -> 0.23975028 | E11: =$E$20 -> 2.002349 | F11: =E11/B11*100% -> 0.04768633 | G11: =$C$36 -> 4.16 | H11: =B11*0.15 -> 6.2985 | I11: 0 | J11: =B11*0.1 -> 4.199 | K11: =B11*0.03 -> 1.2597 | L11: =B11*$C$29 -> 2.0995 | M11: =(B11-J11)/1.21*0.21 -> 6.5587686 | N11: =B11-C11-E11-G11-H11-J11-K11-L11-I11-M11 -> 5.3450683 | O11: =N11/B11 -> 0.12729384 | Q11: =C11/B11*100% -> 0.23975028 | R11: =$E$21 -> 4.9391275 | S11: =R11/B11*100% -> 0.11762628 | T11: =B11-C11-R11-G11-H11-J11-K11-L11-I11-M11 -> 2.4082898 | U11: =T11/B11 -> 0.057353889 | W11: =C11/B11*100% -> 0.23975028 | X11: =$E$22 -> 2.8700336 | Y11: =X11/B11*100% -> 0.068350406 | Z11: =B11-C11-X11-G11-H11-J11-K11-L11-I11-M11 -> 4.4773838 | AA11: =Z11/B11 -> 0.10662976
B12: =B11+$B$2 -> 42.99 | C12: =$E$19 -> 10.067114 | D12: =C12/B12*100% -> 0.23417339 | E12: =$E$20 -> 2.002349 | F12: =E12/B12*100% -> 0.046577088 | G12: =$C$36 -> 4.16 | H12: =B12*0.15 -> 6.4485 | I12: 0 | J12: =B12*0.1 -> 4.299 | K12: =B12*0.03 -> 1.2897 | L12: =B12*$C$29 -> 2.1495 | M12: =(B12-J12)/1.21*0.21 -> 6.7149669 | N12: =B12-C12-E12-G12-H12-J12-K12-L12-I12-M12 -> 5.85887 | O12: =N12/B12 -> 0.13628448 | Q12: =C12/B12*100% -> 0.23417339 | R12: =$E$21 -> 4.9391275 | S12: =R12/B12*100% -> 0.11489015 | T12: =B12-C12-R12-G12-H12-J12-K12-L12-I12-M12 -> 2.9220914 | U12: =T12/B12 -> 0.067971422 | W12: =C12/B12*100% -> 0.23417339 | X12: =$E$22 -> 2.8700336 | Y12: =X12/B12*100% -> 0.066760492 | Z12: =B12-C12-X12-G12-H12-J12-K12-L12-I12-M12 -> 4.9911854 | AA12: =Z12/B12 -> 0.11610108
B13: =B12+$B$2 -> 43.99 | C13: =$E$19 -> 10.067114 | D13: =C13/B13*100% -> 0.22885006 | E13: =$E$20 -> 2.002349 | F13: =E13/B13*100% -> 0.045518277 | G13: =$C$36 -> 4.16 | H13: =B13*0.15 -> 6.5985 | I13: 0 | J13: =B13*0.1 -> 4.399 | K13: =B13*0.03 -> 1.3197 | L13: =B13*$C$29 -> 2.1995 | M13: =(B13-J13)/1.21*0.21 -> 6.8711653 | N13: =B13-C13-E13-G13-H13-J13-K13-L13-I13-M13 -> 6.3726716 | O13: =N13/B13 -> 0.14486637 | Q13: =C13/B13*100% -> 0.22885006 | R13: =$E$21 -> 4.9391275 | S13: =R13/B13*100% -> 0.11227842 | T13: =B13-C13-R13-G13-H13-J13-K13-L13-I13-M13 -> 3.4358931 | U13: =T13/B13 -> 0.078106231 | W13: =C13/B13*100% -> 0.22885006 | X13: =$E$22 -> 2.8700336 | Y13: =X13/B13*100% -> 0.065242863 | Z13: =B13-C13-X13-G13-H13-J13-K13-L13-I13-M13 -> 5.5049871 | AA13: =Z13/B13 -> 0.12514178
B14: =B13+$B$2 -> 44.99 | C14: =$E$19 -> 10.067114 | D14: =C14/B14*100% -> 0.22376337 | E14: =$E$20 -> 2.002349 | F14: =E14/B14*100% -> 0.044506535 | G14: =$C$36 -> 4.16 | H14: =B14*0.15 -> 6.7485 | I14: 0 | J14: =B14*0.1 -> 4.499 | K14: =B14*0.03 -> 1.3497 | L14: =B14*$C$29 -> 2.2495 | M14: =(B14-J14)/1.21*0.21 -> 7.0273636 | N14: =B14-C14-E14-G14-H14-J14-K14-L14-I14-M14 -> 6.8864733 | O14: =N14/B14 -> 0.15306675 | Q14: =C14/B14*100% -> 0.22376337 | R14: =$E$21 -> 4.9391275 | S14: =R14/B14*100% -> 0.10978279 | T14: =B14-C14-R14-G14-H14-J14-K14-L14-I14-M14 -> 3.9496948 | U14: =T14/B14 -> 0.087790504 | W14: =C14/B14*100% -> 0.22376337 | X14: =$E$22 -> 2.8700336 | Y14: =X14/B14*100% -> 0.0637927 | Z14: =B14-C14-X14-G14-H14-J14-K14-L14-I14-M14 -> 6.0187887 | AA14: =Z14/B14 -> 0.13378059
B16: 设定售价
B17: 39.99
C18: 人民币 | E18: 欧罗
B19: 采购成本 | C19: 75 | E19: =C19/$C$23 -> 10.067114
B20: 海运成本 | C20: =MAX(C28*C32,C27*C32) -> 14.9175 | E20: =C20/$C$23 -> 2.002349
B21: 空派成本 | C21: =MAX(C27*C33,C28*C33) -> 36.7965 | E21: =C21/$C$23 -> 4.9391275
B22: DHL成本 | C22: =MAX(C34*C27,C34*C28) -> 21.38175 | E22: =C22/$C$23 -> 2.8700336
B23: 汇率 | C23: 7.45
B24: 长 | C24: 25.5 | E24: 厘米
B25: 宽 | C25: 19.5 | E25: 厘米
B26: 高 | C26: 12 | E26: 厘米
B27: 产品实重 | C27: 0.81 | E27: 千克
B28: 海运体积重 | C28: =C24*C25*C26/6000 -> 0.9945 | E28: 千克
B29: 预估退款率 | C29: 0.05
B31: 渠道 | C31: 实时价格
B32: 海运价格 | C32: 15 | E32: 元/KG
B33: 空派价格 | C33: 37 | E33: 元/KG
B34: 卡航价格 | C34: 21.5 | E34: 元/KG
B36: FBA配送费 | C36: 4.16

Sheet 价格策略
B2: 成本(¥) | C2: 头程(¥) | D2: 配送费($） | E2: 汇率
B3: ='毛利测算表-US'!C19 -> 75 | C3: 10.9 | D3: ='毛利测算表-US'!C36 -> 6.37 | E3: ='毛利测算表-US'!C23 -> 7.15
B5: 新品期价格
B6: 正常 | C6: 售价 | D6: 成本 | E6: 头程 | F6: 佣金 （美金）成交价的15% | G6: 配送费 （美金） | H6: 利润 | I6: 毛利润率 | J6: 总订单 | K6: 正常订单 | L6: 总销售额 | M6: 总毛利 | N6: 退款损失 | O6: 退款率
C7: 35.99 | D7: =B3/E3 -> 10.48951 | E7: =C3/E3 -> 1.5244755 | F7: =C7*0.15 -> 5.3985 | G7: =D3 -> 6.37 | H7: =C7-D7-E7-F7-G7 -> 12.207514 | I7: =H7/C7 -> 0.33919183 | J7: 5 | K7: =J7-M10 -> 1.65 | L7: =K7*C7 -> 59.3835 | M7: =H7*K7 -> 20.142398 | N7: =O7*L7 -> 2.969175 | O7: 0.05
B9: 优惠券使用利润 | C9: 售价 | D9: 成本 | E9: 头程 | F9: 优惠券/促销 | G9: 佣金 （美金） | H9: 配送费 （美金） | I9: 优惠券费用 | J9: 毛利 | K9: 毛利率 | L9: 优惠券使用率 | M9: 日均订单 | N9: 总销售额 | O9: 总毛利 | P9: 退款损失 | Q9: 退款率
C10: =C7-C7*F10 -> 28.792 | D10: =D7 -> 10.48951 | E10: =E7 -> 1.5244755 | F10: 0.2 | G10: =C10*0.15 -> 4.3188 | H10: =G7 -> 6.37 | I10: 0.6 | J10: =C10-D10-E10-G10-H10-I10 -> 5.489214 | K10: =J10/C10 -> 0.19065067 | L10: 0.67 | M10: =J7*L10 -> 3.35 | N10: =M10*C10 -> 96.4532 | O10: =M10*J10 -> 18.388867 | P10: =Q10*N10 -> 4.82266 | Q10: =O7 -> 0.05
B12: 周期 | C12: 总销售额 | D12: 总毛利 | E12: 广告费 | F12: 退款费 | G12: 净利 | H12: 净利率 | I12: 广销比
B13: 日 | C13: =L7+N10 -> 155.8367 | D13: =M7+O10 -> 38.531265 | E13: 25 | F13: =P10+N7 -> 7.791835 | G13: =D13-E13-F13 -> 5.7394299 | H13: =G13/C13 -> 0.036829771 | I13: =E13/C13 -> 0.16042434
B14: 周 | C14: =C13*7 -> 1090.8569 | D14: =D13*7 -> 269.71885 | E14: =E13*7 -> 175 | F14: =F13*7 -> 54.542845 | G14: =D14-E14-F14 -> 40.17601 | H14: =G14/C14 -> 0.036829771 | I14: =E14/C14 -> 0.16042434
B15: 旬 | C15: =C13*10 -> 1558.367 | D15: =D13*10 -> 385.31265 | E15: =E13*10 -> 250 | F15: =F13*10 -> 77.91835 | G15: =D15-E15-F15 -> 57.394299 | H15: =G15/C15 -> 0.036829771 | I15: =E15/C15 -> 0.16042434 | L15: 欢迎扫码联系顾问咨询详情
B16: 半月 | C16: =C13*15 -> 2337.5505 | D16: =D13*15 -> 577.96897 | E16: =E13*15 -> 375 | F16: =F13*15 -> 116.87753 | G16: =D16-E16-F16 -> 86.091449 | H16: =G16/C16 -> 0.036829771 | I16: =E16/C16 -> 0.16042434
B17: 月 | C17: =C13*30 -> 4675.101 | D17: =D13*30 -> 1155.9379 | E17: =E13*30 -> 750 | F17: =F13*30 -> 233.75505 | G17: =D17-E17-F17 -> 172.1829 | H17: =G17/C17 -> 0.036829771 | I17: =E17/C17 -> 0.16042434
B19: 成熟期价格
B20: 正常 | C20: 售价 | D20: 成本 | E20: 头程 | F20: 佣金 （美金）成交价的15% | G20: 配送费 （美金） | H20: 利润 | I20: 毛利润率 | J20: 总订单 | K20: 正常订单 | L20: 总销售额 | M20: 总毛利 | N20: 退款损失 | O20: 退款率
C21: 39.99 | D21: =B3/E3 -> 10.48951 | E21: =E7 -> 1.5244755 | F21: =C21*0.15 -> 5.9985 | G21: =D3 -> 6.37 | H21: =C21-D21-E21-F21-G21 -> 15.607514 | I21: =H21/C21 -> 0.39028542 | J21: 20 | K21: =J21-M24 -> 10 | L21: =K21*C21 -> 399.9 | M21: =H21*K21 -> 156.07514 | N21: =O21*L21 -> 19.995 | O21: 0.05
B23: 优惠券使用利润 | C23: 售价 | D23: 成本 | E23: 头程 | F23: 优惠券/促销 | G23: 佣金 （美金） | H23: 配送费 （美金） | I23: 优惠券费用 | J23: 毛利 | K23: 毛利率 | L23: 优惠券使用率 | M23: 日均订单 | N23: 总销售额 | O23: 总毛利 | P23: 退款损失 | Q23: 退款率
C24: =C21-C21*F24 -> 35.991 | D24: =D21 -> 10.48951 | E24: =E21 -> 1.5244755 | F24: 0.1 | G24: =C24*0.15 -> 5.39865 | H24: =G21 -> 6.37 | I24: 0.6 | J24: =C24-D24-E24-G24-H24-I24 -> 11.608364 | K24: =J24/C24 -> 0.32253519 | L24: 0.5 | M24: =J21*L24 -> 10 | N24: =M24*C24 -> 359.91 | O24: =M24*J24 -> 116.08364 | P24: =Q24*N24 -> 17.9955 | Q24: =O21 -> 0.05
B26: 周期 | C26: 总销售额 | D26: 总毛利 | E26: 广告费 | F26: 退款费 | G26: 净利 | H26: 净利率 | I26: 广销比
B27: 日 | C27: =L21+N24 -> 759.81 | D27: =M21+O24 -> 272.15878 | E27: 60 | F27: =P24+N21 -> 37.9905 | G27: =D27-E27-F27 -> 174.16828 | H27: =G27/C27 -> 0.2292261 | I27: =E27/C27 -> 0.07896711
B28: 周 | C28: =C27*7 -> 5318.67 | D28: =D27*7 -> 1905.1115 | E28: =E27*7 -> 420 | F28: =F27*7 -> 265.9335 | G28: =D28-E28-F28 -> 1219.178 | H28: =G28/C28 -> 0.2292261 | I28: =E28/C28 -> 0.07896711
B29: 旬 | C29: =C27*10 -> 7598.1 | D29: =D27*10 -> 2721.5878 | E29: =E27*10 -> 600 | F29: =F27*10 -> 379.905 | G29: =D29-E29-F29 -> 1741.6828 | H29: =G29/C29 -> 0.2292261 | I29: =E29/C29 -> 0.07896711
B30: 半月 | C30: =C27*15 -> 11397.15 | D30: =D27*15 -> 4082.3817 | E30: =E27*15 -> 900 | F30: =F27*15 -> 569.8575 | G30: =D30-E30-F30 -> 2612.5242 | H30: =G30/C30 -> 0.2292261 | I30: =E30/C30 -> 0.07896711
B31: 月 | C31: =C27*30 -> 22794.3 | D31: =D27*30 -> 8164.7634 | E31: =E27*30 -> 1800 | F31: =F27*30 -> 1139.715 | G31: =D31-E31-F31 -> 5225.0484 | H31: =G31/C31 -> 0.2292261 | I31: =E31/C31 -> 0.07896711
