Workbook

Sheet 小类目分析
A4: 大会当天，我一开场就会带老铁们来分析【矫正带】这个小类目，这个类目老铁们好好研究一下，可以用几套方法。点击下面的链接，复制到浏览器打开这个小类目。
A9: https://www.amazon.com/Best-Sellers-Health-Household-Back-Braces/zgbs/hpc/5006367011
A14: 对标竞品链接
A15: https://www.amazon.com/dp/B07ZQPKTVV

Sheet 新品订单数据
A1: https://www.amazon.com/dp/B07ZQPKTVV
D2: 常规数据 | P2: 广告数据 | AF2: 实时更新 | AH2: 操作备注
A3: 日期 | B3: 星期 | C3: FBA 可售 | D3: 价格 | E3: 会员价 | F3: 站内 coupon | G3: 站内 code | H3: 站外 code | I3: 新品 榜单 | J3: 类目 排名 | K3: 总 销量 | L3: 总访 问量 | M3: CVR 总转化 | N3: 评论 数量 | O3: 评分 | P3: 曝光 量 | Q3: 点击 量 | R3: CTR 点击率 | S3: 广告 单 | T3: CVR 转化率 | U3: 平均 CPC | V3: 广告 花费 | W3: CPA | X3: ACOS | Y3: 自然 访问 | Z3: 非广告单 | AA3: 非广告单占比 | AB3: 站外 订单 | AC3: 站内 订单 | AD3: 站内 自然单 | AE3: 最终 盈亏 | AF3: 西柚 质量分 | AG3: 西柚 截图 | AH3: 运营操作/调整 | AI3: 广告操作 | AJ3: 站外投放截图

Sheet 每日实际盈亏
A1: 每日盈亏数据预估
A2: 日期 | B2: 订单类型 | C2: 定价 | D2: code | E2: coupon | F2: 折后价 | G2: FBA 配送费 | H2: 亚马逊 佣金 | I2: 账号 回款 | J2: 仓储费 | K2: coupon 费用 | L2: 产品 成本 | M2: 物流费 海运 | N2: 退货成本(公式后面加的是单套产品的移除费） | O2: 退货率 | P2: 每单平摊 退货成本 | Q2: 每单 毛利 | R2: 毛利率 | S2: 订单 数量 | T2: 每日 订单 亏损 | U2: 每日 订单 亏损 | V2: 每日 站外 费用 | W2: 每日 广告 费用 | X2: 每日 总盈亏 | Y2: 每日 出单 | Z2: 备注
A3: 45231 | B3: 原价订单 | C3: 12.99 | D3: 0 | E3: 0 | F3: =SUM(C3*(1-D3-E3)) -> 12.99 | G3: 4.38 | H3: =SUM(F3*15%) -> 1.9485 | I3: =SUM(F3-G3-H3) -> 6.6615 | J3: 0.01 | K3: 0 | L3: 2.5 | M3: 0.5 | N3: =SUM(20%*15%*F3+G3+J3+50%*L3+M3+1.46) -> 7.9897 | O3: 0.15 | P3: =SUM(N3*O3/(1-O3)) -> 1.4099471 | Q3: =SUM(I3-J3-K3-L3-M3-P3) -> 2.2415529 | R3: =SUM(Q3/C3) -> 0.17255989 | S3: 1 | T3: =SUM(Q3*S3) -> 2.2415529 | U3: =T3:T4 -> 2.2415529 | V3: 0 | W3: 0 | X3: =U3+V3+W3 -> 2.2415529 | Y3: =SUM(S3:S4) -> 1
B4: coupon订单 | C4: 12.99 | D4: 0 | E4: 0.1 | F4: =SUM(C4*(1-D4-E4)) -> 11.691 | G4: 4.38 | H4: =SUM(F4*15%) -> 1.75365 | I4: =SUM(F4-G4-H4) -> 5.55735 | J4: 0.01 | K4: 0.6 | L4: 2.5 | M4: 0.5 | N4: =SUM(20%*15%*F4+G4+J4+50%*L4+M4+1.46) -> 7.95073 | O4: 0.15 | P4: =SUM(N4*O4/(1-O4)) -> 1.40307 | Q4: =SUM(I4-J4-K4-L4-M4-P4) -> 0.54428 | R4: =SUM(Q4/C4) -> 0.041899923 | S4: 0 | T4: =SUM(Q4*S4) -> 0
A5: 45232 | B5: 原价订单 | C5: 12.99 | D5: 0 | E5: 0 | F5: =SUM(C5*(1-D5-E5)) -> 12.99 | G5: 4.38 | H5: =SUM(F5*15%) -> 1.9485 | I5: =SUM(F5-G5-H5) -> 6.6615 | J5: 0.01 | K5: 0 | L5: 2.5 | M5: 0.5 | N5: =SUM(20%*15%*F5+G5+J5+50%*L5+M5+1.46) -> 7.9897 | O5: 0.15 | P5: =SUM(N5*O5/(1-O5)) -> 1.4099471 | Q5: =SUM(I5-J5-K5-L5-M5-P5) -> 2.2415529 | R5: =SUM(Q5/C5) -> 0.17255989 | S5: 1 | T5: =SUM(Q5*S5) -> 2.2415529 | U5: =T5:T6 -> 2.2415529 | V5: 0 | W5: 0 | X5: =U5+V5+W5 -> 2.2415529 | Y5: =SUM(S5:S6) -> 1
B6: coupon订单 | C6: 12.99 | D6: 0 | E6: 0.1 | F6: =SUM(C6*(1-D6-E6)) -> 11.691 | G6: 4.38 | H6: =SUM(F6*15%) -> 1.75365 | I6: =SUM(F6-G6-H6) -> 5.55735 | J6: 0.01 | K6: 0.6 | L6: 2.5 | M6: 0.5 | N6: =SUM(20%*15%*F6+G6+J6+50%*L6+M6+1.46) -> 7.95073 | O6: 0.15 | P6: =SUM(N6*O6/(1-O6)) -> 1.40307 | Q6: =SUM(I6-J6-K6-L6-M6-P6) -> 0.54428 | R6: =SUM(Q6/C6) -> 0.041899923 | S6: 0 | T6: =SUM(Q6*S6) -> 0
A7: 45233 | B7: 原价订单 | C7: 12.99 | D7: 0 | E7: 0 | F7: =SUM(C7*(1-D7-E7)) -> 12.99 | G7: 4.38 | H7: =SUM(F7*15%) -> 1.9485 | I7: =SUM(F7-G7-H7) -> 6.6615 | J7: 0.01 | K7: 0 | L7: 2.5 | M7: 0.5 | N7: =SUM(20%*15%*F7+G7+J7+50%*L7+M7+1.46) -> 7.9897 | O7: 0.15 | P7: =SUM(N7*O7/(1-O7)) -> 1.4099471 | Q7: =SUM(I7-J7-K7-L7-M7-P7) -> 2.2415529 | R7: =SUM(Q7/C7) -> 0.17255989 | S7: 1 | T7: =SUM(Q7*S7) -> 2.2415529 | U7: =T7:T8 -> 2.2415529 | V7: 0 | W7: 0 | X7: =U7+V7+W7 -> 2.2415529 | Y7: =SUM(S7:S8) -> 1
B8: coupon订单 | C8: 12.99 | D8: 0 | E8: 0.1 | F8: =SUM(C8*(1-D8-E8)) -> 11.691 | G8: 4.38 | H8: =SUM(F8*15%) -> 1.75365 | I8: =SUM(F8-G8-H8) -> 5.55735 | J8: 0.01 | K8: 0.6 | L8: 2.5 | M8: 0.5 | N8: =SUM(20%*15%*F8+G8+J8+50%*L8+M8+1.46) -> 7.95073 | O8: 0.15 | P8: =SUM(N8*O8/(1-O8)) -> 1.40307 | Q8: =SUM(I8-J8-K8-L8-M8-P8) -> 0.54428 | R8: =SUM(Q8/C8) -> 0.041899923 | S8: 0 | T8: =SUM(Q8*S8) -> 0

Sheet 阶段实际盈亏
A1: 时间 | B1: 实际 | C1: 价格 | D1: 站内 coupon | E1: 站内 code | F1: 站外 折扣 | G1: 站外 订单 | H1: 站内 自然单 | I1: 站内 广告单 | J1: 阶段 销售 订单 | K1: 时间 /天 | L1: 阶段广告费 （出1单广告单预估） | M1: 阶段站外费用 （5美金/单） | N1: 阶段订单 盈亏 | O1: 阶段亏损 /美金 | P1: 六阶段 总亏损 | R1: 阶段日均 订单 | S1: 阶段日均 广告订单 | T1: 阶段日均 自然订单 | U1: 新品 排行榜 | V1: 小类目 排名
A2: 9月7-9月12 | B2: 第一阶段 | C2: 99.99 | D2: 0.05 | E2: 0.5 | F2: 0.68 | G2: =SUM(每日实际盈亏!S3:S6) -> 2 | H2: 0 | I2: 0 | J2: =SUM(G2:I2) -> 2 | K2: 6 | L2: 0 | M2: =SUM(每日实际盈亏!V3:V6) -> 0 | N2: =SUM(每日实际盈亏!U3:U6) -> 4.4831059 | O2: =SUM(L2:N2) -> 4.4831059
A3: 9月13-9月21 | B3: 第二阶段 | C3: 79.99 | D3: 0.3 | E3: 0.2 | F3: 0.3 | G3: 81 | H3: 14 | I3: 0 | J3: =SUM(G3:I3) -> 95 | K3: 9 | L3: =SUM(每日实际盈亏!#REF!) -> #REF! | M3: =SUM(每日实际盈亏!#REF!) -> #REF! | N3: =SUM(每日实际盈亏!#REF!) -> #REF! | O3: =SUM(L3:N3) -> #REF!
A4: 9月22-10月1 | B4: 第三阶段 | C4: 69.99 | D4: 0.3 | E4: 0.2 | F4: 0.25 | G4: 45 | H4: 60 | I4: 3 | J4: =SUM(G4:I4) -> 108 | K4: 10 | L4: =SUM(每日实际盈亏!#REF!) -> #REF! | M4: =SUM(每日实际盈亏!#REF!) -> #REF! | N4: =SUM(每日实际盈亏!#REF!) -> #REF! | O4: =SUM(L4:N4) -> #REF!
A5: 10月2-10月11 | B5: 第四阶段 | C5: 69.99 | D5: 0.3 | E5: 0 | F5: 0.25
A6: 10月12-10月21 | B6: 第五阶段 | C6: 69.99 | D6: 0.3 | E6: 0 | F6: 0.25
A7: 10月22-10月31 | B7: 第六阶段 | C7: 69.99 | D7: 0.3 | E7: 0 | F7: 0
A9: 11月1-11月30 | B9: 十一月份 | C9: 69.99 | D9: 0.2 | E9: 0 | F9: 0
A10: 12月1-12月31 | B10: 十二月份 | C10: 69.99 | D10: 0.2 | E10: 0 | F10: 0
A11: 1月1-1月31 | B11: 一月份 | C11: 69.99 | D11: 0.2 | E11: 0 | F11: 0

Sheet 阶段盈亏模拟
A1: 时间 | B1: 模拟 | C1: 价格 | D1: 站内 coupon | E1: 站内 code | F1: 站外 折扣 | G1: 站外 订单 | H1: 站内 自然单 | I1: 站内 广告单 | J1: 阶段 销售 订单 | K1: 时间 /天 | L1: CPA | M1: 阶段 广告费 | N1: 阶段 站外费用 2美金/单 | O1: 阶段订单 盈亏 | P1: 阶段亏损 /美金 | Q1: 六阶段 总亏损 | R1: 评论数量 | S1: 阶段 日均 订单 | T1: 阶段 日均 广告单 | U1: 阶段 日均 自然单 | V1: 日均 广告费 | W1: 新品 排行榜 | X1: 小类目 排名
A2: 找真人模特拍摄做图片A+视频要-1000美金，做三条种子链接评论90条，-200*3=-600，一条vine成本8.5美金左右，90条就是-765美金，前期成本1000+600+765 | Q2: =-1000-600-765 -> -2365
A3: 11/1-11/10 | B3: 第一阶段 | C3: 12.99 | D3: 0 | E3: 0 | F3: 0 | G3: 0 | H3: 5 | I3: 25 | J3: =G3+H3+I3 -> 30 | K3: 10 | L3: =CPC模拟!W4 -> 25 | M3: =SUM(I3*-L3) -> -625 | N3: =SUM(G3*-2) -> 0 | O3: =盈亏模拟!V3 -> 67.246588 | P3: =SUM(M3:O3) -> -557.75341 | Q3: =SUM(P3:P8) -> -4562.5586 | S3: =SUM(J3/K3) -> 3 | T3: =SUM(I3/K3) -> 2.5 | U3: =SUM(H3/K3) -> 0.5 | V3: =SUM(M3/K3) -> -62.5 | W3: 稳定在前50名 | X3: 稳定在前200名
A4: 11/11-11/20 | B4: 第二阶段 | C4: 12.99 | D4: 0 | E4: 0 | F4: 0 | G4: 0 | H4: 10 | I4: 40 | J4: =G4+H4+I4 -> 50 | K4: 10 | L4: =CPC模拟!W5 -> 23.076923 | M4: =SUM(I4*-L4) -> -923.07692 | N4: =SUM(G4*-2) -> 0 | O4: =盈亏模拟!V6 -> 112.07765 | P4: =SUM(M4:O4) -> -810.99928 | S4: =SUM(J4/K4) -> 5 | T4: =SUM(I4/K4) -> 4 | U4: =SUM(H4/K4) -> 1 | V4: =SUM(M4/K4) -> -92.307692 | W4: 稳定在前40名 | X4: 稳定在前150名
A5: 11/21-11/30 | B5: 第三阶段 | C5: 13.99 | D5: 0 | E5: 0 | F5: 0 | G5: 0 | H5: 30 | I5: 70 | J5: =G5+H5+I5 -> 100 | K5: 10 | L5: =CPC模拟!W6 -> 18.571429 | M5: =SUM(I5*-L5) -> -1300 | N5: =SUM(G5*-2) -> 0 | O5: =盈亏模拟!V9 -> 308.62588 | P5: =SUM(M5:O5) -> -991.37412 | S5: =SUM(J5/K5) -> 10 | T5: =SUM(I5/K5) -> 7 | U5: =SUM(H5/K5) -> 3 | V5: =SUM(M5/K5) -> -130 | W5: 稳定在前30名 | X5: 稳定在前100名
A6: 12/1-12/10 | B6: 第四阶段 | C6: 13.99 | D6: 0 | E6: 0 | F6: 0 | G6: 0 | H6: 60 | I6: 90 | J6: =G6+H6+I6 -> 150 | K6: 10 | L6: =CPC模拟!W7 -> 17.333333 | M6: =SUM(I6*-L6) -> -1560 | N6: =SUM(G6*-2) -> 0 | O6: =盈亏模拟!V12 -> 462.93882 | P6: =SUM(M6:O6) -> -1097.0612 | S6: =SUM(J6/K6) -> 15 | T6: =SUM(I6/K6) -> 9 | U6: =SUM(H6/K6) -> 6 | V6: =SUM(M6/K6) -> -156 | W6: 稳定在前20名 | X6: 稳定在前80名
A7: 12/11-12/20 | B7: 第五阶段 | C7: 14.99 | D7: 0 | E7: 0 | F7: 0 | G7: 0 | H7: 90 | I7: 110 | J7: =G7+H7+I7 -> 200 | K7: 10 | L7: =CPC模拟!W8 -> 13.75 | M7: =SUM(I7*-L7) -> -1512.5 | N7: =SUM(G7*-2) -> 0 | O7: =盈亏模拟!V15 -> 786.19294 | P7: =SUM(M7:O7) -> -726.30706 | S7: =SUM(J7/K7) -> 20 | T7: =SUM(I7/K7) -> 11 | U7: =SUM(H7/K7) -> 9 | V7: =SUM(M7/K7) -> -151.25 | W7: 稳定在前10名 | X7: 稳定在前60名
A8: 12/21-12/30 | B8: 第六阶段 | C8: 15.99 | D8: 0 | E8: 0 | F8: 0 | G8: 0 | H8: 160 | I8: 140 | J8: =G8+H8+I8 -> 300 | K8: 10 | L8: =CPC模拟!W9 -> 12.941176 | M8: =SUM(I8*-L8) -> -1811.7647 | N8: =SUM(G8*-2) -> 0 | O8: =盈亏模拟!V18 -> 1432.7012 | P8: =SUM(M8:O8) -> -379.06353 | S8: =SUM(J8/K8) -> 30 | T8: =SUM(I8/K8) -> 14 | U8: =SUM(H8/K8) -> 16 | V8: =SUM(M8/K8) -> -181.17647 | W8: 稳定在前10名 | X8: 稳定在前50名
A9: 一月份 | B9: 十一月份 | C9: 16.99 | D9: 0.1 | E9: 0 | F9: 0 | G9: 0 | H9: 750 | I9: 450 | J9: =G9+H9+I9 -> 1200 | K9: 30 | L9: =CPC模拟!W10 -> 11.111111 | M9: =SUM(I9*-L9) -> -5000 | N9: =SUM(G9*-2) -> 0 | O9: =盈亏模拟!V21 -> 5523.3586 | P9: =SUM(M9:O9) -> 523.35859 | Q9: =P9 -> 523.35859 | S9: =SUM(J9/K9) -> 40 | T9: =SUM(I9/K9) -> 15 | U9: =SUM(H9/K9) -> 25 | V9: =SUM(M9/K9) -> -166.66667 | W9: 稳定在前10名 | X9: 前40名
A10: 二月份 | B10: 十二月份 | C10: 17.99 | D10: 0.1 | E10: 0 | F10: 0 | G10: 0 | H10: 1000 | I10: 500 | J10: =G10+H10+I10 -> 1500 | K10: 30 | L10: =CPC模拟!W11 -> 10.526316 | M10: =SUM(I10*-L10) -> -5263.1579 | N10: =SUM(G10*-2) -> 0 | O10: =盈亏模拟!V24 -> 8107.9041 | P10: =SUM(M10:O10) -> 2844.7462 | Q10: =P10 -> 2844.7462 | S10: =SUM(J10/K10) -> 50 | T10: =SUM(I10/K10) -> 16.666667 | U10: =SUM(H10/K10) -> 33.333333 | V10: =SUM(M10/K10) -> -175.4386 | X10: 前30名
A11: 三月份 | B11: 一月份 | C11: 18.99 | D11: 0.1 | E11: 0 | F11: 0 | G11: 0 | H11: 1200 | I11: 600 | J11: =G11+H11+I11 -> 1800 | K11: 30 | L11: =CPC模拟!W12 -> 10 | M11: =SUM(I11*-L11) -> -6000 | N11: =SUM(G11*-2) -> 0 | O11: =盈亏模拟!V27 -> 11173.932 | P11: =SUM(M11:O11) -> 5173.932 | Q11: =P11 -> 5173.932 | S11: =SUM(J11/K11) -> 60 | T11: =SUM(I11/K11) -> 20 | U11: =SUM(H11/K11) -> 40 | V11: =SUM(M11/K11) -> -200 | X11: 前20名
A12: 未来 | B12: 未来 | C12: 19.99 | D12: 0.1 | E12: 0 | F12: 0 | G12: 0 | H12: 1600 | I12: 800 | J12: =G12+H12+I12 -> 2400 | K12: 30 | L12: =CPC模拟!W13 -> 6.6666667 | M12: =SUM(I12*-L12) -> -5333.3333 | N12: =SUM(G12*-2) -> 0 | O12: =盈亏模拟!V30 -> 16824.505 | P12: =SUM(M12:O12) -> 11491.172 | Q12: =P12 -> 11491.172 | S12: =SUM(J12/K12) -> 80 | T12: =SUM(I12/K12) -> 26.666667 | U12: =SUM(H12/K12) -> 53.333333 | V12: =SUM(M12/K12) -> -177.77778 | X12: 前10名
A17: 时间 | B17: 实际 | C17: 价格 | D17: 站内 coupon | E17: 站内 code | F17: 站外 折扣 | G17: 站外 订单 | H17: 站内 自然单 | I17: 站内 广告单 | J17: 阶段 销售 订单 | K17: 时间 /天 | L17: CPA | M17: 实际 广告费 | N17: 实际 站外费用 | O17: 阶段订单 盈亏 | P17: 阶段亏损 /美金 | Q17: 六阶段 总亏损 | R17: 评论数量 | S17: 阶段 日均 订单 | T17: 阶段 日均 广告单 | U17: 阶段 日均 自然单 | V17: 日均 广告费 | W17: 新品 排行榜 | X17: 小类目 排名
A19: 11/1-11/10 | B19: 第一阶段
A20: 11/11-11/20 | B20: 第二阶段
A21: 11/21-11/30 | B21: 第三阶段
A22: 12/1-12/10 | B22: 第四阶段
A23: 12/11-12/20 | B23: 第五阶段
A24: 12/21-12/30 | B24: 第六阶段
A25: 一月份 | B25: 十一月份
A26: 二月份 | B26: 十二月份
A27: 三月份 | B27: 一月份
A28: 未来 | B28: 未来

Sheet 盈亏模拟
A1: 每日盈亏数据预估
A2: 日期 | B2: 站外/ 站内 | C2: 订单类型 | D2: 定价 | E2: code | F2: coupon | G2: 折后价 | H2: FBA 配送费 | I2: 亚马逊 佣金 | J2: 账号 回款 | K2: 仓储费 | L2: coupon 费用 | M2: 产品 成本 | N2: 物流费 海运 | O2: 退货成本(公式后面加的是单套产品的移除费） | P2: 退货率 | Q2: 每单平摊 退货成本 | R2: 每单 毛利 | S2: 毛利率 | T2: 订单 数量 | U2: 阶段 订单 亏损 | V2: 阶段 订单 总盈亏 | W2: 阶段 出单
A3: 11/1-11/10 | B3: 站内订单 | C3: 原价订单 | D3: 12.99 | E3: 0 | F3: 0 | G3: =SUM(D3*(1-E3-F3)) -> 12.99 | H3: 4.38 | I3: =SUM(G3*15%) -> 1.9485 | J3: =SUM(G3-H3-I3) -> 6.6615 | K3: 0.01 | L3: 0 | M3: 2.5 | N3: 0.5 | O3: =SUM(20%*15%*G3+H3+K3+50%*M3+N3+1.46) -> 7.9897 | P3: 0.15 | Q3: =SUM(O3*P3/(1-P3)) -> 1.4099471 | R3: =SUM(J3-K3-L3-M3-N3-Q3) -> 2.2415529 | S3: =SUM(R3/D3) -> 0.17255989 | T3: 30 | U3: =SUM(R3*T3) -> 67.246588 | V3: =SUM(U3:U4) -> 67.246588 | W3: =SUM(T3:T4) -> 30
A4: 第一阶段 | B4: 站内订单 | C4: coupon订单 | D4: 12.99 | E4: 0 | F4: 0 | G4: =SUM(D4*(1-E4-F4)) -> 12.99 | H4: 4.38 | I4: =SUM(G4*15%) -> 1.9485 | J4: =SUM(G4-H4-I4) -> 6.6615 | K4: 0.01 | L4: 0.6 | M4: 2.5 | N4: 0.5 | O4: =SUM(20%*15%*G4+H4+K4+50%*M4+N4+1.46) -> 7.9897 | P4: 0.15 | Q4: =SUM(O4*P4/(1-P4)) -> 1.4099471 | R4: =SUM(J4-K4-L4-M4-N4-Q4) -> 1.6415529 | S4: =SUM(R4/D4) -> 0.12637051 | T4: 0 | U4: =SUM(R4*T4) -> 0
A6: 11/11-11/20 | B6: 站内订单 | C6: 原价订单 | D6: 12.99 | E6: 0 | F6: 0 | G6: =SUM(D6*(1-E6-F6)) -> 12.99 | H6: 4.38 | I6: =SUM(G6*15%) -> 1.9485 | J6: =SUM(G6-H6-I6) -> 6.6615 | K6: 0.01 | L6: 0 | M6: 2.5 | N6: 0.5 | O6: =SUM(20%*15%*G6+H6+K6+50%*M6+N6+1.46) -> 7.9897 | P6: 0.15 | Q6: =SUM(O6*P6/(1-P6)) -> 1.4099471 | R6: =SUM(J6-K6-L6-M6-N6-Q6) -> 2.2415529 | S6: =SUM(R6/D6) -> 0.17255989 | T6: 50 | U6: =SUM(R6*T6) -> 112.07765 | V6: =SUM(U6:U7) -> 112.07765 | W6: =SUM(T6:T7) -> 50
A7: 第二阶段 | B7: 站内订单 | C7: coupon订单 | D7: 12.99 | E7: 0 | F7: 0 | G7: =SUM(D7*(1-E7-F7)) -> 12.99 | H7: 4.38 | I7: =SUM(G7*15%) -> 1.9485 | J7: =SUM(G7-H7-I7) -> 6.6615 | K7: 0.01 | L7: 0.6 | M7: 2.5 | N7: 0.5 | O7: =SUM(20%*15%*G7+H7+K7+50%*M7+N7+1.46) -> 7.9897 | P7: 0.15 | Q7: =SUM(O7*P7/(1-P7)) -> 1.4099471 | R7: =SUM(J7-K7-L7-M7-N7-Q7) -> 1.6415529 | S7: =SUM(R7/D7) -> 0.12637051 | T7: 0 | U7: =SUM(R7*T7) -> 0
A9: 11/21-11/30 | B9: 站内订单 | C9: 原价订单 | D9: 13.99 | E9: 0 | F9: 0 | G9: =SUM(D9*(1-E9-F9)) -> 13.99 | H9: 4.38 | I9: =SUM(G9*15%) -> 2.0985 | J9: =SUM(G9-H9-I9) -> 7.5115 | K9: 0.01 | L9: 0 | M9: 2.5 | N9: 0.5 | O9: =SUM(20%*15%*G9+H9+K9+50%*M9+N9+1.46) -> 8.0197 | P9: 0.15 | Q9: =SUM(O9*P9/(1-P9)) -> 1.4152412 | R9: =SUM(J9-K9-L9-M9-N9-Q9) -> 3.0862588 | S9: =SUM(R9/D9) -> 0.22060463 | T9: 100 | U9: =SUM(R9*T9) -> 308.62588 | V9: =SUM(U9:U10) -> 308.62588 | W9: =SUM(T9:T10) -> 100
A10: 第三阶段 | B10: 站内订单 | C10: coupon订单 | D10: 13.99 | E10: 0 | F10: 0 | G10: =SUM(D10*(1-E10-F10)) -> 13.99 | H10: 4.38 | I10: =SUM(G10*15%) -> 2.0985 | J10: =SUM(G10-H10-I10) -> 7.5115 | K10: 0.01 | L10: 0.6 | M10: 2.5 | N10: 0.5 | O10: =SUM(20%*15%*G10+H10+K10+50%*M10+N10+1.46) -> 8.0197 | P10: 0.15 | Q10: =SUM(O10*P10/(1-P10)) -> 1.4152412 | R10: =SUM(J10-K10-L10-M10-N10-Q10) -> 2.4862588 | S10: =SUM(R10/D10) -> 0.17771686 | T10: 0 | U10: =SUM(R10*T10) -> 0
A12: 12/1-12/10 | B12: 站内订单 | C12: 原价订单 | D12: 13.99 | E12: 0 | F12: 0 | G12: =SUM(D12*(1-E12-F12)) -> 13.99 | H12: 4.38 | I12: =SUM(G12*15%) -> 2.0985 | J12: =SUM(G12-H12-I12) -> 7.5115 | K12: 0.01 | L12: 0 | M12: 2.5 | N12: 0.5 | O12: =SUM(20%*15%*G12+H12+K12+50%*M12+N12+1.46) -> 8.0197 | P12: 0.15 | Q12: =SUM(O12*P12/(1-P12)) -> 1.4152412 | R12: =SUM(J12-K12-L12-M12-N12-Q12) -> 3.0862588 | S12: =SUM(R12/D12) -> 0.22060463 | T12: 150 | U12: =SUM(R12*T12) -> 462.93882 | V12: =SUM(U12:U13) -> 462.93882 | W12: =SUM(T12:T13) -> 150
A13: 第四阶段 | B13: 站内订单 | C13: coupon订单 | D13: 13.99 | E13: 0 | F13: 0 | G13: =SUM(D13*(1-E13-F13)) -> 13.99 | H13: 4.38 | I13: =SUM(G13*15%) -> 2.0985 | J13: =SUM(G13-H13-I13) -> 7.5115 | K13: 0.01 | L13: 0.6 | M13: 2.5 | N13: 0.5 | O13: =SUM(20%*15%*G13+H13+K13+50%*M13+N13+1.46) -> 8.0197 | P13: 0.15 | Q13: =SUM(O13*P13/(1-P13)) -> 1.4152412 | R13: =SUM(J13-K13-L13-M13-N13-Q13) -> 2.4862588 | S13: =SUM(R13/D13) -> 0.17771686 | T13: 0 | U13: =SUM(R13*T13) -> 0
A15: 12/11-12/20 | B15: 站内订单 | C15: 原价订单 | D15: 14.99 | E15: 0 | F15: 0 | G15: =SUM(D15*(1-E15-F15)) -> 14.99 | H15: 4.38 | I15: =SUM(G15*15%) -> 2.2485 | J15: =SUM(G15-H15-I15) -> 8.3615 | K15: 0.01 | L15: 0 | M15: 2.5 | N15: 0.5 | O15: =SUM(20%*15%*G15+H15+K15+50%*M15+N15+1.46) -> 8.0497 | P15: 0.15 | Q15: =SUM(O15*P15/(1-P15)) -> 1.4205353 | R15: =SUM(J15-K15-L15-M15-N15-Q15) -> 3.9309647 | S15: =SUM(R15/D15) -> 0.26223914 | T15: 200 | U15: =SUM(R15*T15) -> 786.19294 | V15: =SUM(U15:U16) -> 786.19294 | W15: =SUM(T15:T16) -> 200
A16: 第五阶段 | B16: 站内订单 | C16: coupon订单 | D16: 14.99 | E16: 0 | F16: 0 | G16: =SUM(D16*(1-E16-F16)) -> 14.99 | H16: 4.38 | I16: =SUM(G16*15%) -> 2.2485 | J16: =SUM(G16-H16-I16) -> 8.3615 | K16: 0.01 | L16: 0.6 | M16: 2.5 | N16: 0.5 | O16: =SUM(20%*15%*G16+H16+K16+50%*M16+N16+1.46) -> 8.0497 | P16: 0.15 | Q16: =SUM(O16*P16/(1-P16)) -> 1.4205353 | R16: =SUM(J16-K16-L16-M16-N16-Q16) -> 3.3309647 | S16: =SUM(R16/D16) -> 0.22221246 | T16: 0 | U16: =SUM(R16*T16) -> 0
A18: 12/21-12/30 | B18: 站内订单 | C18: 原价订单 | D18: 15.99 | E18: 0 | F18: 0 | G18: =SUM(D18*(1-E18-F18)) -> 15.99 | H18: 4.38 | I18: =SUM(G18*15%) -> 2.3985 | J18: =SUM(G18-H18-I18) -> 9.2115 | K18: 0.01 | L18: 0 | M18: 2.5 | N18: 0.5 | O18: =SUM(20%*15%*G18+H18+K18+50%*M18+N18+1.46) -> 8.0797 | P18: 0.15 | Q18: =SUM(O18*P18/(1-P18)) -> 1.4258294 | R18: =SUM(J18-K18-L18-M18-N18-Q18) -> 4.7756706 | S18: =SUM(R18/D18) -> 0.29866608 | T18: 300 | U18: =SUM(R18*T18) -> 1432.7012 | V18: =SUM(U18:U19) -> 1432.7012 | W18: =SUM(T18:T19) -> 300
A19: 第六阶段 | B19: 站内订单 | C19: coupon订单 | D19: 15.99 | E19: 0 | F19: 0 | G19: =SUM(D19*(1-E19-F19)) -> 15.99 | H19: 4.38 | I19: =SUM(G19*15%) -> 2.3985 | J19: =SUM(G19-H19-I19) -> 9.2115 | K19: 0.01 | L19: 0.6 | M19: 2.5 | N19: 0.5 | O19: =SUM(20%*15%*G19+H19+K19+50%*M19+N19+1.46) -> 8.0797 | P19: 0.15 | Q19: =SUM(O19*P19/(1-P19)) -> 1.4258294 | R19: =SUM(J19-K19-L19-M19-N19-Q19) -> 4.1756706 | S19: =SUM(R19/D19) -> 0.26114263 | T19: 0 | U19: =SUM(R19*T19) -> 0
A21: 一月份 | B21: 站内订单 | C21: 原价订单 | D21: 16.99 | E21: 0 | F21: 0 | G21: =SUM(D21*(1-E21-F21)) -> 16.99 | H21: 4.38 | I21: =SUM(G21*15%) -> 2.5485 | J21: =SUM(G21-H21-I21) -> 10.0615 | K21: 0.01 | L21: 0 | M21: 2.5 | N21: 0.5 | O21: =SUM(20%*15%*G21+H21+K21+50%*M21+N21+1.46) -> 8.1097 | P21: 0.15 | Q21: =SUM(O21*P21/(1-P21)) -> 1.4311235 | R21: =SUM(J21-K21-L21-M21-N21-Q21) -> 5.6203765 | S21: =SUM(R21/D21) -> 0.33080497 | T21: 600 | U21: =SUM(R21*T21) -> 3372.2259 | V21: =SUM(U21:U22) -> 5523.3586 | W21: =SUM(T21:T22) -> 1200
A22: 一月份 | B22: 站内订单 | C22: coupon订单 | D22: 16.99 | E22: 0 | F22: 0.1 | G22: =SUM(D22*(1-E22-F22)) -> 15.291 | H22: 4.38 | I22: =SUM(G22*15%) -> 2.29365 | J22: =SUM(G22-H22-I22) -> 8.61735 | K22: 0.01 | L22: 0.6 | M22: 2.5 | N22: 0.5 | O22: =SUM(20%*15%*G22+H22+K22+50%*M22+N22+1.46) -> 8.05873 | P22: 0.15 | Q22: =SUM(O22*P22/(1-P22)) -> 1.4221288 | R22: =SUM(J22-K22-L22-M22-N22-Q22) -> 3.5852212 | S22: =SUM(R22/D22) -> 0.21101949 | T22: 600 | U22: =SUM(R22*T22) -> 2151.1327
A24: 二月份 | B24: 站内订单 | C24: 原价订单 | D24: 17.99 | E24: 0 | F24: 0 | G24: =SUM(D24*(1-E24-F24)) -> 17.99 | H24: 4.38 | I24: =SUM(G24*15%) -> 2.6985 | J24: =SUM(G24-H24-I24) -> 10.9115 | K24: 0.01 | L24: 0 | M24: 2.5 | N24: 0.5 | O24: =SUM(20%*15%*G24+H24+K24+50%*M24+N24+1.46) -> 8.1397 | P24: 0.15 | Q24: =SUM(O24*P24/(1-P24)) -> 1.4364176 | R24: =SUM(J24-K24-L24-M24-N24-Q24) -> 6.4650824 | S24: =SUM(R24/D24) -> 0.35937089 | T24: 750 | U24: =SUM(R24*T24) -> 4848.8118 | V24: =SUM(U24:U25) -> 8107.9041 | W24: =SUM(T24:T25) -> 1500
A25: 二月份 | B25: 站内订单 | C25: coupon订单 | D25: 17.99 | E25: 0 | F25: 0.1 | G25: =SUM(D25*(1-E25-F25)) -> 16.191 | H25: 4.38 | I25: =SUM(G25*15%) -> 2.42865 | J25: =SUM(G25-H25-I25) -> 9.38235 | K25: 0.01 | L25: 0.6 | M25: 2.5 | N25: 0.5 | O25: =SUM(20%*15%*G25+H25+K25+50%*M25+N25+1.46) -> 8.08573 | P25: 0.15 | Q25: =SUM(O25*P25/(1-P25)) -> 1.4268935 | R25: =SUM(J25-K25-L25-M25-N25-Q25) -> 4.3454565 | S25: =SUM(R25/D25) -> 0.24154844 | T25: 750 | U25: =SUM(R25*T25) -> 3259.0924
A27: 三月份 | B27: 站内订单 | C27: 原价订单 | D27: 18.99 | E27: 0 | F27: 0 | G27: =SUM(D27*(1-E27-F27)) -> 18.99 | H27: 4.38 | I27: =SUM(G27*15%) -> 2.8485 | J27: =SUM(G27-H27-I27) -> 11.7615 | K27: 0.01 | L27: 0 | M27: 2.5 | N27: 0.5 | O27: =SUM(20%*15%*G27+H27+K27+50%*M27+N27+1.46) -> 8.1697 | P27: 0.15 | Q27: =SUM(O27*P27/(1-P27)) -> 1.4417118 | R27: =SUM(J27-K27-L27-M27-N27-Q27) -> 7.3097882 | S27: =SUM(R27/D27) -> 0.38492829 | T27: 900 | U27: =SUM(R27*T27) -> 6578.8094 | V27: =SUM(U27:U28) -> 11173.932 | W27: =SUM(T27:T28) -> 1800
A28: 三月份 | B28: 站内订单 | C28: coupon订单 | D28: 18.99 | E28: 0 | F28: 0.1 | G28: =SUM(D28*(1-E28-F28)) -> 17.091 | H28: 4.38 | I28: =SUM(G28*15%) -> 2.56365 | J28: =SUM(G28-H28-I28) -> 10.14735 | K28: 0.01 | L28: 0.6 | M28: 2.5 | N28: 0.5 | O28: =SUM(20%*15%*G28+H28+K28+50%*M28+N28+1.46) -> 8.11273 | P28: 0.15 | Q28: =SUM(O28*P28/(1-P28)) -> 1.4316582 | R28: =SUM(J28-K28-L28-M28-N28-Q28) -> 5.1056918 | S28: =SUM(R28/D28) -> 0.26886213 | T28: 900 | U28: =SUM(R28*T28) -> 4595.1226
A30: 未来 | B30: 站内订单 | C30: 原价订单 | D30: 19.99 | E30: 0 | F30: 0 | G30: =SUM(D30*(1-E30-F30)) -> 19.99 | H30: 4.38 | I30: =SUM(G30*15%) -> 2.9985 | J30: =SUM(G30-H30-I30) -> 12.6115 | K30: 0.01 | L30: 0 | M30: 2.5 | N30: 0.5 | O30: =SUM(20%*15%*G30+H30+K30+50%*M30+N30+1.46) -> 8.1997 | P30: 0.15 | Q30: =SUM(O30*P30/(1-P30)) -> 1.4470059 | R30: =SUM(J30-K30-L30-M30-N30-Q30) -> 8.1544941 | S30: =SUM(R30/D30) -> 0.40792867 | T30: 1200 | U30: =SUM(R30*T30) -> 9785.3929 | V30: =SUM(U30:U31) -> 16824.505 | W30: =SUM(T30:T31) -> 2400
A31: 未来 | B31: 站内订单 | C31: coupon订单 | D31: 19.99 | E31: 0 | F31: 0.1 | G31: =SUM(D31*(1-E31-F31)) -> 17.991 | H31: 4.38 | I31: =SUM(G31*15%) -> 2.69865 | J31: =SUM(G31-H31-I31) -> 10.91235 | K31: 0.01 | L31: 0.6 | M31: 2.5 | N31: 0.5 | O31: =SUM(20%*15%*G31+H31+K31+50%*M31+N31+1.46) -> 8.13973 | P31: 0.15 | Q31: =SUM(O31*P31/(1-P31)) -> 1.4364229 | R31: =SUM(J31-K31-L31-M31-N31-Q31) -> 5.8659271 | S31: =SUM(R31/D31) -> 0.29344307 | T31: 1200 | U31: =SUM(R31*T31) -> 7039.1125

Sheet CPC模拟
D2: 常规数据 | O2: 广告数据 | AC2: 实时更新 | AE2: 操作备注
A3: 日期 | B3: 星期 | C3: FBA 可售 | D3: 价格 | E3: 站内 coupon | F3: 站内 code | G3: 站外 code | H3: 新品 榜单 | I3: 小类目 排名 | J3: 总 销量 | K3: 总访 问量 | L3: CVR | M3: 评论 数量 | N3: 评分 | O3: 曝光量 | P3: 点击量 | Q3: CTR | R3: 广告单 | S3: 平均 CVR | T3: 平均 CPC | U3: 花费 | V3: ACOS | W3: CPA | X3: 自然 访问 | Y3: 自然 订单 | Z3: 自然 单占比 | AA3: 站内 自然单 | AB3: 最终 盈亏 | AC3: 西柚 质量分 | AD3: 西柚 截图 | AE3: 运营调整 | AF3: 广告操作
A4: 11/1-11/10 | D4: 12.99 | E4: 0 | F4: 0 | G4: 0 | P4: =R4/S4 -> 416.66667 | R4: =阶段盈亏模拟!I3 -> 25 | S4: 0.06 | T4: 1.5 | U4: =P4*T4 -> 625 | V4: =T4/S4/D4 -> 1.9245574 | W4: =SUM(U4/R4) -> 25
A5: 11/11-11/20 | D5: 12.99 | E5: 0 | F5: 0 | G5: 0 | P5: =R5/S5 -> 615.38462 | R5: =阶段盈亏模拟!I4 -> 40 | S5: 0.065 | T5: 1.5 | U5: =P5*T5 -> 923.07692 | V5: =T5/S5/D5 -> 1.7765145 | W5: =SUM(U5/R5) -> 23.076923
A6: 11/21-11/30 | D6: 13.99 | E6: 0 | F6: 0 | G6: 0 | P6: =R6/S6 -> 1000 | R6: =阶段盈亏模拟!I5 -> 70 | S6: 0.07 | T6: 1.3 | U6: =SUM(P6*T6) -> 1300 | V6: =SUM(T6/S6/D6) -> 1.3274788 | W6: =SUM(U6/R6) -> 18.571429
A7: 12/1-12/10 | D7: 13.99 | E7: 0 | F7: 0 | G7: 0 | P7: =SUM(R7/S7) -> 1200 | R7: =阶段盈亏模拟!I6 -> 90 | S7: 0.075 | T7: 1.3 | U7: =SUM(P7*T7) -> 1560 | V7: =SUM(T7/S7/D7) -> 1.2389802 | W7: =SUM(U7/R7) -> 17.333333
A8: 12/11-12/20 | D8: 14.99 | E8: 0 | F8: 0 | G8: 0 | P8: =SUM(R8/S8) -> 1375 | R8: =阶段盈亏模拟!I7 -> 110 | S8: 0.08 | T8: 1.1 | U8: =SUM(P8*T8) -> 1512.5 | V8: =SUM(T8/S8/D8) -> 0.91727819 | W8: =SUM(U8/R8) -> 13.75
A9: 12/21-12/30 | D9: 15.99 | E9: 0 | F9: 0 | G9: 0 | P9: =SUM(R9/S9) -> 1647.0588 | R9: =阶段盈亏模拟!I8 -> 140 | S9: 0.085 | T9: 1.1 | U9: =SUM(P9*T9) -> 1811.7647 | V9: =SUM(T9/S9/D9) -> 0.80932936 | W9: =SUM(U9/R9) -> 12.941176
A10: 一月份 | D10: 16.99 | E10: 0.1 | F10: 0 | G10: 0 | P10: =SUM(R10/S10) -> 5000 | R10: =阶段盈亏模拟!I9 -> 450 | S10: 0.09 | T10: 1 | U10: =SUM(P10*T10) -> 5000 | V10: =SUM(T10/S10/D10) -> 0.65397947 | W10: =SUM(U10/R10) -> 11.111111
A11: 二月份 | D11: 17.99 | E11: 0.1 | F11: 0 | G11: 0 | P11: =SUM(R11/S11) -> 5263.1579 | R11: =阶段盈亏模拟!I10 -> 500 | S11: 0.095 | T11: 1 | U11: =SUM(P11*T11) -> 5263.1579 | V11: =SUM(T11/S11/D11) -> 0.58512039 | W11: =SUM(U11/R11) -> 10.526316
A12: 三月份 | D12: 18.99 | E12: 0.1 | F12: 0 | G12: 0 | P12: =SUM(R12/S12) -> 6000 | R12: =阶段盈亏模拟!I11 -> 600 | S12: 0.1 | T12: 1 | U12: =SUM(P12*T12) -> 6000 | V12: =SUM(T12/S12/D12) -> 0.52659294 | W12: =SUM(U12/R12) -> 10
A13: 未来 | D13: 19.99 | E13: 0.1 | F13: 0 | G13: 0 | P13: =SUM(R13/S13) -> 6666.6667 | R13: =阶段盈亏模拟!I12 -> 800 | S13: 0.12 | T13: 0.8 | U13: =SUM(P13*T13) -> 5333.3333 | V13: =SUM(T13/S13/D13) -> 0.33350008 | W13: =SUM(U13/R13) -> 6.6666667

Sheet 主要出单词
A1: 关键词 | B1: 7天展示量 | C1: 流量占比 | D1: 流量分布(自然) | E1: 流量分布(广告) | F1: 展示位置 | G1: 自然排名 | H1: 自然排名(页码-页内排名) | I1: sp广告排名 | J1: sp广告排名(页码-页内排名) | K1: 关键词排名 | L1: 周搜索量 | M1: 亚马逊建议竞价
A2: posture corrector for women | B2: 102490 | C2: 0.25373963 | D2: 0.5267929 | E2: 0.47320715 | F2: 自然,SP,OOR,HR | G2: 1 | H2: P1-1 | I2: 1 | J2: P1-1 | K2: 1604 | L2: 79073 | M2: 2.08
A3: posture corrector | B3: 50096 | C3: 0.12402517 | D3: 0.5772517 | E3: 0.42274833 | F3: 自然,SP,OOR,HR | G3: 2 | H3: P1-2 | I3: 1 | J3: P1-1 | K3: 11292 | L3: 13394 | M3: 2.31
A4: posture corrector for men | B4: 33698 | C4: 0.083427824 | D4: 0.5654045 | E4: 0.43459553 | F4: 自然,SP,OOR,HR | G4: 4 | H4: P1-4 | I4: 1 | J4: P1-1 | K4: 5765 | L4: 23020 | M4: 3.13
A5: back brace posture corrector | B5: 17567 | C5: 0.0434915 | D5: 0.64000684 | E5: 0.35999316 | F5: 自然,SP,OOR,HR | G5: 4 | H5: P1-4 | I5: 3 | J5: P1-3 | K5: 13181 | L5: 11923 | M5: 2.24
A6: back posture corrector | B6: 16300 | C6: 0.040354725 | D6: 0.56453985 | E6: 0.43546012 | F6: 自然,SP,OOR,HR | G6: 1 | H6: P1-1 | I6: 1 | J6: P1-1 | K6: 46272 | L6: 4885 | M6: 2.49
A7: back posture corrector women | B7: 13350 | C7: 0.033051264 | D7: 0.5414981 | E7: 0.45850188 | F7: 自然,SP,OOR,HR | G7: 5 | H7: P1-5 | I7: 2 | J7: P1-2 | K7: 25323 | L7: 7505 | M7: 1.43
A8: back straightener posture corrector | B8: 10216 | C8: 0.025292262 | D8: 0.5456147 | E8: 0.45438528 | F8: 自然,SP,OOR,HR | G8: 2 | H8: P1-2 | I8: 1 | J8: P1-1 | K8: 42579 | L8: 5204 | M8: 2.51
A9: posture brace | B9: 8317 | C9: 0.020590814 | D9: 0.53757364 | E9: 0.46242636 | F9: 自然,SP,OOR,HR | G9: 3 | H9: P1-3 | I9: 1 | J9: P1-1 | K9: 75464 | L9: 3077 | M9: 2.39
A10: back posture corrector for men | B10: 3574 | C10: 0.008848331 | D10: 0.61135983 | E10: 0.38864017 | F10: 自然,SP,OOR,HR | G10: 2 | H10: P1-2 | I10: 2 | J10: P1-2 | K10: 87697 | L10: 2504 | M10: 1.61
A11: back straightener | B11: 3007 | C11: 0.0074445806 | D11: 0.55237776 | E11: 0.4476222 | F11: 自然,SP,OOR,HR | G11: 5 | H11: P1-5 | I11: 1 | J11: P1-1 | K11: 88173 | L11: 2483 | M11: 2.06

Sheet 广告策略
A1: 广告类似 | B1: 匹配类型 | C1: 竞价策略 | D1: CPC | E1: 关键词
A2: 自动广告 | B2: 紧密匹配 | C2: 提降 | D2: 0.5
A3: 手动广告 | B3: 精准匹配 | C3: 提降 | D3: 0.8 | E3: 词根 posture corrector
A4: 手动广告 | B4: 精准匹配 | C4: 提降 | D4: 0.8 | E4: 词根 back brace
A5: 手动广告 | B5: 精准匹配 | C5: 提降 | D5: 0.8 | E5: 词根 posture brace
A6: 品牌视频广告 | B6: 精准匹配 | C6: 自动竞价 | D6: 0.8
A7: 品牌视频广告 | B7: 精准匹配 | C7: 自动竞价 | D7: 0.8
A8: 品牌视频广告 | B8: 精准匹配 | C8: 自动竞价 | D8: 0.8

Sheet 2
A1: amazon-order-id | B1: merchant-order-id | C1: purchase-date | D1: last-updated-date | E1: order-status | F1: fulfillment-channel | G1: sales-channel | H1: order-channel | I1: url | J1: ship-service-level | K1: product-name | L1: sku | M1: asin | N1: item-status | O1: quantity | P1: currency | Q1: item-price | R1: item-tax | S1: shipping-price | T1: shipping-tax | U1: gift-wrap-price | V1: gift-wrap-tax | W1: item-promotion-discount | X1: ship-promotion-discount | Y1: ship-city | Z1: ship-state | AA1: ship-postal-code | AB1: ship-country | AC1: promotion-ids | AD1: is-business-order | AE1: purchase-order-number | AF1: price-designation | AG1: default-ship-from-address-name | AH1: default-ship-from-address-field-1 | AI1: default-ship-from-address-field-2 | AJ1: default-ship-from-address-field-3 | AK1: default-ship-from-city | AL1: default-ship-from-state | AM1: default-ship-from-country | AN1: default-ship-from-postal-code | AO1: actual-ship-from-address-name | AP1: actual-ship-from-address-field-1 | AQ1: actual-ship-from-address-field-2 | AR1: actual-ship-from-address-field-3 | AS1: actual-ship-from-city | AT1: actual-ship-from-state | AU1: actual-ship-from-country | AV1: actual-ship-from-postal-code | AW1: is-buyer-requested-cancellation | AX1: buyer-requested-cancel-reason | AY1: serial-numbers | AZ1: signature-confirmation-recommended
A2: 111-9858618-2103444 | B2: 111-9858618-2103444 | C2: 2023-09-12T05:37:43+00:00 | D2: 2023-09-12T05:37:48+00:00 | E2: Pending | F2: Amazon | G2: Amazon.com | J2: Expedited | K2: Dash Cam Front with FHD 1080p, Wanlipo 2 Inch LCD Dashcam, Dashboard Camera for Cars with 24h Parking Monitor, G-Sensor, Loop Recording, Free 32GB SD | L2: J09-C1 | M2: B0BG6WPM3W | N2: Unshipped | O2: 1 | P2: USD | Q2: 79.99 | Y2: BELLMAWR | Z2: NJ | AA2: 08031-2115 | AB2: US | AC2: MPC-S Percentage Off 2023/09/10 11-52-12-900 | AD2: FALSE | AW2: FALSE | AZ2: FALSE
A3: 114-5667916-6324215 | B3: 114-5667916-6324215 | C3: 2023-09-12T03:37:05+00:00 | D3: 2023-09-12T09:02:46+00:00 | E3: Shipped | F3: Amazon | G3: Amazon.com | J3: Expedited | K3: 4K Dash Cam Front Built-in WiFi, WANLIPO Dash Camera for Cars with 64GB SD Card, Car Camera with 3" IPS Screen, 2160P Dashcam for Cars with App Contro | L3: Wanlipo M03-3 | M3: B0CC8CHTTJ | N3: Shipped | O3: 1 | P3: USD | Q3: 99.99 | R3: 1.89 | W3: 72.99 | Y3: MONROE | Z3: GA | AA3: 30656-4723 | AB3: US | AC3: MPC-S Percentage Off 2023/09/11 9-53-46-600 | AD3: FALSE | AW3: FALSE | AZ3: FALSE
A4: 111-1595396-9168227 | B4: 111-1595396-9168227 | C4: 2023-09-11T23:55:05+00:00 | D4: 2023-09-11T23:55:11+00:00 | E4: Pending | F4: Amazon | G4: Amazon.com | J4: Expedited | K4: Dash Cam Front with FHD 1080p, Wanlipo 2 Inch LCD Dashcam, Dashboard Camera for Cars with 24h Parking Monitor, G-Sensor, Loop Recording, Free 32GB SD | L4: J09-C1 | M4: B0BG6WPM3W | N4: Unshipped | O4: 1 | P4: USD | Q4: 79.99 | Y4: SILVER SPRING | Z4: MD | AA4: 20906-4527 | AB4: US | AC4: MPC-S Percentage Off 2023/09/10 11-52-3-698 | AD4: FALSE | AW4: FALSE | AZ4: FALSE
A5: 112-7810040-2837843 | B5: 112-7810040-2837843 | C5: 2023-09-11T19:41:13+00:00 | D5: 2023-09-12T01:35:23+00:00 | E5: Shipped | F5: Amazon | G5: Amazon.com | J5: Expedited | K5: Dash Cam Front with FHD 1080p, Wanlipo 2 Inch LCD Dashcam, Dashboard Camera for Cars with 24h Parking Monitor, G-Sensor, Loop Recording, Free 32GB SD | L5: J09-C1 | M5: B0BG6WPM3W | N5: Shipped | O5: 1 | P5: USD | Q5: 79.99 | R5: 1.85 | W5: 59.99 | Y5: Nashville | Z5: TN | AA5: 37208-1058 | AB5: US | AC5: MPC-S Percentage Off 2023/09/10 11-52-13-889 | AD5: FALSE | AW5: FALSE | AZ5: FALSE
A6: 111-4369826-2407442 | B6: 111-4369826-2407442 | C6: 2023-09-11T18:52:15+00:00 | D6: 2023-09-11T18:52:21+00:00 | E6: Pending | F6: Amazon | G6: Amazon.com | J6: Standard | K6: 4K Dash Cam Front with WiFi 2160P, VOFRTY Dash Camera for Cars with 3" IPS, Car Camera with App Control, Dashcam with G-Sensor, Loop Recording, 64GB S | L6: M03-3 | M6: B0C1C9T9KP | N6: Unshipped | O6: 1 | P6: USD | Q6: 79.99 | Y6: HUNTINGTON | Z6: WV | AA6: 25704-1119 | AB6: US | AC6: US Core Free Shipping Promotion A3JU1FCINF5SD0,Percentage Off 2023/08/28 6-17-47-400 | AD6: FALSE | AW6: FALSE | AZ6: FALSE
A7: 114-0862837-0430606 | B7: 114-0862837-0430606 | C7: 2023-09-11T17:17:31+00:00 | D7: 2023-09-11T17:17:37+00:00 | E7: Pending | F7: Amazon | G7: Amazon.com | J7: Expedited | K7: Dash Cam Front with FHD 1080p, Wanlipo 2 Inch LCD Dashcam, Dashboard Camera for Cars with 24h Parking Monitor, G-Sensor, Loop Recording, Free 32GB SD | L7: J09-C1 | M7: B0BG6WPM3W | N7: Unshipped | O7: 1 | P7: USD | Q7: 79.99 | Y7: LOS ANGELES | Z7: CA | AA7: 90016-2009 | AB7: US | AC7: MPC-S Percentage Off 2023/09/10 11-52-3-698 | AD7: FALSE | AW7: FALSE | AZ7: FALSE
A8: 114-2447819-7327466 | B8: 114-2447819-7327466 | C8: 2023-09-11T15:45:23+00:00 | D8: 2023-09-11T15:45:29+00:00 | E8: Pending | F8: Amazon | G8: Amazon.com | J8: Expedited | K8: 4K Dash Cam Front with WiFi 2160P, VOFRTY Dash Camera for Cars with 3" IPS, Car Camera with App Control, Dashcam with G-Sensor, Loop Recording, 64GB S | L8: M03-3 | M8: B0C1C9T9KP | N8: Unshipped | O8: 1 | P8: USD | Q8: 79.99 | Y8: DES MOINES | Z8: IA | AA8: 50317-6307 | AB8: US | AC8: MPC-S Percentage Off 2023/09/11 9-54-8-40 | AD8: FALSE | AW8: FALSE | AZ8: FALSE
A9: 114-3078544-2276207 | B9: 114-3078544-2276207 | C9: 2023-09-11T15:21:19+00:00 | D9: 2023-09-12T04:25:37+00:00 | E9: Shipped | F9: Amazon | G9: Amazon.com | J9: Expedited | K9: 4K Dash Cam Front with WiFi 2160P, VOFRTY Dash Camera for Cars with 3" IPS, Car Camera with App Control, Dashcam with G-Sensor, Loop Recording, 64GB S | L9: M03-3 | M9: B0C1C9T9KP | N9: Shipped | O9: 1 | P9: USD | Q9: 79.99 | R9: 3.12 | W9: 47.99 | Y9: LA VERGNE | Z9: TN | AA9: 37086-1439 | AB9: US | AC9: MPC-S Percentage Off 2023/09/11 9-54-8-40 | AD9: FALSE | AW9: FALSE | AZ9: FALSE
A10: 114-1356066-5534643 | B10: 114-1356066-5534643 | C10: 2023-09-11T13:58:53+00:00 | D10: 2023-09-12T07:08:25+00:00 | E10: Shipped | F10: Amazon | G10: Amazon.com | J10: Expedited | K10: Dash Cam Front with FHD 1080p, Wanlipo 2 Inch LCD Dashcam, Dashboard Camera for Cars with 24h Parking Monitor, G-Sensor, Loop Recording, Free 32GB SD | L10: J09-C1 | M10: B0BG6WPM3W | N10: Shipped | O10: 1 | P10: USD | Q10: 79.99 | R10: 1.25 | S10: 2.99 | W10: 59.99 | X10: 2.99 | Y10: BLACKSTONE | Z10: MA | AA10: 01504-1408 | AB10: US | AC10: MPC-S Percentage Off 2023/09/10 5-41-22-292 | AD10: FALSE | AW10: FALSE | AZ10: FALSE
A11: 112-9726611-4879461 | B11: 112-9726611-4879461 | C11: 2023-09-11T12:39:23+00:00 | D11: 2023-09-12T09:25:25+00:00 | E11: Shipped | F11: Amazon | G11: Amazon.com | J11: Standard | K11: 4K Dash Cam Front Built-in WiFi, WANLIPO Dash Camera for Cars with 64GB SD Card, Car Camera with 3" IPS Screen, 2160P Dashcam for Cars with App Contro | L11: Wanlipo M03-3 | M11: B0CC8CHTTJ | N11: Shipped | O11: 1 | P11: USD | Q11: 99.99 | R11: 2.84 | W11: 67.99 | Y11: Brooklyn | Z11: NY | AA11: 11235 | AB11: US | AC11: MPC-S Percentage Off 2023/09/07 1-34-35-547 | AD11: FALSE | AW11: FALSE | AZ11: FALSE
A12: 113-6400382-4997016 | B12: 113-6400382-4997016 | C12: 2023-09-11T11:06:47+00:00 | D12: 2023-09-11T11:06:52+00:00 | E12: Pending | F12: Amazon | G12: Amazon.com | J12: Expedited | K12: Dash Cam Front with FHD 1080p, Wanlipo 2 Inch LCD Dashcam, Dashboard Camera for Cars with 24h Parking Monitor, G-Sensor, Loop Recording, Free 32GB SD | L12: J09-C1 | M12: B0BG6WPM3W | N12: Unshipped | O12: 1 | P12: USD | Q12: 79.99 | Y12: BRONX | Z12: NY | AA12: 10461 | AB12: US | AC12: MPC-S Percentage Off 2023/09/10 11-52-12-900 | AD12: FALSE | AW12: FALSE | AZ12: FALSE
A13: 112-9947498-4884232 | B13: 112-9947498-4884232 | C13: 2023-09-11T07:15:23+00:00 | D13: 2023-09-11T18:12:08+00:00 | E13: Shipped | F13: Amazon | G13: Amazon.com | J13: Expedited | K13: 4K Dash Cam Front with WiFi 2160P, VOFRTY Dash Camera for Cars with 3" IPS, Car Camera with App Control, Dashcam with G-Sensor, Loop Recording, 64GB S | L13: M03-3 | M13: B0C1C9T9KP | N13: Shipped | O13: 1 | P13: USD | Q13: 79.99 | R13: 3.8 | W13: 40 | Y13: WEST COVINA | Z13: CA | AA13: 91792-1494 | AB13: US | AC13: Percentage Off 2023/08/28 6-17-47-400 | AD13: FALSE | AW13: FALSE | AZ13: FALSE

Sheet WpsReserved_CellImgList
