Workbook
Name ATTRIBUTEPTDMAP: [1]attributePTDMap!$A$1:$B$83
Name item_type_: '[1]Dropdown Lists'!$A$4

Sheet 销售记录
I1: 201803月份销售明细 | AN1: 三月销量 | AO1: 三月销售额 | AS1: 28400 | AT1: 201804月份销售明细 | BX1: 四月销量 | BY1: 四月销售 | CC1: 40700 | CD1: 201805月份销售明细 | DI1: 四月销量 | DJ1: 四月销售
A2: ASIN | B2: SKU | C2: 产品 | D2: 客单价 | E2: 超链 | F2: FBA在途 | G2: FBA库存 | H2: 下月目标 | I2: 1 | J2: 2 | K2: 3 | L2: 4 | M2: 5 | N2: 6 | O2: 7 | P2: 8 | Q2: 9 | R2: 10 | S2: 11 | T2: 12 | U2: 13 | V2: 14 | W2: 15 | X2: 16 | Y2: 17 | Z2: 18 | AA2: 19 | AB2: 20 | AC2: 21 | AD2: 22 | AE2: 23 | AF2: 24 | AG2: 25 | AH2: 26 | AI2: 27 | AJ2: 28 | AK2: 29 | AL2: 30 | AM2: 31 | AN2: 总计 | AO2: 总计 | AP2: 完成比例 | AQ2: 加权平均 | AR2: 预计下月 | AS2: 4月目标 | AT2: 1 | AU2: 2 | AV2: 3 | AW2: 4 | AX2: 5 | AY2: 6 | AZ2: 7 | BA2: 8 | BB2: 9 | BC2: 10 | BD2: 11 | BE2: 12 | BF2: 13 | BG2: 14 | BH2: 15 | BI2: 16 | BJ2: 17 | BK2: 18 | BL2: 19 | BM2: 20 | BN2: 21 | BO2: 22 | BP2: 23 | BQ2: 24 | BR2: 25 | BS2: 26 | BT2: 27 | BU2: 28 | BV2: 29 | BW2: 30 | BX2: 总计 | BY2: 总计 | BZ2: 完成比例 | CA2: 加权平均 | CB2: 预计下月 | CC2: 5月目标 | CD2: 1 | CE2: 2 | CF2: 3 | CG2: 4 | CH2: 5 | CI2: 6 | CJ2: 7 | CK2: 8 | CL2: 9 | CM2: 10 | CN2: 11 | CO2: 12 | CP2: 13 | CQ2: 14 | CR2: 15 | CS2: 16 | CT2: 17 | CU2: 18 | CV2: 19 | CW2: 20 | CX2: 21 | CY2: 22 | CZ2: 23 | DA2: 24 | DB2: 25 | DC2: 26 | DD2: 27 | DE2: 28 | DF2: 29 | DG2: 30 | DH2: 31 | DI2: 总计 | DJ2: 总计 | DK2: 完成比例 | DL2: 加权平均 | DM2: 预计下月
D3: 合计 | F3: =SUM(F4:F4) -> 1100 | G3: =SUM(G4:G4) -> 1184 | H3: =SUM(H4:H4) -> 0 | I3: =SUM(I4:I4) -> 6 | J3: =SUM(J4:J4) -> 3 | K3: =SUM(K4:K4) -> 11 | L3: =SUM(L4:L4) -> 10 | M3: =SUM(M4:M4) -> 12 | ... AM3: =SUM(AM4:AM4) -> 0 | AN3: =SUM(I3:AM3) -> 163 | AO3: =SUM(AO4:AO4) -> 1483.77 | AS3: =SUM(AS4:AS4) -> 160 | AT3: =SUM(AT4:AT4) -> 0 | AU3: =SUM(AU4:AU4) -> 0 | AV3: =SUM(AV4:AV4) -> 0 | AW3: =SUM(AW4:AW4) -> 0 | AX3: =SUM(AX4:AX4) -> 1 | AY3: =SUM(AY4:AY4) -> 0 | AZ3: =SUM(AZ4:AZ4) -> 4 | ... BW3: =SUM(BW4:BW4) -> 8 | BX3: =SUM(AT3:BW3) -> 172 | BY3: =SUM(BY4:BY4) -> 1718.28 | BZ3: =BY3/AS1 -> 0.060502817 | CC3: =SUM(CC4:CC4) -> 250 | CD3: =SUM(CD4:CD4) -> 7 | CE3: =SUM(CE4:CE4) -> 8 | CF3: =SUM(CF4:CF4) -> 6 | CG3: =SUM(CG4:CG4) -> 11 | CH3: =SUM(CH4:CH4) -> 8 | CI3: =SUM(CI4:CI4) -> 8 | CJ3: =SUM(CJ4:CJ4) -> 7 | ... DJ3: =SUM(DJ4:DJ4) -> 1708.29 | DK3: =DJ3/CC1 -> 0.041972727
A4: B01M72VYXM | B4: 2091010 | C4: 宠物梳 | D4: 9.99 | F4: =VLOOKUP(A4,FBA库存!D:AQ,40,0) -> 1100 | G4: =VLOOKUP(A4,FBA库存!D:J,7,0) -> 1184 | I4: 6 | J4: 3 | K4: 11 | L4: 10 | M4: 12 | N4: 5 | O4: 5 | P4: 5 | Q4: 5 | R4: 2 | S4: 0 | T4: 0 | U4: 0 | V4: 0 | W4: 0 | X4: 2 | Y4: 7 | Z4: 10 | AA4: 7 | AB4: 6 | AC4: 6 | AD4: 9 | AE4: 10 | AF4: 9 | AG4: 10 | AH4: 10 | AI4: 2 | AJ4: 6 | AK4: 4 | AL4: 1 | AM4: 0 | AN4: =SUM(I4:AM4) -> 163 | AO4: 1483.77 | AQ4: =ROUNDUP((((SUM(AF4:AL4)*0.6+SUM(Y4:AE4)*0.25+SUM(R4:X4)*0.15))/7),1) -> 5.7 | AR4: =AQ4*30 -> 171 | AS4: 160 | AT4: 0 | AU4: 0 | AV4: 0 | AW4: 0 | AX4: 1 | AY4: 0 | AZ4: 4 | BA4: 7 | BB4: 6 | BC4: 9 | BD4: 9 | BE4: 8 | BF4: 8 | BG4: 5 | BH4: 6 | BI4: 5 | BJ4: 8 | BK4: 4 | BL4: 6 | BM4: 4 | BN4: 11 | BO4: 10 | BP4: 12 | BQ4: 10 | BR4: 7 | BS4: 5 | BT4: 7 | BU4: 10 | BV4: 2 | BW4: 8 | BX4: =SUM(AT4:BW4) -> 172 | BY4: =BX4*D4 -> 1718.28 | BZ4: =BX4/AS4 -> 1.075 | CA4: =ROUNDUP((((SUM(BP4:BW4)*0.6+SUM(BI4:BO4)*0.25+SUM(BB4:BH4)*0.15))/7),1) -> 8.1 | CB4: =CA4*30 -> 243 | CC4: 250 | CD4: 7 | CE4: 8 | CF4: 6 | CG4: 11 | CH4: 8 | CI4: 8 | CJ4: 7 | CK4: 3 | CL4: 5 | CM4: 7 | CN4: 8 | CO4: 8 | CP4: 8 | CQ4: 6 | CR4: 12 | CS4: 12 | CT4: 13 | CU4: 11 | CV4: 9 | CW4: 14 | DI4: =SUM(CD4:DH4) -> 171 | DJ4: =DI4*D4 -> 1708.29 | DK4: =DI4/CC4 -> 0.684

Sheet 重点产品数据跟踪
A1: ASIN | B1: SKU | C1: 产品 | D1: 指标 | E1: 4.2-4.8 | F1: 4.9-4.15 | G1: 4.16-4.22 | H1: 4.23-4.30 | I1: 5.1-5.6 | J1: 5.7-5.13 | K1: 5.14-5.20
D2: 周销量 | E2: 12 | F2: 52 | G2: 48 | H2: 61 | I2: 49 | J2: 46 | K2: =VLOOKUP($A7,业务报表!$B:$J,9,0)+VLOOKUP($A7,业务报表!$B:$K,10,0) -> 80
D3: 日均销量 | E3: 1.7142857 | F3: 7.4285714 | G3: 6.8571429 | H3: 8.7142857 | I3: 7 | J3: 6.5714286 | K3: =K2/7 -> 11.428571
D4: 销售额 | E4: 119.88 | F4: 519.14 | G4: 479.47 | H4: 609.39 | I4: 489.51 | J4: 459.54 | K4: =VLOOKUP($A7,业务报表!$B:$N,13,0)+VLOOKUP($A7,业务报表!$B:$O,14,0) -> 799.2
D5: 广告销售额 | E5: 19.98 | F5: 59.91 | G5: 39.95 | H5: 39.96 | I5: 49.95 | J5: 79.92 | K5: =VLOOKUP($B7,广告费用!$A:$C,3,0) -> 39.96
D6: 流量 | E6: 66 | F6: 158 | G6: 153 | H6: 344 | I6: 114 | J6: 216 | K6: =VLOOKUP($A7,业务报表!$B:$E,4,0) -> 223
A7: B01M72VYXM | B7: 2091010 | C7: 宠物梳 | D7: 转化率 | E7: 0.1818 | F7: 0.3291 | G7: 0.3137 | H7: 0.1773 | I7: 0.4211 | J7: 0.213 | K7: =VLOOKUP($A7,业务报表!$B:$L,11,0) -> 0.3453
D8: 排名 | E8: 7/1767 | F8: 8/2020 | G8: 3/1109 | H8: 9/1626 | I8: 5./1458 | J8: 1683 | K8: =VLOOKUP(A7,'排名+评分'!A:L,12,0) -> 985
D9: 评论数 | E9: 63 | F9: 64 | G9: 67 | H9: 69 | I9: 70 | J9: 72 | K9: =VLOOKUP(A7,'排名+评分'!A:O,15,0) -> 73
D10: 评分 | E10: 4.8 | F10: 4.8 | G10: 4.8 | H10: 4.8 | I10: 4.8 | J10: 5 | K10: =VLOOKUP(A7,'排名+评分'!A:R,18,0) -> 4.8
D11: 推广费用 | E11: 7.63 | F11: 16.29 | G11: 7.93 | H11: 7.63 | I11: 5.27 | J11: 7.97 | K11: =VLOOKUP($B7,广告费用!$A:$B,2,0) -> 7.34
D12: 推广费用占比 | E12: 0.06364698 | F12: 0.031378819 | G12: 0.016539095 | H12: 0.012520717 | I12: 0.010765868 | J12: 0.01734343 | K12: =K11/K4 -> 0.0091841842

Sheet FBA库存
A1: snapshot-date | B1: sku | C1: fnsku | D1: asin | E1: product-name | F1: condition | G1: sales-rank | H1: product-group | I1: total-quantity | J1: sellable-quantity | K1: unsellable-quantity | L1: inv-age-0-to-90-days | M1: inv-age-91-to-180-days | N1: inv-age-181-to-270-days | O1: inv-age-271-to-365-days | P1: inv-age-365-plus-days | Q1: units-shipped-last-24-hrs | R1: units-shipped-last-7-days | S1: units-shipped-last-30-days | T1: units-shipped-last-90-days | U1: units-shipped-last-180-days | V1: units-shipped-last-365-days | W1: weeks-of-cover-t7 | X1: weeks-of-cover-t30 | Y1: weeks-of-cover-t90 | Z1: weeks-of-cover-t180 | AA1: weeks-of-cover-t365 | AB1: num-afn-new-sellers | AC1: num-afn-used-sellers | AD1: currency | AE1: your-price | AF1: sales-price | AG1: lowest-afn-new-price | AH1: lowest-afn-used-price | AI1: lowest-mfn-new-price | AJ1: lowest-mfn-used-price | AK1: qty-to-be-charged-ltsf-12-mo | AL1: qty-in-long-term-storage-program | AM1: qty-with-removals-in-progress | AN1: projected-ltsf-12-mo | AO1: per-unit-volume | AP1: is-hazmat | AQ1: in-bound-quantity | AR1: asin-limit | AS1: inbound-recommend-quantity | AT1: qty-to-be-charged-ltsf-6-mo | AU1: projected-ltsf-6-mo
A2: 2018-05-19T23:00:00+00:00 | B2: 2091010 | C2: B01M72VYXM | D2: B01M72VYXM | E2: Pet Grooming Undercoat Rake Comb Tool Kit, Double Sided Blade Rake Comb and Grooming Comb, Morpilot Pet Dematting Stripping Comb for Dogs and Cats-Removes Loose Undercoat, Knots, Mats and Tangled Hair | F2: New | G2: 701 | H2: pet_products_display_on_website | I2: 1193 | J2: 1184 | K2: 9 | L2: 1184 | M2: 0 | N2: 0 | O2: 0 | P2: 0 | Q2: 31 | R2: 247 | S2: 1028 | T2: 2288 | U2: 3492 | V2: 5850 | W2: 9.2469636 | X2: 8.8871595 | Y2: 12.977273 | Z2: 17.005727 | AA2: 20.302222 | AB2: 1 | AC2: 0 | AD2: GBP | AE2: 15.99 | AF2: 9.99 | AG2: 9.99 | AH2: 0 | AI2: 0 | AJ2: 0 | AK2: 0 | AL2: 0 | AN2: 0 | AO2: 0 | AP2: N | AQ2: 1100 | AR2: 0 | AS2: 0 | AT2: 0 | AU2: 0

Sheet 业务报表
A1: (Parent) ASIN | B1: (Child) ASIN | C1: Title | D1: SKU | E1: Sessions | F1: Session Percentage | G1: Page Views | H1: Page Views Percentage | I1: Buy Box Percentage | J1: Units Ordered | K1: Units Ordered – B2B | L1: Unit Session Percentage | M1: Unit Session Percentage – B2B | N1: Ordered Product Sales | O1: Ordered Product Sales – B2B | P1: Total Order Items | Q1: Total Order Items – B2B
A2: B076B27ZRD | B2: B01M72VYXM | C2: Pet Grooming Undercoat Rake Comb Tool Kit, Double Sided Blade Rake Comb and Grooming Comb, Morpilot Pet Dematting Stripping Comb for Dogs and Cats-Removes Loose Undercoat, Knots, Mats and Tangled Hair | D2: 2091010 | E2: 223 | F2: 0.0418 | G2: 310 | H2: 0.0409 | I2: 1 | J2: 77 | K2: 3 | L2: 0.3453 | M2: 0.0135 | N2: 769.23 | O2: 29.97 | P2: 76 | Q2: 3

Sheet 广告费用
A3: SKU | B3: 求和项:Spend | C3: 求和项:Sales
A4: 1011002 | B4: 0.97 | C4: 0
A5: 1011013 | B5: 0.42 | C5: 0
A6: 1012010 | B6: 5.11 | C6: 0
A7: 1041001 | B7: 2.74 | C7: 104.45
A8: 1051001 | B8: 36.17 | C8: 300.85
A9: 1051002 | B9: 15.2 | C9: 47.97
A10: 1051003 | B10: 0 | C10: 0
A11: 1051007 | B11: 21.06 | C11: 137.92
A12: 1051019 | B12: 25.29 | C12: 412.85
A13: 1051025 | B13: 42.91 | C13: 276.92
A14: 1051028 | B14: 26.39 | C14: 65.97
A15: 1071001 | B15: 13.28 | C15: 0
... A58: 2391021 | B58: 1.66 | C58: 0
A59: 1011028-1 | B59: 15.59 | C59: 152.91
A60: 2041015-2 | B60: 0 | C60: 0
A61: 2051005-2 | B61: 0.56 | C61: 0
A62: 2081001-1 | B62: 0.19 | C62: 0
A63: 2100002-1 | B63: 18.63 | C63: 59.97
A64: 2100003-1 | B64: 6.57 | C64: 0
A65: 2100004-1 | B65: 5.77 | C65: 0
A66: 2100008-2 | B66: 0 | C66: 0
A67: 2100009-1 | B67: 10.57 | C67: 134.95
A68: 2300006-1 | B68: 475.29 | C68: 2305.47
A69: 2371039-1 | B69: 2.36 | C69: 0
A70: 总计 | B70: 1260.02 | C70: 6115.66

Sheet 排名+评分
A1: ASIN | B1: # | C1: 商品名称 | D1: 品牌 | E1: 价格 | F1: 最低售价 | G1: 净利 | H1: FBA费用 | I1: LQS | J1: 品类 | K1: 卖家 | L1: 排名 | M1: 预计销量 | N1: 预估收入 | O1: 第#条评论 | P1: RPR | Q1: 生效日期 | R1: 评分 | S1: 重量 | T1: 卖家 | U1: 变体 | V1: 链接
A2: B01M72VYXM | B2: 3 | C2: Pet Grooming Undercoat Rake Comb Tool Kit, Double Sided Blade Rake Comb and Grooming Comb, Morpilot Pet Dematting Stripping Comb for Dogs and Cats-Removes Loose Undercoat, Knots, Mats and Tangled Hair | D2: morpilot | E2: 9.99 | F2: 9.99 | G2: 6.7 | H2: 3.29 | I2: 86 | J2: Pet Supplies | K2: 1 | L2: 985 | M2: 248 | N2: 2477.52 | O2: 73 | P2: 34 | Q2: 7/23/2016 | R2: 4.8 | S2: 0.44 | T2: FBA | U2: 2 | V2: https://www.amazon.co.uk/dp/B01M72VYXM
C4: Saved from URL https://www.amazon.co.uk/s/ref=sr_pg_1?me=A1UV2AENXGRF1A&rh=i%3Amerchant-items&ie=UTF8&qid=1527491491
