Workbook

Sheet 源数据
B2: 科目
B4: 销量 | C4: =C7/C5 -> 43333.333
B5: 价格（不含增值税税） | C5: 150
C6: 总额 | D6: 单个 | E6: %
B7: 销售收入（年） | C7: 6500000 | D7: =+C5 -> 150 | E7: 1
B8: 产品成本（年） | C8: =C7*E8 -> 2210000 | D8: =C5*E8 -> 51 | E8: 0.34
B9: 产品毛利（销售毛利） | C9: =C7-C8 -> 4290000 | D9: =D7-D8 -> 99 | E9: =C9/C7 -> 0.66
B10: 平台佣金 | C10: =$C$7*E10 -> 975000 | D10: =$C$5*E10 -> 22.5 | E10: 0.15
B11: 平台费用 | C11: =$C$7*E11 -> 910000 | D11: =$C$5*E11 -> 21 | E11: 0.14
B12: 头程费用 | C12: =$C$7*E12 -> 520000 | D12: =$C$5*E12 -> 12 | E12: 0.08
B13: 广告费用 | C13: =$C$7*E13 -> 487500 | D13: =$C$5*E13 -> 11.25 | E13: 0.075
B14: 其他推广费用 | C14: =$C$7*E14 -> 195000 | D14: =$C$5*E14 -> 4.5 | E14: 0.03
B15: 代扣税 | C15: =$C$7*E15 -> 260000 | D15: =$C$5*E15 -> 6 | E15: 0.04
B16: 其它 | C16: =$C$7*E16 -> 130000 | D16: =$C$5*E16 -> 3 | E16: 0.02
B17: 运营成本小计（变动成本） | C17: =SUM(C10:C16) -> 3477500 | D17: =C17/$C$4 -> 80.25 | E17: =C17/C7 -> 0.535
B18: 净毛利率 | C18: =C9-C17 -> 812500 | D18: =D9-D17 -> 18.75 | E18: =C18/C7 -> 0.125
B19: 房租 | C19: 30000 | D19: =C19/$C$4 -> 0.69230769 | E19: =C19/$C$7 -> 0.0046153846
B20: 物业管理及水电费 | C20: 6000 | D20: =C20/$C$4 -> 0.13846154 | E20: =C20/$C$7 -> 0.00092307692
B21: 工资 | C21: 240000 | D21: =C21/$C$4 -> 5.5384615 | E21: =C21/$C$7 -> 0.036923077
B22: 社保公积金 | C22: 15000 | D22: =C22/$C$4 -> 0.34615385 | E22: =C22/$C$7 -> 0.0023076923
B23: 办公费用 | C23: 7000 | D23: =C23/$C$4 -> 0.16153846 | E23: =C23/$C$7 -> 0.0010769231
B24: 交通差旅费 | C24: 1000 | D24: =C24/$C$4 -> 0.023076923 | E24: =C24/$C$7 -> 0.00015384615
B25: 网络费用 | C25: 5000 | D25: =C25/$C$4 -> 0.11538462 | E25: =C25/$C$7 -> 0.00076923077
B26: 折旧费用 | C26: 8000 | D26: =C26/$C$4 -> 0.18461538 | E26: =C26/$C$7 -> 0.0012307692
B27: 财务费用 | C27: 2000 | D27: =C27/$C$4 -> 0.046153846 | E27: =C27/$C$7 -> 0.00030769231
B28: 经营成本小计（固定成本） | C28: =SUM(C19:C27) -> 314000 | D28: =C28/$C$4 -> 7.2461538 | E28: =C28/C7 -> 0.048307692
B29: 成本/费用合计 | C29: =C17+C28 -> 3791500 | D29: =C29/$C$4 -> 87.496154 | E29: =C29/C7 -> 0.58330769
B30: 息税前利润 | C30: =C9-C29 -> 498500 | D30: =C30/$C$4 -> 11.503846 | E30: =C30/C7 -> 0.076692308
B31: 利息费用 | E31: =C31/C7 -> 0
B32: 税前利润 | C32: =C30-C31 -> 498500 | E32: =C32/C7 -> 0.076692308
B33: 税金 | C33: =C32*0.13 -> 64805 | E33: =C33/C9 -> 0.015106061
B34: 税后净利润 | C34: =C32-C33 -> 433695 | D34: =C34/$C$4 -> 10.008346 | E34: =C34/C7 -> 0.066722308

Sheet 计算结果
B3: 产品名称： | C3: A项目 | E3: 计量单位： | F3: PCS | I3: =C3&"盈亏平衡分析图" -> A项目盈亏平衡分析图 | J3: ="数量（"&F3&"）" -> 数量（PCS）
B5: 项目名称 | C5: 成本项目（本） | E5: 项目名称 | F5: 数量单价（量） | I5: 生产数量 | J5: 边际贡献 | K5: 固定成本 | L5: 销售毛利
B6: 固定成本总额： | C6: =源数据!C28 -> 314000 | E6: 当前销量： | F6: =源数据!C4 -> 43333.333 | I6: 0 | J6: 0 | K6: =C6 -> 314000 | L6: =J6-K6 -> -314000
B7: 变动成本总额： | C7: =源数据!C8+源数据!C17 -> 5687500 | E7: 销售单价（不含税）： | F7: =源数据!C5 -> 150 | I7: =(LEFT(F6)+5)*(F6-MID(F6,2,LEN(F6)))/LEFT(F6) -> 90000 | J7: =ROUND(I7*C19,2) -> 1687500 | K7: =C6 -> 314000 | L7: =J7-K7 -> 1373500
B8: 成 本 总 额： | C8: =SUM(C6:C7) -> 6001500 | E8: 盈亏平衡销量： | F8: =C6/C19 -> 16746.667
B11: 项目名称 | C11: 单位成本（本） | E11: 项目名称 | F11: 收入毛利（利） | I11: 盈亏点销量垂直参考线：
B12: 单位固定成本: | C12: =C6/源数据!C4 -> 7.2461538 | E12: 销售收入： | F12: =F6*F7 -> 6500000 | I12: =$F$8 -> 16746.667 | J12: =(LEFT(J7)+1)*(J7-MID(J7,2,LEN(J7)))/LEFT(J7) -> 2000000
B13: 单位变动成本： | C13: =C7/源数据!C4 -> 131.25 | E13: 销售成本： | F13: =F6*C14 -> 6001500 | I13: =$F$8 -> 16746.667 | J13: =C6 -> 314000
B14: 单位成本总额： | C14: =SUM(C12:C13) -> 138.49615 | E14: 销售毛利： | F14: =F12-F13 -> 498500 | I14: =$F$8 -> 16746.667 | J14: 0
I15: =$F$8 -> 16746.667 | J15: =(LEFT(J7)+1)*(J7-MID(J7,2,LEN(J7)))/LEFT(J7)*-1 -> -2000000
B17: 项目名称 | C17: 边际贡献 | E17: 盈亏平衡分析 | I17: 当前销量垂直参考线：
B18: 边际贡献总额： | C18: =F6*C19 -> 812500 | E18: ="当"&C3&"销量为"&F6&F3&"，售价等于"&F7&"元/"&F3&"、单位变动成本为"&ROUND(C13,2)&"元/PCS"&"时，销量为"&ROUND(F8,2)&F3&"可达到盈亏平衡；将生产的"&F6&F3&"产品全部销售可实现销售毛利"&ROUND(F14,2)&"元。" -> 当A项目销量为43333.3333333333PCS，售价等于150元/PCS、单位变动成本为131.25元/PCS时，销量为16746.67PCS可达到盈亏平衡；将生产的43333.3333333333PCS产品全部销售可实现销售毛利498500元。 | I18: =$F$6 -> 43333.333 | J18: =(LEFT(J7)+1)*(J7-MID(J7,2,LEN(J7)))/LEFT(J7) -> 2000000
B19: 单位边际贡献： | C19: =F7-C13 -> 18.75 | I19: =$F$6 -> 43333.333 | J19: =C18 -> 812500
B20: 边际贡献率： | C20: =C19/F7 -> 0.125 | I20: =$F$6 -> 43333.333 | J20: =C6 -> 314000
I21: =$F$6 -> 43333.333 | J21: =F14 -> 498500
I22: =$F$6 -> 43333.333 | J22: =(LEFT(J7)+1)*(J7-MID(J7,2,LEN(J7)))/LEFT(J7)*-1 -> -2000000

Sheet 项目盈利试算
B1: 收入成本利润表-盈亏平衡图
E2: 销量 | F2: 固定成本 | G2: 可变成本 | H2: 总成本 | I2: 总收入 | J2: 利润
C3: 单位：元 | E3: 0 | F3: =$C$4 -> 314000 | G3: 0 | H3: =E3*$C$6+F3 -> 314000 | I3: =E3*$C$5 -> 0 | J3: =I3-H3 -> -314000
B4: 固定成本 | C4: =源数据!C28 -> 314000 | E4: 8000 | F4: =$C$4 -> 314000 | G4: =I4*0.535 -> 642000 | H4: =E4*$C$6+F4+G4 -> 1364000 | I4: =E4*$C$5 -> 1200000 | J4: =I4-H4 -> -164000
B5: 单 价 | C5: 150 | E5: 16000 | F5: =$C$4 -> 314000 | G5: =I5*0.535 -> 1284000 | H5: =E5*$C$6+F5+G5 -> 2414000 | I5: =E5*$C$5 -> 2400000 | J5: =I5-H5 -> -14000
B6: 单位变动成本 | C6: 51 | E6: 24000 | F6: =$C$4 -> 314000 | G6: =I6*0.535 -> 1926000 | H6: =E6*$C$6+F6+G6 -> 3464000 | I6: =E6*$C$5 -> 3600000 | J6: =I6-H6 -> 136000
B7: 单位边际贡献 | C7: =(C5-C6) -> 99 | E7: 32000 | F7: =$C$4 -> 314000 | G7: =I7*0.535 -> 2568000 | H7: =E7*$C$6+F7+G7 -> 4514000 | I7: =E7*$C$5 -> 4800000 | J7: =I7-H7 -> 286000
E8: 40000 | F8: =$C$4 -> 314000 | G8: =I8*0.535 -> 3210000 | H8: =E8*$C$6+F8+G8 -> 5564000 | I8: =E8*$C$5 -> 6000000 | J8: =I8-H8 -> 436000
B9: 项目盈利 | C9: =TEXT(源数据!C7-源数据!C8-源数据!C29,"盈利0；亏损0；平衡") -> 盈利498500 | E9: 48000 | F9: =$C$4 -> 314000 | G9: =I9*0.535 -> 3852000 | H9: =E9*$C$6+F9+G9 -> 6614000 | I9: =E9*$C$5 -> 7200000 | J9: =I9-H9 -> 586000
B14: 单价变动情况
B18: 单位变动成本变动情况
