Workbook
Name 数据: #REF!
Name 数据名称: #REF!

Sheet 运营库存周监控表（敏感分析，环比分析）
A1: 运营库存周监控表（敏感分析，环比分析）
A2: 序号 | B2: 关键词（产品名称） | C2: SKU | D2: ASIN | E2: 记录时间 | F2: price($) | I2: rank | L2: 周库存环比 | O2: 销售环比 | R2: 月均库存 | S2: 实际月库存周转率环比 | T2: 月均周转率 | U2: 产品趋势备注（升/降，平）
F3: 上周rank | G3: 本周rank | H3: 环比上周 | I3: 上周rank | J3: 本周rank | K3: 环比上周 | L3: 上周库存 | M3: 本周库存 | N3: 库存环比 | O3: 上周销量 | P3: 本周销量 | Q3: 本周月周转率
A4: 1 | F4: 5 | G4: 4 | H4: =-(G4-F4)/F4 -> 0.2 | I4: 5000 | J4: 4000 | K4: =-(J4-I4)/I4 -> 0.2 | L4: 300 | M4: 400 | N4: =(M4-L4)/L4 -> 0.33333333 | O4: 100 | P4: 110 | Q4: =(P4-O4)/O4 -> 0.1 | R4: 600 | S4: =P4*4/M4 -> 1.1 | T4: =(P4*4)/R4 -> 0.73333333
A5: 2
A6: 3
A7: 4
A8: 5
A9: 6
A10: 7
A11: 8
A12: 9
A13: 10
A14: 11
A15: 12
A16: 13
... A28: 25
A29: 使用指导：填入价格，排名，库存，销量即可以。看价格和销量及库存是否呈现一致规律，如果销量和库存不成正比或者环比率过大则有滞销风险。（表格中绿色标志为自动公式，其他区域为填写区域）
A30: 防止问题：1.不要找大卖家也在卖不出去的产品，这样做起来压力大。2.价值高的产品批量前先测试市场。 3.测试市场过程中刷单时候分清流量来源，如果刷单了一周或半个月都没达到理想状态，要么就是刷单力度小，要么就是产品竞争大或者没有市场
A31: 这个方法可以第一：防止库存挤压， 第二：防止断货，第三：明确销售变化，第四：更加明确你需要投入时间的货物业务
A32: 销量怀比是 =（本周销量-上周）/上周销量
A33: 周转率= 销量*4 /库存

Sheet 亚马逊站内站外运营追踪表
A1: 亚马逊站内站外运营追踪表（同时站外可追踪竞争对手，数据并可直接引用到运营库存周监控表中去）
A2: 项目 | B2: 站外追踪（可每隔7天登记一次） | M2: 站内追踪（每日登记或定期登记皆可）可以发现上述之间关系，便于找出原因，及广告型产品，同类产品比较，各变量之间关系比较。
A3: 日期 | B3: Type | C3: SKU | D3: Brand | E3: ASIN | F3: Track Date | G3: Price | H3: RANK | I3: product star | J3: review (数量） | K3: Note | L3: Inventory | M3: 总共花费 | N3: 点击率 | O3: 广告点击 | P3: 自然点击 | Q3: 总共点击 | R3: 订单销量 | S3: 广告点击/曝光 | T3: 广告Acos（广告成本/广告收入） | U3: 广告点击转化（广告订单量/广告点击） | V3: 转化率 | W3: 当天排名 | X3: 发出促销code
A4: 42884 | E4: a
A5: 42884 | E5: b
A6: 42884 | E6: a
A7: 42884 | E7: b
A8: 42885 | E8: a
A9: 42885 | E9: b
A10: 42885 | E10: a
A11: 42886 | E11: b
A12: 42887 | E12: b
A13: 42888
A14: 42889
A15: 42890
A16: 42891

Sheet 横版
A1: 项目 | B1: 星期一 | C1: 星期二 | D1: 星期三 | E1: 星期四 | F1: 星期五 | G1: 星期六 | H1: 星期日 | I1: 星期一 | J1: 星期二 | K1: 星期三 | L1: 星期四 | M1: 星期五 | N1: 星期六
A2: 日期 | B2: 42884 | C2: 42885 | D2: 42886 | E2: 42887 | F2: 42888 | G2: 42889 | H2: 42890 | I2: 42891 | J2: 42892 | K2: 42893 | L2: 42894 | M2: 42895 | N2: 42896
A3: 曝光量
A4: 总共花费 | B4: 15
A5: 点击率 | B5: 0.01
A6: 广告点击 | B6: 10
A7: 自然点击 | B7: =B8-B6 -> 2 | C7: =C8-C6 -> 0 | D7: =D8-D6 -> 0 | E7: =E8-E6 -> 0 | F7: =F8-F6 -> 0 | G7: =G8-G6 -> 0 | H7: =H8-H6 -> 0 | I7: =I8-I6 -> 0 | ... N7: =N8-N6 -> 0
A8: 总共点击 | B8: 12
A9: 订单 | B9: 10
A10: 广告点击/曝光
A11: 广告Acos（广告成本/广告收入）
A12: 广告点击转化（广告订单量/广告点击）
A13: 转化率 | B13: =B9/B8 -> 0.83333333 | C13: =C9/C8 -> #DIV/0! | D13: =D9/D8 -> #DIV/0! | E13: =E9/E8 -> #DIV/0! | F13: =F9/F8 -> #DIV/0! | G13: =G9/G8 -> #DIV/0! | H13: =H9/H8 -> #DIV/0! | I13: =I9/I8 -> #DIV/0! | ... N13: =N9/N8 -> #DIV/0!
A14: 当天排名 | B14: 1
A15: 发出促销code
A16: 可以发现上述之间关系，便于找出原因，及广告型产品，同类产品比较，各变量之间关系比较。

Sheet 库存确认汇总
A1: Product track table (模板 2016.11.10) | AA1: 单次/月均 | AB1: 存货周转率：使用/库存数*100% | AD1: 上周数据(无公式） | AQ1: 季度/（季度初+季度末）/2=标准3，为某资金/3=可以使用的某资金流转3次，标准：120.存货周转天数=360/存货周转率
A2: NO. | B2: Type | C2: SKU | D2: Brand | E2: ASIN | F2: 其它 | G2: Track Date | H2: Price | J2: Rank | L2: Product Star | O2: Review (数量） | Q2: Note | R2: Inventory（数量） | X2: Sales volume | AA2: Type | AB2: SKU | AC2: Brand | AD2: ASIN | AE2: 其它 | AF2: Track Date | AG2: Price | AI2: Rank | AK2: Product Star | AN2: Review (数量） | AP2: Note | AQ2: Inventory（数量） | AW2: Sales volume | AZ2: 手动
H3: 本周 | I3: 环比上周 | J3: 本周 | K3: 环比上周 | L3: 本周 | M3: 标准评级 | N3: 环比上周 | O3: 本周 | P3: 环比上周 | R3: 亚马逊本周 | S3: 亚马逊上周 | T3: 环比上周 | U3: 上周月周转率 | V3: 本次月周转率 | W3: 店铺库存量 | X3: 本周销量 | Y3: 销量环比 | Z3: 总销量 | AG3: 本周 | AH3: 环比上周 | AI3: 本周 | AJ3: 环比上周 | AK3: 本周 | AL3: 标准评级 | AM3: 环比上周 | AN3: 本周 | AO3: 环比上周 | AQ3: 本周 | AR3: 上周 | AS3: 环比上周 | AT3: 上周周转率 | AU3: 本周周转率 | AV3: 店铺库存 | AW3: 本周销量 | AX3: 销量环比 | AY3: 总销量 | AZ3: 第1周库存使用量 | BA3: 第2周库存使用量 | BB3: 第3周库存使用量 | BC3: 第4周库存最近使用量 | BD3: 一期差异 | BE3: 二期差异 | BF3: 三期差异 | BG3: 合计差异 | BH3: 合计库存量 | BI3: 库存周转率
A4: 1 | B4: =INDEX(本周库存数据整理表!A:A,MATCH($E:$E,本周库存数据整理表!$D:$D,0),1) -> iphone | C4: =INDEX(本周库存数据整理表!B:B,MATCH($E:$E,本周库存数据整理表!$D:$D,0),1) -> YQ5 | D4: =INDEX(本周库存数据整理表!C:C,MATCH($E:$E,本周库存数据整理表!$D:$D,0),1) -> EAV | E4: B0005 | F4: =INDEX(本周库存数据整理表!E:E,MATCH($E:$E,本周库存数据整理表!$D:$D,0),1) -> 0 | G4: =INDEX(本周库存数据整理表!F:F,MATCH($E:$E,本周库存数据整理表!$D:$D,0),1) -> 42754 | H4: =INDEX(本周库存数据整理表!G:G,MATCH(E:E,本周库存数据整理表!D:D,0),1) -> 23.99 | I4: =IF((H4-AG4)/AG4=0,"无变化",(H4-AG4)/AG4) -> 无变化 | J4: =INDEX(本周库存数据整理表!H:H,MATCH($E:$E,本周库存数据整理表!$D:$D,0),1) -> 3131 | K4: =-(J4-AI4)/AI4 -> 0 | L4: =INDEX(本周库存数据整理表!I:I,MATCH($E:$E,本周库存数据整理表!$D:$D,0),1) -> 3.7 | M4: 4 | N4: =IF((L4-AK4)/AK4=0,"无变化",(L4-AK4)/AK4) -> 无变化 | O4: =INDEX(本周库存数据整理表!J:J,MATCH($E:$E,本周库存数据整理表!$D:$D,0),1) -> 1004 | P4: =(O4-AN4)/AN4 -> 0 | Q4: =IFERROR(VLOOKUP(E4,本周库存数据整理表!D:K,8,0),"") -> 0 | R4: =IFERROR(INDEX(本周库存数据整理表!L:L,MATCH($E:$E,本周库存数据整理表!$D:$D,0),1),"无") -> 4000 | S4: =INDEX(库存确认汇总!AQ:AQ,MATCH($E:$E,库存确认汇总!$AD:$AD,0),1) -> 3004 | T4: =(R4-S4)/S4 -> 0.33155792 | U4: 0.27206946 | V4: =X4*4/W4 -> 3.9840319 | W4: =IFERROR(INDEX(本周库存数据整理表!M:M,MATCH($E:$E,本周库存数据整理表!$D:$D,0),1),"无") -> 2004 | X4: =INDEX(本周库存数据整理表!N:N,MATCH($E:$E,本周库存数据整理表!$D:$D,0),1) -> 1996 | Y4: =(X4-AW4)/AW4 -> 0.996 | Z4: =INDEX(本周库存数据整理表!#REF!,MATCH($E:$E,本周库存数据整理表!$D:$D,0),1) -> #REF! | AA4: iphone | AB4: YQ5 | AC4: EAV | AD4: B0005 | AE4: 0 | AF4: 42754 | AG4: 23.99 | AH4: -0.60010002 | AI4: 3131 | AJ4: 0.31816202 | AK4: 3.7 | AL4: 4 | AM4: 无变化 | AN4: 1004 | AO4: 1.3027523 | AP4: 0 | AQ4: 3004 | AR4: #N/A | AS4: #N/A | AT4: 0.27206946 | AU4: 1.996008 | AV4: 4000 | AW4: 1000 | AX4: 7.1300813 | AY4: #DIV/0! | AZ4: 500 | BA4: 600 | BB4: 4000 | BC4: 1163 | BD4: =AZ4-BA4 -> -100 | BE4: =BB4-BA4 -> 3400 | BF4: 2004 | BG4: =BD4+BE4+BF4 -> 5304 | BH4: =AZ4+BA4+BB4+BC4 -> 6263 | BI4: =-BG4/BC4 -> -4.5606191 | BJ4: =-BG4/BH4 -> -0.84687849
A5: 2 | B5: =INDEX(本周库存数据整理表!A:A,MATCH(E:E,本周库存数据整理表!D:D,0),1) -> iphone | C5: =INDEX(本周库存数据整理表!B:B,MATCH($E:$E,本周库存数据整理表!$D:$D,0),1) -> YQ2 | D5: =INDEX(本周库存数据整理表!C:C,MATCH($E:$E,本周库存数据整理表!$D:$D,0),1) -> EAV | E5: B0002 | F5: =INDEX(本周库存数据整理表!E:E,MATCH($E:$E,本周库存数据整理表!$D:$D,0),1) -> 0 | G5: =INDEX(本周库存数据整理表!F:F,MATCH($E:$E,本周库存数据整理表!$D:$D,0),1) -> 42754 | H5: =INDEX(本周库存数据整理表!G:G,MATCH(E:E,本周库存数据整理表!D:D,0),1) -> 20.99 | I5: =IF((H5-AG5)/AG5=0,"无变化",(H5-AG5)/AG5) -> 无变化 | J5: =INDEX(本周库存数据整理表!H:H,MATCH($E:$E,本周库存数据整理表!$D:$D,0),1) -> 3128 | K5: =-(J5-AI5)/AI5 -> 0 | L5: =INDEX(本周库存数据整理表!I:I,MATCH($E:$E,本周库存数据整理表!$D:$D,0),1) -> 4.1 | M5: 4.1 | N5: =IF((L5-AK5)/AK5=0,"无变化",(L5-AK5)/AK5) -> 无变化 | O5: =INDEX(本周库存数据整理表!J:J,MATCH($E:$E,本周库存数据整理表!$D:$D,0),1) -> 1001 | P5: =(O5-AN5)/AN5 -> 0 | Q5: =IFERROR(VLOOKUP(E5,本周库存数据整理表!D:K,8,0),"") -> 0 | R5: =IFERROR(INDEX(本周库存数据整理表!L:L,MATCH($E:$E,本周库存数据整理表!$D:$D,0),1),"无") -> 4000 | S5: =INDEX(库存确认汇总!AQ:AQ,MATCH($E:$E,库存确认汇总!$AD:$AD,0),1) -> 3001 | T5: =(R5-S5)/S5 -> 0.33288904 | U5: 0 | V5: =X5*4/W5 -> 3.996002 | W5: =IFERROR(INDEX(本周库存数据整理表!M:M,MATCH($E:$E,本周库存数据整理表!$D:$D,0),1),"无") -> 2001 | X5: =INDEX(本周库存数据整理表!N:N,MATCH($E:$E,本周库存数据整理表!$D:$D,0),1) -> 1999 | Y5: =(X5-AW5)/AW5 -> 0.999 | Z5: =INDEX(本周库存数据整理表!#REF!,MATCH($E:$E,本周库存数据整理表!$D:$D,0),1) -> #REF! | AA5: iphone | AB5: YQ2 | AC5: EAV | AD5: B0002 | AE5: 0 | AF5: 42754 | AG5: 20.99 | AH5: -0.65010835 | AI5: 3128 | AJ5: -0.20493066 | AK5: 4.1 | AL5: 4.1 | AM5: 无变化 | AN5: 1001 | AO5: 4.3244681 | AP5: 0 | AQ5: 3001 | AR5: #N/A | AS5: #N/A | AT5: 0 | AU5: 1.9990005 | AV5: 4000 | AW5: 1000 | AX5: 15.949153 | AY5: #DIV/0! | AZ5: 501 | BA5: 601 | BB5: 4000 | BC5: 288 | BD5: =AZ5-BA5 -> -100 | BE5: =BB5-BA5 -> 3399 | BF5: 2001 | BG5: =BD5+BE5+BF5 -> 5300 | BH5: =AZ5+BA5+BB5+BC5 -> 5390 | BI5: =-BG5/BC5 -> -18.402778 | BJ5: =-BG5/BH5 -> -0.98330241
A6: 3 | B6: =INDEX(本周库存数据整理表!A:A,MATCH(E:E,本周库存数据整理表!D:D,0),1) -> iphone | C6: =INDEX(本周库存数据整理表!B:B,MATCH($E:$E,本周库存数据整理表!$D:$D,0),1) -> YQ3 | D6: =INDEX(本周库存数据整理表!C:C,MATCH($E:$E,本周库存数据整理表!$D:$D,0),1) -> EAV | E6: B0003 | F6: =INDEX(本周库存数据整理表!E:E,MATCH($E:$E,本周库存数据整理表!$D:$D,0),1) -> 0 | G6: =INDEX(本周库存数据整理表!F:F,MATCH($E:$E,本周库存数据整理表!$D:$D,0),1) -> 42754 | H6: =INDEX(本周库存数据整理表!G:G,MATCH(E:E,本周库存数据整理表!D:D,0),1) -> 21.99 | I6: =IF((H6-AG6)/AG6=0,"无变化",(H6-AG6)/AG6) -> 无变化 | J6: =INDEX(本周库存数据整理表!H:H,MATCH($E:$E,本周库存数据整理表!$D:$D,0),1) -> 3129 | K6: =-(J6-AI6)/AI6 -> 0 | L6: =INDEX(本周库存数据整理表!I:I,MATCH($E:$E,本周库存数据整理表!$D:$D,0),1) -> 3.7 | M6: 4 | N6: =IF((L6-AK6)/AK6=0,"无变化",(L6-AK6)/AK6) -> 无变化 | O6: =INDEX(本周库存数据整理表!J:J,MATCH($E:$E,本周库存数据整理表!$D:$D,0),1) -> 1002 | P6: =(O6-AN6)/AN6 -> 0 | Q6: =IFERROR(VLOOKUP(E6,本周库存数据整理表!D:K,8,0),"") -> 0 | R6: =IFERROR(INDEX(本周库存数据整理表!L:L,MATCH($E:$E,本周库存数据整理表!$D:$D,0),1),"无") -> 4000 | S6: =INDEX(库存确认汇总!AQ:AQ,MATCH($E:$E,库存确认汇总!$AD:$AD,0),1) -> 3002 | T6: =(R6-S6)/S6 -> 0.33244504 | U6: 0 | V6: =X6*4/W6 -> 3.992008 | W6: =IFERROR(INDEX(本周库存数据整理表!M:M,MATCH($E:$E,本周库存数据整理表!$D:$D,0),1),"无") -> 2002 | X6: =INDEX(本周库存数据整理表!N:N,MATCH($E:$E,本周库存数据整理表!$D:$D,0),1) -> 1998 | Y6: =(X6-AW6)/AW6 -> 0.998 | Z6: =INDEX(本周库存数据整理表!#REF!,MATCH($E:$E,本周库存数据整理表!$D:$D,0),1) -> #REF! | AA6: iphone | AB6: YQ3 | AC6: EAV | AD6: B0003 | AE6: 0 | AF6: 42754 | AG6: 21.99 | AH6: #DIV/0! | AI6: 3129 | AJ6: 0.62201015 | AK6: 3.7 | AL6: 4 | AM6: -0.075 | AN6: 1002 | AO6: 15.983051 | AP6: 0 | AQ6: 3002 | AR6: #N/A | AS6: #N/A | AT6: 0 | AU6: 1.998002 | AV6: 4000 | AW6: 1000 | AX6: #DIV/0! | AY6: #DIV/0! | AZ6: 502 | BA6: 602 | BB6: 4000 | BC6: 468 | BD6: =AZ6-BA6 -> -100 | BE6: =BB6-BA6 -> 3398 | BF6: 2002 | BG6: =BD6+BE6+BF6 -> 5300 | BH6: =AZ6+BA6+BB6+BC6 -> 5572 | BI6: =-BG6/BC6 -> -11.324786 | BJ6: =-BG6/BH6 -> -0.95118449
A7: 4 | B7: =INDEX(本周库存数据整理表!A:A,MATCH(E:E,本周库存数据整理表!D:D,0),1) -> iphone | C7: =INDEX(本周库存数据整理表!B:B,MATCH($E:$E,本周库存数据整理表!$D:$D,0),1) -> YQ4 | D7: =INDEX(本周库存数据整理表!C:C,MATCH($E:$E,本周库存数据整理表!$D:$D,0),1) -> EAV | E7: B0004 | F7: =INDEX(本周库存数据整理表!E:E,MATCH($E:$E,本周库存数据整理表!$D:$D,0),1) -> 0 | G7: =INDEX(本周库存数据整理表!F:F,MATCH($E:$E,本周库存数据整理表!$D:$D,0),1) -> 42754 | H7: 9.99 | I7: =IF((H7-AG7)/AG7=0,"无变化",(H7-AG7)/AG7) -> 无变化 | J7: =INDEX(本周库存数据整理表!H:H,MATCH($E:$E,本周库存数据整理表!$D:$D,0),1) -> 3130 | K7: =-(J7-AI7)/AI7 -> 0 | L7: =INDEX(本周库存数据整理表!I:I,MATCH($E:$E,本周库存数据整理表!$D:$D,0),1) -> 3.4 | M7: 4 | N7: =IF((L7-AK7)/AK7=0,"无变化",(L7-AK7)/AK7) -> 无变化 | O7: =INDEX(本周库存数据整理表!J:J,MATCH($E:$E,本周库存数据整理表!$D:$D,0),1) -> 1003 | P7: =(O7-AN7)/AN7 -> 0 | Q7: =IFERROR(VLOOKUP(E7,本周库存数据整理表!D:K,8,0),"") -> 0 | R7: =IFERROR(INDEX(本周库存数据整理表!L:L,MATCH($E:$E,本周库存数据整理表!$D:$D,0),1),"无") -> 4000 | S7: =INDEX(库存确认汇总!AQ:AQ,MATCH($E:$E,库存确认汇总!$AD:$AD,0),1) -> 3003 | T7: =(R7-S7)/S7 -> 0.33200133 | U7: 0.36746257 | V7: =X7*4/W7 -> 3.988018 | W7: =IFERROR(INDEX(本周库存数据整理表!M:M,MATCH($E:$E,本周库存数据整理表!$D:$D,0),1),"无") -> 2003 | X7: =INDEX(本周库存数据整理表!N:N,MATCH($E:$E,本周库存数据整理表!$D:$D,0),1) -> 1997 | Y7: =(X7-AW7)/AW7 -> 0.997 | Z7: =INDEX(本周库存数据整理表!#REF!,MATCH($E:$E,本周库存数据整理表!$D:$D,0),1) -> #REF! | AA7: iphone | AB7: YQ4 | AC7: EAV | AD7: B0004 | AE7: 0 | AF7: 42754 | AG7: 9.99 | AH7: 无变化 | AI7: 3130 | AJ7: -0.01228978 | AK7: 3.4 | AL7: 4 | AM7: -0.17073171 | AN7: 1003 | AO7: -0.73715933 | AP7: 0 | AQ7: 3003 | AR7: #N/A | AS7: #N/A | AT7: 0.36746257 | AU7: 1.9970045 | AV7: 4000 | AW7: 1000 | AX7: 2.6101083 | AY7: #DIV/0! | AZ7: 503 | BA7: 603 | BB7: 4000 | BC7: 2018 | BD7: =AZ7-BA7 -> -100 | BE7: =BB7-BA7 -> 3397 | BF7: 2003 | BG7: =BD7+BE7+BF7 -> 5300 | BH7: =AZ7+BA7+BB7+BC7 -> 7124 | BI7: 0.2 | BJ7: =-BG7/BH7 -> -0.74396407
A8: 5 | B8: =INDEX(本周库存数据整理表!A:A,MATCH(E:E,本周库存数据整理表!D:D,0),1) -> iphone | C8: =INDEX(本周库存数据整理表!B:B,MATCH($E:$E,本周库存数据整理表!$D:$D,0),1) -> YQ1 | D8: =INDEX(本周库存数据整理表!C:C,MATCH($E:$E,本周库存数据整理表!$D:$D,0),1) -> EAV | E8: B0001 | F8: =INDEX(本周库存数据整理表!E:E,MATCH($E:$E,本周库存数据整理表!$D:$D,0),1) -> 0 | G8: =INDEX(本周库存数据整理表!F:F,MATCH($E:$E,本周库存数据整理表!$D:$D,0),1) -> 42754 | H8: =INDEX(本周库存数据整理表!G:G,MATCH($E:$E,本周库存数据整理表!$D:$D,0),1) -> 19.99 | I8: =IF((H8-AG8)/AG8=0,"无变化",(H8-AG8)/AG8) -> 无变化 | J8: =INDEX(本周库存数据整理表!H:H,MATCH($E:$E,本周库存数据整理表!$D:$D,0),1) -> 3127 | K8: =-(J8-AI8)/AI8 -> 0 | L8: =INDEX(本周库存数据整理表!I:I,MATCH($E:$E,本周库存数据整理表!$D:$D,0),1) -> 4.1 | M8: 4 | N8: =IF((L8-AK8)/AK8=0,"无变化",(L8-AK8)/AK8) -> 无变化 | O8: =INDEX(本周库存数据整理表!J:J,MATCH($E:$E,本周库存数据整理表!$D:$D,0),1) -> 1000 | P8: =(O8-AN8)/AN8 -> 0 | Q8: =IFERROR(VLOOKUP(E8,本周库存数据整理表!D:K,8,0),"") -> 0 | R8: =IFERROR(INDEX(本周库存数据整理表!L:L,MATCH($E:$E,本周库存数据整理表!$D:$D,0),1),"无") -> 4000 | S8: =INDEX(库存确认汇总!AQ:AQ,MATCH($E:$E,库存确认汇总!$AD:$AD,0),1) -> 3000 | T8: =(R8-S8)/S8 -> 0.33333333 | U8: 0.16462347 | V8: =X8*4/W8 -> 4 | W8: =IFERROR(INDEX(本周库存数据整理表!M:M,MATCH($E:$E,本周库存数据整理表!$D:$D,0),1),"无") -> 2000 | X8: =INDEX(本周库存数据整理表!N:N,MATCH($E:$E,本周库存数据整理表!$D:$D,0),1) -> 2000 | Y8: =(X8-AW8)/AW8 -> 1 | Z8: =INDEX(本周库存数据整理表!#REF!,MATCH($E:$E,本周库存数据整理表!$D:$D,0),1) -> #REF! | AA8: iphone | AB8: YQ1 | AC8: EAV | AD8: B0001 | AE8: 0 | AF8: 42754 | AG8: 19.99 | AH8: 1.001001 | AI8: 3127 | AJ8: 0.39946226 | AK8: 4.1 | AL8: 4 | AM8: 无变化 | AN8: 1000 | AO8: -0.73794549 | AP8: 0 | AQ8: 3000 | AR8: #N/A | AS8: #N/A | AT8: 0.16462347 | AU8: 2 | AV8: 4000 | AW8: 1000 | AX8: 4.4347826 | AY8: #DIV/0! | AZ8: 504 | BA8: 604 | BB8: 4000 | BC8: 2021 | BD8: =AZ8-BA8 -> -100 | BE8: =BB8-BA8 -> 3396 | BF8: 2000 | BG8: =BD8+BE8+BF8 -> 5296 | BH8: =AZ8+BA8+BB8+BC8 -> 7129 | BI8: 0.05 | BJ8: =-BG8/BH8 -> -0.74288119
A9: 6 | B9: =INDEX(本周库存数据整理表!A:A,MATCH(E:E,本周库存数据整理表!D:D,0),1) -> iphone | C9: =INDEX(本周库存数据整理表!B:B,MATCH($E:$E,本周库存数据整理表!$D:$D,0),1) -> YQ6 | D9: =INDEX(本周库存数据整理表!C:C,MATCH($E:$E,本周库存数据整理表!$D:$D,0),1) -> EAV | E9: B0006 | F9: =INDEX(本周库存数据整理表!E:E,MATCH($E:$E,本周库存数据整理表!$D:$D,0),1) -> 0 | G9: =INDEX(本周库存数据整理表!F:F,MATCH($E:$E,本周库存数据整理表!$D:$D,0),1) -> 42754 | H9: =INDEX(本周库存数据整理表!G:G,MATCH($E:$E,本周库存数据整理表!$D:$D,0),1) -> 24.99 | I9: =IF((H9-AG9)/AG9=0,"无变化",(H9-AG9)/AG9) -> 无变化 | J9: =INDEX(本周库存数据整理表!H:H,MATCH($E:$E,本周库存数据整理表!$D:$D,0),1) -> 3132 | K9: =-(J9-AI9)/AI9 -> 0 | L9: =INDEX(本周库存数据整理表!I:I,MATCH($E:$E,本周库存数据整理表!$D:$D,0),1) -> 4 | M9: 3.7 | N9: =IF((L9-AK9)/AK9=0,"无变化",(L9-AK9)/AK9) -> 无变化 | O9: =INDEX(本周库存数据整理表!J:J,MATCH($E:$E,本周库存数据整理表!$D:$D,0),1) -> 1005 | P9: =(O9-AN9)/AN9 -> 0 | Q9: =IFERROR(VLOOKUP(E9,本周库存数据整理表!D:K,8,0),"") -> 0 | R9: =IFERROR(INDEX(本周库存数据整理表!L:L,MATCH($E:$E,本周库存数据整理表!$D:$D,0),1),"无") -> 4000 | S9: =INDEX(库存确认汇总!AQ:AQ,MATCH($E:$E,库存确认汇总!$AD:$AD,0),1) -> 3005 | T9: =(R9-S9)/S9 -> 0.33111481 | U9: 0 | V9: =X9*4/W9 -> 3.9800499 | W9: =IFERROR(INDEX(本周库存数据整理表!M:M,MATCH($E:$E,本周库存数据整理表!$D:$D,0),1),"无") -> 2005 | X9: =INDEX(本周库存数据整理表!N:N,MATCH($E:$E,本周库存数据整理表!$D:$D,0),1) -> 1995 | Y9: =(X9-AW9)/AW9 -> 0.995 | Z9: =INDEX(本周库存数据整理表!#REF!,MATCH($E:$E,本周库存数据整理表!$D:$D,0),1) -> #REF! | AA9: iphone | AB9: YQ6 | AC9: EAV | AD9: B0006 | AE9: 0 | AF9: 42754 | AG9: 24.99 | AH9: -0.5902607 | AI9: 3132 | AJ9: 0.81490456 | AK9: 4 | AL9: 3.7 | AM9: 0.17647059 | AN9: 1005 | AO9: 3.8317308 | AP9: 0 | AQ9: 3005 | AR9: #N/A | AS9: #N/A | AT9: 0 | AU9: 1.9950125 | AV9: 4000 | AW9: 1000 | AX9: #DIV/0! | AY9: #DIV/0! | AZ9: 505 | BA9: 605 | BB9: 4000 | BC9: 296 | BD9: =AZ9-BA9 -> -100 | BE9: =BB9-BA9 -> 3395 | BF9: 2005 | BG9: =BD9+BE9+BF9 -> 5300 | BH9: =AZ9+BA9+BB9+BC9 -> 5406 | BI9: =-BG9/BC9 -> -17.905405 | BJ9: =-BG9/BH9 -> -0.98039216
A10: 7 | B10: =INDEX(本周库存数据整理表!A:A,MATCH(E:E,本周库存数据整理表!D:D,0),1) -> iphone | C10: =INDEX(本周库存数据整理表!B:B,MATCH($E:$E,本周库存数据整理表!$D:$D,0),1) -> YQ7 | D10: =INDEX(本周库存数据整理表!C:C,MATCH($E:$E,本周库存数据整理表!$D:$D,0),1) -> EAV | E10: B0007 | F10: =INDEX(本周库存数据整理表!E:E,MATCH($E:$E,本周库存数据整理表!$D:$D,0),1) -> 0 | G10: =INDEX(本周库存数据整理表!F:F,MATCH($E:$E,本周库存数据整理表!$D:$D,0),1) -> 42754 | H10: =INDEX(本周库存数据整理表!G:G,MATCH($E:$E,本周库存数据整理表!$D:$D,0),1) -> 25.99 | I10: =IF((H10-AG10)/AG10=0,"无变化",(H10-AG10)/AG10) -> 无变化 | J10: =INDEX(本周库存数据整理表!H:H,MATCH($E:$E,本周库存数据整理表!$D:$D,0),1) -> 3133 | K10: =-(J10-AI10)/AI10 -> 0 | L10: =INDEX(本周库存数据整理表!I:I,MATCH($E:$E,本周库存数据整理表!$D:$D,0),1) -> 3.9 | M10: 4.6 | N10: =IF((L10-AK10)/AK10=0,"无变化",(L10-AK10)/AK10) -> 无变化 | O10: =INDEX(本周库存数据整理表!J:J,MATCH($E:$E,本周库存数据整理表!$D:$D,0),1) -> 1006 | P10: =(O10-AN10)/AN10 -> 0 | Q10: =IFERROR(VLOOKUP(E10,本周库存数据整理表!D:K,8,0),"") -> 0 | R10: =IFERROR(INDEX(本周库存数据整理表!L:L,MATCH($E:$E,本周库存数据整理表!$D:$D,0),1),"无") -> 4000 | S10: =INDEX(库存确认汇总!AQ:AQ,MATCH($E:$E,库存确认汇总!$AD:$AD,0),1) -> 3006 | T10: =(R10-S10)/S10 -> 0.33067199 | U10: 0.66501241 | V10: =X10*4/W10 -> 3.9760718 | W10: =IFERROR(INDEX(本周库存数据整理表!M:M,MATCH($E:$E,本周库存数据整理表!$D:$D,0),1),"无") -> 2006 | X10: =INDEX(本周库存数据整理表!N:N,MATCH($E:$E,本周库存数据整理表!$D:$D,0),1) -> 1994 | Y10: =(X10-AW10)/AW10 -> 0.994 | Z10: =INDEX(本周库存数据整理表!#REF!,MATCH($E:$E,本周库存数据整理表!$D:$D,0),1) -> #REF! | AA10: iphone | AB10: YQ7 | AC10: EAV | AD10: B0007 | AE10: 0 | AF10: 42754 | AG10: 25.99 | AH10: -0.62866124 | AI10: 3133 | AJ10: 0.61628904 | AK10: 3.9 | AL10: 4.6 | AM10: -0.11363636 | AN10: 1006 | AO10: 3.1916667 | AP10: 0 | AQ10: 3006 | AR10: #N/A | AS10: #N/A | AT10: 0.66501241 | AU10: 1.9940179 | AV10: 4000 | AW10: 1000 | AX10: 12.513514 | AY10: #DIV/0! | AZ10: 506 | BA10: 606 | BB10: 4000 | BC10: 2395 | BD10: =AZ10-BA10 -> -100 | BE10: =BB10-BA10 -> 3394 | BF10: 2006 | BG10: =BD10+BE10+BF10 -> 5300 | BH10: =AZ10+BA10+BB10+BC10 -> 7507 | BI10: 0.86 | BJ10: =-BG10/BH10 -> -0.70600773
A11: 8 | B11: =INDEX(本周库存数据整理表!A:A,MATCH(E:E,本周库存数据整理表!D:D,0),1) -> iphone | C11: =INDEX(本周库存数据整理表!B:B,MATCH($E:$E,本周库存数据整理表!$D:$D,0),1) -> YQ8 | D11: =INDEX(本周库存数据整理表!C:C,MATCH($E:$E,本周库存数据整理表!$D:$D,0),1) -> EAV | E11: B0008 | F11: =INDEX(本周库存数据整理表!E:E,MATCH($E:$E,本周库存数据整理表!$D:$D,0),1) -> 0 | G11: =INDEX(本周库存数据整理表!F:F,MATCH($E:$E,本周库存数据整理表!$D:$D,0),1) -> 42754 | H11: =INDEX(本周库存数据整理表!G:G,MATCH($E:$E,本周库存数据整理表!$D:$D,0),1) -> 26.99 | I11: =IF((H11-AG11)/AG11=0,"无变化",(H11-AG11)/AG11) -> 无变化 | J11: =INDEX(本周库存数据整理表!H:H,MATCH($E:$E,本周库存数据整理表!$D:$D,0),1) -> 3134 | K11: =-(J11-AI11)/AI11 -> 0 | L11: =INDEX(本周库存数据整理表!I:I,MATCH($E:$E,本周库存数据整理表!$D:$D,0),1) -> 4.4 | M11: 4.2 | N11: =IF((L11-AK11)/AK11=0,"无变化",(L11-AK11)/AK11) -> 无变化 | O11: =INDEX(本周库存数据整理表!J:J,MATCH($E:$E,本周库存数据整理表!$D:$D,0),1) -> 1007 | P11: =(O11-AN11)/AN11 -> 0 | Q11: =IFERROR(VLOOKUP(E11,本周库存数据整理表!D:K,8,0),"") -> 0 | R11: =IFERROR(INDEX(本周库存数据整理表!L:L,MATCH($E:$E,本周库存数据整理表!$D:$D,0),1),"无") -> 4000 | S11: =INDEX(库存确认汇总!AQ:AQ,MATCH($E:$E,库存确认汇总!$AD:$AD,0),1) -> 3007 | T11: =(R11-S11)/S11 -> 0.33022946 | U11: 0.98019802 | V11: =X11*4/W11 -> 3.9720977 | W11: =IFERROR(INDEX(本周库存数据整理表!M:M,MATCH($E:$E,本周库存数据整理表!$D:$D,0),1),"无") -> 2007 | X11: =INDEX(本周库存数据整理表!N:N,MATCH($E:$E,本周库存数据整理表!$D:$D,0),1) -> 1993 | Y11: =(X11-AW11)/AW11 -> 0.993 | Z11: =INDEX(本周库存数据整理表!#REF!,MATCH($E:$E,本周库存数据整理表!$D:$D,0),1) -> #REF! | AA11: iphone | AB11: YQ8 | AC11: EAV | AD11: B0008 | AE11: 0 | AF11: 42754 | AG11: 26.99 | AH11: -0.55009168 | AI11: 3134 | AJ11: 0.60736657 | AK11: 4.4 | AL11: 4.2 | AM11: 0.18918919 | AN11: 1007 | AO11: 6.4044118 | AP11: 0 | AQ11: 3007 | AR11: #N/A | AS11: #N/A | AT11: 0.98019802 | AU11: 1.9930244 | AV11: 4000 | AW11: 1000 | AX11: 10.764706 | AZ11: 507 | BA11: 607 | BB11: 4000 | BC11: 341 | BD11: =AZ11-BA11 -> -100 | BE11: =BB11-BA11 -> 3393 | BF11: 2007 | BG11: =BD11+BE11+BF11 -> 5300 | BH11: =AZ11+BA11+BB11+BC11 -> 5455 | BI11: =-BG11/BC11 -> -15.542522 | BJ11: =-BG11/BH11 -> -0.9715857
A12: 本表自动匹配本周库存数据整理表数据进行分析环比价格和其它信息对比，本周库存数据整理表源于后台FBA库存导出数据。 | AA12: 本部分数据只需要复制左边的上周数据的值和数字格式粘贴到右边即可，左边则自动计算环比和匹配数据源。

Sheet 本周库存数据整理表
A1: 本周库存整理表
A2: Type | B2: SKU | C2: Brand | D2: ASIN | E2: 其它 | F2: Track Date | G2: Price | H2: RANK | I2: product star | J2: review (数量） | K2: Note | L2: Inventory（上周库存） | M2: （上周库存）Store inventory | N2: Sale
A3: iphone | B3: YQ1 | C3: EAV | D3: B0001 | F3: 42754 | G3: 19.99 | H3: 3127 | I3: 4.1 | J3: 1000 | L3: 4000 | M3: 2000 | N3: =L3-M3 -> 2000
A4: iphone | B4: YQ2 | C4: EAV | D4: B0002 | F4: 42754 | G4: 20.99 | H4: 3128 | I4: 4.1 | J4: 1001 | L4: 4000 | M4: 2001 | N4: =L4-M4 -> 1999
A5: iphone | B5: YQ3 | C5: EAV | D5: B0003 | F5: 42754 | G5: 21.99 | H5: 3129 | I5: 3.7 | J5: 1002 | L5: 4000 | M5: 2002 | N5: =L5-M5 -> 1998
A6: iphone | B6: YQ4 | C6: EAV | D6: B0004 | F6: 42754 | G6: 22.99 | H6: 3130 | I6: 3.4 | J6: 1003 | L6: 4000 | M6: 2003 | N6: =L6-M6 -> 1997
A7: iphone | B7: YQ5 | C7: EAV | D7: B0005 | F7: 42754 | G7: 23.99 | H7: 3131 | I7: 3.7 | J7: 1004 | L7: 4000 | M7: 2004 | N7: =L7-M7 -> 1996
A8: iphone | B8: YQ6 | C8: EAV | D8: B0006 | F8: 42754 | G8: 24.99 | H8: 3132 | I8: 4 | J8: 1005 | L8: 4000 | M8: 2005 | N8: =L8-M8 -> 1995
A9: iphone | B9: YQ7 | C9: EAV | D9: B0007 | F9: 42754 | G9: 25.99 | H9: 3133 | I9: 3.9 | J9: 1006 | L9: 4000 | M9: 2006 | N9: =L9-M9 -> 1994
A10: iphone | B10: YQ8 | C10: EAV | D10: B0008 | F10: 42754 | G10: 26.99 | H10: 3134 | I10: 4.4 | J10: 1007 | L10: 4000 | M10: 2007 | N10: =L10-M10 -> 1993

Sheet 库存记录数据源
A1: Type | B1: SKU | C1: Brand | D1: ASIN | E1: mAh | F1: Track Date | G1: Price | H1: RANK | I1: product star | J1: review (数量） | K1: Note | L1: Inventory（数量） | M1: Store inventory | N1: Sale
A2: iphone | B2: YQ1 | C2: EAV | D2: B0001 | F2: 42754 | G2: 19.99 | H2: 3127 | I2: 4.1 | J2: 1000 | L2: 3000 | M2: 2000 | N2: 1000
A3: iphone | B3: YQ2 | C3: EAV | D3: B0002 | F3: 42754 | G3: 20.99 | H3: 3128 | I3: 4.1 | J3: 1001 | L3: 3001 | M3: 2001 | N3: 1000
A4: iphone | B4: YQ3 | C4: EAV | D4: B0003 | F4: 42754 | G4: 21.99 | H4: 3129 | I4: 3.7 | J4: 1002 | L4: 3002 | M4: 2002 | N4: 1000
A5: iphone | B5: YQ4 | C5: EAV | D5: B0004 | F5: 42754 | G5: 22.99 | H5: 3130 | I5: 3.4 | J5: 1003 | L5: 3003 | M5: 2003 | N5: 1000
A6: iphone | B6: YQ5 | C6: EAV | D6: B0005 | F6: 42754 | G6: 23.99 | H6: 3131 | I6: 3.7 | J6: 1004 | L6: 3004 | M6: 2004 | N6: 1000
A7: iphone | B7: YQ6 | C7: EAV | D7: B0006 | F7: 42754 | G7: 24.99 | H7: 3132 | I7: 4 | J7: 1005 | L7: 3005 | M7: 2005 | N7: 1000
A8: iphone | B8: YQ7 | C8: EAV | D8: B0007 | F8: 42754 | G8: 25.99 | H8: 3133 | I8: 3.9 | J8: 1006 | L8: 3006 | M8: 2006 | N8: 1000
A9: iphone | B9: YQ8 | C9: EAV | D9: B0008 | F9: 42754 | G9: 26.99 | H9: 3134 | I9: 4.4 | J9: 1007 | L9: 3007 | M9: 2007 | N9: 1000
