Workbook

Sheet 运营总表
A1: Date | B1: 买家访问次数 | C1: 订单商品数量转化率 | D1: 销量 | E1: 多渠道数量 | F1: 商品销售额 | G1: 退款量 | H1: 退款金额 | I1: Promote折扣 | J1: 促销占比 | K1: 广告花费 | L1: ACoAs | M1: 曝光量 | N1: 点击量 | O1: 点击率 | P1: 直接订单量 | Q1: 直接销售额 | R1: 直接订单量占比 | S1: 间接订单量

Sheet 推广计划
A1: 推广计划
A2: 推广计划时长： | B2: 4周 | D2: 前期准备 | E2: 负责人 | F2: 完成情况 | G2: 备注
A3: 目标排名 | D3: 市场调研
D4: 关键词规划
A5: 推广期测评量： | D5: 链接文案
D6: 图片需求
D7: 下采购单
A8: 重点推广关键词： | D8: 头程发货
D9: 推广计划
A11: 推广规划
A12: 推广周期 | C12: 上线第1周 | D12: 上线第2周 | E12: 上线第3周 | F12: 上线第4周 | G12: 第一阶段推广期结束
A13: 售价
A14: 测评 | B14: 留评单：
B15: 免评单（包含留feedback）：
B16: 总量
B17: 预估链接review数
A18: Q&A | B18: 文字
B19: 视频
A20: 站内广告 | B20: 自动
B21: 广泛
B22: 词组
B23: 精准
B24: 类目定投
B25: ASIN定投
B26: 品牌广告
A27: 其他动作(Coupon, Promotion, giveaway, 站内回访, 站内索评,秒杀)
A28: 目标排名 | B28: 大类排名
B29: 小类排名
A30: 主打关键词

Sheet 推广记录表
A1: 产品推广记录表
A4: 周推广目的 | C4: 周 | D4: 日 | E4: 刷单 关键词 | F4: 关键词排名 | H4: 流量 | I4: 转化率 | J4: 实际转化率 (自然订单) | L4: 订单 | O4: 大类排名 | P4: 小类排名 | Q4: 售价 | R4: 评论数量 | S4: Q&A数量 | T4: 星级评分 | U4: 广告曝光 | V4: 广告点击 | W4: 广告 点击率 | X4: 广告花费 | Y4: 广告直接订单 | Z4: 广告直接销售额 | AA4: 站内推广动作 | AB4: 站外推广动作 | AC4: 周推广总结
B5: ASIN | F5: 自然排名 | G5: 广告排名 | K5: 总订单 | L5: 自然订单 | M5: 广告订单 | N5: 站外送测
A6: 1. 链接因安全问题被下架近10天, 29号恢复在售, 重新进行链接的转化激活以及引流 2. 站内建立引流的广告结构,配合站外推词 3. 页面优惠券 进行活动流量入口布局及吸引转化 | C6: Week1 | D6: 44593 | H6: =SUMIF(运营总表!A:A,D:D,运营总表!B:B) -> 0 | I6: =SUMIF(运营总表!A:A,D:D,运营总表!C:C) -> 0 | J6: / | K6: =SUMIF(运营总表!A:A,D:D,运营总表!D:D) -> 0 | L6: / | M6: / | N6: / | U6: =SUMIF(运营总表!A:A,D:D,运营总表!M:M) -> 0 | V6: =SUMIF(运营总表!A:A,D:D,运营总表!N:N) -> 0 | W6: =IFERROR(V6/U6,0) -> 0 | X6: =SUMIF(运营总表!A:A,D:D,运营总表!K:K) -> 0 | Y6: =SUMIF(运营总表!A:A,D:D,运营总表!P:P) -> 0 | Z6: =SUMIF(运营总表!A:A,D:D,运营总表!Q:Q) -> 0
D7: 44594 | H7: =SUMIF(运营总表!A:A,D:D,运营总表!B:B) -> 0 | I7: =SUMIF(运营总表!A:A,D:D,运营总表!C:C) -> 0 | J7: / | K7: =SUMIF(运营总表!A:A,D:D,运营总表!D:D) -> 0 | L7: / | M7: / | N7: / | U7: =SUMIF(运营总表!A:A,D:D,运营总表!M:M) -> 0 | V7: =SUMIF(运营总表!A:A,D:D,运营总表!N:N) -> 0 | W7: =IFERROR(V7/U7,0) -> 0 | X7: =SUMIF(运营总表!A:A,D:D,运营总表!K:K) -> 0 | Y7: =SUMIF(运营总表!A:A,D:D,运营总表!P:P) -> 0 | Z7: =SUMIF(运营总表!A:A,D:D,运营总表!Q:Q) -> 0
D8: 44595 | H8: =SUMIF(运营总表!A:A,D:D,运营总表!B:B) -> 0 | I8: =SUMIF(运营总表!A:A,D:D,运营总表!C:C) -> 0 | J8: / | K8: =SUMIF(运营总表!A:A,D:D,运营总表!D:D) -> 0 | L8: / | M8: / | N8: / | U8: =SUMIF(运营总表!A:A,D:D,运营总表!M:M) -> 0 | V8: =SUMIF(运营总表!A:A,D:D,运营总表!N:N) -> 0 | W8: =IFERROR(V8/U8,0) -> 0 | X8: =SUMIF(运营总表!A:A,D:D,运营总表!K:K) -> 0 | Y8: =SUMIF(运营总表!A:A,D:D,运营总表!P:P) -> 0 | Z8: =SUMIF(运营总表!A:A,D:D,运营总表!Q:Q) -> 0
D9: 44596 | H9: =SUMIF(运营总表!A:A,D:D,运营总表!B:B) -> 0 | I9: =SUMIF(运营总表!A:A,D:D,运营总表!C:C) -> 0 | J9: / | K9: =SUMIF(运营总表!A:A,D:D,运营总表!D:D) -> 0 | L9: / | M9: / | N9: / | U9: =SUMIF(运营总表!A:A,D:D,运营总表!M:M) -> 0 | V9: =SUMIF(运营总表!A:A,D:D,运营总表!N:N) -> 0 | W9: =IFERROR(V9/U9,0) -> 0 | X9: =SUMIF(运营总表!A:A,D:D,运营总表!K:K) -> 0 | Y9: =SUMIF(运营总表!A:A,D:D,运营总表!P:P) -> 0 | Z9: =SUMIF(运营总表!A:A,D:D,运营总表!Q:Q) -> 0
D10: 44597 | H10: =SUMIF(运营总表!A:A,D:D,运营总表!B:B) -> 0 | I10: =SUMIF(运营总表!A:A,D:D,运营总表!C:C) -> 0 | J10: =IFERROR(K10/H10,0) -> 0 | K10: =SUMIF(运营总表!A:A,D:D,运营总表!D:D) -> 0 | L10: =IFERROR(K10-M10,0) -> 0 | M10: =Y10 -> 0 | N10: 0 | U10: =SUMIF(运营总表!A:A,D:D,运营总表!M:M) -> 0 | V10: =SUMIF(运营总表!A:A,D:D,运营总表!N:N) -> 0 | W10: =IFERROR(V10/U10,0) -> 0 | X10: =SUMIF(运营总表!A:A,D:D,运营总表!K:K) -> 0 | Y10: =SUMIF(运营总表!A:A,D:D,运营总表!P:P) -> 0 | Z10: =SUMIF(运营总表!A:A,D:D,运营总表!Q:Q) -> 0
D11: 44598 | H11: =SUMIF(运营总表!A:A,D:D,运营总表!B:B) -> 0 | I11: =SUMIF(运营总表!A:A,D:D,运营总表!C:C) -> 0 | J11: =IFERROR(K11/H11,0) -> 0 | K11: 1 | L11: =IFERROR(K11-M11,0) -> 1 | M11: =Y11 -> 0 | N11: 0 | U11: =SUMIF(运营总表!A:A,D:D,运营总表!M:M) -> 0 | V11: =SUMIF(运营总表!A:A,D:D,运营总表!N:N) -> 0 | W11: =IFERROR(V11/U11,0) -> 0 | X11: =SUMIF(运营总表!A:A,D:D,运营总表!K:K) -> 0 | Y11: =SUMIF(运营总表!A:A,D:D,运营总表!P:P) -> 0 | Z11: =SUMIF(运营总表!A:A,D:D,运营总表!Q:Q) -> 0
D12: 44599 | H12: =SUMIF(运营总表!A:A,D:D,运营总表!B:B) -> 0 | I12: =SUMIF(运营总表!A:A,D:D,运营总表!C:C) -> 0 | J12: =IFERROR(K12/H12,0) -> 0 | K12: =SUMIF(运营总表!A:A,D:D,运营总表!D:D) -> 0 | L12: =IFERROR(K12-M12,0) -> 0 | M12: =Y12 -> 0 | N12: 0 | U12: =SUMIF(运营总表!A:A,D:D,运营总表!M:M) -> 0 | V12: =SUMIF(运营总表!A:A,D:D,运营总表!N:N) -> 0 | W12: =IFERROR(V12/U12,0) -> 0 | X12: =SUMIF(运营总表!A:A,D:D,运营总表!K:K) -> 0 | Y12: =SUMIF(运营总表!A:A,D:D,运营总表!P:P) -> 0 | Z12: =SUMIF(运营总表!A:A,D:D,运营总表!Q:Q) -> 0
A13: 1. 上线3-5条Q&A 2.基础流量涌进 , 词的位置逐渐上升, 调整广告 重新分配预算 以偏转化的广告结构增加销量及转化 3. coupon从10%调至15% 刺激转化 | C13: Week2 | D13: 44600 | H13: =SUMIF(运营总表!A:A,D:D,运营总表!B:B) -> 0 | I13: =SUMIF(运营总表!A:A,D:D,运营总表!C:C) -> 0 | J13: =IFERROR(K13/H13,0) -> 0 | K13: =SUMIF(运营总表!A:A,D:D,运营总表!D:D) -> 0 | L13: =IFERROR(K13-M13,0) -> 0 | M13: =Y13 -> 0 | N13: 1 | U13: =SUMIF(运营总表!A:A,D:D,运营总表!M:M) -> 0 | V13: =SUMIF(运营总表!A:A,D:D,运营总表!N:N) -> 0 | W13: =IFERROR(V13/U13,0) -> 0 | X13: =SUMIF(运营总表!A:A,D:D,运营总表!K:K) -> 0 | Y13: =SUMIF(运营总表!A:A,D:D,运营总表!P:P) -> 0 | Z13: =SUMIF(运营总表!A:A,D:D,运营总表!Q:Q) -> 0
D14: 44601 | H14: =SUMIF(运营总表!A:A,D:D,运营总表!B:B) -> 0 | I14: =SUMIF(运营总表!A:A,D:D,运营总表!C:C) -> 0 | J14: =IFERROR(K14/H14,0) -> 0 | K14: =SUMIF(运营总表!A:A,D:D,运营总表!D:D) -> 0 | L14: =IFERROR(K14-M14,0) -> 0 | M14: =Y14 -> 0 | N14: 2 | U14: =SUMIF(运营总表!A:A,D:D,运营总表!M:M) -> 0 | V14: =SUMIF(运营总表!A:A,D:D,运营总表!N:N) -> 0 | W14: =IFERROR(V14/U14,0) -> 0 | X14: =SUMIF(运营总表!A:A,D:D,运营总表!K:K) -> 0 | Y14: =SUMIF(运营总表!A:A,D:D,运营总表!P:P) -> 0 | Z14: =SUMIF(运营总表!A:A,D:D,运营总表!Q:Q) -> 0
D15: 44602 | H15: =SUMIF(运营总表!A:A,D:D,运营总表!B:B) -> 0 | I15: =SUMIF(运营总表!A:A,D:D,运营总表!C:C) -> 0 | J15: =IFERROR(K15/H15,0) -> 0 | K15: =SUMIF(运营总表!A:A,D:D,运营总表!D:D) -> 0 | L15: =IFERROR(K15-M15,0) -> 0 | M15: =Y15 -> 0 | N15: 2 | U15: =SUMIF(运营总表!A:A,D:D,运营总表!M:M) -> 0 | V15: =SUMIF(运营总表!A:A,D:D,运营总表!N:N) -> 0 | W15: =IFERROR(V15/U15,0) -> 0 | X15: =SUMIF(运营总表!A:A,D:D,运营总表!K:K) -> 0 | Y15: =SUMIF(运营总表!A:A,D:D,运营总表!P:P) -> 0 | Z15: =SUMIF(运营总表!A:A,D:D,运营总表!Q:Q) -> 0
D16: 44603 | H16: =SUMIF(运营总表!A:A,D:D,运营总表!B:B) -> 0 | I16: =SUMIF(运营总表!A:A,D:D,运营总表!C:C) -> 0 | J16: =IFERROR(K16/H16,0) -> 0 | K16: =SUMIF(运营总表!A:A,D:D,运营总表!D:D) -> 0 | L16: =IFERROR(K16-M16,0) -> 0 | M16: =Y16 -> 0 | N16: 0 | U16: =SUMIF(运营总表!A:A,D:D,运营总表!M:M) -> 0 | V16: =SUMIF(运营总表!A:A,D:D,运营总表!N:N) -> 0 | W16: =IFERROR(V16/U16,0) -> 0 | X16: =SUMIF(运营总表!A:A,D:D,运营总表!K:K) -> 0 | Y16: =SUMIF(运营总表!A:A,D:D,运营总表!P:P) -> 0 | Z16: =SUMIF(运营总表!A:A,D:D,运营总表!Q:Q) -> 0
D17: 44604 | H17: =SUMIF(运营总表!A:A,D:D,运营总表!B:B) -> 0 | I17: =SUMIF(运营总表!A:A,D:D,运营总表!C:C) -> 0 | J17: =IFERROR(K17/H17,0) -> 0 | K17: =SUMIF(运营总表!A:A,D:D,运营总表!D:D) -> 0 | L17: =IFERROR(K17-M17,0) -> 0 | M17: =Y17 -> 0 | N17: 1 | U17: =SUMIF(运营总表!A:A,D:D,运营总表!M:M) -> 0 | V17: =SUMIF(运营总表!A:A,D:D,运营总表!N:N) -> 0 | W17: =IFERROR(V17/U17,0) -> 0 | X17: =SUMIF(运营总表!A:A,D:D,运营总表!K:K) -> 0 | Y17: =SUMIF(运营总表!A:A,D:D,运营总表!P:P) -> 0 | Z17: =SUMIF(运营总表!A:A,D:D,运营总表!Q:Q) -> 0
D18: 44605 | H18: =SUMIF(运营总表!A:A,D:D,运营总表!B:B) -> 0 | I18: =SUMIF(运营总表!A:A,D:D,运营总表!C:C) -> 0 | J18: =IFERROR(K18/H18,0) -> 0 | K18: =SUMIF(运营总表!A:A,D:D,运营总表!D:D) -> 0 | L18: =IFERROR(K18-M18,0) -> 0 | M18: =Y18 -> 0 | N18: 0 | U18: =SUMIF(运营总表!A:A,D:D,运营总表!M:M) -> 0 | V18: =SUMIF(运营总表!A:A,D:D,运营总表!N:N) -> 0 | W18: =IFERROR(V18/U18,0) -> 0 | X18: =SUMIF(运营总表!A:A,D:D,运营总表!K:K) -> 0 | Y18: =SUMIF(运营总表!A:A,D:D,运营总表!P:P) -> 0 | Z18: =SUMIF(运营总表!A:A,D:D,运营总表!Q:Q) -> 0
D19: 44606 | H19: =SUMIF(运营总表!A:A,D:D,运营总表!B:B) -> 0 | I19: =SUMIF(运营总表!A:A,D:D,运营总表!C:C) -> 0 | J19: =IFERROR(K19/H19,0) -> 0 | K19: =SUMIF(运营总表!A:A,D:D,运营总表!D:D) -> 0 | L19: =IFERROR(K19-M19,0) -> 0 | M19: =Y19 -> 0 | N19: 0 | U19: =SUMIF(运营总表!A:A,D:D,运营总表!M:M) -> 0 | V19: =SUMIF(运营总表!A:A,D:D,运营总表!N:N) -> 0 | W19: =IFERROR(V19/U19,0) -> 0 | X19: =SUMIF(运营总表!A:A,D:D,运营总表!K:K) -> 0 | Y19: =SUMIF(运营总表!A:A,D:D,运营总表!P:P) -> 0 | Z19: =SUMIF(运营总表!A:A,D:D,运营总表!Q:Q) -> 0
A20: 1. 稳定产品大类排名在2000名以内, 小类前15名 2. 保持当前强转化的广告结构 提升链接转化, 获得更多的流量分配 3. 提报站内秒杀及会员专属折扣, 在这个月冲销量排名 | C20: Week3 | D20: 44607 | H20: =SUMIF(运营总表!A:A,D:D,运营总表!B:B) -> 0 | I20: =SUMIF(运营总表!A:A,D:D,运营总表!C:C) -> 0 | J20: =IFERROR(K20/H20,0) -> 0 | K20: =SUMIF(运营总表!A:A,D:D,运营总表!D:D) -> 0 | L20: =IFERROR(K20-M20,0) -> 0 | M20: =Y20 -> 0 | N20: 3 | U20: =SUMIF(运营总表!A:A,D:D,运营总表!M:M) -> 0 | V20: =SUMIF(运营总表!A:A,D:D,运营总表!N:N) -> 0 | W20: =IFERROR(V20/U20,0) -> 0 | X20: =SUMIF(运营总表!A:A,D:D,运营总表!K:K) -> 0 | Y20: =SUMIF(运营总表!A:A,D:D,运营总表!P:P) -> 0 | Z20: =SUMIF(运营总表!A:A,D:D,运营总表!Q:Q) -> 0
D21: 44608 | H21: =SUMIF(运营总表!A:A,D:D,运营总表!B:B) -> 0 | I21: =SUMIF(运营总表!A:A,D:D,运营总表!C:C) -> 0 | J21: =IFERROR(K21/H21,0) -> 0 | K21: =SUMIF(运营总表!A:A,D:D,运营总表!D:D) -> 0 | L21: =IFERROR(K21-M21,0) -> 0 | M21: =Y21 -> 0 | N21: 5 | U21: =SUMIF(运营总表!A:A,D:D,运营总表!M:M) -> 0 | V21: =SUMIF(运营总表!A:A,D:D,运营总表!N:N) -> 0 | W21: =IFERROR(V21/U21,0) -> 0 | X21: =SUMIF(运营总表!A:A,D:D,运营总表!K:K) -> 0 | Y21: =SUMIF(运营总表!A:A,D:D,运营总表!P:P) -> 0 | Z21: =SUMIF(运营总表!A:A,D:D,运营总表!Q:Q) -> 0
D22: 44609 | H22: =SUMIF(运营总表!A:A,D:D,运营总表!B:B) -> 0 | I22: =SUMIF(运营总表!A:A,D:D,运营总表!C:C) -> 0 | J22: =IFERROR(K22/H22,0) -> 0 | K22: =SUMIF(运营总表!A:A,D:D,运营总表!D:D) -> 0 | L22: =IFERROR(K22-M22,0) -> 0 | M22: =Y22 -> 0 | N22: 2 | U22: =SUMIF(运营总表!A:A,D:D,运营总表!M:M) -> 0 | V22: =SUMIF(运营总表!A:A,D:D,运营总表!N:N) -> 0 | W22: =IFERROR(V22/U22,0) -> 0 | X22: 、 | Y22: =SUMIF(运营总表!A:A,D:D,运营总表!P:P) -> 0 | Z22: =SUMIF(运营总表!A:A,D:D,运营总表!Q:Q) -> 0
D23: 44610 | H23: =SUMIF(运营总表!A:A,D:D,运营总表!B:B) -> 0 | I23: =SUMIF(运营总表!A:A,D:D,运营总表!C:C) -> 0 | J23: =IFERROR(K23/H23,0) -> 0 | K23: =SUMIF(运营总表!A:A,D:D,运营总表!D:D) -> 0 | L23: =IFERROR(K23-M23,0) -> 0 | M23: =Y23 -> 0 | N23: 3 | U23: =SUMIF(运营总表!A:A,D:D,运营总表!M:M) -> 0 | V23: =SUMIF(运营总表!A:A,D:D,运营总表!N:N) -> 0 | W23: =IFERROR(V23/U23,0) -> 0 | X23: =SUMIF(运营总表!A:A,D:D,运营总表!K:K) -> 0 | Y23: =SUMIF(运营总表!A:A,D:D,运营总表!P:P) -> 0 | Z23: =SUMIF(运营总表!A:A,D:D,运营总表!Q:Q) -> 0
D24: 44611 | H24: =SUMIF(运营总表!A:A,D:D,运营总表!B:B) -> 0 | I24: =SUMIF(运营总表!A:A,D:D,运营总表!C:C) -> 0 | J24: =IFERROR(K24/H24,0) -> 0 | K24: =SUMIF(运营总表!A:A,D:D,运营总表!D:D) -> 0 | L24: =IFERROR(K24-M24,0) -> 0 | M24: =Y24 -> 0 | N24: 0 | U24: =SUMIF(运营总表!A:A,D:D,运营总表!M:M) -> 0 | V24: =SUMIF(运营总表!A:A,D:D,运营总表!N:N) -> 0 | W24: =IFERROR(V24/U24,0) -> 0 | X24: =SUMIF(运营总表!A:A,D:D,运营总表!K:K) -> 0 | Y24: =SUMIF(运营总表!A:A,D:D,运营总表!P:P) -> 0 | Z24: =SUMIF(运营总表!A:A,D:D,运营总表!Q:Q) -> 0
D25: 44612 | H25: =SUMIF(运营总表!A:A,D:D,运营总表!B:B) -> 0 | I25: =SUMIF(运营总表!A:A,D:D,运营总表!C:C) -> 0 | J25: =IFERROR(K25/H25,0) -> 0 | K25: =SUMIF(运营总表!A:A,D:D,运营总表!D:D) -> 0 | L25: =IFERROR(K25-M25,0) -> 0 | M25: =Y25 -> 0 | N25: 0 | U25: =SUMIF(运营总表!A:A,D:D,运营总表!M:M) -> 0 | V25: =SUMIF(运营总表!A:A,D:D,运营总表!N:N) -> 0 | W25: =IFERROR(V25/U25,0) -> 0 | X25: =SUMIF(运营总表!A:A,D:D,运营总表!K:K) -> 0 | Y25: =SUMIF(运营总表!A:A,D:D,运营总表!P:P) -> 0 | Z25: =SUMIF(运营总表!A:A,D:D,运营总表!Q:Q) -> 0
D26: 44613 | H26: =SUMIF(运营总表!A:A,D:D,运营总表!B:B) -> 0 | I26: =SUMIF(运营总表!A:A,D:D,运营总表!C:C) -> 0 | J26: =IFERROR(K26/H26,0) -> 0 | K26: =SUMIF(运营总表!A:A,D:D,运营总表!D:D) -> 0 | L26: =IFERROR(K26-M26,0) -> 0 | M26: =Y26 -> 0 | N26: 0 | U26: =SUMIF(运营总表!A:A,D:D,运营总表!M:M) -> 0 | V26: =SUMIF(运营总表!A:A,D:D,运营总表!N:N) -> 0 | W26: =IFERROR(V26/U26,0) -> 0 | X26: =SUMIF(运营总表!A:A,D:D,运营总表!K:K) -> 0 | Y26: =SUMIF(运营总表!A:A,D:D,运营总表!P:P) -> 0 | Z26: =SUMIF(运营总表!A:A,D:D,运营总表!Q:Q) -> 0
A27: 1. 产品排名稳定在1000名以内 2. 增评及增加Q&A | C27: Week4 | D27: 44614 | H27: =SUMIF(运营总表!A:A,D:D,运营总表!B:B) -> 0 | I27: =SUMIF(运营总表!A:A,D:D,运营总表!C:C) -> 0 | J27: =IFERROR(K27/H27,0) -> 0 | K27: =SUMIF(运营总表!A:A,D:D,运营总表!D:D) -> 0 | L27: =IFERROR(K27-M27,0) -> 0 | M27: =Y27 -> 0 | N27: 3 | U27: =SUMIF(运营总表!A:A,D:D,运营总表!M:M) -> 0 | V27: =SUMIF(运营总表!A:A,D:D,运营总表!N:N) -> 0 | W27: =IFERROR(V27/U27,0) -> 0 | X27: =SUMIF(运营总表!A:A,D:D,运营总表!K:K) -> 0 | Y27: =SUMIF(运营总表!A:A,D:D,运营总表!P:P) -> 0 | Z27: =SUMIF(运营总表!A:A,D:D,运营总表!Q:Q) -> 0
D28: 44615 | H28: =SUMIF(运营总表!A:A,D:D,运营总表!B:B) -> 0 | I28: =SUMIF(运营总表!A:A,D:D,运营总表!C:C) -> 0 | J28: =IFERROR(K28/H28,0) -> 0 | K28: =SUMIF(运营总表!A:A,D:D,运营总表!D:D) -> 0 | L28: =IFERROR(K28-M28,0) -> 0 | M28: =Y28 -> 0 | N28: 4 | U28: =SUMIF(运营总表!A:A,D:D,运营总表!M:M) -> 0 | V28: =SUMIF(运营总表!A:A,D:D,运营总表!N:N) -> 0 | W28: =IFERROR(V28/U28,0) -> 0 | X28: =SUMIF(运营总表!A:A,D:D,运营总表!K:K) -> 0 | Y28: =SUMIF(运营总表!A:A,D:D,运营总表!P:P) -> 0 | Z28: =SUMIF(运营总表!A:A,D:D,运营总表!Q:Q) -> 0
D29: 44616 | H29: =SUMIF(运营总表!A:A,D:D,运营总表!B:B) -> 0 | I29: =SUMIF(运营总表!A:A,D:D,运营总表!C:C) -> 0 | J29: =IFERROR(K29/H29,0) -> 0 | K29: =SUMIF(运营总表!A:A,D:D,运营总表!D:D) -> 0 | L29: =IFERROR(K29-M29,0) -> 0 | M29: =Y29 -> 0 | N29: 2 | U29: =SUMIF(运营总表!A:A,D:D,运营总表!M:M) -> 0 | V29: =SUMIF(运营总表!A:A,D:D,运营总表!N:N) -> 0 | W29: =IFERROR(V29/U29,0) -> 0 | X29: =SUMIF(运营总表!A:A,D:D,运营总表!K:K) -> 0 | Y29: =SUMIF(运营总表!A:A,D:D,运营总表!P:P) -> 0 | Z29: =SUMIF(运营总表!A:A,D:D,运营总表!Q:Q) -> 0
D30: 44617 | H30: =SUMIF(运营总表!A:A,D:D,运营总表!B:B) -> 0 | I30: =SUMIF(运营总表!A:A,D:D,运营总表!C:C) -> 0 | J30: =IFERROR(K30/H30,0) -> 0 | K30: =SUMIF(运营总表!A:A,D:D,运营总表!D:D) -> 0 | L30: =IFERROR(K30-M30,0) -> 0 | M30: =Y30 -> 0 | N30: 1 | U30: =SUMIF(运营总表!A:A,D:D,运营总表!M:M) -> 0 | V30: =SUMIF(运营总表!A:A,D:D,运营总表!N:N) -> 0 | W30: =IFERROR(V30/U30,0) -> 0 | X30: =SUMIF(运营总表!A:A,D:D,运营总表!K:K) -> 0 | Y30: =SUMIF(运营总表!A:A,D:D,运营总表!P:P) -> 0 | Z30: =SUMIF(运营总表!A:A,D:D,运营总表!Q:Q) -> 0
D31: 44618 | H31: =SUMIF(运营总表!A:A,D:D,运营总表!B:B) -> 0 | I31: =SUMIF(运营总表!A:A,D:D,运营总表!C:C) -> 0 | J31: =IFERROR(K31/H31,0) -> 0 | K31: =SUMIF(运营总表!A:A,D:D,运营总表!D:D) -> 0 | L31: =IFERROR(K31-M31,0) -> 0 | M31: =Y31 -> 0 | N31: 0 | U31: =SUMIF(运营总表!A:A,D:D,运营总表!M:M) -> 0 | V31: =SUMIF(运营总表!A:A,D:D,运营总表!N:N) -> 0 | W31: =IFERROR(V31/U31,0) -> 0 | X31: =SUMIF(运营总表!A:A,D:D,运营总表!K:K) -> 0 | Y31: =SUMIF(运营总表!A:A,D:D,运营总表!P:P) -> 0 | Z31: =SUMIF(运营总表!A:A,D:D,运营总表!Q:Q) -> 0
D32: 44619 | H32: =SUMIF(运营总表!A:A,D:D,运营总表!B:B) -> 0 | I32: =SUMIF(运营总表!A:A,D:D,运营总表!C:C) -> 0 | J32: =IFERROR(K32/H32,0) -> 0 | K32: =SUMIF(运营总表!A:A,D:D,运营总表!D:D) -> 0 | L32: =IFERROR(K32-M32,0) -> 0 | M32: =Y32 -> 0 | N32: 0 | U32: =SUMIF(运营总表!A:A,D:D,运营总表!M:M) -> 0 | V32: =SUMIF(运营总表!A:A,D:D,运营总表!N:N) -> 0 | W32: =IFERROR(V32/U32,0) -> 0 | X32: =SUMIF(运营总表!A:A,D:D,运营总表!K:K) -> 0 | Y32: =SUMIF(运营总表!A:A,D:D,运营总表!P:P) -> 0 | Z32: =SUMIF(运营总表!A:A,D:D,运营总表!Q:Q) -> 0
D33: 44620 | H33: =SUMIF(运营总表!A:A,D:D,运营总表!B:B) -> 0 | I33: =SUMIF(运营总表!A:A,D:D,运营总表!C:C) -> 0 | J33: =IFERROR(K33/H33,0) -> 0 | K33: =SUMIF(运营总表!A:A,D:D,运营总表!D:D) -> 0 | L33: =IFERROR(K33-M33,0) -> 0 | M33: =Y33 -> 0 | N33: 0 | U33: =SUMIF(运营总表!A:A,D:D,运营总表!M:M) -> 0 | V33: =SUMIF(运营总表!A:A,D:D,运营总表!N:N) -> 0 | W33: =IFERROR(V33/U33,0) -> 0 | X33: =SUMIF(运营总表!A:A,D:D,运营总表!K:K) -> 0 | Y33: =SUMIF(运营总表!A:A,D:D,运营总表!P:P) -> 0 | Z33: =SUMIF(运营总表!A:A,D:D,运营总表!Q:Q) -> 0

Sheet 广告预算计算
A1: 广告预算计算
A2: ASIN | B2: 产品单价 | C2: 日均销售额 | D2: 当前广告转化率 | E2: 当前CPC | F2: 当前点击率 | G2: 预估广告花费 | H2: 预期曝光量 | I2: 预期点击次数(日均) | J2: 预期广告出单(日均) | K2: 预期销售额(日均) | L2: 预估综合ACOS | M2: 预估ACOS | N2: 预估ROAS
G3: =IFERROR(J3/D3*E3,0) -> 0 | H3: =IFERROR(I3/F3,0) -> 0 | I3: =IFERROR(J3/D3,0) -> 0 | K3: =J3*B3 -> 0 | L3: =IFERROR(G3/(C3+K3),0) -> 0 | M3: =IFERROR(G3/K3,0) -> 0 | N3: =IFERROR(K3/G3,0) -> 0

Sheet 广告竞价计算
A1: 基础竞价
A2: 目标ACoS
A3: 产品售价
A4: 转化率
A5: 调整比例
A7: 期望投入多少产生1个销售 | B7: =B2*B3 -> 0
A8: 多少次点击产生1个销售 | B8: =IFERROR(1/B4,0) -> 0
A9: 单次点击收入 | B9: =IFERROR(B3*B4,0) -> 0
A10: 目标竞价 | B10: =IFERROR(B2*B3*B4*(1+B5),0) -> 0
A12: 广告位调整竞价
A13: 广告位 Placement | B13: 点击 | C13: 销售额 | D13: CPC
A14: First page Top of Search on Amazon | D14: =IFERROR(C14/B14,0) -> 0
A15: Product pages on Amazon | D15: =IFERROR(C15/B15,0) -> 0
A16: Rest of search on Amazon | D16: =IFERROR(C16/B16,0) -> 0
A17: 总计 | B17: =SUM(B14:B16) -> 0 | C17: =SUM(C14:C16) -> 0 | D17: =IFERROR(C17/B17,0) -> 0
A18: 最高SPC位置点击占比 | B18: =IFERROR(B14/B17,0) -> 0
A20: 默认竞价(单关键词广告活动） | B20: =_xlfn.IFS(AND(D16<D15,D16<D14),D16*B2,AND(D15<D14,D15<D16),(C15+C16)/(B15+B16)*B2,AND(D14<D15,D14<D16),(C14+C16)/(B14+B16)*B2) -> #N/A
A21: Top of Search 调整比例 | B21: =IFERROR(IF((D14/((C15+C16)/(B15+B16))-1)<0,"0%",(D14/((C15+C16)/(B15+B16))-1)),0) -> 0
A22: Product pages 调整比例 | B22: =IFERROR(IF((D15/((C16+C17)/(B16+B17))-1)<0,"0%",(D15/((C16+C17)/(B16+B17))-1)),0) -> 0
A24: 多关键词广告活动
A25: 关键词 | B25: 点击 | C25: 销售额 | D25: CPC | E25: 竞价
E26: =IFERROR(D26*$C$2/(1+$C$21*$C$18),0) -> 0
E27: =IFERROR(D27*$C$2/(1+$C$21*$C$18),0) -> 0

Sheet 广告调整记录
A1: 广告调整记录
A4: 日期 | B4: ASIN | C4: 广告结构调整 | J4: 广告活动 | L4: 调整记录
C5: 自动广告 | D5: 手动广告 | E5: 产品定投 | F5: 类目定投 | G5: 品牌广告 | H5: 视频广告 | I5: SD广告 | J5: 广告活动 | K5: 广告组 | L5: 预算/竞价调整 | Q5: 广告策略调整 | S5: 位置比例调整 | V5: 添加/删除关键词 ASIN | X5: 关键词/ASIN否定
L6: 原始预算 | M6: 调整预算 | N6: 关键词 | O6: 原始竞价 | P6: 调整竞价 | Q6: 原始策略 | R6: 调整策略 | S6: 位置 | T6: 原始比例 | U6: 调整比例 | V6: 添加 | W6: 删除(Archive Or Pause) | X6: 词组否定 | Y6: 精准否定

Sheet 广告周数据和月数据
A1: 产品广告数据周/月统计
A3: 1-7日产品广告数据分析 | O3: 8-14日产品广告数据分析
A4: 产品 | B4: 月份 | C4: 站点 | D4: 花费 | E4: 曝光 | F4: 点击次数 | G4: 每次点击费用 | H4: 点击率 | I4: 销售额 | J4: 订单 | K4: ACOS | L4: 总销售额 | M4: 广告花费占总销售比 | O4: 产品 | P4: 月份 | Q4: 站点 | R4: 花费 | S4: 曝光 | T4: 点击次数 | U4: 每次点击费用 | V4: 点击率 | W4: 销售额 | X4: 订单 | Y4: ACOS | Z4: 总销售额 | AA4: 广告花费占总销售比
AA5: =IFERROR(R5/Z5,0) -> 0
A15: 总计 | O15: 总计
A17: 15-22日产品广告数据分析 | O17: 23-30日产品广告数据分析
A18: 产品 | B18: 月份 | C18: 站点 | D18: 花费 | E18: 曝光 | F18: 点击次数 | G18: 每次点击费用 | H18: 点击率 | I18: 销售额 | J18: 订单 | K18: ACOS | L18: 总销售额 | M18: 广告花费占总销售比 | O18: 产品 | P18: 月份 | Q18: 站点 | R18: 花费 | S18: 曝光 | T18: 点击次数 | U18: 每次点击费用 | V18: 点击率 | W18: 销售额 | X18: 订单 | Y18: ACOS | Z18: 总销售额 | AA18: 广告花费占总销售比
A29: 总计 | O29: 总计
A31: 上半月和下半月产品分析
A32: 1-14日产品广告数据分析 | O32: 15-31日产品广告数据分析
A33: 产品 | B33: 月份 | C33: 站点 | D33: 花费 | E33: 曝光 | F33: 点击次数 | G33: 每次点击费用 | H33: 点击率 | I33: 销售额 | J33: 订单 | K33: ACOS | L33: 总销售额 | M33: 广告花费占总销售比 | O33: 产品 | P33: 月份 | Q33: 站点 | R33: 花费 | S33: 曝光 | T33: 点击次数 | U33: 每次点击费用 | V33: 点击率 | W33: 销售额 | X33: 订单 | Y33: ACOS | Z33: 总销售额 | AA33: 广告花费占总销售比
A44: 总计 | O44: 总计
A46: 当月产品广告数据分析
A47: 产品 | B47: 月份 | C47: 站点 | D47: 花费 | E47: 曝光 | F47: 点击次数 | G47: 每次点击费用 | H47: 点击率 | I47: 销售额 | J47: 订单 | K47: ACOS | L47: 总销售额 | M47: 广告花费占总销售比
A58: 总计

Sheet 刷单留评记录表
A1: 时间 | B1: 订单号 | C1: 渠道SKU | D1: 产品名称 | E1: ID | F1: Paypal账号 | G1: 金额 | H1: 刷单关键词 | I1: 刷单类型(免评单OR留评单） | J1: review质量 | K1: 订单备注 | L1: 留评日期 | M1: review链接 | N1: review profile链接 | O1: 备注

Sheet 关键词位置
A1: 主要关键词 | B1: 位置 | C1: 44593 | D1: 44594 | E1: 44595 | F1: 44596 | G1: 44597 | H1: 44598 | I1: 44599 | J1: 44600 | K1: 44601 | L1: 44602 | M1: 44603 | N1: 44604 | O1: 44605 | P1: 44606 | Q1: 44607 | R1: 44608 | S1: 44609 | T1: 44610 | U1: 44611 | V1: 44612 | W1: 44613 | X1: 44614 | Y1: 44615 | Z1: 44616 | AA1: 44617 | AB1: 44618 | AC1: 44619 | AD1: 44620
B2: 广告排位
B3: 自然排位
B4: 广告排位
B5: 自然排位
B6: 广告排位
B7: 自然排位

Sheet WpsReserved_CellImgList
